{
  "type": "Feature",
  "properties": {
    "date:cessation_lower": "2012-09-10",
    "date:cessation_upper": "2012-09-10",
    "date:inception_lower": "2012-09-10",
    "date:inception_upper": "2012-09-10",
    "instagram:post": {
      "caption": {
        "body": "Lella Vignetti's necklace for San Lorenzo has roots in 17th century Dutch fashion",
        "excerpt": "Lella Vignetti's necklace for San Lorenzo has roots in 17th century Dutch fashion"
      },
      "media_id": "bfa6086a8c54d21fb7be020a75621b6d",
      "path": "media/posts/201209/11189888_835151816533740_24173815_n_17842269433062499.jpg",
      "perceptual_hash": "p:d653643f1f12da03",
      "taken": 1347274260,
      "taken_at": "Sep 10, 2012, 10:51 AM"
    },
    "sfomuseum:placetype": "instagram",
    "wof:name": "Lella Vignetti's necklace for San Lorenzo has roots in 17th century Dutch fashion..",
    "wof:placetype": "custom"
  },
  "geometry": {"coordinates":[-122.386166,37.616356],"type":"Point"}
}
