{
  "type": "Feature",
  "properties": {
    "date:cessation_lower": "2016-11-10",
    "date:cessation_upper": "2016-11-10",
    "date:inception_lower": "2016-11-10",
    "date:inception_upper": "2016-11-10",
    "instagram:post": {
      "caption": {
        "body": "This 1943 wartime inflight information brochure by TWA (Transcontinental \u0026 Western Air) was given out to passengers flying in their DC-3s. \"Vacant Seats on a 'Sold Out' Plane?\" explained how vacant seats meant that sometimes passengers didn't show up, the planes needed more fuel, or airmail was a priority.",
        "excerpt": "This 1943 wartime inflight information brochure by TWA (Transcontinental \u0026 Western Air) was given out to passengers flying in their DC-3s.",
        "hashtags": [
          "TWA"
        ]
      },
      "media_id": "25665c647cbee144d1ca93d23ae8d3f8",
      "path": "media/posts/201611/14488085_1030462860395509_3498802765889536000_n_17844174994154634.jpg",
      "perceptual_hash": "p:f89b6c29349833c7",
      "taken": 1478802360,
      "taken_at": "Nov 10, 2016, 6:26 PM"
    },
    "sfomuseum:placetype": "instagram",
    "wof:name": "This 1943 wartime inflight information brochure by TWA (Transcontinental \u0026 Western Air) was given out to passengers flying in their DC-3s...",
    "wof:placetype": "custom"
  },
  "geometry": {"coordinates":[-122.386166,37.616356],"type":"Point"}
}
