{
  "type": "Feature",
  "properties": {
    "date:cessation_lower": "2020-07-10",
    "date:cessation_upper": "2020-07-10",
    "date:inception_lower": "2020-07-10",
    "date:inception_upper": "2020-07-10",
    "instagram:post": {
      "caption": {
        "body": "In honor of our 40th anniversary, every week this year we are highlighting one of our past exhibitions. In 2018, we presented “A Legacy of Pride: Gilbert Baker and the 40th Anniversary of the Rainbow Flag” featuring a rainbow flag sewn by Gilbert Baker, the original designer of what has now become the universal symbol of queer pride. He assigned symbolic meaning to each of the flag’s original eight colors—pink for sexuality, red for life, orange for healing, yellow for sunlight, green for nature, turquoise for art, indigo for peace and harmony, and purple for spirit. Do you remember this exhibition? https://bit.ly/3eiTsa4",
        "excerpt": "In honor of our 40th anniversary, every week this year we are highlighting one of our past exhibitions.",
        "hashtags": [
          "SFOMTBT",
          "SFOat40"
        ]
      },
      "media_id": "a59a44f1e482c94072cccb1de3b24a94",
      "path": "photos/202007/a59a44f1e482c94072cccb1de3b24a94.jpg",
      "perceptual_hash": "p:bdc3c214d3ede821",
      "taken": 1594311900,
      "taken_at": "Jul 9, 2020, 4:25 PM"
    },
    "sfomuseum:placetype": "instagram",
    "wof:name": "In honor of our 40th anniversary, every week this year we are highlighting one of our past exhibitions...",
    "wof:placetype": "custom"
  },
  "geometry": {"coordinates":[-122.386166,37.616356],"type":"Point"}
}
