{
  "type": "Feature",
  "properties": {
    "date:cessation_lower": "2018-01-30",
    "date:cessation_upper": "2018-01-30",
    "date:inception_lower": "2018-01-30",
    "date:inception_upper": "2018-01-30",
    "instagram:post": {
      "caption": {
        "body": "Founded as Inter-Island Airways #onthisday in 1929, Hawaiian Airlines is one of the oldest airlines still in operation in the United States. Passenger service started later that year with two eight-passenger Sikorsky S-38s, flying from Honolulu to the other Hawaiian Islands. In 1941, the company changed its name to Hawaiian Airlines and acquired three Douglas DC-3s. Have you ever flown on Hawaiian Airlines?  Image: Hawaiian Airlines postcard, 80th anniversary, 2009. Gift of Frank A. Norick. 2011.200.002, .003, .004",
        "excerpt": "Founded as Inter-Island Airways #onthisday in 1929, Hawaiian Airlines is one of the oldest airlines still in operation in the United States.",
        "hashtags": [
          "TravelTuesday",
          "avgeek",
          "avationgeek",
          "aviation",
          "aviationhistory",
          "vintageaviation",
          "history",
          "avhistory",
          "aviationgeeks",
          "avgeeks",
          "hawaiianairlines",
          "hawaiianislands",
          "hawaii"
        ]
      },
      "media_id": "13184e6c18db06f4daef4d4ed260b273271bad55",
      "path": "media/posts/201801/26866892_808056079402476_168927102475698176_n_17891444014170439.jpg",
      "perceptual_hash": "p:efc01a6aad9ad027",
      "taken": 1517314740,
      "taken_at": "Jan 30, 2018, 12:19 PM"
    },
    "sfomuseum:placetype": "instagram",
    "wof:name": "Founded as Inter-Island Airways #onthisday in 1929, Hawaiian Airlines is one of the oldest airlines still in operation in the United States...",
    "wof:placetype": "custom",
    "wof:placetype_alt": [
      "instagram"
    ]
  },
  "geometry": {"coordinates":[-122.386166,37.616356],"type":"Point"}
}
