{
  "type": "Feature",
  "properties": {
    "date:cessation_lower": "2017-11-06",
    "date:cessation_upper": "2017-11-06",
    "date:inception_lower": "2017-11-06",
    "date:inception_upper": "2017-11-06",
    "instagram:post": {
      "caption": {
        "body": "This is your last week to see \"Stepping Out: Shoes in World Culture\". Featuring an incredible diversity among footwear from around the world, \"Stepping Out\" showcases shoes from various different cultures. For centuries, elevated shoes with platforms, stilts, or heels served to keep one’s feet and clothing protected from dirt, water, and other unfavorable conditions. This exhibition features shoes from the nineteenth and twentieth centuries from a variety of countries and cultures. Western wedding shoes, early basketball sneakers, beaded moccasins, European clogs, Chinese children’s shoes, and Japanese geta are a few of the many types on display.  Learn more about shoes from all over the world in \"Stepping Out: Shoes in World Culture\" on display, pre-security, in the International Terminal. http://bit.ly/ShoesinCulture",
        "excerpt": "This is your last week to see \"Stepping Out: Shoes in World Culture\".",
        "hashtags": [
          "ShoesinCulture",
          "shoes",
          "instashoes",
          "shoestagram",
          "shoeswag",
          "shoesoftheday",
          "shoedesign",
          "shoefashion",
          "shoeslover"
        ]
      },
      "location": "San Francisco International Airport (SFO)",
      "media_id": "cd08451ba82acc189cac0fd57e7080c8",
      "path": "photos/201711/cd08451ba82acc189cac0fd57e7080c8.jpg",
      "perceptual_hash": "p:bbea053378dc2169",
      "taken": 1509967080,
      "taken_at": "Nov 6, 2017, 11:18 AM"
    },
    "sfomuseum:placetype": "instagram",
    "wof:name": "This is your last week to see \"Stepping Out: Shoes in World Culture\"...",
    "wof:placetype": "custom"
  },
  "geometry": {"coordinates":[-122.386166,37.616356],"type":"Point"}
}
