{
  "type": "Feature",
  "properties": {
    "date:cessation_lower": "2024-07-15",
    "date:cessation_upper": "2024-07-15",
    "date:inception_lower": "2024-07-15",
    "date:inception_upper": "2024-07-15",
    "instagram:post": {
      "caption": {
        "body": "Shaped by decades of creating posters and sets for the stage and movies, Mark von Arenburg’s airline poster painting style evoked a similar drama and allure to his previous work in the entertainment industry. Von Arenburg created this dramatic, stage-like Australia and New Zealand poster featuring Sydney Harbour in the 1940s. It features many of the recognizable attractions of the New South Wales region, including a kookaburra sitting in a gum (eucalyptus) tree, inspired by the popular 1934 song, and an endearing koala with its baby. Pan American’s latest Boeing 377 Stratocruiser airliner flies overhead.  See \"Artists of the Airways: Airline Travel Posters from the SFO Museum Collection\" on display in the Aviation Museum and Library. The Aviation Museum and Library is located pre-security, in the International Terminal. https://bit.ly/AirwaysArtists  📸: poster: Pan American World Airways, Australia and New Zealand; c. 1950 Gift of the Pan Am Historical Foundation 2014.039.002 https://bit.ly/4cZ3vja",
        "excerpt": "Shaped by decades of creating posters and sets for the stage and movies, Mark von Arenburg’s airline poster painting style evoked a similar drama and allure to his previous work in the entertainment industry.",
        "hashtags": [
          "AirwaysArtists",
          "AvGeek"
        ]
      },
      "media_id": "73737d0daaf2700c56988e5add3a20ddad9bdbab",
      "path": "media/posts/202407/451567677_984164743720455_4241945238570302906_n_18444880369005184.jpg",
      "perceptual_hash": "p:875bd906dc39c5c4",
      "taken": 1721055840,
      "taken_at": "Jul 15, 2024 3:04 pm"
    },
    "sfomuseum:placetype": "instagram",
    "wof:name": "Shaped by decades of creating posters and sets for the stage and movies, Mark von Arenburg’s airline poster painting style evoked a similar drama and allure to his previous work in the entertainment industry...",
    "wof:placetype": "custom"
  },
  "geometry": {"coordinates":[-122.386166,37.616356],"type":"Point"}
}
