{
  "type": "Feature",
  "properties": {
    "date:cessation_lower": "2017-02-06",
    "date:cessation_upper": "2017-02-06",
    "date:inception_lower": "2017-02-06",
    "date:inception_upper": "2017-02-06",
    "instagram:post": {
      "caption": {
        "body": "Author Roger Kislingbury pursues early saloon photographs, sharing his passion for the subject in the hardbound publications Saloons, Bars \u0026 Cigar Stores: Historical Interior Photographs (1999) and American Saloons: Pre-Prohibition Photographs (2015). These selections from the author’s collection offer a glimpse into environments made largely extinct by the enactment of Prohibition in 1920 and provide historic context for that nearly ubiquitous feature in saloons and cigar stands during the earliest years of the twentieth century—the mechanical gambling device.  See \"#GamesofChance: Gambling Devices of the Mechanical Age\" and the accompanying photography show, \"The American Saloon: Historical Photographs from the Collection of Roger E. Kislingbury\", on display, post-security, in Terminal 3. http://bit.ly/AmericanSaloon",
        "excerpt": "Author Roger Kislingbury pursues early saloon photographs, sharing his passion for the subject in the hardbound publications Saloons, Bars \u0026 Cigar Stores: Historical Interior Photographs (1999) and American Saloons: Pre-Prohibition Photographs (2015)."
      },
      "media_id": "22542bb627178cc64ed6b03a50dded92",
      "path": "media/posts/201702/16464479_375932126097719_2303917377806401536_n_17865307327067191.jpg",
      "perceptual_hash": "p:ebb6dc2847d72c20",
      "taken": 1486410540,
      "taken_at": "Feb 06, 2017 7:49 pm"
    },
    "sfomuseum:placetype": "instagram",
    "wof:name": "Author Roger Kislingbury pursues early saloon photographs, sharing his passion for the subject in the hardbound publications Saloons, Bars \u0026 Cigar Stores: Historical Interior Photographs (1999) and American Saloons: Pre-Prohibition Photographs (2015)...",
    "wof:placetype": "custom",
    "wof:placetype_alt": [
      "instagram"
    ]
  },
  "geometry": {"coordinates":[-122.386166,37.616356],"type":"Point"}
}
