{
  "type": "Feature",
  "properties": {
    "date:cessation_lower": "2024-02-28",
    "date:cessation_upper": "2024-02-28",
    "date:inception_lower": "2024-02-28",
    "date:inception_upper": "2024-02-28",
    "instagram:post": {
      "caption": {
        "body": "Murat Brièrre (1938–88) was the first to study under visionary artist Georges Liautaud (1899–1991), and he quickly gained recognition as one of the preeminent metal sculptors of Haiti. Brièrre premiered new themes, such as sunbursts with facial expressions and pregnant women carrying babies in their bellies. Fantastical creatures and figures linked together to form narratives comprise some of his highly imaginative, distinctive work. Like other Haitian artists, much of his sculpture displays elements of Haitian Vodou.   See “The Enduring Spirit of Haitian Metal Sculpture” on display, pre-security, in the Mayor Edwin M. Lee International Terminal Departures Hall and online at: https://ow.ly/colB50QIZUG",
        "excerpt": "Murat Brièrre (1938–88) was the first to study under visionary artist Georges Liautaud (1899–1991), and he quickly gained recognition as one of the preeminent metal sculptors of Haiti.",
        "hashtags": [
          "HaitianMetal"
        ]
      },
      "media_id": "17347feba0e2d70e2499d8d7f1d547925d44692a",
      "path": "media/posts/202402/425381570_885303290273268_803108219547674529_n_18218912644283056.jpg",
      "perceptual_hash": "p:b7b28e43789a11c7",
      "taken": 1709138460,
      "taken_at": "Feb 28, 2024 4:41 pm"
    },
    "sfomuseum:placetype": "instagram",
    "wof:name": "Murat Brièrre (1938–88) was the first to study under visionary artist Georges Liautaud (1899–1991), and he quickly gained recognition as one of the preeminent metal sculptors of Haiti...",
    "wof:placetype": "custom"
  },
  "geometry": {"coordinates":[-122.386166,37.616356],"type":"Point"}
}
