{
  "type": "Feature",
  "properties": {
    "date:cessation_lower": "2014-11-03",
    "date:cessation_upper": "2014-11-03",
    "date:inception_lower": "2014-11-03",
    "date:inception_upper": "2014-11-03",
    "instagram:post": {
      "caption": {
        "hashtags": [
          "AdIcons",
          "astrogirl",
          "sonyboy",
          "pekochan"
        ]
      },
      "media_id": "cc808ad0189366c86ad01b8896217c34",
      "path": "media/other/915686_313568132182283_1100885086_n_17842490728062499.jpg",
      "perceptual_hash": "p:86491d36654a6d9f",
      "taken": 1415031720,
      "taken_at": "Nov 03, 2014 4:22 pm"
    },
    "sfomuseum:placetype": "instagram",
    "wof:name": "..",
    "wof:placetype": "custom",
    "wof:placetype_alt": [
      "instagram"
    ]
  },
  "geometry": {"coordinates":[-122.386166,37.616356],"type":"Point"}
}
