{
  "type": "Feature",
  "properties": {
    "date:cessation_lower": "2012-12-28",
    "date:cessation_upper": "2012-12-28",
    "date:inception_lower": "2012-12-28",
    "date:inception_upper": "2012-12-28",
    "instagram:post": {
      "caption": {
        "body": "It's quiet around here, but exhibitions are humming along as usual. Up next: Souvenirs.",
        "excerpt": "It's quiet around here, but exhibitions are humming along as usual."
      },
      "media_id": "337755dda2db67bcfb936d012f138cc3",
      "path": "media/posts/201212/11242300_770463076403205_1109228880_n_17842290670062499.jpg",
      "perceptual_hash": "p:8f97872ba9d0f0c8",
      "taken": 1356691860,
      "taken_at": "Dec 28, 2012, 10:51 AM"
    },
    "sfomuseum:placetype": "instagram",
    "wof:name": "It's quiet around here, but exhibitions are humming along as usual...",
    "wof:placetype": "custom"
  },
  "geometry": {"coordinates":[-122.386166,37.616356],"type":"Point"}
}
