{
  "type": "Feature",
  "properties": {
    "instagram:post": {
      "caption": {
        "body": "Happy Friday! TWA's \"Great Cities of the World\" ticket jacket features two icons of San Francisco. Did you ever fly on TWA (Trans World Airlines)? TWA (Trans World Airlines), San Francisco ticket jacket 1960 SFO Museum Collection Gift of David A. Abercrombie, in memory of Stanley A. Abercrombie  2001.039.525 a b",
        "excerpt": "Happy Friday!"
      },
      "location": "San Francisco International Airport (SFO)",
      "media_id": "d535ca3102f95a06ef8bed2585f61257",
      "path": "photos/201606/d535ca3102f95a06ef8bed2585f61257.jpg",
      "taken": 1465577279,
      "taken_at": "2016-06-10T16:47:59+00:00"
    },
    "sfomuseum:placetype": "instagram",
    "wof:name": "Happy Friday!..",
    "wof:placetype": "custom"
  },
  "geometry": {"coordinates":[-122.386166,37.616356],"type":"Point"}
}
