{
  "type": "Feature",
  "properties": {
    "date:cessation_lower": "2018-08-09",
    "date:cessation_upper": "2018-08-09",
    "date:inception_lower": "2018-08-09",
    "date:inception_upper": "2018-08-09",
    "instagram:post": {
      "caption": {
        "body": "It's International Cat Day and we cannot get enough of cats at SFO Museum! We are presenting not one but TWO cat exhibitions! \"Maneki Neko: Japanese Beckoning Cat\" is on display post-security in Terminal 2 and \"Caticons: The Cat in Art\" is on display, pre-security in the International Terminal. Check out our website for more information. http://bit.ly/SFOExhibitions",
        "excerpt": "It's International Cat Day and we cannot get enough of cats at SFO Museum!",
        "hashtags": [
          "InternationalCatDay",
          "caticons",
          "beckoningcats",
          "manekineko",
          "catsofinstagram",
          "cats",
          "neko",
          "meow",
          "mewseum",
          "japan",
          "mingei",
          "japanese",
          "caticon",
          "cat",
          "catsofinstagram",
          "cats",
          "meow",
          "mewseum",
          "catstagram",
          "catsagram",
          "catscatscats",
          "catlover"
        ]
      },
      "media_id": "c6bdde8d4aef87939f67833413d4f069",
      "path": "photos/201808/c6bdde8d4aef87939f67833413d4f069.jpg",
      "perceptual_hash": "p:8e4759817d84a5de",
      "taken": 1533773911,
      "taken_at": "2018-08-09T00:18:31+00:00"
    },
    "sfomuseum:placetype": "instagram",
    "wof:name": "It's International Cat Day and we cannot get enough of cats at SFO Museum!..",
    "wof:placetype": "custom"
  },
  "geometry": {"coordinates":[-122.386166,37.616356],"type":"Point"}
}
