{
  "type": "Feature",
  "properties": {
    "date:cessation_lower": "2020-10-20",
    "date:cessation_upper": "2020-10-20",
    "date:inception_lower": "2020-10-20",
    "date:inception_upper": "2020-10-20",
    "instagram:post": {
      "caption": {
        "body": "This is your last week to see “Extra ’O’!: African Barbershop and Hairdressing Signs.” Hand-painted barbershop and hairdressing signs are a vibrant form of African folk art in the form of advertising. Barbershops and hair salons may consist of a simple structure with a hand-painted sign nailed to its exterior. These signs are painted on wood or particle board by self-taught sign artists who work in studios or independently. Our exhibition displays a variety of colorful signs from the past forty years from West Africa and Kenya, where barbershops are called kinyozi. What is your favorite sign?   See “Extra ’O’!” African Barbershop and Hairdressing Signs” online at: http://bit.ly/Extrao",
        "excerpt": "This is your last week to see “Extra ’O’!: African Barbershop and Hairdressing Signs.” Hand-painted barbershop and hairdressing signs are a vibrant form of African folk art in the form of advertising.",
        "hashtags": [
          "ExtraO",
          "Africa",
          "barbershop",
          "barbershopsign",
          "MuseumFromHome"
        ]
      },
      "media_id": "0445ba309a6d21037137ae74d1db30f0ed05df11",
      "path": "media/posts/202010/122197591_384377769607105_7358694448175247658_n_17911365709519215.jpg",
      "perceptual_hash": "p:9f11301982bbbd3d",
      "taken": 1603207860,
      "taken_at": "Oct 20, 2020 3:31 pm"
    },
    "sfomuseum:placetype": "instagram",
    "wof:name": "This is your last week to see “Extra ’O’!: African Barbershop and Hairdressing Signs.” Hand-painted barbershop and hairdressing signs are a vibrant form of African folk art in the form of advertising...",
    "wof:placetype": "custom",
    "wof:placetype_alt": [
      "instagram"
    ]
  },
  "geometry": {"coordinates":[-122.386166,37.616356],"type":"Point"}
}
