{
  "type": "Feature",
  "properties": {
    "date:cessation_lower": "2021-03-10",
    "date:cessation_upper": "2021-03-10",
    "date:inception_lower": "2021-03-10",
    "date:inception_upper": "2021-03-10",
    "instagram:post": {
      "caption": {
        "body": "The Douglas DC-3 was arguably the most significant commercial airliner introduced prior to World War II. Conceived of by Arthur Raymond and introduced in 1936, the DC-3 incorporated numerous advancements, including a strong, highly streamlined, all-aluminum, semi-monocoque fuselage, and a low-drag wing design. The aircraft proved aerodynamically superior, highly reliable, safe, easy to maintain, and for the first time, enabled carriers to make a profit from passenger services. More than four hundred DC-3s were initially ordered by most major airlines. By 1940, nearly three million passengers had flown in DC-3s, and the aircraft had collectively logged over one hundred million miles. By the end of production, more than ten thousand commercial and military transport versions had been built, and a few are still flown today.  (We're not gonna lie: choosing images for this post was HARD. Check out additional images in our story!)",
        "excerpt": "The Douglas DC-3 was arguably the most significant commercial airliner introduced prior to World War II.",
        "hashtags": [
          "WingWednesday",
          "DC3",
          "avgeek"
        ]
      },
      "media_id": "bcd826cd913270df6c4aba7198fe605a3640f51b",
      "path": "media/posts/202103/158908897_286581699521445_8673093157468409870_n_17863871762362060.jpg",
      "perceptual_hash": "p:858712787e978b8b",
      "taken": 1615379040,
      "taken_at": "Mar 10, 2021 12:24 pm"
    },
    "sfomuseum:placetype": "instagram",
    "wof:name": "The Douglas DC-3 was arguably the most significant commercial airliner introduced prior to World War II...",
    "wof:placetype": "custom",
    "wof:placetype_alt": [
      "instagram"
    ]
  },
  "geometry": {"coordinates":[-122.386166,37.616356],"type":"Point"}
}
