{
  "type": "Feature",
  "properties": {
    "date:cessation_lower": "2018-12-05",
    "date:cessation_upper": "2018-12-05",
    "date:inception_lower": "2018-12-05",
    "date:inception_upper": "2018-12-05",
    "instagram:post": {
      "caption": {
        "body": "Sisters María (1922–90) and Juanita (b. 1927) Mendoza were born in Monterrey, Mexico. Although their sister Lydia Mendoza would become the most famous member of the family, Juanita and María also achieved acclaim performing and recording as the duet Las Hermanas Mendoza beginning in the 1950s. These recordings were licensed from Azteca Records. \"Down-Home Music: The Story of Arhoolie Records\" is on display,  post-security, in Terminal 2. http://bit.ly/StoryofArhoolie",
        "excerpt": "Sisters María (1922–90) and Juanita (b.",
        "hashtags": [
          "storyofarhoolie",
          "arhoolie",
          "arhoolierecords",
          "ChrisStrachwitz",
          "MariaMendoza",
          "JuanitaMendoza",
          "LydiaMendoza",
          "LasHermanas",
          "LasHermanasMendoza",
          "Mexico",
          "Mexican",
          "Tejano",
          "graphicdesign",
          "album",
          "albumcover",
          "music"
        ]
      },
      "file_hash": "156fe2523e85d8812eb40d7fe7454f7dd59a32852fb1ff005295b1e40e41923b",
      "media_id": "af6a4dc2cefdaf0961f262f9c2777f73396c79fe",
      "path": "media/other/724F9F93A970D1D5589C8CC0B7A567A0_video_dashinit_17946248668202461.mp4",
      "taken": 1544016180,
      "taken_at": "Dec 05, 2018 1:23 pm"
    },
    "sfomuseum:placetype": "instagram",
    "wof:name": "Sisters María (1922–90) and Juanita (b...",
    "wof:placetype": "custom"
  },
  "geometry": {"coordinates":[-122.386166,37.616356],"type":"Point"}
}
