{
  "type": "Feature",
  "properties": {
    "date:cessation_lower": "2017-05-15",
    "date:cessation_upper": "2017-05-15",
    "date:inception_lower": "2017-05-15",
    "date:inception_upper": "2017-05-15",
    "instagram:post": {
      "caption": {
        "body": "Happy Mother's Day! To all the moms traveling with children, we hope you have a wonderful trip!  Image:  TWA (Trans World Airlines), Sky Chief Service, 1951, Gift of TWA Clipped Wings International, Inc. 2002.113.201",
        "excerpt": "Happy Mother's Day!",
        "hashtags": [
          "Happymothersday",
          "mothersday",
          "twa",
          "avgeek",
          "aviationhistory",
          "paxex"
        ]
      },
      "media_id": "c71841644a586aa07c5619a921da06b0",
      "path": "photos/201705/c71841644a586aa07c5619a921da06b0.jpg",
      "perceptual_hash": "p:8d296e6f606698b6",
      "taken": 1494781860,
      "taken_at": "May 14, 2017, 5:11 PM"
    },
    "sfomuseum:placetype": "instagram",
    "wof:name": "Happy Mother's Day!..",
    "wof:placetype": "custom"
  },
  "geometry": {"coordinates":[-122.386166,37.616356],"type":"Point"}
}
