{
  "type": "Feature",
  "properties": {
    "date:cessation_lower": "2022-07-07",
    "date:cessation_upper": "2022-07-07",
    "date:inception_lower": "2022-07-07",
    "date:inception_upper": "2022-07-07",
    "instagram:post": {
      "caption": {
        "body": "Ozark Air Lines was founded in 1943 in Springfield, Missouri, and although service began in 1945, it was quickly halted as the Civil Aeronautics Board (CAB) had not issued them a license to operate. When another airline, Parks Air Lines, failed to commence operations, Ozark purchased the airline, received their certification, and began operating their routes in 1950. Flights from St. Louis to Chicago, Tulsa, and Memphis were on Douglas DC-3s acquired from Parks. Instead of repainting the DC-3s, Ozark took off the P and S from the aircraft and painted on OZ to the beginning.   By the end of the 1950s, the airline had rapidly expanded into 35 cities.  In 1966, Ozark entered the jet age and purchased several Douglas DC-9 aircraft, and added destinations to Denver, Indianapolis, Louisville, Washington, New York, Miami, Tampa, and Orlando. From 1978 to 1984, Ozark flew DC-9s almost exclusively as they phased out their older aircraft. In 1986, Ozark was purchased by Trans World Airlines (TWA).",
        "excerpt": "Ozark Air Lines was founded in 1943 in Springfield, Missouri, and although service began in 1945, it was quickly halted as the Civil Aeronautics Board (CAB) had not issued them a license to operate.",
        "hashtags": [
          "DefunctThursday",
          "Ozark",
          "AvGeek",
          "AviationHistory"
        ]
      },
      "media_id": "32f6884ef7bb8a16c59e2e7328ac3d8c5de3bfc2",
      "path": "media/posts/202207/292287181_1084354499134718_7700284908816683366_n_17948071571013079.jpg",
      "perceptual_hash": "p:ac93926ccb961cf1",
      "taken": 1657212660,
      "taken_at": "Jul 7, 2022, 4:51 PM"
    },
    "sfomuseum:placetype": "instagram",
    "wof:name": "Ozark Air Lines was founded in 1943 in Springfield, Missouri, and although service began in 1945, it was quickly halted as the Civil Aeronautics Board (CAB) had not issued them a license to operate...",
    "wof:placetype": "custom",
    "wof:placetype_alt": [
      "instagram"
    ]
  },
  "geometry": {"coordinates":[-122.386166,37.616356],"type":"Point"}
}
