{
  "type": "Feature",
  "properties": {
    "date:cessation_lower": "2017-10-16",
    "date:cessation_upper": "2017-10-16",
    "date:inception_lower": "2017-10-16",
    "date:inception_upper": "2017-10-16",
    "instagram:post": {
      "caption": {
        "body": "“Can I take a photo of your dog?” @thedogist, run by Elias Weiss Friedman has become an internet sensation. Friedman does what some would consider a dream job, walking around New York City taking photos of people’s dogs. In this charming and heartwarming documentary, we follow Friedman as his social media profile is taking off. See this documentary in full in our Video Arts Room, located pre-security in the International Terminal. http://bit.ly/2xKqZJR “If I had all the money, I’d probably travel with my camera and hang out with dogs. I’m doing it.”",
        "excerpt": "“Can I take a photo of your dog?” @thedogist, run by Elias Weiss Friedman has become an internet sensation.",
        "hashtags": [
          "dogs",
          "dogist",
          "dogsofinstagram",
          "dogsofinsta",
          "ilovedogs",
          "video",
          "documentary",
          "fineart",
          "docs",
          "newyork",
          "dog"
        ]
      },
      "file_hash": "3b800fcfcd5cab6fc199d99c3a7c6b383f2067f6a9d9bf3a9078cd26eae21675",
      "media_id": "8dccb5e606490cb31d38a45d65a6d02cd9f83bed",
      "path": "media/posts/201710/C042696F818EB8D2B68D3B1DFBC93194_video_dashinit_17903323636053443.mp4",
      "taken": 1508149200,
      "taken_at": "Oct 16, 2017 10:20 am"
    },
    "sfomuseum:placetype": "instagram",
    "wof:name": "“Can I take a photo of your dog?” @thedogist, run by Elias Weiss Friedman has become an internet sensation...",
    "wof:placetype": "custom"
  },
  "geometry": {"coordinates":[-122.386166,37.616356],"type":"Point"}
}
