{
  "type": "Feature",
  "properties": {
    "date:cessation_lower": "2016-05-31",
    "date:cessation_upper": "2016-05-31",
    "date:inception_lower": "2016-05-31",
    "date:inception_upper": "2016-05-31",
    "instagram:post": {
      "caption": {
        "hashtags": [
          "TravelTuesday"
        ]
      },
      "media_id": "273e1f40f1cdac6f2191ec4a631ac2a0",
      "path": "media/posts/201605/13256618_912217572220077_652489739_n_17848063741090809.jpg",
      "perceptual_hash": "p:be3ed8c493c91b84",
      "taken": 1464724860,
      "taken_at": "May 31, 2016, 8:01 PM"
    },
    "sfomuseum:placetype": "instagram",
    "wof:name": "..",
    "wof:placetype": "custom",
    "wof:placetype_alt": [
      "instagram"
    ]
  },
  "geometry": {"coordinates":[-122.386166,37.616356],"type":"Point"}
}
