{
  "type": "Feature",
  "properties": {
    "instagram:post": {
      "caption": {
        "body": "Radio is one of the great technological triumphs of the 20th century. Envisioned for wireless communication, radio became a universal mass media and captivated audiences around the world. For the first time in history, populations separated by thousands of miles could be notified of important news at a moment’s notice. In the United States, radio programming shaped popular culture and strengthened national unity. Millions of Americans gathered around their radios every night during the 1930s and 1940s to hear live comedies, serials, musical performances, and news reports. Radio was the most exciting and accessible technology of its time and galvanized the imagination of countless listeners. What are your favorite memories about the radio? \"On the Radio\" is on display, post-security, in Terminal 3. http://bit.ly/RadioSFO",
        "excerpt": "Radio is one of the great technological triumphs of the 20th century.",
        "hashtags": [
          "radioSFO", 
          "ontheradio", 
          "radio", 
          "radios", 
          "wireless", 
          "vintage", 
          "antique", 
          "vintageradios", 
          "transistorradio", 
          "portableradio", 
          "retroradio", 
          "retro", 
          "1950s", 
          "1960s"
        ]
      },
      "location": "San Francisco International Airport (SFO)",
      "media_id": "1e04e1e73a121a2dc9dbdfef82d69fbf",
      "path": "photos/201808/1e04e1e73a121a2dc9dbdfef82d69fbf.jpg",
      "taken": 1534997142,
      "taken_at": "2018-08-23T04:05:42+00:00"
    },
    "sfomuseum:placetype": "instagram",
    "wof:name": "Radio is one of the great technological triumphs of the 20th century...",
    "wof:placetype": "custom"
  },
  "geometry": {"coordinates":[-122.386166,37.616356],"type":"Point"}
}
