{
  "type": "Feature",
  "properties": {
    "instagram:post": {
      "caption": {
        "hashtags": [
          "JoseffOfHollywood", 
          "costumejewelry", 
          "tiara", 
          "crown"
        ]
      },
      "media_id": "b15818cda6f2715e50af114e14aeb5bf",
      "path": "photos/201506/b15818cda6f2715e50af114e14aeb5bf.jpg",
      "taken": 1434583441,
      "taken_at": "2015-06-17T23:24:01+00:00"
    },
    "sfomuseum:placetype": "instagram",
    "wof:name": "Instagram message #%!d(string=b15818cda6f2715e50af114e14aeb5bf)",
    "wof:placetype": "custom"
  },
  "geometry": {"coordinates":[-122.386166,37.616356],"type":"Point"}
}
