{
  "type": "Feature",
  "properties": {
    "date:cessation_lower": "2016-07-06",
    "date:cessation_upper": "2016-07-06",
    "date:inception_lower": "2016-07-06",
    "date:inception_upper": "2016-07-06",
    "instagram:post": {
      "caption": {
        "body": "During the mid-1920s to ‘30s, women’s fashions changed dramatically. Inspired by film stars, women now wore eye makeup and lipstick, cut their hair in short bobs, and smoked openly in public for the first time. The handbags of this era reflect these changing times. Purses tended to be more glamorous than practical. In the evenings, women wore sleeveless dresses with low cut backs and sported ultra compact purses, which allowed them to carry just a few essentials. Easy to dance with, these lightweight, tiny bags dangled from the wrist, complementing a woman’s attire. Vanity purses had built-in mirrors with powder or rouge compacts and a full tassel fringe that cleverly concealed a lipstick compartment. Lipstick containers also dangled from the top of purses. Some contained inset watches, lighters, scent bottles, and compartments for cigarettes. They came in a variety of shapes, from figurative to triangular, round, and square. Many of these bags were made in France from newly introduced plastics, such as celluloid and Bakelite, and were lined with rayon, the first synthetic fabric.",
        "excerpt": "During the mid-1920s to ‘30s, women’s fashions changed dramatically.",
        "hashtags": [
          "EssentialPurses"
        ]
      },
      "media_id": "f00472b630e1434fd24c13b27f06b83f",
      "path": "media/posts/201607/13562008_251206098596751_209990185_n_17857841005048185.jpg",
      "perceptual_hash": "p:a5cbb4393f20df10",
      "taken": 1467798300,
      "taken_at": "Jul 6, 2016, 9:45 AM"
    },
    "sfomuseum:placetype": "instagram",
    "wof:name": "During the mid-1920s to ‘30s, women’s fashions changed dramatically...",
    "wof:placetype": "custom"
  },
  "geometry": {"coordinates":[-122.386166,37.616356],"type":"Point"}
}
