{
  "type": "Feature",
  "properties": {
    "date:cessation_lower": "2020-12-21",
    "date:cessation_upper": "2020-12-21",
    "date:inception_lower": "2020-12-21",
    "date:inception_upper": "2020-12-21",
    "instagram:post": {
      "caption": {
        "body": "#OnThisDay in 1969, the first widebody jet landed at San Francisco International Airport. In advance of the regularly scheduled widebody service that would begin in 1970, Pan American World Airways brought its new Boeing 747 “jumbo jet” to SFO to display the new class of airliner for the people of the Bay Area. SFO had reconfigured and equipped its gating areas to handle the new airliner with its top-mounted cockpit and partial upper level passenger deck.   Image: San Francisco International Airport (SFO), Pan American World Airways, Boeing 747, 12/21/1969.  SFO Museum Collection. 1997.52.084.055",
        "excerpt": "#OnThisDay in 1969, the first widebody jet landed at San Francisco International Airport.",
        "hashtags": [
          "MuseumFromHome",
          "SFOHistory",
          "PanAm",
          "avgeek"
        ]
      },
      "media_id": "bcf41eb27a8a9b80f6ca6dca5386e0d1191a6f75",
      "path": "media/posts/202012/131917117_177489294108346_7794096504733283268_n_18021906289288707.jpg",
      "perceptual_hash": "p:cb96c9966299d649",
      "taken": 1608553980,
      "taken_at": "Dec 21, 2020, 12:33 PM"
    },
    "sfomuseum:placetype": "instagram",
    "wof:name": "#OnThisDay in 1969, the first widebody jet landed at San Francisco International Airport...",
    "wof:placetype": "custom",
    "wof:placetype_alt": [
      "instagram"
    ]
  },
  "geometry": {"coordinates":[-122.386166,37.616356],"type":"Point"}
}
