{
  "type": "Feature",
  "properties": {
    "instagram:post": {
      "caption": {
        "body": "\"Children behave so well you hardly believe they're yours\" \"Travel with children becomes a pleasure instead of a problem when you go by Flagship. That's because most Flagship journeys are over before children become tired, bored and cross the way they do from driving all day or from other tedious surface transportation.\" In 1955, The Saturday Evening Post printed this American Airlines advertisement which featured well behaved children traveling on a speedy Flagship journey.  Image: American Airlines advertisement, The Saturday Evening Post, 1955. Gift of Barnaby Conrad III. 2001.038.165",
        "hashtags": [
          "avgeek", 
          "avationgeek", 
          "aviation", 
          "aviationhistory", 
          "vintageaviation", 
          "history", 
          "avhistory", 
          "aviationgeeks", 
          "avgeeks", 
          "saturdayeveningpost", 
          "americanairlines", 
          "flagship", 
          "travelwithkids", 
          "1955"
        ]
      },
      "location": "San Francisco International Airport (SFO)",
      "media_id": "91e445c2105070c3d41c7a80b74f4917",
      "path": "photos/201712/91e445c2105070c3d41c7a80b74f4917.jpg",
      "taken": 1513836603,
      "taken_at": "2017-12-21T06:10:03+00:00"
    },
    "sfomuseum:placetype": "instagram",
    "wof:name": "Instagram message #%!d(string=91e445c2105070c3d41c7a80b74f4917)",
    "wof:placetype": "custom"
  },
  "geometry": {"coordinates":[-122.386166,37.616356],"type":"Point"}
}
