{
  "type": "Feature",
  "properties": {
    "instagram:post": {
      "caption": {
        "body": "The Aviation Museum and Library is closed today to observe Martin Luther King, Jr. Day. All other exhibitions around the airport are still open! For more information on our exhibitions check out our website: http://www.flysfo.com/museum/exhibitions"
      },
      "location": "San Francisco International Airport (SFO)",
      "media_id": "becf3e29a7ab9b475b653c907552514f",
      "path": "photos/201601/becf3e29a7ab9b475b653c907552514f.jpg",
      "taken": 1453166320,
      "taken_at": "2016-01-19T01:18:40+00:00"
    },
    "sfomuseum:placetype": "instagram",
    "wof:name": "Instagram message #%!d(string=becf3e29a7ab9b475b653c907552514f)",
    "wof:placetype": "custom"
  },
  "geometry": {"coordinates":[-122.386166,37.616356],"type":"Point"}
}
