{
  "type": "Feature",
  "properties": {
    "date:cessation_lower": "2016-01-18",
    "date:cessation_upper": "2016-01-18",
    "date:inception_lower": "2016-01-18",
    "date:inception_upper": "2016-01-18",
    "instagram:post": {
      "caption": {
        "body": "The Aviation Museum and Library is closed today to observe Martin Luther King, Jr. Day. All other exhibitions around the airport are still open! For more information on our exhibitions check out our website: http://www.flysfo.com/museum/exhibitions",
        "excerpt": "The Aviation Museum and Library is closed today to observe Martin Luther King, Jr. Day."
      },
      "media_id": "becf3e29a7ab9b475b653c907552514f",
      "path": "media/posts/201601/12552305_153222465052630_401723844_n_17844048586121610.jpg",
      "perceptual_hash": "p:abb56624495d466b",
      "taken": 1453137480,
      "taken_at": "Jan 18, 2016, 5:18 PM"
    },
    "sfomuseum:placetype": "instagram",
    "wof:name": "The Aviation Museum and Library is closed today to observe Martin Luther King, Jr. Day...",
    "wof:placetype": "custom"
  },
  "geometry": {"coordinates":[-122.386166,37.616356],"type":"Point"}
}
