{
  "type": "Feature",
  "properties": {
    "date:cessation_lower": "2013-08-26",
    "date:cessation_upper": "2013-08-26",
    "date:inception_lower": "2013-08-26",
    "date:inception_upper": "2013-08-26",
    "instagram:post": {
      "caption": {
        "hashtags": [
          "plastics"
        ]
      },
      "media_id": "1001b6fe6dbc5d56c95c571c278e82ea",
      "path": "photos/201308/1001b6fe6dbc5d56c95c571c278e82ea.jpg",
      "perceptual_hash": "p:948e75607e998d5a",
      "taken": 1377551016,
      "taken_at": "2013-08-26T21:03:36+00:00"
    },
    "sfomuseum:placetype": "instagram",
    "wof:name": "..",
    "wof:placetype": "custom"
  },
  "geometry": {"coordinates":[-122.386166,37.616356],"type":"Point"}
}
