{
  "type": "Feature",
  "properties": {
    "date:cessation_lower": "2019-01-11",
    "date:cessation_upper": "2019-01-11",
    "date:inception_lower": "2019-01-11",
    "date:inception_upper": "2019-01-11",
    "instagram:post": {
      "caption": {
        "body": "Our graphic designers go through multiple design iterations of exhibition labels. Laid out for design review in our office are those for our upcoming exhibition, \"Reflections in Wood — Surfboards and Shapers\". These exhibition labels will fit into our G side cases, pre-security, in the International Terminal. . . .",
        "excerpt": "Our graphic designers go through multiple design iterations of exhibition labels.",
        "hashtags": [
          "surfers",
          "shapers",
          "behindthescenes",
          "graphicdesign",
          "graphics",
          "design",
          "labels"
        ]
      },
      "location": "San Francisco International Airport (SFO)",
      "media_id": "bc437ffb10c64741cd5c3e362d6ae738",
      "path": "photos/201901/bc437ffb10c64741cd5c3e362d6ae738.jpg",
      "perceptual_hash": "p:88c12d92ef7d2aa5",
      "taken": 1547169958,
      "taken_at": "2019-01-11T01:25:58+00:00"
    },
    "sfomuseum:placetype": "instagram",
    "wof:name": "Our graphic designers go through multiple design iterations of exhibition labels...",
    "wof:placetype": "custom"
  },
  "geometry": {"coordinates":[-122.386166,37.616356],"type":"Point"}
}
