{
  "type": "Feature",
  "properties": {
    "instagram:post": {
      "caption": {
        "body": "“Time, Turn, and Light” by #WoodyDeOthello depicts ambiguous sets of hands interacting with everyday objects such as clocks, a flashlight, a candle, and a doorknob. These objects are rendered in an uncanny fashion with a sense of play, emotional intuition, and surrealism that provokes viewers to reimagine themselves and the way they view the world around them.  “Time, Turn, and Light” by #WoodyDeOthello online at: https://bit.ly/3kiuVFq",
        "excerpt": "“Time, Turn, and Light” by #WoodyDeOthello depicts ambiguous sets of hands interacting with everyday objects such as clocks, a flashlight, a candle, and a doorknob.",
        "hashtags": [
          "MuseumFromHome", 
          "publicart", 
          "sculpture", 
          "surrealism"
        ]
      },
      "media_id": "6fed5cf156562e7434aa62db0fe023cb",
      "path": "photos/202009/6fed5cf156562e7434aa62db0fe023cb.jpg",
      "taken": 1600828057,
      "taken_at": "2020-09-23T02:27:37+00:00"
    },
    "sfomuseum:placetype": "instagram",
    "wof:name": "“Time, Turn, and Light” by #WoodyDeOthello depicts ambiguous sets of hands interacting with everyday objects such as clocks, a flashlight, a candle, and a doorknob...",
    "wof:placetype": "custom"
  },
  "geometry": {"coordinates":[-122.386166,37.616356],"type":"Point"}
}
