{
  "type": "Feature",
  "properties": {
    "date:cessation_lower": "2024-05-13",
    "date:cessation_upper": "2024-05-13",
    "date:inception_lower": "2024-05-13",
    "date:inception_upper": "2024-05-13",
    "instagram:post": {
      "caption": {
        "body": "Africa’s rich cultural heritage encompasses a tremendous range of music, musical instruments, and performing arts. Music is enjoyed recreationally, and permeates celebrations, festivals, processions, masquerades, ceremonies, rituals, royal occasions, and community events. The variety of instruments made and used in Africa ranges from drums, xylophones, and zithers, to electric guitars and keyboards. Many traditional musical instruments appear utilitarian, while others are embellished with geometric, anthropomorphic, and zoomorphic features, allowing them to simultaneously serve as works of art.   The musical instruments on view are from the Fowler Museum at UCLA from the West and Central African countries of Liberia, Republic of Côte d’Ivoire, Nigeria, Cameroon, Gabon, and Democratic Republic of the Congo.  “The Art of the African Instrument” is on display, post-security, in Harvey Milk Terminal 1 and online at: https://bit.ly/African-Instruments  Yoruba batá drummer  1951 Photograph by William Bascom (1912–81) Oyo State, Nigeria © Phoebe A. Hearst Museum of Anthropology and the Regents of the University of California 15-31827, R2024.0204.001",
        "excerpt": "Africa’s rich cultural heritage encompasses a tremendous range of music, musical instruments, and performing arts.",
        "hashtags": [
          "ArtoftheAfricanInstrument",
          "AfricanInstruments",
          "UCLA"
        ]
      },
      "media_id": "e570f4dd13702d947ba1c5d77a39f16726556cc4",
      "path": "media/other/442471645_938515668285363_5734213733920685697_n_17897002845003521.jpg",
      "perceptual_hash": "p:b68c4d25769607d9",
      "taken": 1715614980,
      "taken_at": "May 13, 2024 3:43 pm"
    },
    "sfomuseum:placetype": "instagram",
    "wof:name": "Africa’s rich cultural heritage encompasses a tremendous range of music, musical instruments, and performing arts...",
    "wof:placetype": "custom"
  },
  "geometry": {"coordinates":[-122.386166,37.616356],"type":"Point"}
}
