{
  "type": "Feature",
  "properties": {
    "date:cessation_lower": "2021-02-03",
    "date:cessation_upper": "2021-02-03",
    "date:inception_lower": "2021-02-03",
    "date:inception_upper": "2021-02-03",
    "instagram:post": {
      "caption": {
        "body": "The all-metal, twin-engine Boeing 247 was a revolutionary airliner when it entered into service with United AIr Lines in 1933. Often referred to as the first modern airliner, it featured numerous advancements including all-aluminum, semi-monocoque construction, wing flaps, autopilot, and semi-retractable landing gear. Seventy-five of the aircraft were eventually built, with most going to the United Air Lines’ fleet and operating on its \"Mainline\" transcontinental route.  Although advanced for its time, the Model 247 accommodated only ten passengers, which made it less economical to operate than larger capacity airliners, particularly the more fuel-efficient, fourteen-seat Douglas DC-2, introduced a year later.",
        "excerpt": "The all-metal, twin-engine Boeing 247 was a revolutionary airliner when it entered into service with United AIr Lines in 1933.",
        "hashtags": [
          "WingWednesday",
          "avgeek",
          "aviationhistory",
          "boeing",
          "1930s"
        ]
      },
      "media_id": "89056a3c24343adda53a82ee49ad15ba12f92953",
      "path": "media/posts/202102/145623103_3976717352379501_6121991351618051232_n_17883432686058132.jpg",
      "perceptual_hash": "p:a35c40a37dc29f2d",
      "taken": 1612352700,
      "taken_at": "Feb 3, 2021, 11:45 AM"
    },
    "sfomuseum:placetype": "instagram",
    "wof:name": "The all-metal, twin-engine Boeing 247 was a revolutionary airliner when it entered into service with United AIr Lines in 1933...",
    "wof:placetype": "custom"
  },
  "geometry": {"coordinates":[-122.386166,37.616356],"type":"Point"}
}
