{
  "type": "Feature",
  "properties": {
    "instagram:post": {
      "caption": {
        "body": "It is difficult to imagine modern Western civilization without the context of ancient Rome, the Eternal City. Rome was the world’s largest city from circa 100 BCE to 400 CE, and the cultural and political center of an empire lasting for more than a millennium. Arguably, Rome resonates most potently in its enduring architectural forms and public monuments, which were first widely disseminated in a very familiar method—through tourism. \"All Roads Lead to Rome: 17th–19th Century Architectural Souvenirs from the Collection of Piraneseum\" displays a collection of souvenirs from the \"Grand Tour\", a trip that all “young lords” took to better understand their world and prepare for their role in it.",
        "excerpt": "It is difficult to imagine modern Western civilization without the context of ancient Rome, the Eternal City.",
        "hashtags": [
          "Rome:", 
          "Piraneseum\",", 
          "AllRoadsRome", 
          "GrandTour", 
          "Italy", 
          "travel"
        ]
      },
      "location": "San Francisco International Airport (SFO)",
      "media_id": "f44dd4cbc86ec7367861088a279eb724",
      "path": "photos/201702/f44dd4cbc86ec7367861088a279eb724.jpg",
      "taken": 1486008132,
      "taken_at": "2017-02-02T04:02:12+00:00"
    },
    "sfomuseum:placetype": "instagram",
    "wof:name": "It is difficult to imagine modern Western civilization without the context of ancient Rome, the Eternal City...",
    "wof:placetype": "custom"
  },
  "geometry": {"coordinates":[-122.386166,37.616356],"type":"Point"}
}
