{
  "type": "Feature",
  "properties": {
    "date:cessation_lower": "2022-04-21",
    "date:cessation_upper": "2022-04-21",
    "date:inception_lower": "2022-04-21",
    "date:inception_upper": "2022-04-21",
    "instagram:post": {
      "caption": {
        "body": "Continental Airlines began as Varney Speed Lines in 1934. It originally used symbols and slogans to promote its claim to be the “Fastest Airline In The World.” Renamed in 1937 as Continental Airlines, the carrier introduced a red, white, and blue eagle symbol with its block letter logotype in 1944. When Continental became an international carrier in 1968, it launched a new corporate identity created by Saul Bass \u0026 Associates. An oval, defined in spreading jet contrails, and an updated typeface communicated its new global status and market position. “Contrails Red” became the predominant color, while gold, orange, and black were retained as secondary colors. In 2011, Continental merged with United Airlines.",
        "excerpt": "Continental Airlines began as Varney Speed Lines in 1934.",
        "hashtags": [
          "DefunctThursday",
          "avgeek",
          "aviationhistory",
          "ContinentalAirlines"
        ]
      },
      "media_id": "c0764b53627a8181a81d70d2656abdda6a65e5ec",
      "path": "media/posts/202204/278938810_725405551820574_6784077548436111874_n_17935774555976471.jpg",
      "perceptual_hash": "p:856cfa3395c4623b",
      "taken": 1650559800,
      "taken_at": "Apr 21, 2022, 4:50 PM"
    },
    "sfomuseum:placetype": "instagram",
    "wof:name": "Continental Airlines began as Varney Speed Lines in 1934...",
    "wof:placetype": "custom"
  },
  "geometry": {"coordinates":[-122.386166,37.616356],"type":"Point"}
}
