{
  "type": "Feature",
  "properties": {
    "date:cessation_lower": "2017-10-04",
    "date:cessation_upper": "2017-10-04",
    "date:inception_lower": "2017-10-04",
    "date:inception_upper": "2017-10-04",
    "instagram:post": {
      "caption": {
        "body": "We're getting ready for our newest exhibition in our design lab. What's going on, you ask? We're going to display some model planes! Can you guess what airline we'll be showcasing?",
        "excerpt": "We're getting ready for our newest exhibition in our design lab.",
        "hashtags": [
          "behindthescenes",
          "alexandercalder",
          "sneakpeek",
          "avgeek",
          "avationgeek",
          "aviation",
          "aviationhistory",
          "aviationlovers",
          "modelairplane",
          "vintageaviation",
          "history",
          "avhistory",
          "aviationgeeks",
          "instaplane",
          "flying",
          "plane",
          "flight",
          "airline",
          "avgeeks",
          "aviation4u",
          "aviationdaily"
        ]
      },
      "media_id": "e1daa4324de763ae4e6633e4a0196554",
      "path": "media/posts/201710/22277554_391338084618316_3769630583097917440_n_17896092568067658.jpg",
      "perceptual_hash": "p:ba3ecce1f10c1c1e",
      "taken": 1507107000,
      "taken_at": "Oct 04, 2017 8:50 am"
    },
    "sfomuseum:placetype": "instagram",
    "wof:name": "We're getting ready for our newest exhibition in our design lab...",
    "wof:placetype": "custom",
    "wof:placetype_alt": [
      "instagram"
    ]
  },
  "geometry": {"coordinates":[-122.386166,37.616356],"type":"Point"}
}
