{
  "type": "Feature",
  "properties": {
    "instagram:post": {
      "caption": {
        "body": "We're getting ready for our newest exhibition in our design lab. What's going on, you ask? We're going to display some model planes! Can you guess what airline we'll be showcasing?",
        "excerpt": "We're getting ready for our newest exhibition in our design lab.",
        "hashtags": [
          "behindthescenes", 
          "alexandercalder", 
          "sneakpeek", 
          "avgeek", 
          "avationgeek", 
          "aviation", 
          "aviationhistory", 
          "aviationlovers", 
          "modelairplane", 
          "vintageaviation", 
          "history", 
          "avhistory", 
          "aviationgeeks", 
          "instaplane", 
          "flying", 
          "plane", 
          "flight", 
          "airline", 
          "avgeeks", 
          "aviation4u", 
          "aviationdaily"
        ]
      },
      "media_id": "e1daa4324de763ae4e6633e4a0196554",
      "path": "photos/201710/e1daa4324de763ae4e6633e4a0196554.jpg",
      "taken": 1507135829,
      "taken_at": "2017-10-04T16:50:29+00:00"
    },
    "sfomuseum:placetype": "instagram",
    "wof:name": "We're getting ready for our newest exhibition in our design lab...",
    "wof:placetype": "custom"
  },
  "geometry": {"coordinates":[-122.386166,37.616356],"type":"Point"}
}
