{
  "type": "Feature",
  "properties": {
    "date:cessation_lower": "2017-06-18",
    "date:cessation_upper": "2017-06-18",
    "date:inception_lower": "2017-06-18",
    "date:inception_upper": "2017-06-18",
    "instagram:post": {
      "caption": {
        "body": "#Onthisday in 1971, Southwest Airlines began operation in Texas. The “Love Bird” service out of Dallas Love Field offered twelve daily round-trip flights from Dallas to Houston and six round-trip flights from Dallas to San Antonio on Boeing 737-200s. The airline inaugurated service to SFO in 1982. Have you ever flown on Southwest Airlines?  Image: Southwest Airlines, San Francisco International Airport (SFO), International Terminal with Southwest Airlines Boeing 737-200, 1985. SFO Museum Collection. 1993.07.39",
        "excerpt": "#Onthisday in 1971, Southwest Airlines began operation in Texas.",
        "hashtags": [
          "avgeek",
          "aviationhistory",
          "southwest",
          "southwestairline",
          "flysouthwest",
          "Texas",
          "Dallas",
          "SanAntonio",
          "Houston",
          "LoveBird",
          "boeing",
          "737",
          "otdih"
        ]
      },
      "media_id": "a01ce4d9ea2cb0c76f6e9e421aefa8be",
      "path": "photos/201706/a01ce4d9ea2cb0c76f6e9e421aefa8be.jpg",
      "perceptual_hash": "p:c40c3bf1132b9ef1",
      "taken": 1497810387,
      "taken_at": "2017-06-18T18:26:27+00:00"
    },
    "sfomuseum:placetype": "instagram",
    "wof:name": "#Onthisday in 1971, Southwest Airlines began operation in Texas...",
    "wof:placetype": "custom"
  },
  "geometry": {"coordinates":[-122.386166,37.616356],"type":"Point"}
}
