{
  "type": "Feature",
  "properties": {
    "date:cessation_lower": "2016-12-18",
    "date:cessation_upper": "2016-12-18",
    "date:inception_lower": "2016-12-18",
    "date:inception_upper": "2016-12-18",
    "instagram:post": {
      "caption": {
        "body": "Our online database contains a selection of ticket jackets from our collection. Beginning in the 1930s, airline tickets have consisted of long, rectangular strips of paper, or coupons, for each leg of a flight. Tickets usually came in a jacket that incorporated the name and logo of the carrier, along with aircraft and service promotions. A flight packet with information about the airline, the flight, and the destination was often included. http://bit.ly/2h0zFQe",
        "excerpt": "Our online database contains a selection of ticket jackets from our collection."
      },
      "media_id": "9ab882df72879a112f65a4f805d6da73",
      "path": "media/posts/201612/15538756_241821159573312_4514450634610573312_n_17868552283031055.jpg",
      "perceptual_hash": "p:b0e63092ce9bce93",
      "taken": 1482059220,
      "taken_at": "Dec 18, 2016 11:07 am"
    },
    "sfomuseum:placetype": "instagram",
    "wof:name": "Our online database contains a selection of ticket jackets from our collection...",
    "wof:placetype": "custom",
    "wof:placetype_alt": [
      "instagram"
    ]
  },
  "geometry": {"coordinates":[-122.386166,37.616356],"type":"Point"}
}
