{
  "type": "Feature",
  "properties": {
    "instagram:post": {
      "caption": {
        "body": "Our online database contains a selection of ticket jackets from our collection. Beginning in the 1930s, airline tickets have consisted of long, rectangular strips of paper, or coupons, for each leg of a flight. Tickets usually came in a jacket that incorporated the name and logo of the carrier, along with aircraft and service promotions. A flight packet with information about the airline, the flight, and the destination was often included. http://bit.ly/2h0zFQe",
        "excerpt": "Our online database contains a selection of ticket jackets from our collection."
      },
      "location": "San Francisco International Airport (SFO)",
      "media_id": "9ab882df72879a112f65a4f805d6da73",
      "path": "photos/201612/9ab882df72879a112f65a4f805d6da73.jpg",
      "taken": 1482088078,
      "taken_at": "2016-12-18T19:07:58+00:00"
    },
    "sfomuseum:placetype": "instagram",
    "wof:name": "Our online database contains a selection of ticket jackets from our collection...",
    "wof:placetype": "custom"
  },
  "geometry": {"coordinates":[-122.386166,37.616356],"type":"Point"}
}
