{
  "type": "Feature",
  "properties": {
    "date:cessation_lower": "2015-10-28",
    "date:cessation_upper": "2015-10-28",
    "date:inception_lower": "2015-10-28",
    "date:inception_upper": "2015-10-28",
    "instagram:post": {
      "caption": {
        "hashtags": [
          "TravelTuesday"
        ]
      },
      "location": "SFO Museum",
      "media_id": "7b2b3e2b734b9ab0c56f61a869ab75d1",
      "path": "photos/201510/7b2b3e2b734b9ab0c56f61a869ab75d1.jpg",
      "perceptual_hash": "p:eee4b581d61ec243",
      "taken": 1445973960,
      "taken_at": "Oct 27, 2015, 7:26 PM"
    },
    "sfomuseum:placetype": "instagram",
    "wof:name": "..",
    "wof:placetype": "custom"
  },
  "geometry": {"coordinates":[-122.386166,37.616356],"type":"Point"}
}
