{
  "type": "Feature",
  "properties": {
    "date:cessation_lower": "2021-06-07",
    "date:cessation_upper": "2021-06-07",
    "date:inception_lower": "2021-06-07",
    "date:inception_upper": "2021-06-07",
    "instagram:post": {
      "caption": {
        "body": "The Astronauts formed in Boulder, Colorado, in the late 1950s. Originally named The Stormtroopers after bass guitarist Jon “Stormy” Patterson, they changed their name to reflect the NASA Mercury space program and its astronaut crew, which included Colorado native Scott Carpenter. In 1962, The Astronauts met with Steven Sholes, RCA Records’ A\u0026R Director, at the Hollywood Plaza Hotel. At this stage, the group was primarily a rock ‘n’ roll quintet and had no experience playing surf music. During the interview, Sholes received a call from a record distributor who was excited by sales of the Beach Boys’ vocal surf album \"Surfin’ USA.\" According to drummer Jim Gallagher, Sholes “covered the phone and asked if we played surf music, and naturally we said yes!”   The Fender Jazzmaster on display was owned by The Astronauts’ rhythm guitarist Bob Demmon and was likely from a matching set of guitars given to the band as an endorsement from Fender.   See more of “Surf’s Up! Instrumental Rock ‘n’ Roll,” online, where you can also find a link to the exhibition playlist on Spotify. Link in bio.",
        "excerpt": "The Astronauts formed in Boulder, Colorado, in the late 1950s.",
        "hashtags": [
          "InstrumentalSurf",
          "surfrock",
          "surfmusic",
          "theastronauts",
          "fender",
          "fenderjazzmaster"
        ]
      },
      "media_id": "86852d190812446ac622f9013074d38dde6fdc8c",
      "path": "media/posts/202106/197395945_1424980514532257_448879389901937019_n_17899493819047943.jpg",
      "perceptual_hash": "p:ce74927d42ea0d72",
      "taken": 1623083820,
      "taken_at": "Jun 7, 2021, 4:37 PM"
    },
    "sfomuseum:placetype": "instagram",
    "wof:name": "The Astronauts formed in Boulder, Colorado, in the late 1950s...",
    "wof:placetype": "custom",
    "wof:placetype_alt": [
      "instagram"
    ]
  },
  "geometry": {"coordinates":[-122.386166,37.616356],"type":"Point"}
}
