{
  "type": "Feature",
  "properties": {
    "date:cessation_lower": "2019-11-22",
    "date:cessation_upper": "2019-11-22",
    "date:inception_lower": "2019-11-22",
    "date:inception_upper": "2019-11-22",
    "instagram:post": {
      "caption": {
        "body": "Today marks the eighty-fourth anniversary of Pan American Airways’ daring transpacific endeavor. Crowds of people watched from around the Bay Area as the Martin M-130 “China Clipper” lifted off from the waters of San Francisco Bay and strained into the sky threading its way under and over two partially built bridges. It soared through the Golden Gate and slowly disappeared from land as the ship’s crew of seven set course for the Far East and opened the age of regular transpacific oceanic commercial air service. The aircraft is shown here on its cradle being prepped for its launch from Alameda.  Learn more about early transpacific aviation in \"China Clipper\" on display, pre-security, in the Aviation Museum and Library. http://bit.ly/chinaclipper  Image: Pan American Airways, Martin M-130 China Clipper, Alameda, 1935, Gift of Beatrice H. Springer, 1995.35.25 ",
        "excerpt": "Today marks the eighty-fourth anniversary of Pan American Airways’ daring transpacific endeavor.",
        "hashtags": [
          "ChinaClipper",
          "aviationhistory",
          "avgeek",
          "panam",
          "onthisday",
          "SFhistory"
        ]
      },
      "location": "San Francisco International Airport (SFO)",
      "media_id": "c6d6e5b1e2eef2edd9951ebed4067566",
      "path": "photos/201911/c6d6e5b1e2eef2edd9951ebed4067566.jpg",
      "perceptual_hash": "p:b1cecd1907a6a738",
      "taken": 1574455468,
      "taken_at": "2019-11-22T20:44:28+00:00"
    },
    "sfomuseum:placetype": "instagram",
    "wof:name": "Today marks the eighty-fourth anniversary of Pan American Airways’ daring transpacific endeavor...",
    "wof:placetype": "custom"
  },
  "geometry": {"coordinates":[-122.386166,37.616356],"type":"Point"}
}
