{
  "type": "Feature",
  "properties": {
    "instagram:post": {
      "caption": {
        "body": "Did you know that New York Airways offered helicopter service directly to the Pan American building? In 1965, New York Airways scheduled seventeen daily flights from John F. Kennedy Airport right to the heart of Manhattan, a flight that only took seven minutes. Fares were $7 one way and $10 round trip. Did you ever fly on New York Airways' helicopter service?  Image: Pan American World Airways Building, New York City, 1960s. Gift of the Pan Am Association. 2000.058.0466.023",
        "hashtags": [
          "avgeek", 
          "avationgeek", 
          "aviation", 
          "aviationhistory", 
          "vintageaviation", 
          "history", 
          "avhistory", 
          "aviationgeeks", 
          "avgeeks", 
          "Omniflight", 
          "helicopter", 
          "Clipper", 
          "JFKAirport", 
          "Manhattan", 
          "panambuilding", 
          "nyc"
        ]
      },
      "location": "San Francisco International Airport (SFO)",
      "media_id": "73ccefd8e969c8803eaeaa8e4dbec690",
      "path": "photos/201801/73ccefd8e969c8803eaeaa8e4dbec690.jpg",
      "taken": 1515715352,
      "taken_at": "2018-01-12T00:02:32+00:00"
    },
    "sfomuseum:placetype": "instagram",
    "wof:name": "Instagram message #%!d(string=73ccefd8e969c8803eaeaa8e4dbec690)",
    "wof:placetype": "custom"
  },
  "geometry": {"coordinates":[-122.386166,37.616356],"type":"Point"}
}
