{
  "type": "Feature",
  "properties": {
    "date:cessation_lower": "2018-05-06",
    "date:cessation_upper": "2018-05-06",
    "date:inception_lower": "2018-05-06",
    "date:inception_upper": "2018-05-06",
    "instagram:post": {
      "caption": {
        "body": "Since 2004, Brooklyn-based artist Rachel Sussman has been traveling the globe in search of continuously living organisms that are at least two thousand years old, which she photographs and chronicles in her series, \"The Oldest Living Things in the World\". Shown here are 2,000-3,000 year old stromalites in Western Australia; 5,500 year old Antarctic moss; and a 9,550 year old spruce gran picea tree in Sweden.  See \"The Oldest Living Things in the World\" by Rachel Sussman (@_sussman_) on display pre-security in Terminal 3. http://bit.ly/2qWJSTC",
        "excerpt": "Since 2004, Brooklyn-based artist Rachel Sussman has been traveling the globe in search of continuously living organisms that are at least two thousand years old, which she photographs and chronicles in her series, \"The Oldest Living Things in the World\".",
        "hashtags": [
          "RachelSussman",
          "photography",
          "brooklyn",
          "organisms",
          "photographs",
          "airportart",
          "oldestlivingthings",
          "nature"
        ]
      },
      "media_id": "6ce4a3f3ed7ce0da9f1baec41cafe21ead901b3b",
      "path": "media/posts/201805/30890539_411600379310890_8161683660613877760_n_17924171605091121.jpg",
      "perceptual_hash": "p:e4f379e422199a66",
      "taken": 1525605780,
      "taken_at": "May 6, 2018, 11:23 AM"
    },
    "sfomuseum:placetype": "instagram",
    "wof:name": "Since 2004, Brooklyn-based artist Rachel Sussman has been traveling the globe in search of continuously living organisms that are at least two thousand years old, which she photographs and chronicles in her series, \"The Oldest Living Things in the World\"...",
    "wof:placetype": "custom"
  },
  "geometry": {"coordinates":[-122.386166,37.616356],"type":"Point"}
}
