{
  "type": "Feature",
  "properties": {
    "date:cessation_lower": "2018-01-09",
    "date:cessation_upper": "2018-01-09",
    "date:inception_lower": "2018-01-09",
    "date:inception_upper": "2018-01-09",
    "instagram:post": {
      "caption": {
        "body": "Prior to Prohibition and the Volstead Act of 1919, gambling was a mainstay of the saloon. Patrons played card games such as poker, wagered on bagatelle and billiard games, and bet on the outcome of coin-operated, mechanical horse racing and strength testing devices. Payout slot machines simplified gambling and functioned automatically. Played by an individual or in a group, slot machines dispensed rewards for winning bets with minimal oversight by the owner. Early slot machines incorporated a vertically mounted gaming wheel marked by segmented colors. Freestanding models in ornately carved oak and walnut cabinets stood over five feet high and were aesthetically impressive devices. When space was at a premium, saloon owners installed machines similar to the larger slots atop their bars. This countertop model by Watling features an optional music box and is decorated with characters from the Brownies cartoon series by Palmer Cox (1840–1924). \"The Automatic Age: Coin-Operated Machines\" is on display, pre-security, in the International Terminal. http://bit.ly/CoinOperated",
        "excerpt": "Prior to Prohibition and the Volstead Act of 1919, gambling was a mainstay of the saloon.",
        "hashtags": [
          "coinoperated",
          "TheAutomaticAge",
          "coinop",
          "vintage",
          "antique",
          "gamemachines",
          "slotmachine",
          "slotmachines"
        ]
      },
      "media_id": "fa5460f984ae93828058ad158eb488ab",
      "path": "photos/201801/fa5460f984ae93828058ad158eb488ab.jpg",
      "perceptual_hash": "p:c3bd3530d2d28dca",
      "taken": 1515430920,
      "taken_at": "Jan 8, 2018, 5:02 PM"
    },
    "sfomuseum:placetype": "instagram",
    "wof:name": "Prior to Prohibition and the Volstead Act of 1919, gambling was a mainstay of the saloon...",
    "wof:placetype": "custom"
  },
  "geometry": {"coordinates":[-122.386166,37.616356],"type":"Point"}
}
