{
  "type": "Feature",
  "properties": {
    "date:cessation_lower": "2021-07-07",
    "date:cessation_upper": "2021-07-07",
    "date:inception_lower": "2021-07-07",
    "date:inception_upper": "2021-07-07",
    "instagram:post": {
      "caption": {
        "body": "Douglas developed the DC-8 jetliner during the mid-1950s as a competitive design to Boeing’s 707 jetliner. Built in Douglas’ new Long Beach, California, plant, the first aircraft was rolled out and flown in 1958. It comprised a swept-wing, four-jet-engine layout similar to that of the Boeing 707 with a capacity for up to 179 passengers. Powered by four Pratt \u0026 Whitney J57 turbojet engines, the DC-8 was capable of cruising speeds reaching 600 miles per hour, and with a transcontinental range of almost 4,000 miles, it could easily fly nonstop from San Francisco to New York in just over five hours. The transcontinental flight time for the piston-powered Douglas DC-7 it replaced was around eight hours. The DC-8 was also pressurized, which enabled it to fly high in the stratosphere, above most weather conditions.   On September 18, 1959, the DC-8 entered service with Delta Air Lines and United Air Lines, nearly a year after the introduction of the Boeing 707. Although initially not as successful as the 707, the DC-8 had a more viable lifespan within the commercial aviation industry. Upgraded variants were introduced during the 1960s, including a stretched version that was the largest capacity airliner until the introduction of the widebody Boeing 747 in 1970.",
        "excerpt": "Douglas developed the DC-8 jetliner during the mid-1950s as a competitive design to Boeing’s 707 jetliner."
      },
      "media_id": "e0daa952c66d540303e4a42e2a8b0751a73a3d6f",
      "path": "media/posts/202107/210893774_2718498438440377_4972440482159138340_n_18086744341263074.jpg",
      "perceptual_hash": "p:fe118a4cb37a0df0",
      "taken": 1625675340,
      "taken_at": "Jul 7, 2021, 4:29 PM"
    },
    "sfomuseum:placetype": "instagram",
    "wof:name": "Douglas developed the DC-8 jetliner during the mid-1950s as a competitive design to Boeing’s 707 jetliner...",
    "wof:placetype": "custom"
  },
  "geometry": {"coordinates":[-122.386166,37.616356],"type":"Point"}
}
