{
  "type": "Feature",
  "properties": {
    "date:cessation_lower": "2022-05-16",
    "date:cessation_upper": "2022-05-16",
    "date:inception_lower": "2022-05-16",
    "date:inception_upper": "2022-05-16",
    "instagram:post": {
      "caption": {
        "body": "Get a glimpse into San Francisco’s Outer Mission neighborhood through Kari Orvik’s ongoing photography series, “Geneva”, centered on the corner of Mission Street and Geneva Avenue. A resident of the Mission for over twenty years, Orvik has developed relationships with other residents and small business owners in the neighborhood, photographing them both on the street corner and in her studio.   Over time, the photographs have become a document of the neighborhood, parts of which remain and parts of which are no longer there. Her work is often site-specific and engages ideas of presence and absence; exploring what we hold onto, what we let go, and where we place value.  See “Geneva” by Kari Orvik on display in the Ruth Kadish Gallery, located in the post-security connector between Terminal 2 and Terminal 3, and online at: https://bit.ly/3MjrKM8",
        "excerpt": "Get a glimpse into San Francisco’s Outer Mission neighborhood through Kari Orvik’s ongoing photography series, “Geneva”, centered on the corner of Mission Street and Geneva Avenue.",
        "hashtags": [
          "KariOrvik",
          "Geneva",
          "photography",
          "SFHistory",
          "SFmission"
        ]
      },
      "media_id": "8459fd0e7cc0058172eea4822161b32c29a71903",
      "path": "media/posts/202205/280951733_517551976766264_7387562774337038987_n_17966335693626876.jpg",
      "perceptual_hash": "p:afc0956dd03fc093",
      "taken": 1652695560,
      "taken_at": "May 16, 2022, 10:06 AM"
    },
    "sfomuseum:placetype": "instagram",
    "wof:name": "Get a glimpse into San Francisco’s Outer Mission neighborhood through Kari Orvik’s ongoing photography series, “Geneva”, centered on the corner of Mission Street and Geneva Avenue...",
    "wof:placetype": "custom",
    "wof:placetype_alt": [
      "instagram"
    ]
  },
  "geometry": {"coordinates":[-122.386166,37.616356],"type":"Point"}
}
