{
  "type": "Feature",
  "properties": {
    "date:cessation_lower": "2018-02-13",
    "date:cessation_upper": "2018-02-13",
    "date:inception_lower": "2018-02-13",
    "date:inception_upper": "2018-02-13",
    "instagram:post": {
      "caption": {
        "body": "Air New Zealand started as TEAL (Tasman Empire Airways Limited) in 1940. TEAL was created as a joint venture between BOAC (British Overseas Airways Corporation), Qantas Empire Airways, and the New Zealand government. Service was launched from Auckland, New Zealand, to Sydney, Australia, in April of 1940, with the Short S. 30 flying boat \"Aotearoa\" (the Maori name for New Zealand). In 1953, TEAL became owned jointly by the New Zealand and Australian governments. In 1961, the New Zealand government bought out the Australian government share of TEAL, and, in 1965, the company changed its name to Air New Zealand. Have you ever been to New Zealand?  Image:  Air New Zealand postcard, c. 1989. Gift of the William Hough Collection. 2008.055.136",
        "excerpt": "Air New Zealand started as TEAL (Tasman Empire Airways Limited) in 1940.",
        "hashtags": [
          "TravelTuesday",
          "newzealand",
          "teal",
          "BOAC",
          "british",
          "sydney",
          "auckland",
          "Aotearoa",
          "avgeek",
          "avationgeek",
          "aviation",
          "aviationhistory",
          "vintageaviation",
          "history",
          "avhistory",
          "aviationgeeks",
          "avgeeks"
        ]
      },
      "media_id": "c768a16c16988972008022c3e02af802",
      "path": "photos/201802/c768a16c16988972008022c3e02af802.jpg",
      "perceptual_hash": "p:823d7fd2a0499be4",
      "taken": 1518549906,
      "taken_at": "2018-02-13T19:25:06+00:00"
    },
    "sfomuseum:placetype": "instagram",
    "wof:name": "Air New Zealand started as TEAL (Tasman Empire Airways Limited) in 1940...",
    "wof:placetype": "custom"
  },
  "geometry": {"coordinates":[-122.386166,37.616356],"type":"Point"}
}
