{
  "type": "Feature",
  "properties": {
    "date:cessation_lower": "2017-05-11",
    "date:cessation_upper": "2017-05-11",
    "date:inception_lower": "2017-05-11",
    "date:inception_upper": "2017-05-11",
    "instagram:post": {
      "caption": {
        "body": "The semi-nomadic Manchu conquerors who founded the Qing dynasty (1644–1911) embraced much of the cultural and artistic practices of the Han Chinese. However, they rejected female foot binding, in which young girls’ feet were bound to keep them extremely small. Foot binding conveyed a woman’s prominent place in Han society and made her more desirable to men. Instead of forcibly reshaping the foot, elite Manchu women conveyed their prestige by wearing platform shoes. The upper parts of the shoes were often elaborately embroidered with a variety of motifs and made of colorful silk or satin brocade. The platform shoes produced a stilted gait that slightly emulated the desirable “lotus walk” of women with bound feet. Such shoes also helped to keep feet and clothing hems clean and dry.  See more shoes from all over the world in \"Stepping Out: Shoes in World Culture\" on display, pre-security, in the International Terminal. http://bit.ly/ShoesinCulture #ShoesinCulture  Manchu platform shoes  late 19th–early 20th century China fabric, embroidery thread  Courtesy of Sally Yu Leung L2017.0107.007a,b",
        "excerpt": "The semi-nomadic Manchu conquerors who founded the Qing dynasty (1644–1911) embraced much of the cultural and artistic practices of the Han Chinese.",
        "hashtags": [
          "shoes",
          "shoestagram",
          "shoeswag",
          "shoesoftheday",
          "shoedesign",
          "instashoes",
          "shoefashion",
          "shoeslover",
          "platformshoes"
        ]
      },
      "media_id": "12d0043a6241b544fbb178de4431e01b",
      "path": "photos/201705/12d0043a6241b544fbb178de4431e01b.jpg",
      "perceptual_hash": "p:a305ad6e2f21f652",
      "taken": 1494443760,
      "taken_at": "May 10, 2017, 7:16 PM"
    },
    "sfomuseum:placetype": "instagram",
    "wof:name": "The semi-nomadic Manchu conquerors who founded the Qing dynasty (1644–1911) embraced much of the cultural and artistic practices of the Han Chinese...",
    "wof:placetype": "custom"
  },
  "geometry": {"coordinates":[-122.386166,37.616356],"type":"Point"}
}
