{
  "type": "Feature",
  "properties": {
    "instagram:post": {
      "caption": {
        "body": "In 1965, Pacific Air Lines leased two Boeing 727 jet airliners and placed orders for four more. Emphasizing its entry into the jet age, the following year the airline streamlined its thunderbird logo and announced the introduction of new station agent uniforms with light-blue blazers and bright pink stewardess uniforms designed by Saks Fifth Avenue. \"Catch Our Style: California Regional Airlines 1950s–1980s\" features more objects from Pacific Air Lines and other California regional airlines. The exhibition is on display pre-security, in the Aviation Museum and Library in the International Terminal. The Aviation Museum and Library is open from Sunday through Friday, 10am to 4:30pm. Do you remembering flying on Pacific Air Lines?"
      },
      "location": "San Francisco International Airport (SFO)",
      "media_id": "3b44d7df11d0821ed5e2edb995e92992",
      "path": "photos/201511/3b44d7df11d0821ed5e2edb995e92992.jpg",
      "taken": 1447880248,
      "taken_at": "2015-11-18T20:57:28+00:00"
    },
    "sfomuseum:placetype": "instagram",
    "wof:name": "Instagram message #%!d(string=3b44d7df11d0821ed5e2edb995e92992)",
    "wof:placetype": "custom"
  },
  "geometry": {"coordinates":[-122.386166,37.616356],"type":"Point"}
}
