{
  "type": "Feature",
  "properties": {
    "date:cessation_lower": "2017-12-15",
    "date:cessation_upper": "2017-12-15",
    "date:inception_lower": "2017-12-15",
    "date:inception_upper": "2017-12-15",
    "instagram:post": {
      "caption": {
        "body": "Nick Albertson’s work draws focus on the mass-produced objects that occupy the corners of our daily lives. Working with single-use materials, Albertson produces photographs that borrow from the language of abstraction. Straws, napkins, rubber bands, and other items—often consigned to the edges of our desks or the depths of our kitchen drawers—are repurposed and foregrounded in his large-scale images. \"One Hundred Count\" by Nick Albertson is on display, pre-security, in Terminal 3. http://bit.ly/2AGWsNb",
        "excerpt": "Nick Albertson’s work draws focus on the mass-produced objects that occupy the corners of our daily lives.",
        "hashtags": [
          "nickalbertson",
          "fineart",
          "fineartphotography",
          "photography",
          "photos",
          "photographer",
          "abstration",
          "singleuse",
          "rubberbands",
          "napkins"
        ]
      },
      "media_id": "635189b8d8e1d7f3c9e018d2a8e75700ab5f9557",
      "path": "media/posts/201712/25006754_520976121612668_6837348353366294528_n_17888870428187413.jpg",
      "perceptual_hash": "p:83996a5af61ecf10",
      "taken": 1513341720,
      "taken_at": "Dec 15, 2017, 12:42 PM"
    },
    "sfomuseum:placetype": "instagram",
    "wof:name": "Nick Albertson’s work draws focus on the mass-produced objects that occupy the corners of our daily lives...",
    "wof:placetype": "custom"
  },
  "geometry": {"coordinates":[-122.386166,37.616356],"type":"Point"}
}
