{
  "type": "Feature",
  "properties": {
    "date:cessation_lower": "2014-12-10",
    "date:cessation_upper": "2014-12-10",
    "date:inception_lower": "2014-12-10",
    "date:inception_upper": "2014-12-10",
    "instagram:post": {
      "caption": {
        "hashtags": [
          "WhenArtRocked",
          "BigBrotherandTheHoldingCompany",
          "YouAreHear"
        ]
      },
      "media_id": "35924ad970ce809be74578d32df9463c",
      "path": "photos/201412/35924ad970ce809be74578d32df9463c.jpg",
      "perceptual_hash": "p:96d33d3a174e2552",
      "taken": 1418214360,
      "taken_at": "Dec 10, 2014, 12:26 PM"
    },
    "sfomuseum:placetype": "instagram",
    "wof:name": "..",
    "wof:placetype": "custom"
  },
  "geometry": {"coordinates":[-122.386166,37.616356],"type":"Point"}
}
