{
  "type": "Feature",
  "properties": {
    "date:cessation_lower": "2019-04-25",
    "date:cessation_upper": "2019-04-25",
    "date:inception_lower": "2019-04-25",
    "date:inception_upper": "2019-04-25",
    "instagram:post": {
      "caption": {
        "body": "One of the first uses of aluminum in rotor blades was in the Hiller XH-44 “Hiller-copter”, designed and built by Stanley Hiller, Jr. (1924–2006) in 1944 at the age of nineteen. A 1:8 scale model of a Hiller XH-44 is shown here. Prior helicopter rotor blade designs, such as on the Sikorsky VS-300, were primarily constructed of wood and had a slight amount of flexibility. The XH-44 featured two rigid, counter-rotating rotor blades designed to cancel out the torque caused by a single main rotor, which in turn eliminated the need for a tail rotor to counteract the spinning of the helicopter. They required the rigidity of aluminum in order to prevent contact at high revolutions, potentially causing severe damage to both. By the 1960s, most helicopter rotors were made out of aluminum, often combined with other materials. In recent decades, helicopter rotors have been constructed of composite materials. \"Aluminum: The Miracle Metal of Aviation\" is on display, pre-security, in the Aviation Museum and Library in the International Terminal. http://bit.ly/AviationAluminum",
        "excerpt": "One of the first uses of aluminum in rotor blades was in the Hiller XH-44 “Hiller-copter”, designed and built by Stanley Hiller, Jr. (1924–2006) in 1944 at the age of nineteen.",
        "hashtags": [
          "AviationAluminum",
          "Aluminum",
          "design",
          "industrialdesign",
          "avgeek",
          "helicopter",
          "modelaircraft"
        ]
      },
      "media_id": "17087f5b8ac33cb2c9a0ff300cfd84b3",
      "path": "photos/201904/17087f5b8ac33cb2c9a0ff300cfd84b3.jpg",
      "perceptual_hash": "p:f14689397cc3272e",
      "taken": 1556235132,
      "taken_at": "2019-04-25T23:32:12+00:00"
    },
    "sfomuseum:placetype": "instagram",
    "wof:name": "One of the first uses of aluminum in rotor blades was in the Hiller XH-44 “Hiller-copter”, designed and built by Stanley Hiller, Jr. (1924–2006) in 1944 at the age of nineteen...",
    "wof:placetype": "custom"
  },
  "geometry": {"coordinates":[-122.386166,37.616356],"type":"Point"}
}
