{
  "type": "Feature",
  "properties": {
    "date:cessation_lower": "2013-07-29",
    "date:cessation_upper": "2013-07-29",
    "date:inception_lower": "2013-07-29",
    "date:inception_upper": "2013-07-29",
    "instagram:post": {
      "caption": {
        "body": "Photography owes a lot to early #plastics. Film from cellulose nitrate was first produced in 1889, and in 1900, Kodak introduced the Brownie, the first point-and-shoot portable camera.",
        "excerpt": "Photography owes a lot to early #plastics."
      },
      "media_id": "c55fb066ba00c0f807d03e982099beea",
      "path": "media/other/11272975_798173576964634_1065801497_n_17842345312062499.jpg",
      "perceptual_hash": "p:eaad91918252ba6f",
      "taken": 1375099020,
      "taken_at": "Jul 29, 2013 11:57 am"
    },
    "sfomuseum:placetype": "instagram",
    "wof:name": "Photography owes a lot to early #plastics...",
    "wof:placetype": "custom",
    "wof:placetype_alt": [
      "instagram"
    ]
  },
  "geometry": {"coordinates":[-122.386166,37.616356],"type":"Point"}
}
