{
  "type": "Feature",
  "properties": {
    "date:cessation_lower": "2023-10-06",
    "date:cessation_upper": "2023-10-06",
    "date:inception_lower": "2023-10-06",
    "date:inception_upper": "2023-10-06",
    "instagram:post": {
      "caption": {
        "body": "Established 100 years ago in 1923, Czech Airlines is one of the five oldest airlines in the world. The airline commenced operations in October of 1923. In the 1970s, the airline’s livery featured the letters OK on its tail as is Czech Airlines two letter IATA designation is OK. Additionally, the beginning of each aircraft registered with the Czech Republic begins with OK.   The airline currently operates service to three destinations with two Airbus A320-200s.",
        "excerpt": "Established 100 years ago in 1923, Czech Airlines is one of the five oldest airlines in the world.",
        "hashtags": [
          "AvGeek",
          "CzechAirlines"
        ]
      },
      "media_id": "9fce8b6094d76541d0051751f8e32ee0d3e3a5fc",
      "path": "media/other/387159971_784896093647322_1311271052963078747_n_18100534351350538.jpg",
      "perceptual_hash": "p:d6c049f8d43bb274",
      "taken": 1696602120,
      "taken_at": "Oct 06, 2023 2:22 pm"
    },
    "sfomuseum:placetype": "instagram",
    "wof:name": "Established 100 years ago in 1923, Czech Airlines is one of the five oldest airlines in the world...",
    "wof:placetype": "custom"
  },
  "geometry": {"coordinates":[-122.386166,37.616356],"type":"Point"}
}
