{
  "type": "Feature",
  "properties": {
    "date:cessation_lower": "2014-08-25",
    "date:cessation_upper": "2014-08-25",
    "date:inception_lower": "2014-08-25",
    "date:inception_upper": "2014-08-25",
    "instagram:post": {
      "caption": {
        "hashtags": [
          "RemainOverNight",
          "PanAm"
        ]
      },
      "media_id": "e35c70402d04f56b87caa728d107c70b",
      "path": "photos/201408/e35c70402d04f56b87caa728d107c70b.jpg",
      "perceptual_hash": "p:a9cbce769330f086",
      "taken": 1408998590,
      "taken_at": "2014-08-25T20:29:50+00:00"
    },
    "sfomuseum:placetype": "instagram",
    "wof:name": "..",
    "wof:placetype": "custom"
  },
  "geometry": {"coordinates":[-122.386166,37.616356],"type":"Point"}
}
