{
  "type": "Feature",
  "properties": {
    "instagram:post": {
      "caption": {
        "body": "These Pan American service pins feature the company's new distinctive blue globe logo. In order, 1-year, 3-year, 5-year, 10-year, 15-year, 20-year, 25-year, 25-year, and 30-year pin."
      },
      "location": "SFO Museum",
      "media_id": "2306bd7ca7f08a623e3fd72a66023251",
      "path": "photos/201605/2306bd7ca7f08a623e3fd72a66023251.jpg",
      "taken": 1462570851,
      "taken_at": "2016-05-06T21:40:51+00:00"
    },
    "sfomuseum:placetype": "instagram",
    "wof:name": "Instagram message #%!d(string=2306bd7ca7f08a623e3fd72a66023251)",
    "wof:placetype": "custom"
  },
  "geometry": {"coordinates":[-122.386166,37.616356],"type":"Point"}
}
