{
  "type": "Feature",
  "properties": {
    "instagram:post": {
      "caption": {
        "body": "#OnThisDay in 1924, the Huff Daland Dusters, based in Macon, Georgia, began one of the earliest known commercial aerial crop-dusting operations in America. In 1928, when C.E. Woolman took over the company, he renamed it Delta Air Service, a predecessor to the contemporary Delta Air Lines. Delta is one of the five remaining legacy air carriers in the U.S., along with Alaska, American, Hawaiian, and United. Have you ever flown on Delta Air Lines?  Image: Delta Air Lines, travel agent sign, 1950s. Gift of Thomas G. Dragges. 2011.051.372 ",
        "hashtags": [
          "delta", 
          "deltaairlines", 
          "HuffDalandDusters", 
          "map", 
          "routemap"
        ]
      },
      "location": "San Francisco International Airport",
      "media_id": "3778e6f902826f8321d1f357b6c1154a",
      "path": "photos/201905/3778e6f902826f8321d1f357b6c1154a.jpg",
      "taken": 1559253554,
      "taken_at": "2019-05-30T21:59:14+00:00"
    },
    "sfomuseum:placetype": "instagram",
    "wof:name": "Instagram message #%!d(string=3778e6f902826f8321d1f357b6c1154a)",
    "wof:placetype": "custom"
  },
  "geometry": {"coordinates":[-122.386166,37.616356],"type":"Point"}
}
