{
  "type": "Feature",
  "properties": {
    "date:cessation_lower": "2023-05-19",
    "date:cessation_upper": "2023-05-19",
    "date:inception_lower": "2023-05-19",
    "date:inception_upper": "2023-05-19",
    "instagram:post": {
      "caption": {
        "body": "Our newest exhibition, “Recollections… from the Unknown Museum” is now on display in Terminal 2! An “exploration into America’s brain,” the Unknown Museum was founded by artist, curator, and archivist Mickey McGowan (b. 1946) and artist Dickens “44” Bascom (b. 1944) in a former automotive radiator shop at 39 Corte Madera Avenue in Mill Valley. McGowan and Bascom created art and installations in a singular, large room that allowed for mass assemblages and the “assault of the objects” on one’s senses. According to McGowan, “curating the museum allowed me to present my ‘two-cents-worth’ reactions to postwar American culture, its fads, trends, joys, and ‘important’ moments.” Formally opened in December 1974, the Unknown Museum became a center of local creativity, rotating its own exhibitions, displaying the work of other artists, and hosting concerts and themed events.  The Unknown Museum continues as a private museum and lending archives. This exhibition presents a sampling of the fantastic art and object installations from various locations of the Unknown Museum.   See “Recollections… from the Unknown Museum” on display post-security in Terminal 2. https://bit.ly/UnknownMuseum",
        "excerpt": "Our newest exhibition, “Recollections… from the Unknown Museum” is now on display in Terminal 2!",
        "hashtags": [
          "UnknownMuseum",
          "MickeyMcGowan",
          "BayArea",
          "BayAreaHistory"
        ]
      },
      "media_id": "200e14dc7ab23c63a8b652e9cd130f3eaf0dd088",
      "path": "media/posts/202305/348261998_634336371538808_3008399222753714545_n_17931038741680150.jpg",
      "perceptual_hash": "p:c70aead56c31d06e",
      "taken": 1684497540,
      "taken_at": "May 19, 2023, 11:59 AM"
    },
    "sfomuseum:placetype": "instagram",
    "wof:name": "Our newest exhibition, “Recollections… from the Unknown Museum” is now on display in Terminal 2!..",
    "wof:placetype": "custom",
    "wof:placetype_alt": [
      "instagram"
    ]
  },
  "geometry": {"coordinates":[-122.386166,37.616356],"type":"Point"}
}
