{
  "type": "Feature",
  "properties": {
    "date:cessation_lower": "2023-03-15",
    "date:cessation_upper": "2023-03-15",
    "date:inception_lower": "2023-03-15",
    "date:inception_upper": "2023-03-15",
    "instagram:post": {
      "caption": {
        "body": "#Onthisday in 1927 the City and County of San Francisco signed a lease with the Mills Estate for 150 acres to use as an airport. The lease, signed by Ogden L. Mills, grandson of the Gold Rush banker Darius Ogden Mills, allocated 150 acres of pastureland located twelve miles south of San Francisco’s Civic Center. The terms were for three years at the rate of $1,500 per year for this “temporary and experimental” municipal airport. This original tract of land remains part of SFO today.",
        "excerpt": "#Onthisday in 1927 the City and County of San Francisco signed a lease with the Mills Estate for 150 acres to use as an airport.",
        "hashtags": [
          "SFHistory",
          "SFOHistory",
          "AvGeek"
        ]
      },
      "media_id": "4d2a636d6b8151cad7d4088144f31ead424153c3",
      "path": "media/posts/202303/335502677_1268203750742643_7898473070396903405_n_18000735190723247.jpg",
      "perceptual_hash": "p:aa95c9dae49aa469",
      "taken": 1678874580,
      "taken_at": "Mar 15, 2023, 10:03 AM"
    },
    "sfomuseum:placetype": "instagram",
    "wof:name": "#Onthisday in 1927 the City and County of San Francisco signed a lease with the Mills Estate for 150 acres to use as an airport...",
    "wof:placetype": "custom"
  },
  "geometry": {"coordinates":[-122.386166,37.616356],"type":"Point"}
}
