{
  "type": "Feature",
  "properties": {
    "date:cessation_lower": "2018-10-31",
    "date:cessation_upper": "2018-10-31",
    "date:inception_lower": "2018-10-31",
    "date:inception_upper": "2018-10-31",
    "instagram:post": {
      "caption": {
        "body": "For generations of Californians and visitors to the Golden State, the Nut Tree Restaurant in Vacaville, California was a popular destination. Located along Interstate Highway 80 between San Francisco and Sacramento, it made an ideal roadside stop for motorists. Many visitors, however, reached the Nut Tree by air. In addition to restaurants and shops, it had its own airport that was a favorite among private pilots. In 1996, after 75 years of successful operation, the Nut Tree Restaurant closed. The airfield, donated to Solano County in 1973, continues operating as the Nut Tree Airport. Have you ever been to the Nut Tree Airport?  Image: Nut Tree Airport poster, 1969. Gift of Zoe Dell Lantis Nutter. 1997.75.24",
        "excerpt": "For generations of Californians and visitors to the Golden State, the Nut Tree Restaurant in Vacaville, California was a popular destination.",
        "hashtags": [
          "NutTree",
          "California",
          "Vacaville",
          "generalaviation",
          "NutTreeRestaurant",
          "SanFrancisco",
          "airfield",
          "solonocounty"
        ]
      },
      "media_id": "bab6cb87783b951cf780ade653227d3c",
      "path": "photos/201810/bab6cb87783b951cf780ade653227d3c.jpg",
      "perceptual_hash": "p:ed64c6ce92709399",
      "taken": 1540953343,
      "taken_at": "2018-10-31T02:35:43+00:00"
    },
    "sfomuseum:placetype": "instagram",
    "wof:name": "For generations of Californians and visitors to the Golden State, the Nut Tree Restaurant in Vacaville, California was a popular destination...",
    "wof:placetype": "custom"
  },
  "geometry": {"coordinates":[-122.386166,37.616356],"type":"Point"}
}
