{
  "type": "Feature",
  "properties": {
    "instagram:post": {
      "caption": {
        "body": "This 1750s microscope is one of only nine known to be by Alexis Magny",
        "excerpt": "This 1750s microscope is one of only nine known to be by Alexis Magny"
      },
      "media_id": "d461c4f70e7a3a750cb9a1de7ca402db",
      "path": "photos/201206/d461c4f70e7a3a750cb9a1de7ca402db.jpg",
      "taken": 1339794343,
      "taken_at": "2012-06-15T21:05:43+00:00"
    },
    "sfomuseum:placetype": "instagram",
    "wof:name": "This 1750s microscope is one of only nine known to be by Alexis Magny..",
    "wof:placetype": "custom"
  },
  "geometry": {"coordinates":[-122.386166,37.616356],"type":"Point"}
}
