{
  "type": "Feature",
  "properties": {
    "date:cessation_lower": "2012-06-15",
    "date:cessation_upper": "2012-06-15",
    "date:inception_lower": "2012-06-15",
    "date:inception_upper": "2012-06-15",
    "instagram:post": {
      "caption": {
        "body": "This 1750s microscope is one of only nine known to be by Alexis Magny",
        "excerpt": "This 1750s microscope is one of only nine known to be by Alexis Magny"
      },
      "media_id": "d461c4f70e7a3a750cb9a1de7ca402db",
      "path": "media/posts/201206/11201560_1832564453635793_1755767914_n_17842253791062499.jpg",
      "perceptual_hash": "p:859362fc724f1d68",
      "taken": 1339765500,
      "taken_at": "Jun 15, 2012, 1:05 PM"
    },
    "sfomuseum:placetype": "instagram",
    "wof:name": "This 1750s microscope is one of only nine known to be by Alexis Magny..",
    "wof:placetype": "custom"
  },
  "geometry": {"coordinates":[-122.386166,37.616356],"type":"Point"}
}
