{
  "type": "Feature",
  "properties": {
    "instagram:post": {
      "caption": {
        "body": "Do you remember this sign? It was located on the roadway approach to San Francisco International Airport and read “Welcome to San Francisco - Mayor Joseph L. Alioto.” Image: San Francisco International Airport (SFO), signage, 1970. SFO Museum Collection. 2011.032.2104",
        "excerpt": "Do you remember this sign?",
        "hashtags": [
          "ThrowbackThursday", 
          "TBT", 
          "SFOHistory", 
          "SFO", 
          "paxex", 
          "avgeek", 
          "avationgeek", 
          "aviation", 
          "aviationhistory", 
          "aviationlovers", 
          "vintageaviation", 
          "history", 
          "avhistory", 
          "aviationgeeks", 
          "avgeeks", 
          "SanFrancisco"
        ]
      },
      "media_id": "d46f9002c5a436103c10693e38cfd244",
      "path": "photos/201709/d46f9002c5a436103c10693e38cfd244.jpg",
      "taken": 1504806399,
      "taken_at": "2017-09-07T17:46:39+00:00"
    },
    "sfomuseum:placetype": "instagram",
    "wof:name": "Do you remember this sign?..",
    "wof:placetype": "custom"
  },
  "geometry": {"coordinates":[-122.386166,37.616356],"type":"Point"}
}
