{
  "type": "Feature",
  "properties": {
    "date:cessation_lower": "2017-09-07",
    "date:cessation_upper": "2017-09-07",
    "date:inception_lower": "2017-09-07",
    "date:inception_upper": "2017-09-07",
    "instagram:post": {
      "caption": {
        "body": "Do you remember this sign? It was located on the roadway approach to San Francisco International Airport and read “Welcome to San Francisco - Mayor Joseph L. Alioto.” Image: San Francisco International Airport (SFO), signage, 1970. SFO Museum Collection. 2011.032.2104",
        "excerpt": "Do you remember this sign?",
        "hashtags": [
          "ThrowbackThursday",
          "TBT",
          "SFOHistory",
          "SFO",
          "paxex",
          "avgeek",
          "avationgeek",
          "aviation",
          "aviationhistory",
          "aviationlovers",
          "vintageaviation",
          "history",
          "avhistory",
          "aviationgeeks",
          "avgeeks",
          "SanFrancisco"
        ]
      },
      "media_id": "d46f9002c5a436103c10693e38cfd244",
      "path": "media/posts/201709/21480573_1388663497853966_2855859153954406400_n_17885519602102637.jpg",
      "perceptual_hash": "p:d4807a6a6a3b3db4",
      "taken": 1504777560,
      "taken_at": "Sep 7, 2017, 9:46 AM"
    },
    "sfomuseum:placetype": "instagram",
    "wof:name": "Do you remember this sign?..",
    "wof:placetype": "custom"
  },
  "geometry": {"coordinates":[-122.386166,37.616356],"type":"Point"}
}
