{
  "type": "Feature",
  "properties": {
    "date:cessation_lower": "2015-08-05",
    "date:cessation_upper": "2015-08-05",
    "date:inception_lower": "2015-08-05",
    "date:inception_upper": "2015-08-05",
    "instagram:post": {
      "caption": {
        "hashtags": [
          "womeninaviation",
          "wiaw",
          "avgeek"
        ]
      },
      "media_id": "3e31b24a5f68748d2f4b5c685ad32f4e",
      "path": "media/posts/201508/11373872_670556499745788_771497227_n_17842089487062499.jpg",
      "perceptual_hash": "p:88b7334ece315396",
      "taken": 1438800120,
      "taken_at": "Aug 5, 2015, 6:42 PM"
    },
    "sfomuseum:placetype": "instagram",
    "wof:name": "..",
    "wof:placetype": "custom"
  },
  "geometry": {"coordinates":[-122.386166,37.616356],"type":"Point"}
}
