{
  "type": "Feature",
  "properties": {
    "instagram:post": {
      "caption": {
        "hashtags": [
          "womeninaviation", 
          "wiaw", 
          "avgeek"
        ]
      },
      "location": "San Francisco International Airport (SFO)",
      "media_id": "3e31b24a5f68748d2f4b5c685ad32f4e",
      "path": "photos/201508/3e31b24a5f68748d2f4b5c685ad32f4e.jpg",
      "taken": 1438828920,
      "taken_at": "2015-08-06T02:42:00+00:00"
    },
    "sfomuseum:placetype": "instagram",
    "wof:name": "Instagram message #%!d(string=3e31b24a5f68748d2f4b5c685ad32f4e)",
    "wof:placetype": "custom"
  },
  "geometry": {"coordinates":[-122.386166,37.616356],"type":"Point"}
}
