{
  "type": "Feature",
  "properties": {
    "date:cessation_lower": "2018-03-13",
    "date:cessation_upper": "2018-03-13",
    "date:inception_lower": "2018-03-13",
    "date:inception_upper": "2018-03-13",
    "instagram:post": {
      "caption": {
        "body": "These two cats, imitating the gods Daikoku and Ebisu, are playing Go, a strategy board game invented in China more than 2,500 years ago. One cat holds a wish-granting mallet and mimics Daikoku; the other holds a sea bream, a symbol of good luck, and mimics Ebisu, two of the Seven Gods of Good Fortune in Japan.  This exhibition was made possible by a generous loan from Mingei International Museum. See more #BeckoningCats from across the centuries in \"Maneki Neko: Japanese Beckoning Cat\", on display post-security, in Terminal 2. http://bit.ly/BeckoningCats",
        "excerpt": "These two cats, imitating the gods Daikoku and Ebisu, are playing Go, a strategy board game invented in China more than 2,500 years ago.",
        "hashtags": [
          "beckoningcats",
          "manekineko",
          "catsofinstagram",
          "cats",
          "neko",
          "meow",
          "mewseum",
          "japan",
          "mingei",
          "japanese",
          "go",
          "Daikoku",
          "Ebisu"
        ]
      },
      "media_id": "51b656bf995aedc32c5ce45e393cefd9",
      "path": "media/other/29089875_875395689329524_8188652722338136064_n_17921668051075166.jpg",
      "perceptual_hash": "p:ac94c33bd03ee44e",
      "taken": 1520964180,
      "taken_at": "Mar 13, 2018 6:03 pm"
    },
    "sfomuseum:placetype": "instagram",
    "wof:name": "These two cats, imitating the gods Daikoku and Ebisu, are playing Go, a strategy board game invented in China more than 2,500 years ago...",
    "wof:placetype": "custom",
    "wof:placetype_alt": [
      "instagram"
    ]
  },
  "geometry": {"coordinates":[-122.386166,37.616356],"type":"Point"}
}
