{
  "type": "Feature",
  "properties": {
    "instagram:post": {
      "caption": {
        "body": "#OnThisDay in 2015, the last branded US Airways flight departed from Philadelphia International Airport and landed at San Francisco International Airport as American Airlines Flight 1939 (for the year the airline was established as All American Aviation). US Airways merged with American Airlines in 2013. Did you ever fly on US Airways?  Image: US Airways, Airbus A319, San Francisco International Airport (SFO), 2000. Gift of the William Hough Collection. 2017.095.006",
        "hashtags": [
          "avgeek", 
          "USAirways", 
          "AmericanAir"
        ]
      },
      "location": "San Francisco International Airport (SFO)",
      "media_id": "f8188bad694bd5b124e5711fa9906311",
      "path": "photos/201910/f8188bad694bd5b124e5711fa9906311.jpg",
      "taken": 1571355715,
      "taken_at": "2019-10-17T23:41:55+00:00"
    },
    "sfomuseum:placetype": "instagram",
    "wof:name": "Instagram message #%!d(string=f8188bad694bd5b124e5711fa9906311)",
    "wof:placetype": "custom"
  },
  "geometry": {"coordinates":[-122.386166,37.616356],"type":"Point"}
}
