{
  "type": "Feature",
  "properties": {
    "date:cessation_lower": "2018-12-14",
    "date:cessation_upper": "2018-12-14",
    "date:inception_lower": "2018-12-14",
    "date:inception_upper": "2018-12-14",
    "instagram:post": {
      "caption": {
        "body": "\"Behind the world of the artisan is…that desire to take an inanimate material, and bring it to life in a form or image that will sing out; that desire to pay homage to my surroundings, to my creativity; that thanksgiving to that first bite into the apple of awareness.\" - Michael Lloyd (b. 1950)  Vase made in memory of John Andrew’s mother  2018 Michael Lloyd (b. 1950) Edinburgh Britannia silver, parcel-gilt The Pearson Silver Collection L2018.1801.018  Special thanks to The Pearson Silver Collection. \"A Sterling Renaissance: British Silver Design 1957 to 2018\" is on display, pre-security, in the International Terminal. http://bit.ly/BritishSilver",
        "excerpt": "\"Behind the world of the artisan is…that desire to take an inanimate material, and bring it to life in a form or image that will sing out; that desire to pay homage to my surroundings, to my creativity; that thanksgiving to that first bite into the apple of awareness.\"",
        "hashtags": [
          "BritishSilver",
          "silver",
          "sterling",
          "sterlingsilver",
          "silverdesign",
          "silver",
          "silversmith",
          "silversmithing",
          "MichaelLloyd",
          "Vase"
        ]
      },
      "media_id": "c549f90ffff012f62793f45b08261ecd",
      "path": "media/posts/201812/46792475_2379729138913286_2975980186253138028_n_18005794306065760.jpg",
      "perceptual_hash": "p:91d0442fb1b86fd5",
      "taken": 1544810760,
      "taken_at": "Dec 14, 2018 6:06 pm"
    },
    "sfomuseum:placetype": "instagram",
    "wof:name": "\"Behind the world of the artisan is…that desire to take an inanimate material, and bring it to life in a form or image that will sing out; that desire to pay homage to my surroundings, to my creativity; that thanksgiving to that first bite into the apple of awareness.\"..",
    "wof:placetype": "custom",
    "wof:placetype_alt": [
      "instagram"
    ]
  },
  "geometry": {"coordinates":[-122.386166,37.616356],"type":"Point"}
}
