{
  "type": "Feature",
  "properties": {
    "date:cessation_lower": "2023-01-12",
    "date:cessation_upper": "2023-01-12",
    "date:inception_lower": "2023-01-12",
    "date:inception_upper": "2023-01-12",
    "instagram:post": {
      "caption": {
        "body": "Qantas (Queensland and Northern Territory Aerial Services) is one of the oldest continually operating airlines in the world; it celebrated its centennial in 2020. The airline was founded in 1920 by Paul McGinness (1896–1952), Hudson Fysh (1895–1974), Fergus McMaster (1879–1950), and Arthur Baird (1889–1954). In 1934, in a joint venture with Imperial Airways, Qantas Empire Airways was formed. After World War II, Qantas Empire Airways was nationalized and began rapidly expanding its route system. International routes with Douglas DC-4 airliners were established to Manila, Hong Kong, and Tokyo. New, advanced, long-range aircraft, beginning with the Lockheed L-749 Constellation in 1947, were also acquired, which enabled the airline to fly the long-distance “Kangaroo Route” to London. With the acquisition of BCPA (British Commonwealth Pacific Airlines) in 1954, Qantas added BCPA’s transpacific “Southern Cross Route” from Australia to America.   “Flying the Southern Cross Route: Seventy-Five years of Australian Commercial Air Service to North America” is on display, pre-security, in the Aviation Museum and Library, located on the departures level of the International Terminal and online at: https://bit.ly/3oyMqFX",
        "excerpt": "Qantas (Queensland and Northern Territory Aerial Services) is one of the oldest continually operating airlines in the world; it celebrated its centennial in 2020.",
        "hashtags": [
          "FlyingSouthernCross",
          "Australia",
          "AvGeek",
          "AviationHistory"
        ]
      },
      "media_id": "100c44db4cf1878973aeb10e3af3946b2598516c",
      "path": "media/posts/202301/324700713_140640045476919_8668093195371959274_n_17939281688425409.jpg",
      "perceptual_hash": "p:c2c23d05bd3ac86f",
      "taken": 1673541960,
      "taken_at": "Jan 12, 2023, 4:46 PM"
    },
    "sfomuseum:placetype": "instagram",
    "wof:name": "Qantas (Queensland and Northern Territory Aerial Services) is one of the oldest continually operating airlines in the world; it celebrated its centennial in 2020...",
    "wof:placetype": "custom",
    "wof:placetype_alt": [
      "instagram"
    ]
  },
  "geometry": {"coordinates":[-122.386166,37.616356],"type":"Point"}
}
