{
  "type": "Feature",
  "properties": {
    "date:cessation_lower": "2018-07-25",
    "date:cessation_upper": "2018-07-25",
    "date:inception_lower": "2018-07-25",
    "date:inception_upper": "2018-07-25",
    "instagram:post": {
      "caption": {
        "body": "The Douglas DC-3 was one of the first airliners to be equipped with a galley. It had upper and lower level storage cabinets for hot and cold meals and a serving counter with a drain. A folding seat and a phone to provide communication with the pilot were also offered. Meals on day-use flights were usually served with paper or plastic cups and plates to reduce weight. When ceramic dishes were used, they were specifically designed to be light for inflight use. American Airlines offered Airlite China produced by the Onondaga Pottery Company of Syracuse, New York, and flatware resembling the DC-3 forward fuselage made by the International Silver Company",
        "excerpt": "The Douglas DC-3 was one of the first airliners to be equipped with a galley.",
        "hashtags": [
          "avgeek",
          "avationgeek",
          "aviation",
          "aviationhistory",
          "vintageaviation",
          "history",
          "avhistory",
          "aviationgeeks",
          "avgeeks",
          "DC3",
          "dinnerware",
          "onthetable",
          "tableware"
        ]
      },
      "media_id": "9a5a1953aef49d785dbefd907d913e79",
      "path": "media/posts/201807/37392300_2212940658940013_4539502697811804160_n_17939266105184257.jpg",
      "perceptual_hash": "p:ceec94929963e195",
      "taken": 1532533620,
      "taken_at": "Jul 25, 2018, 3:47 PM"
    },
    "sfomuseum:placetype": "instagram",
    "wof:name": "The Douglas DC-3 was one of the first airliners to be equipped with a galley...",
    "wof:placetype": "custom",
    "wof:placetype_alt": [
      "instagram"
    ]
  },
  "geometry": {"coordinates":[-122.386166,37.616356],"type":"Point"}
}
