{
  "type": "Feature",
  "properties": {
    "date:cessation_lower": "2018-12-19",
    "date:cessation_upper": "2018-12-19",
    "date:inception_lower": "2018-12-19",
    "date:inception_upper": "2018-12-19",
    "instagram:post": {
      "caption": {
        "body": "A unique form of gospel music, Sacred Steel features lap and pedal steel guitars. It developed in the 1930s by members of the House of God, a Holiness/Pentecostal church. Music serves as an integral part of their church services. The music is typically marked by spontaneous singing, clapping, dancing, and shout-outs. Robert Stone, a Florida folklorist, made the first compilation recording on cassette in the early 1990s. Upon hearing it, Chris Strachwitz released the recordings on CD and later dove further into the evocative musical genre, recording talented performers such as The Campbell Brothers and Aubrey Ghent. Strachwitz also helped produce the documentary Sacred Steel, which visits several churches, tracing the development of this compelling genre. Previously these talented players were largely unknown outside of the church; but groups such as The Campbell Brothers, Robert Randolph, and The Lee Boys now tour and perform for secular audiences at various venues. \"Down-Home Music: The Story of Arhoolie Records\" is on display, post-security, in Terminal 2. http://bit.ly/StoryofArhoolie",
        "excerpt": "A unique form of gospel music, Sacred Steel features lap and pedal steel guitars.",
        "hashtags": [
          "storyofarhoolie",
          "arhoolie",
          "arhoolierecords",
          "ChrisStrachwitz",
          "gospel",
          "church",
          "lapsteelguitar",
          "guitar",
          "sacredsteel",
          "steelguitar",
          "guitars"
        ]
      },
      "file_hash": "fb1e002f2368d12a4f6ea028db0ca7deee7d7287eebb30ea8cb8c43586bc9be0",
      "media_id": "10860aa603770ece943ba020451c63622e338e2c",
      "path": "media/other/9A4F208E21E35894FB211CD4F191ADAD_video_dashinit_17986273129137394.mp4",
      "taken": 1545227880,
      "taken_at": "Dec 19, 2018 1:58 pm"
    },
    "sfomuseum:placetype": "instagram",
    "wof:name": "A unique form of gospel music, Sacred Steel features lap and pedal steel guitars...",
    "wof:placetype": "custom"
  },
  "geometry": {"coordinates":[-122.386166,37.616356],"type":"Point"}
}
