{
  "type": "Feature",
  "properties": {
    "date:cessation_lower": "2014-07-22",
    "date:cessation_upper": "2014-07-22",
    "date:inception_lower": "2014-07-22",
    "date:inception_upper": "2014-07-22",
    "instagram:post": {
      "caption": {
        "hashtags": [
          "maps",
          "sfmaps",
          "sfhistory"
        ]
      },
      "media_id": "1685cda62c2569636ab0298339d78bdf",
      "path": "media/posts/201407/10542756_836870046346593_1582020318_n_17842456003062499.jpg",
      "perceptual_hash": "p:fea480895dfe7a80",
      "taken": 1406021700,
      "taken_at": "Jul 22, 2014, 9:35 AM"
    },
    "sfomuseum:placetype": "instagram",
    "wof:name": "..",
    "wof:placetype": "custom"
  },
  "geometry": {"coordinates":[-122.386166,37.616356],"type":"Point"}
}
