{
  "type": "Feature",
  "properties": {
    "instagram:post": {
      "caption": {
        "body": "Lesser known and slightly older than the Golden Gate Bridge, the San Francisco-Oakland Bay Bridge has one of the longest spans in the United States and carries over 260,000 cars each day. Designed by Charles H. Purcell, it opened six months before the Golden Gate Bridge, on #onthisday in 1936. After part of the East Span collapsed during the 1989 Loma Prieta earthquake, work began on a seismic retrofit. Ultimately, the East Span was replaced and reopened in 2013. Have you ever traveled across the Bay Bridge?  Image: San Francisco - Oakland Bay Bridge approach, 1937. SFO Museum Collection. 2013.117.025",
        "hashtags": [
          "baybridge", 
          "SFBridge", 
          "Bridge", 
          "SFhistory"
        ]
      },
      "location": "San Francisco International Airport (SFO)",
      "media_id": "c4bdf68850465cf8a1053fa6c59ddd0a",
      "path": "photos/201911/c4bdf68850465cf8a1053fa6c59ddd0a.jpg",
      "taken": 1573589047,
      "taken_at": "2019-11-12T20:04:07+00:00"
    },
    "sfomuseum:placetype": "instagram",
    "wof:name": "Instagram message #%!d(string=c4bdf68850465cf8a1053fa6c59ddd0a)",
    "wof:placetype": "custom"
  },
  "geometry": {"coordinates":[-122.386166,37.616356],"type":"Point"}
}
