{
  "type": "Feature",
  "properties": {
    "date:cessation_lower": "2019-07-13",
    "date:cessation_upper": "2019-07-13",
    "date:inception_lower": "2019-07-13",
    "date:inception_upper": "2019-07-13",
    "instagram:post": {
      "caption": {
        "body": "Airlines have customarily used landmarks to advertise their destinations. How many San Francisco landmarks can you recognize?  Image: TWA (Trans World Airlines) stationery card, San Francisco, early 1960s. Gift of Daniel Kusrow. 2018.061.052",
        "excerpt": "Airlines have customarily used landmarks to advertise their destinations.",
        "hashtags": [
          "TWA",
          "SanFrancisco",
          "poster",
          "1960s"
        ]
      },
      "media_id": "da4d1853e950eaf7050a799611335e60",
      "path": "media/other/66270420_183015846063522_5035505019907760915_n_17876873125400883.jpg",
      "perceptual_hash": "p:bcc3963f9a38e034",
      "taken": 1563028140,
      "taken_at": "Jul 13, 2019 2:29 pm"
    },
    "sfomuseum:placetype": "instagram",
    "wof:name": "Airlines have customarily used landmarks to advertise their destinations...",
    "wof:placetype": "custom",
    "wof:placetype_alt": [
      "instagram"
    ]
  },
  "geometry": {"coordinates":[-122.386166,37.616356],"type":"Point"}
}
