{
  "type": "Feature",
  "properties": {
    "date:cessation_lower": "2016-08-06",
    "date:cessation_upper": "2016-08-06",
    "date:inception_lower": "2016-08-06",
    "date:inception_upper": "2016-08-06",
    "instagram:post": {
      "caption": {
        "body": "The first McDonnell Douglas DC-10 entered service #onthisday in 1971. American had requested an aircraft designed to hold 250 passengers with medium to long-haul range. McDonnell Douglas delivered with the DC-10. American's  first day of DC-10 service flew the LA to Chicago route. Did you ever fly on a McDonnell Douglas DC-10?  American Airlines postcard, McDonnell Douglas DC-10 c. 1980 SFO Museum Collection Gift of Thomas G. Dragges 2015.166.0286",
        "excerpt": "The first McDonnell Douglas DC-10 entered service #onthisday in 1971."
      },
      "location": "SFO Museum",
      "media_id": "8ee8f0f57c87bf357cb06557a355dbe7",
      "path": "photos/201608/8ee8f0f57c87bf357cb06557a355dbe7.jpg",
      "perceptual_hash": "p:ee769171189c86cb",
      "taken": 1470443287,
      "taken_at": "2016-08-06T00:28:07+00:00"
    },
    "sfomuseum:placetype": "instagram",
    "wof:name": "The first McDonnell Douglas DC-10 entered service #onthisday in 1971...",
    "wof:placetype": "custom"
  },
  "geometry": {"coordinates":[-122.386166,37.616356],"type":"Point"}
}
