{
  "type": "Feature",
  "properties": {
    "date:cessation_lower": "2015-12-09",
    "date:cessation_upper": "2015-12-09",
    "date:inception_lower": "2015-12-09",
    "date:inception_upper": "2015-12-09",
    "instagram:post": {
      "caption": {
        "body": "One of our current photo exhibitions features stunning shots of satellite images composed by artist Benjamin Grant (@DailyOverview). Check out “Abstracts from Space” pre-security in Terminal 3 or see our website for an online exhibition.",
        "excerpt": "One of our current photo exhibitions features stunning shots of satellite images composed by artist Benjamin Grant (@DailyOverview)."
      },
      "media_id": "e3e12c1710c8c4b6044cadb72950bad9",
      "path": "media/posts/201512/12298916_1508226502810535_1835422422_n_17845508938068420.jpg",
      "perceptual_hash": "p:95e487f194bd7821",
      "taken": 1449654960,
      "taken_at": "Dec 9, 2015, 9:56 AM"
    },
    "sfomuseum:placetype": "instagram",
    "wof:name": "One of our current photo exhibitions features stunning shots of satellite images composed by artist Benjamin Grant (@DailyOverview)...",
    "wof:placetype": "custom"
  },
  "geometry": {"coordinates":[-122.386166,37.616356],"type":"Point"}
}
