{
  "type": "Feature",
  "properties": {
    "instagram:post": {
      "caption": {
        "body": "#Onthisday in 2007 Airbus delivered their first A380 to Singapore Airlines. The largest passenger jet in service, the A380 can carry between 544 and 853 passengers, depending on seating configuration. Have you ever flown on an A380?",
        "hashtags": [
          "A380", 
          "airbus", 
          "Singaporeairlines", 
          "Singapore"
        ]
      },
      "media_id": "a4f40fe7f64a6523738d838f127da56e",
      "path": "photos/201710/a4f40fe7f64a6523738d838f127da56e.jpg",
      "taken": 1508113477,
      "taken_at": "2017-10-16T00:24:37+00:00"
    },
    "sfomuseum:placetype": "instagram",
    "wof:name": "Instagram message #%!d(string=a4f40fe7f64a6523738d838f127da56e)",
    "wof:placetype": "custom"
  },
  "geometry": {"coordinates":[-122.386166,37.616356],"type":"Point"}
}
