{
  "type": "Feature",
  "properties": {
    "date:cessation_lower": "2018-10-03",
    "date:cessation_upper": "2018-10-03",
    "date:inception_lower": "2018-10-03",
    "date:inception_upper": "2018-10-03",
    "instagram:post": {
      "caption": {
        "body": "Fred McDowell’s version of “You Got to Move,” featured on this album, gained widespread recognition after the Rolling Stones covered the song on their 1971 album “Sticky Fingers.” Royalties from the song eventually garnered a significant sum for both McDowell and Chris Strachwitz’s Tradition Music Company, his song publishing wing, thanks largely to the Rolling Stones putting McDowell’s name as composer on the label of their record. Listen to a snippet of his song on the Folkways website: https://folkways.si.edu/fred-mcdowell/you-gotta-move/african-american-blues/music/song/smithsonian \"Down-Home Music: The Story of Arhoolie Records\" is on display, post-security, in Terminal 2. http://bit.ly/StoryofArhoolie",
        "excerpt": "Fred McDowell’s version of “You Got to Move,” featured on this album, gained widespread recognition after the Rolling Stones covered the song on their 1971 album “Sticky Fingers.” Royalties from the song eventually garnered a significant sum for both McDowell and Chris Strachwitz’s Tradition Music Company, his song publishing wing, thanks largely to the Rolling Stones putting McDowell’s name as composer on the label of their record.",
        "hashtags": [
          "storyofarhoolie",
          "arhoolie",
          "arhoolierecords",
          "ChrisStrachwitz",
          "Mississippi",
          "MississippiFredMcdowell",
          "blues",
          "folkmusic",
          "FredMcdowell",
          "slideguitar",
          "bottleneckslideguitar",
          "spirituals",
          "bluesman",
          "bluesmusic",
          "folkways",
          "smithsonian"
        ],
        "users": [
          "arhooliefoundation"
        ]
      },
      "file_hash": "4cecb71186e0a9de149ab043484de42c7f10936911e89a03876577da1b089fe9",
      "media_id": "1fbeb734be985d4b95cd44301e357719a097aa01",
      "path": "media/other/E941E7F518C550908127AE643479C1B6_video_dashinit_17922560185222429.mp4",
      "taken": 1538585400,
      "taken_at": "Oct 03, 2018 4:50 pm"
    },
    "sfomuseum:placetype": "instagram",
    "wof:name": "Fred McDowell’s version of “You Got to Move,” featured on this album, gained widespread recognition after the Rolling Stones covered the song on their 1971 album “Sticky Fingers.” Royalties from the song eventually garnered a significant sum for both McDowell and Chris Strachwitz’s Tradition Music Company, his song publishing wing, thanks largely to the Rolling Stones putting McDowell’s name as composer on the label of their record...",
    "wof:placetype": "custom"
  },
  "geometry": {"coordinates":[-122.386166,37.616356],"type":"Point"}
}
