{
  "type": "Feature",
  "properties": {
    "date:cessation_lower": "2018-11-09",
    "date:cessation_upper": "2018-11-09",
    "date:inception_lower": "2018-11-09",
    "date:inception_upper": "2018-11-09",
    "instagram:post": {
      "caption": {
        "body": "Hollywood fashion designer Howard Greer (1896–1974) created this fitted suit in light blue wool gabardine for TWA (Trans World Airlines) in 1944. It was known as the “cutout” for the openwork TWA lettering on the shoulder. With suggestions from supervisor of hostess services Ida Staggers, Greer introduced the “blou-slip,” a combined undergarment in rayon and satin that did not need constant tucking in. The triangular jacket flap could be unbuttoned to cover the TWA lettering, allowing the hostess to smoke or have a cocktail while off duty. This style of uniform was worn until 1955.  Image: TWA (Trans World Airlines), Audrey McNamara Nevis, c. 1949. Gift of the Estate of Audrey McNamara Nevis. 2013.057.001",
        "excerpt": "Hollywood fashion designer Howard Greer (1896–1974) created this fitted suit in light blue wool gabardine for TWA (Trans World Airlines) in 1944.",
        "hashtags": [
          "HowardGreer",
          "TWA",
          "Hollywood",
          "fashiondesign",
          "fashion",
          "satin",
          "IdaStaggers",
          "uniform",
          "flightattendant"
        ]
      },
      "media_id": "422e7ee5de3c8e4f65d06fcd023ee923",
      "path": "photos/201811/422e7ee5de3c8e4f65d06fcd023ee923.jpg",
      "perceptual_hash": "p:8b055c3d63e28e9d",
      "taken": 1541790349,
      "taken_at": "2018-11-09T19:05:49+00:00"
    },
    "sfomuseum:placetype": "instagram",
    "wof:name": "Hollywood fashion designer Howard Greer (1896–1974) created this fitted suit in light blue wool gabardine for TWA (Trans World Airlines) in 1944...",
    "wof:placetype": "custom"
  },
  "geometry": {"coordinates":[-122.386166,37.616356],"type":"Point"}
}
