{
  "type": "Feature",
  "properties": {
    "date:cessation_lower": "2016-05-14",
    "date:cessation_upper": "2016-05-14",
    "date:inception_lower": "2016-05-14",
    "date:inception_upper": "2016-05-14",
    "instagram:post": {
      "caption": {
        "body": "A trip on the Martin M-130 China Clipper in 1937 included five stops from San Francisco to Hong Kong: Honolulu; Midway Island; Wake Island; Guam; and Manila, Philippines. Passenger counts on the San Francisco–Honolulu leg rarely exceeded six or seven. With any more, luggage had to be sent by ship. Twelve passengers were the maximum. The length of the San Francisco–Honolulu flight—eighteen to twenty-two hours depending on winds—required sleeping births. Cabin interiors included dining and passenger lounges. Each trip from San Francisco to Hong Kong took six days with more than seventy hours of flying time. Building on that pioneering achievement over the last seven decades, air service between North America and Asia now takes little more than half a day.  Learn more about China Clipper in our exhibition, on display, pre-security, in the International Terminal. http://bit.ly/chinaclipper",
        "excerpt": "A trip on the Martin M-130 China Clipper in 1937 included five stops from San Francisco to Hong Kong: Honolulu; Midway Island; Wake Island; Guam; and Manila, Philippines."
      },
      "location": "SFO Museum",
      "media_id": "d08cd0f259a4884089a262e97b3209e7",
      "path": "photos/201605/d08cd0f259a4884089a262e97b3209e7.jpg",
      "perceptual_hash": "p:be90896a25de8dd1",
      "taken": 1463224440,
      "taken_at": "May 14, 2016, 11:14 AM"
    },
    "sfomuseum:placetype": "instagram",
    "wof:name": "A trip on the Martin M-130 China Clipper in 1937 included five stops from San Francisco to Hong Kong: Honolulu; Midway Island; Wake Island; Guam; and Manila, Philippines...",
    "wof:placetype": "custom"
  },
  "geometry": {"coordinates":[-122.386166,37.616356],"type":"Point"}
}
