{
  "type": "Feature",
  "properties": {
    "date:cessation_lower": "2020-08-14",
    "date:cessation_upper": "2020-08-14",
    "date:inception_lower": "2020-08-14",
    "date:inception_upper": "2020-08-14",
    "instagram:post": {
      "caption": {
        "body": "Barbershop and hairdressing signs are often an ephemeral form of utilitarian folk art. The African signs in our exhibition had been originally posted outdoors in warm climates, in an environment where many signs quickly weather. This sign in particular, collected by David Spetka of the Niger Bend, had severe flaking paint issues. Our conservator consolidated the paint layer by introducing adhesive beneath the lifting flakes of paint so that the sign could be safely displayed in our exhibition.  See “Extra ’O’!” African Barbershop and Hairdressing Signs” online at: http://bit.ly/Extrao   Barbershop sign  c. 2000 Accra, Ghana oil and/or acrylic paint, wood panel Courtesy of David Spetka – The Niger Bend L2020.0304.004",
        "excerpt": "Barbershop and hairdressing signs are often an ephemeral form of utilitarian folk art.",
        "hashtags": [
          "africa",
          "barbershop",
          "barbershopsign",
          "MuseumFromHome"
        ],
        "users": [
          "thenigerbend",
          "indigoartsgallery",
          "handpaintedkenya",
          "andrewesiebo",
          "erniewolfegallery\n#ExtraO"
        ]
      },
      "media_id": "6fb2525268b3bee578853a903d0f2881",
      "path": "media/posts/202008/117716383_106592571158288_607288406662726648_n_17854888472169860.jpg",
      "perceptual_hash": "p:899e948c9878de4f",
      "taken": 1597421640,
      "taken_at": "Aug 14, 2020, 4:14 PM"
    },
    "sfomuseum:placetype": "instagram",
    "wof:name": "Barbershop and hairdressing signs are often an ephemeral form of utilitarian folk art...",
    "wof:placetype": "custom"
  },
  "geometry": {"coordinates":[-122.386166,37.616356],"type":"Point"}
}
