{
  "type": "Feature",
  "properties": {
    "instagram:post": {
      "caption": {
        "body": "“The interesting way to travel - Eastern Air Lines”. What did commercial air service look like around 1940? The Eastern Air Lines Douglas DC-3 could travel up to 200 mph and was promoted by the airline as clean, fast, and restful, with a quiet cabin. By the looks of this c. 1940 postcard, the passengers on this small plane are enjoying their meals and the view out of the large windows. And of interest to modern-day air travelers, check out the train-like overhead compartments!  Image:  Eastern Air Lines postcard, Douglas, c. 1940. Gift of Thomas G. Dragges. 2015.166.0636",
        "hashtags": [
          "avgeek", 
          "aviationhistory", 
          "easternairlines", 
          "easternair", 
          "douglas", 
          "mealservice", 
          "vintage", 
          "vintagead", 
          "vintageadvertisement"
        ]
      },
      "media_id": "58e5f00f6ff577ab8863fe4a3939a88d",
      "path": "photos/201707/58e5f00f6ff577ab8863fe4a3939a88d.jpg",
      "taken": 1499911631,
      "taken_at": "2017-07-13T02:07:11+00:00"
    },
    "sfomuseum:placetype": "instagram",
    "wof:name": "Instagram message #%!d(string=58e5f00f6ff577ab8863fe4a3939a88d)",
    "wof:placetype": "custom"
  },
  "geometry": {"coordinates":[-122.386166,37.616356],"type":"Point"}
}
