{
  "type": "Feature",
  "properties": {
    "instagram:post": {
      "caption": {
        "body": "“TWA presents three full color motion picture films\". In the 1940s, well before the dawn of the jet age, TWA produced full color travelogue films to promote their overseas and domestic destinations.  Image: TWA (Trans World Airlines) brochure, c. 1945. Gift of Thomas G. Dragges. 2014.110.386",
        "hashtags": [
          "avgeek", 
          "avationgeek", 
          "aviation", 
          "aviationhistory", 
          "TWA", 
          "aviationlovers", 
          "vintageaviation", 
          "history", 
          "avhistory", 
          "aviationgeeks", 
          "instaplane", 
          "flying", 
          "plane", 
          "flight", 
          "airline", 
          "avgeeks", 
          "aviation4u", 
          "aviationdaily", 
          "TransWorldAirlines"
        ]
      },
      "media_id": "e72384f56d51d53f9d375510a39c5c8e",
      "path": "photos/201709/e72384f56d51d53f9d375510a39c5c8e.jpg",
      "taken": 1506744990,
      "taken_at": "2017-09-30T04:16:30+00:00"
    },
    "sfomuseum:placetype": "instagram",
    "wof:name": "Instagram message #%!d(string=e72384f56d51d53f9d375510a39c5c8e)",
    "wof:placetype": "custom"
  },
  "geometry": {"coordinates":[-122.386166,37.616356],"type":"Point"}
}
