{
  "type": "Feature",
  "properties": {
    "date:cessation_lower": "2020-02-15",
    "date:cessation_upper": "2020-02-15",
    "date:inception_lower": "2020-02-15",
    "date:inception_upper": "2020-02-15",
    "instagram:post": {
      "caption": {
        "body": "Did you know that “California Studio Craft: Featuring Works from the Forrest L. Merrill Collection” features work by the husband and wife team of woodworker Bob Stocksdale (1913–2003) and textile artist Kay Sekimachi (b. 1926)? Stocksdale had a masterful talent for revealing dramatic patterns hidden below the surface of rare wood. Sekimachi transformed thread, paper, and organic materials into delightfully expressive textiles, vessels, and sculpture. Married in 1972, Stocksdale and Sekimachi refined their craft together for over three decades, sharing a love of form and innovation in craft.  See \"California Studio Craft: Featuring Works from the Forrest L. Merrill Collection\" on display, post-security, in Terminal 2. http://bit.ly/CaliforniaCrafts",
        "excerpt": "Did you know that “California Studio Craft: Featuring Works from the Forrest L. Merrill Collection” features work by the husband and wife team of woodworker Bob Stocksdale (1913–2003) and textile artist Kay Sekimachi (b.",
        "hashtags": [
          "CaliforniaCrafts",
          "ForrestMerrill",
          "StudioCraft",
          "ValentinesDay",
          "BobStocksdale",
          "KaySekimachi"
        ]
      },
      "media_id": "42865b902ca556eacd29d9d91c1bacb4",
      "path": "photos/202002/42865b902ca556eacd29d9d91c1bacb4.jpg",
      "perceptual_hash": "p:9b22b44da45eeb49",
      "taken": 1581728985,
      "taken_at": "2020-02-15T01:09:45+00:00"
    },
    "sfomuseum:placetype": "instagram",
    "wof:name": "Did you know that “California Studio Craft: Featuring Works from the Forrest L. Merrill Collection” features work by the husband and wife team of woodworker Bob Stocksdale (1913–2003) and textile artist Kay Sekimachi (b...",
    "wof:placetype": "custom"
  },
  "geometry": {"coordinates":[-122.386166,37.616356],"type":"Point"}
}
