{
  "type": "Feature",
  "properties": {
    "date:cessation_lower": "2018-02-15",
    "date:cessation_upper": "2018-02-15",
    "date:inception_lower": "2018-02-15",
    "date:inception_upper": "2018-02-15",
    "instagram:post": {
      "caption": {
        "body": "By the late 1930s, with the introduction of the Douglas DST (Douglas Sleeper Transport) and DC-3 Mainliners, United Air Lines provided standardized beverage service. Coffee was stored in thermos-type dispensers in the galley and served in plastic cups with saucers, while hot and cold water was available from lavatory dispensers for drinking and washing.  See \"Flying the Main Line: A History of United Airlines\", on display, post-security, in Terminal 3. http://bit.ly/TheMainLine  Image: United Air Lines stewardesses prepare to serve coffee in the Douglas DC-3 gallery, late 1936. Collection of United Airlines Archives. R2017.1502.065",
        "excerpt": "By the late 1930s, with the introduction of the Douglas DST (Douglas Sleeper Transport) and DC-3 Mainliners, United Air Lines provided standardized beverage service.",
        "hashtags": [
          "FlyingTheMainLine",
          "TheMainLine",
          "DST",
          "douglasaircraft",
          "dc3",
          "unitedairlines",
          "airlines",
          "airline",
          "avgeek",
          "avationgeek",
          "aviation",
          "aviationhistory",
          "vintageaviation",
          "history",
          "avhistory",
          "aviationgeeks",
          "avgeeks",
          "crewlife",
          "coffeetime"
        ]
      },
      "media_id": "0156b98a0bf2b3f32aed602a3aa27ff4",
      "path": "media/posts/201802/27878957_155237028610470_2662160784649355264_n_17893881043173093.jpg",
      "perceptual_hash": "p:9ae8b29c7cda0e68",
      "taken": 1518717600,
      "taken_at": "Feb 15, 2018, 6:00 PM"
    },
    "sfomuseum:placetype": "instagram",
    "wof:name": "By the late 1930s, with the introduction of the Douglas DST (Douglas Sleeper Transport) and DC-3 Mainliners, United Air Lines provided standardized beverage service...",
    "wof:placetype": "custom",
    "wof:placetype_alt": [
      "instagram"
    ]
  },
  "geometry": {"coordinates":[-122.386166,37.616356],"type":"Point"}
}
