{
  "type": "Feature",
  "properties": {
    "date:cessation_lower": "2022-03-22",
    "date:cessation_upper": "2022-03-22",
    "date:inception_lower": "2022-03-22",
    "date:inception_upper": "2022-03-22",
    "instagram:post": {
      "caption": {
        "body": "#Onthisday in 1920, Hollywood costume designer and Academy Award winner, William Travilla, was born in Los Angeles, California. Well known for dressing Marilyn Monroe, Travilla created this synthetic blend, summer seasonal ensemble for United in a new color named Blue Frost. The lightly fitted jacket has a distinct chelsea collar and a three-quarter-length sleeve with a detachable dropped cuff. The short sleeve blouse has a banded waist and an attached jabot neckpiece for the insignia pin. Smart looking and allowing greater ease of mobility for the demands of jet service, it was issued from 1965 to 1968 and became known as “the cheerleader” because of its flared skirt.",
        "excerpt": "#Onthisday in 1920, Hollywood costume designer and Academy Award winner, William Travilla, was born in Los Angeles, California.",
        "hashtags": [
          "avgeek",
          "WilliamTravilla",
          "united",
          "fashion"
        ]
      },
      "media_id": "245ea91fc849c7a5c9e8d383a2d43e993babd50b",
      "path": "media/posts/202203/277243427_132028156058313_5697831510623229218_n_17924298896212418.jpg",
      "perceptual_hash": "p:97947a6be58d1c90",
      "taken": 1647966060,
      "taken_at": "Mar 22, 2022 4:21 pm"
    },
    "sfomuseum:placetype": "instagram",
    "wof:name": "#Onthisday in 1920, Hollywood costume designer and Academy Award winner, William Travilla, was born in Los Angeles, California...",
    "wof:placetype": "custom",
    "wof:placetype_alt": [
      "instagram"
    ]
  },
  "geometry": {"coordinates":[-122.386166,37.616356],"type":"Point"}
}
