{
  "type": "Feature",
  "properties": {
    "date:cessation_lower": "2014-06-13",
    "date:cessation_upper": "2014-06-13",
    "date:inception_lower": "2014-06-13",
    "date:inception_upper": "2014-06-13",
    "instagram:post": {
      "caption": {
        "hashtags": [
          "DualNatures",
          "korea",
          "ceramics"
        ]
      },
      "media_id": "e8143804c3e3d0a58d5ecd83897d34f2",
      "path": "media/other/926784_255314314656564_662349325_n_17842439218062499.jpg",
      "perceptual_hash": "p:949e69a1bc9c63a3",
      "taken": 1402666260,
      "taken_at": "Jun 13, 2014 1:31 pm"
    },
    "sfomuseum:placetype": "instagram",
    "wof:name": "..",
    "wof:placetype": "custom",
    "wof:placetype_alt": [
      "instagram"
    ]
  },
  "geometry": {"coordinates":[-122.386166,37.616356],"type":"Point"}
}
