{
  "type": "Feature",
  "properties": {
    "date:cessation_lower": "2020-10-05",
    "date:cessation_upper": "2020-10-05",
    "date:inception_lower": "2020-10-05",
    "date:inception_upper": "2020-10-05",
    "instagram:post": {
      "caption": {
        "body": "Construction of a new terminal (now Terminal 2) at San Francisco International Airport began #onthsiday in 1951. Designed in the International Style, the building employed an innovative, dual-level layout that separated departures from arrivals. Panoramic views of the airfield and San Francisco Bay were provided from multiple spectators’ terraces and the International Room restaurant. Have you ever flown out of Terminal 2?  Learn more about the 1954 Terminal in our online exhibition “The 1954 San Francisco International Airport Terminal”: http://bit.ly/32ooxEQ   Images: Construction foreman at San Francisco International Airport terminal building, 1952. SFO Museum Collection. 2011.032.0306 - San Francisco Airport, Terminal Building construction, 1952. SFO Museum Collection. 2011.032.0292",
        "excerpt": "Construction of a new terminal (now Terminal 2) at San Francisco International Airport began #onthsiday in 1951.",
        "hashtags": [
          "SFOhistory",
          "avgeek",
          "MuseumFromHome",
          "airport"
        ]
      },
      "media_id": "79558962d25ee35a4e3e3474401ddd39",
      "path": "media/posts/202010/120752143_334660017794350_8276587230348764365_n_17899116508593051.jpg",
      "perceptual_hash": "p:dae695214cbfe380",
      "taken": 1601905680,
      "taken_at": "Oct 5, 2020, 1:48 PM"
    },
    "sfomuseum:placetype": "instagram",
    "wof:name": "Construction of a new terminal (now Terminal 2) at San Francisco International Airport began #onthsiday in 1951...",
    "wof:placetype": "custom"
  },
  "geometry": {"coordinates":[-122.386166,37.616356],"type":"Point"}
}
