{
  "type": "Feature",
  "properties": {
    "instagram:post": {
      "caption": {
        "body": "Our #ThrowbackThursday offering: 1999's \"Out to Lunch,\" featuring over 100 lunch boxes from the collection of Ralph Persinger and shown in a former exhibition site in Terminal 1. Our crew made the oversized lunch box and thermos; the handle and lid are styrofoam, and the bodies are plywood!",
        "excerpt": "Our #ThrowbackThursday offering: 1999's \"Out to Lunch,\" featuring over 100 lunch boxes from the collection of Ralph Persinger and shown in a former exhibition site in Terminal 1."
      },
      "media_id": "ac67dd980f025c3022a6cf8c9b56f431",
      "path": "photos/201308/ac67dd980f025c3022a6cf8c9b56f431.jpg",
      "taken": 1376601745,
      "taken_at": "2013-08-15T21:22:25+00:00"
    },
    "sfomuseum:placetype": "instagram",
    "wof:name": "Our #ThrowbackThursday offering: 1999's \"Out to Lunch,\" featuring over 100 lunch boxes from the collection of Ralph Persinger and shown in a former exhibition site in Terminal 1...",
    "wof:placetype": "custom"
  },
  "geometry": {"coordinates":[-122.386166,37.616356],"type":"Point"}
}
