{
  "type": "Feature",
  "properties": {
    "date:cessation_lower": "2013-08-15",
    "date:cessation_upper": "2013-08-15",
    "date:inception_lower": "2013-08-15",
    "date:inception_upper": "2013-08-15",
    "instagram:post": {
      "caption": {
        "body": "Our #ThrowbackThursday offering: 1999's \"Out to Lunch,\" featuring over 100 lunch boxes from the collection of Ralph Persinger and shown in a former exhibition site in Terminal 1. Our crew made the oversized lunch box and thermos; the handle and lid are styrofoam, and the bodies are plywood!",
        "excerpt": "Our #ThrowbackThursday offering: 1999's \"Out to Lunch,\" featuring over 100 lunch boxes from the collection of Ralph Persinger and shown in a former exhibition site in Terminal 1."
      },
      "media_id": "ac67dd980f025c3022a6cf8c9b56f431",
      "path": "media/posts/201308/11253254_796819417079859_1771377049_n_17842350697062499.jpg",
      "perceptual_hash": "p:ebecc9c1e41b901e",
      "taken": 1376572920,
      "taken_at": "Aug 15, 2013, 1:22 PM"
    },
    "sfomuseum:placetype": "instagram",
    "wof:name": "Our #ThrowbackThursday offering: 1999's \"Out to Lunch,\" featuring over 100 lunch boxes from the collection of Ralph Persinger and shown in a former exhibition site in Terminal 1...",
    "wof:placetype": "custom"
  },
  "geometry": {"coordinates":[-122.386166,37.616356],"type":"Point"}
}
