{
  "type": "Feature",
  "properties": {
    "date:cessation_lower": "2013-09-26",
    "date:cessation_upper": "2013-09-26",
    "date:inception_lower": "2013-09-26",
    "date:inception_upper": "2013-09-26",
    "instagram:post": {
      "caption": {
        "hashtags": [
          "magic,",
          "throwbackthursday",
          "tbt"
        ]
      },
      "media_id": "4740724eccb44ddccea9c4895e551d86",
      "path": "photos/201309/4740724eccb44ddccea9c4895e551d86.jpg",
      "perceptual_hash": "p:99d86666a99d59c1",
      "taken": 1380234326,
      "taken_at": "2013-09-26T22:25:26+00:00"
    },
    "sfomuseum:placetype": "instagram",
    "wof:name": "..",
    "wof:placetype": "custom"
  },
  "geometry": {"coordinates":[-122.386166,37.616356],"type":"Point"}
}
