{
  "type": "Feature",
  "properties": {
    "date:cessation_lower": "2021-12-06",
    "date:cessation_upper": "2021-12-06",
    "date:inception_lower": "2021-12-06",
    "date:inception_upper": "2021-12-06",
    "instagram:post": {
      "caption": {
        "body": "Each airport around the world is assigned a three-letter IATA (International Air Transport Association) code to make them easily and quickly identifiable. This three-letter system allows for 17,576 permutations. San Francisco International Airport’s three letter code, SFO, first appeared in the “American Aviation Air Traffic Guide” in December 1947.",
        "excerpt": "Each airport around the world is assigned a three-letter IATA (International Air Transport Association) code to make them easily and quickly identifiable.",
        "hashtags": [
          "avgeek",
          "SFO",
          "SFOHistory"
        ]
      },
      "media_id": "6bead5f1042730f1936bb652951a391fc229b18e",
      "path": "media/posts/202112/264148486_651819739159762_3459557600821865152_n_17943851797713498.jpg",
      "perceptual_hash": "p:fd330f06c112f1d9",
      "taken": 1638809280,
      "taken_at": "Dec 6, 2021, 4:48 PM"
    },
    "sfomuseum:placetype": "instagram",
    "wof:name": "Each airport around the world is assigned a three-letter IATA (International Air Transport Association) code to make them easily and quickly identifiable...",
    "wof:placetype": "custom",
    "wof:placetype_alt": [
      "instagram"
    ]
  },
  "geometry": {"coordinates":[-122.386166,37.616356],"type":"Point"}
}
