{
  "type": "Feature",
  "properties": {
    "date:cessation_lower": "2023-02-24",
    "date:cessation_upper": "2023-02-24",
    "date:inception_lower": "2023-02-24",
    "date:inception_upper": "2023-02-24",
    "instagram:post": {
      "caption": {
        "body": "In the 1930s, as commercial aviation evolved into a more practical mode of transportation, San Francisco Airport launched a series of major improvements. Backed by funding and labor from President Franklin D. Roosevelt’s “New Deal” and the Works Progress Administration (WPA), by 1937, more than 790,000 square-feet of concrete runways, taxiways, and aircraft parking were in place, illuminated by modern, multicolored lighting and 45,700 feet of underground power lines.   A new administration and terminal building was also completed that year. Designed in the Spanish Colonial Revival style, the building included a four-story control tower, restaurant, cocktail lounge, and a grand passenger waiting room with terrazzo floors and a stenciled ceiling. A matching building for the complex airfield lighting system sat adjacent to the hangars, and by the end of the decade, two-way radio communications were required for all aircraft.   See “Mills Field and the San Francisco Airport” is on display in the SkyTerrace in Terminal 2 and online at: https://bit.ly/2XU7rAz   The SkyTerrace located pre-security in Terminal 2 and is open Friday to Monday from 10:00 a.m. to 6:00 p.m.",
        "excerpt": "In the 1930s, as commercial aviation evolved into a more practical mode of transportation, San Francisco Airport launched a series of major improvements.",
        "hashtags": [
          "MillsField",
          "SFOHistory",
          "AvGeek"
        ]
      },
      "media_id": "7d9205ff101db259376e0405f8b719c5b884d95e",
      "path": "media/posts/202302/333127136_900564674325018_4220568121213898514_n_18166912288277903.jpg",
      "perceptual_hash": "p:ff4a409a6d8a34cb",
      "taken": 1677258000,
      "taken_at": "Feb 24, 2023, 5:00 PM"
    },
    "sfomuseum:placetype": "instagram",
    "wof:name": "In the 1930s, as commercial aviation evolved into a more practical mode of transportation, San Francisco Airport launched a series of major improvements...",
    "wof:placetype": "custom"
  },
  "geometry": {"coordinates":[-122.386166,37.616356],"type":"Point"}
}
