{
  "type": "Feature",
  "properties": {
    "instagram:post": {
      "caption": {
        "body": "#OnThisDay in 1946, #Philippine Airlines became the first Asian Airline to cross the Pacific Ocean. This non-scheduled flight from Manila to #Oakland, CA, took 41 hours and stopped at #Guam, #Kwajalein, and #Honolulu, flying a DC-4. Scheduled service from #Manila to #SF would commence later that year in December.  Image: Philippine Air Lines postcard, early 1950s. Gift of Thomas G. Dragges. 2015.166.1276"
      },
      "media_id": "75e6b91bce10b7efc31cb0bd78049747",
      "path": "photos/201707/75e6b91bce10b7efc31cb0bd78049747.jpg",
      "taken": 1501535519,
      "taken_at": "2017-07-31T21:11:59+00:00"
    },
    "sfomuseum:placetype": "instagram",
    "wof:name": "Instagram message #%!d(string=75e6b91bce10b7efc31cb0bd78049747)",
    "wof:placetype": "custom"
  },
  "geometry": {"coordinates":[-122.386166,37.616356],"type":"Point"}
}
