{
  "type": "Feature",
  "properties": {
    "date:cessation_lower": "2017-07-31",
    "date:cessation_upper": "2017-07-31",
    "date:inception_lower": "2017-07-31",
    "date:inception_upper": "2017-07-31",
    "instagram:post": {
      "caption": {
        "body": "#OnThisDay in 1946, #Philippine Airlines became the first Asian Airline to cross the Pacific Ocean. This non-scheduled flight from Manila to #Oakland, CA, took 41 hours and stopped at #Guam, #Kwajalein, and #Honolulu, flying a DC-4. Scheduled service from #Manila to #SF would commence later that year in December.  Image: Philippine Air Lines postcard, early 1950s. Gift of Thomas G. Dragges. 2015.166.1276",
        "excerpt": "#OnThisDay in 1946, #Philippine Airlines became the first Asian Airline to cross the Pacific Ocean."
      },
      "media_id": "75e6b91bce10b7efc31cb0bd78049747",
      "path": "photos/201707/75e6b91bce10b7efc31cb0bd78049747.jpg",
      "perceptual_hash": "p:ba19f496c28ec3c3",
      "taken": 1501506660,
      "taken_at": "Jul 31, 2017, 1:11 PM"
    },
    "sfomuseum:placetype": "instagram",
    "wof:name": "#OnThisDay in 1946, #Philippine Airlines became the first Asian Airline to cross the Pacific Ocean...",
    "wof:placetype": "custom"
  },
  "geometry": {"coordinates":[-122.386166,37.616356],"type":"Point"}
}
