{
  "type": "Feature",
  "properties": {
    "date:cessation_lower": "2021-05-20",
    "date:cessation_upper": "2021-05-20",
    "date:inception_lower": "2021-05-20",
    "date:inception_upper": "2021-05-20",
    "instagram:post": {
      "caption": {
        "body": "Be inspired by four short documentary videos featured online, each with stories of dreamers who take action to positively impact our world. From one man’s dream to build community through roller skating to a band of runners taking action to protect a sacred public land from the threat of development, and from a community of activists creatively confronting one of the planet’s greatest environmental challenges to a rising literary star intent on sharing his inspiration with those who may need it most.  Our screening room may still be closed, but you can watch the videos online at: http://bit.ly/VideoArts \u003c--or navigate here via the link in our bio.",
        "excerpt": "Be inspired by four short documentary videos featured online, each with stories of dreamers who take action to positively impact our world.",
        "hashtags": [
          "VideoArtsSFOM",
          "documentary",
          "inspriation",
          "videoart"
        ]
      },
      "media_id": "f2c9b19c3afbfa39b73d785a319ca9a75f2cb1c2",
      "path": "media/posts/202105/189793363_183091637032392_6283523687124222390_n_17927060416596584.jpg",
      "perceptual_hash": "p:f3665c31a28685f3",
      "taken": 1621529160,
      "taken_at": "May 20, 2021, 4:46 PM"
    },
    "sfomuseum:placetype": "instagram",
    "wof:name": "Be inspired by four short documentary videos featured online, each with stories of dreamers who take action to positively impact our world...",
    "wof:placetype": "custom",
    "wof:placetype_alt": [
      "instagram"
    ]
  },
  "geometry": {"coordinates":[-122.386166,37.616356],"type":"Point"}
}
