{
  "type": "Feature",
  "properties": {
    "date:cessation_lower": "2022-03-29",
    "date:cessation_upper": "2022-03-29",
    "date:inception_lower": "2022-03-29",
    "date:inception_upper": "2022-03-29",
    "instagram:post": {
      "caption": {
        "body": "Alicia McCarthy’s paintings are driven by material and repetition. She interlaces ribbons of spray paint, latex paint, crayon, and pencil that are reducible as parts, but expansive in their totality. With roots in the Bay Area’s graffiti and punk scenes, McCarthy’s paintings are an exercise in resisting the impulse to control. Her splatters, smudges, and imperfect lines signal an embrace of variation, disruption, and the limitations of both materials and the hand that wields them.  See “Untitled” by Alicia McCarthy, on display, post-security, in Harvey Milk Terminal 1 and online at: https://bit.ly/36XeD0C",
        "excerpt": "Alicia McCarthy’s paintings are driven by material and repetition.",
        "hashtags": [
          "5WomenArtists",
          "AliciaMcCarthy",
          "painting",
          "publicart"
        ],
        "users": [
          "sfac_public_art_collection\n@helloforevor"
        ]
      },
      "media_id": "53f9d50273dc1e2fc0ced99f23141b9ac726bc24",
      "path": "media/posts/202203/277474135_495328005617305_4239850038400006458_n_17914769309457901.jpg",
      "perceptual_hash": "p:a6bac8556bba5438",
      "taken": 1648566480,
      "taken_at": "Mar 29, 2022 3:08 pm"
    },
    "sfomuseum:placetype": "instagram",
    "wof:name": "Alicia McCarthy’s paintings are driven by material and repetition...",
    "wof:placetype": "custom",
    "wof:placetype_alt": [
      "instagram"
    ]
  },
  "geometry": {"coordinates":[-122.386166,37.616356],"type":"Point"}
}
