{
  "type": "Feature",
  "properties": {
    "date:cessation_lower": "2020-04-15",
    "date:cessation_upper": "2020-04-15",
    "date:inception_lower": "2020-04-15",
    "date:inception_upper": "2020-04-15",
    "instagram:post": {
      "caption": {
        "body": "Dubbed “The Uniform for the Superjet Era,” and created for the new wide-body jet service, this 1971 Pan American uniform marked a new direction in Pan Am’s approach to fashion. Designed by Frank Smith (1927–2007), chief designer at career wear manufacturer Evan-Picone, this uniform was meant to be “a functional and fashionable wardrobe that could be worn in all seasons, and of such quality that it would enhance the Pan Am image.” Image: Pan American World Airways, stewardesses and Boeing 747-100, c. 1971. Gift of the Pan Am Association. 2000.058.0503.009 ",
        "excerpt": "Dubbed “The Uniform for the Superjet Era,” and created for the new wide-body jet service, this 1971 Pan American uniform marked a new direction in Pan Am’s approach to fashion.",
        "hashtags": [
          "avgeek",
          "MuseumFromHome",
          "PanAm",
          "fashion",
          "crewlife"
        ]
      },
      "media_id": "b344bd48c7ef654c5a3909b4f02bfc201feef434",
      "path": "media/posts/202004/93192233_1717033101772727_6424741106282351276_n_17933203036367174.jpg",
      "perceptual_hash": "p:df912a365470e8cb",
      "taken": 1586977200,
      "taken_at": "Apr 15, 2020, 7:00 PM"
    },
    "sfomuseum:placetype": "instagram",
    "wof:name": "Dubbed “The Uniform for the Superjet Era,” and created for the new wide-body jet service, this 1971 Pan American uniform marked a new direction in Pan Am’s approach to fashion...",
    "wof:placetype": "custom"
  },
  "geometry": {"coordinates":[-122.386166,37.616356],"type":"Point"}
}
