{
  "type": "Feature",
  "properties": {
    "instagram:post": {
      "caption": {
        "hashtags": [
          "ArtAndDisability"
        ]
      },
      "location": "San Francisco International Airport (SFO)",
      "media_id": "b2790baeb77f8b73226a4bd34683cdd9",
      "path": "photos/201607/b2790baeb77f8b73226a4bd34683cdd9.jpg",
      "taken": 1467742070,
      "taken_at": "2016-07-05T18:07:50+00:00"
    },
    "sfomuseum:placetype": "instagram",
    "wof:name": "..",
    "wof:placetype": "custom"
  },
  "geometry": {"coordinates":[-122.386166,37.616356],"type":"Point"}
}
