{
  "type": "Feature",
  "properties": {
    "date:cessation_lower": "2022-05-04",
    "date:cessation_upper": "2022-05-04",
    "date:inception_lower": "2022-05-04",
    "date:inception_upper": "2022-05-04",
    "instagram:post": {
      "caption": {
        "body": "May the fourth be with you! Japanese airline ANA (All Nippon Airways) has several planes with fun livery. One of its most famous is a Star Wars-themed aircraft, which visited SFO frequently. Featuring BB-8, an android from the franchise’s most recent trilogy, the Boeing 777-300 was flown on the Tokyo to San Francisco route. The last flight for the aircraft in this livery on March 31, 2022.",
        "excerpt": "May the fourth be with you!",
        "hashtags": [
          "MaytheFourth",
          "StarWarsDay",
          "ANA",
          "BB8",
          "AvGeek",
          "AviationHistory"
        ]
      },
      "media_id": "029cbb76bfb690bb1193130ad2ab45af8e7caf21",
      "path": "media/posts/202205/279711721_325092733041339_4464861144360772075_n_17899136798604094.jpg",
      "perceptual_hash": "p:862fd93812c64f67",
      "taken": 1651653600,
      "taken_at": "May 4, 2022, 8:40 AM"
    },
    "sfomuseum:placetype": "instagram",
    "wof:name": "May the fourth be with you!..",
    "wof:placetype": "custom",
    "wof:placetype_alt": [
      "instagram"
    ]
  },
  "geometry": {"coordinates":[-122.386166,37.616356],"type":"Point"}
}
