{
  "type": "Feature",
  "properties": {
    "date:cessation_lower": "2023-08-07",
    "date:cessation_upper": "2023-08-07",
    "date:inception_lower": "2023-08-07",
    "date:inception_upper": "2023-08-07",
    "instagram:post": {
      "caption": {
        "body": "San Francisco International Airport became the fourth busiest in the nation in 1962. Passenger traffic exceeded 10 million in 1966, and in the late 1960s the airport proposed a master plan. The master plan included the North Terminal (now Terminal 3), Central Terminal (now Terminal 2), and South Terminal (now Harvey Milk Terminal 1) surrounding a multi-level parking garage to make the most out of SFO’s footprint.   negative: San Francisco International Airport (SFO), architectural model; 1968 Transfer from San Francisco International Airport 2011.032.1971  https://bit.ly/44NXP7z",
        "excerpt": "San Francisco International Airport became the fourth busiest in the nation in 1962.",
        "hashtags": [
          "52Objects",
          "SFOHistory"
        ]
      },
      "media_id": "fc1b9c5d1bb657d47da1f1b28e48c2901d4ca714",
      "path": "media/other/361946747_732619462208319_3643759338735082966_n_18273700288150417.jpg",
      "perceptual_hash": "p:81442773763b5a9e",
      "taken": 1691397180,
      "taken_at": "Aug 07, 2023 8:33 am"
    },
    "sfomuseum:placetype": "instagram",
    "wof:name": "San Francisco International Airport became the fourth busiest in the nation in 1962...",
    "wof:placetype": "custom"
  },
  "geometry": {"coordinates":[-122.386166,37.616356],"type":"Point"}
}
