{
  "type": "Feature",
  "properties": {
    "instagram:post": {
      "caption": {
        "hashtags": [
          "KirksMonsters", 
          "KirkVonHammett", 
          "ClassicMonsters", 
          "BehindTheScenes"
        ]
      },
      "media_id": "b3902c1828dab3fc3257a5e9fcba3b06",
      "path": "photos/201505/b3902c1828dab3fc3257a5e9fcba3b06.jpg",
      "taken": 1431729514,
      "taken_at": "2015-05-15T22:38:34+00:00"
    },
    "sfomuseum:placetype": "instagram",
    "wof:name": "..",
    "wof:placetype": "custom"
  },
  "geometry": {"coordinates":[-122.386166,37.616356],"type":"Point"}
}
