{
  "type": "Feature",
  "properties": {
    "date:cessation_lower": "2015-05-15",
    "date:cessation_upper": "2015-05-15",
    "date:inception_lower": "2015-05-15",
    "date:inception_upper": "2015-05-15",
    "instagram:post": {
      "caption": {
        "hashtags": [
          "KirksMonsters",
          "KirkVonHammett",
          "ClassicMonsters",
          "BehindTheScenes"
        ]
      },
      "media_id": "b3902c1828dab3fc3257a5e9fcba3b06",
      "path": "media/other/11269659_813194445425250_1303719043_n_17841499231062499.jpg",
      "perceptual_hash": "p:abcdfc80c312917b",
      "taken": 1431700680,
      "taken_at": "May 15, 2015 2:38 pm"
    },
    "sfomuseum:placetype": "instagram",
    "wof:name": "..",
    "wof:placetype": "custom",
    "wof:placetype_alt": [
      "instagram"
    ]
  },
  "geometry": {"coordinates":[-122.386166,37.616356],"type":"Point"}
}
