{
  "type": "Feature",
  "properties": {
    "date:cessation_lower": "2016-10-27",
    "date:cessation_upper": "2016-10-27",
    "date:inception_lower": "2016-10-27",
    "date:inception_upper": "2016-10-27",
    "instagram:post": {
      "caption": {
        "hashtags": [
          "ThrowbackThursday",
          "SFOHistory",
          "SFOMuseum",
          "AviationHistory"
        ]
      },
      "location": "San Francisco International Airport (SFO)",
      "media_id": "43261e89082a418cbe57e7e9694ab79f",
      "path": "photos/201610/43261e89082a418cbe57e7e9694ab79f.jpg",
      "perceptual_hash": "p:bc029cfb0f2d1cd4",
      "taken": 1477556040,
      "taken_at": "Oct 27, 2016, 8:14 AM"
    },
    "sfomuseum:placetype": "instagram",
    "wof:name": "..",
    "wof:placetype": "custom"
  },
  "geometry": {"coordinates":[-122.386166,37.616356],"type":"Point"}
}
