{
  "type": "Feature",
  "properties": {
    "date:cessation_lower": "2018-08-17",
    "date:cessation_upper": "2018-08-17",
    "date:inception_lower": "2018-08-17",
    "date:inception_upper": "2018-08-17",
    "instagram:post": {
      "caption": {
        "body": "The Golden Gate International Exposition was held from February 1939 to September 1940 to celebrate construction of the Golden Gate Bridge and the San Francisco-Oakland Bay Bridge. The exposition was installed on Treasure Island, a 400-acre artificial island constructed by the Works Progress Administration (WPA) from 1936 to 1937. Technologies such as radio and television were promoted at both expositions, and a number of radios were introduced to commemorate the events, including two versions of the 40X–50 series by RCA, and the magnificent “World's Fair Special” by Zenith. \"On the Radio\" is on display, post-security, in Terminal 3. http://bit.ly/RadioSFO",
        "excerpt": "The Golden Gate International Exposition was held from February 1939 to September 1940 to celebrate construction of the Golden Gate Bridge and the San Francisco-Oakland Bay Bridge.",
        "hashtags": [
          "radioSFO",
          "ontheradio",
          "radio",
          "radios",
          "wireless",
          "vintageradios",
          "transistorradio",
          "portableradio",
          "retroradio",
          "antique",
          "worldsfair",
          "sanfrancisco",
          "baybridge",
          "zenith"
        ]
      },
      "media_id": "7da6e78e3a928efa027b435e2428efcf",
      "path": "media/posts/201808/39082096_259832441518378_966858474757554176_n_17971093267054764.jpg",
      "perceptual_hash": "p:fe9e9cb9a1c090b1",
      "taken": 1534494180,
      "taken_at": "Aug 17, 2018, 8:23 AM"
    },
    "sfomuseum:placetype": "instagram",
    "wof:name": "The Golden Gate International Exposition was held from February 1939 to September 1940 to celebrate construction of the Golden Gate Bridge and the San Francisco-Oakland Bay Bridge...",
    "wof:placetype": "custom"
  },
  "geometry": {"coordinates":[-122.386166,37.616356],"type":"Point"}
}
