{
  "type": "Feature",
  "properties": {
    "instagram:post": {
      "caption": {
        "body": "At the saloon? In a pinch and need some buttons? This coin-operated machine from around 1905 would have had you buttoned-up in no time and for only 5¢. A men’s fashion necessity in the 20th century, buttons kept celluloid collars in place on dress shirts.  All objects are courtesy of Joe Welch American Antique Museum in San Bruno, California. \"The Automatic Age: Coin-Operated Machines\" is on display, pre-security, in the International Terminal. http://bit.ly/CoinOperated",
        "hashtags": [
          "CoinOperated", 
          "TheAutomaticAge", 
          "coinop", 
          "vintage", 
          "antique", 
          "gamemachines", 
          "slotmachine", 
          "slotmachines", 
          "buttons", 
          "mensfashion"
        ]
      },
      "location": "San Francisco International Airport (SFO)",
      "media_id": "a4e826056bc2e149f8e2c51f98690f2d",
      "path": "photos/201806/a4e826056bc2e149f8e2c51f98690f2d.jpg",
      "taken": 1527893106,
      "taken_at": "2018-06-01T22:45:06+00:00"
    },
    "sfomuseum:placetype": "instagram",
    "wof:name": "Instagram message #%!d(string=a4e826056bc2e149f8e2c51f98690f2d)",
    "wof:placetype": "custom"
  },
  "geometry": {"coordinates":[-122.386166,37.616356],"type":"Point"}
}
