{
  "type": "Feature",
  "properties": {
    "date:cessation_lower": "2020-07-22",
    "date:cessation_upper": "2020-07-22",
    "date:inception_lower": "2020-07-22",
    "date:inception_upper": "2020-07-22",
    "instagram:post": {
      "caption": {
        "body": "Artist Alexander Calder was born #onthisday in 1898. In the early 1970s, Calder was commissioned to paint several aircraft operated by Braniff International Airways. One of Calder's contributions was \"The Flying Colors of the United States,\" a livery to commemorate the U.S. Bicentennial and designed for a Boeing 727. Do you have a favorite airline livery?  Image: Braniff International Airways poster, c. 1976. Gift of the William Hough Collection.  2006.010.395",
        "excerpt": "Artist Alexander Calder was born #onthisday in 1898.",
        "hashtags": [
          "AlexanderCalder",
          "avgeek",
          "Braniff",
          "MuseumFromHome"
        ]
      },
      "media_id": "6b808b2160a29d3cc3ebef7aa1e376d6",
      "path": "media/other/109874241_2675535332734459_2225374158058862455_n_17863964887979383.jpg",
      "perceptual_hash": "p:aa470bacfd1f49a0",
      "taken": 1595406660,
      "taken_at": "Jul 22, 2020 8:31 am"
    },
    "sfomuseum:placetype": "instagram",
    "wof:name": "Artist Alexander Calder was born #onthisday in 1898...",
    "wof:placetype": "custom",
    "wof:placetype_alt": [
      "instagram"
    ]
  },
  "geometry": {"coordinates":[-122.386166,37.616356],"type":"Point"}
}
