{
  "type": "Feature",
  "properties": {
    "date:cessation_lower": "2022-02-14",
    "date:cessation_upper": "2022-02-14",
    "date:inception_lower": "2022-02-14",
    "date:inception_upper": "2022-02-14",
    "instagram:post": {
      "caption": {
        "body": "London-based director Jacob Sutton employs the talents of Czech actor and dancer Kristián “Mr. Kriss” Mensa and German artist and choreographer Hannes Langolf to communicate the anticipation of a first kiss.   See “A Kiss” by Jacob Sutton in the Video Arts Gallery, located pre-security in the International Terminal with daily operating hours of 5:00am to 10:00pm, or online at: https://bit.ly/32WmhJJ",
        "excerpt": "London-based director Jacob Sutton employs the talents of Czech actor and dancer Kristián “Mr.",
        "hashtags": [
          "VideoArts",
          "VideoArtsSFO",
          "JacobSutton",
          "Kiss",
          "dance",
          "ValentinesDay"
        ],
        "users": [
          "jacobsutton_studio",
          "films.dance",
          "jacobjonasthecompany"
        ]
      },
      "file_hash": "149f34577100d7b89200b17f2d3cec8acdb7262c506b5e2925eb7b573bd5b6ad",
      "media_id": "d97988b5b338ecb3b01e66ffd6a9f3db550524bb",
      "path": "media/other/684F2CB7E7B5241745393F1EC443DB85_video_dashinit_17924505176127550.mp4",
      "taken": 1644838680,
      "taken_at": "Feb 14, 2022 11:38 am"
    },
    "sfomuseum:placetype": "instagram",
    "wof:name": "London-based director Jacob Sutton employs the talents of Czech actor and dancer Kristián “Mr...",
    "wof:placetype": "custom"
  },
  "geometry": {"coordinates":[-122.386166,37.616356],"type":"Point"}
}
