{
  "type": "Feature",
  "properties": {
    "date:cessation_lower": "2022-11-07",
    "date:cessation_upper": "2022-11-07",
    "date:inception_lower": "2022-11-07",
    "date:inception_upper": "2022-11-07",
    "instagram:post": {
      "caption": {
        "body": "#Onthisday in 2017, United Airlines’ last scheduled Boeing 747 flight departed from SFO. Recreating the journey of the first United 747 flight from SFO to Honolulu in 1970, the airline threw a farewell party in Terminal 3 of SFO. Dubbed the “Friend Ship” when first introduced by United, the wide-body 747 provided an entirely new level of passenger comfort and service. In early versions, the second deck behind the cockpit was outfitted as a “red carpet lounge” that passengers accessed via a spiral staircase. United also boasted that they had moved “the kitchen out of the living room” by moving the galley from the cabin down to the spacious cargo hold.",
        "excerpt": "#Onthisday in 2017, United Airlines’ last scheduled Boeing 747 flight departed from SFO.",
        "hashtags": [
          "united",
          "boeing747",
          "SFOHistory",
          "avgeek"
        ]
      },
      "media_id": "3b04c0b71860d063df24c8cbefd4308269264a67",
      "path": "media/posts/202211/314403398_817726222835026_2952430728649371676_n_18259522933112545.jpg",
      "perceptual_hash": "p:b896c669933c1ec6",
      "taken": 1667841060,
      "taken_at": "Nov 07, 2022 5:11 pm"
    },
    "sfomuseum:placetype": "instagram",
    "wof:name": "#Onthisday in 2017, United Airlines’ last scheduled Boeing 747 flight departed from SFO...",
    "wof:placetype": "custom",
    "wof:placetype_alt": [
      "instagram"
    ]
  },
  "geometry": {"coordinates":[-122.386166,37.616356],"type":"Point"}
}
