{
  "type": "Feature",
  "properties": {
    "date:cessation_lower": "2015-08-28",
    "date:cessation_upper": "2015-08-28",
    "date:inception_lower": "2015-08-28",
    "date:inception_upper": "2015-08-28",
    "instagram:post": {
      "caption": {
        "hashtags": [
          "avgeek"
        ]
      },
      "media_id": "25f9828e8a0b83c30a0af998943dd55f",
      "path": "media/posts/201508/11375219_1134943423187001_1925505094_n_17842238662062499.jpg",
      "perceptual_hash": "p:c1949acf9d699561",
      "taken": 1440785760,
      "taken_at": "Aug 28, 2015, 6:16 PM"
    },
    "sfomuseum:placetype": "instagram",
    "wof:name": "..",
    "wof:placetype": "custom"
  },
  "geometry": {"coordinates":[-122.386166,37.616356],"type":"Point"}
}
