{
  "type": "Feature",
  "properties": {
    "date:cessation_lower": "2021-06-19",
    "date:cessation_upper": "2021-06-19",
    "date:inception_lower": "2021-06-19",
    "date:inception_upper": "2021-06-19",
    "instagram:post": {
      "caption": {
        "body": "In 1834, the South Carolina General Assembly passed a draconian law making it illegal to teach enslaved African Americans to read and write. By inscribing his pottery with poetry and signing his name, the enslaved potter known as Dave engaged in an exceptional act of resistance. Learn more about the life and work of David Drake, the surname he took upon emancipation, in our most recent exhibition, Stoneware Stories.  Juneteenth, a holiday celebrated - and now officially recognized as a federal holiday - nationally on June 19th, commemorates the end of slavery in the United States. In recognition of this historic day and all that it means for our country to continue the fight for equality, San Francisco's annual Juneteenth celebrations honor the achievements and determination of the African-American community with a festival and parade along Fillmore Street, where the first San Francisco Juneteenth celebration was held in 1950. The event usually draws some 75,000 people to the Fillmore District for the parade, a classic car show, a traditional African Uhuru village, and other activities. This year, however, due to COVID-19, smaller in-person and virtual experiences are planned. To learn more about these events, please visit https://www.sftravel.com/article/celebrate-juneteenth-san-francisco-way  On Saturday night, @flysfo will be lighting our International Terminal in red, black and green in celebration.  “Stoneware Stories: Folk Pottery of Edgefield, South Carolina” is on view pre-security in the International Terminal, and online at: https://bit.ly/StonewareStories \u003c— link in bio",
        "excerpt": "In 1834, the South Carolina General Assembly passed a draconian law making it illegal to teach enslaved African Americans to read and write.",
        "hashtags": [
          "Juneteenth",
          "juneteenthcelebration",
          "StonewareStories"
        ]
      },
      "media_id": "f553b8f416efe8eb313d69d81d9d5a130ab7ecd3",
      "path": "media/posts/202106/201896554_172232764870031_9102738687788092708_n_17900922719054015.jpg",
      "perceptual_hash": "p:aaeb818f9cec3390",
      "taken": 1624098900,
      "taken_at": "Jun 19, 2021, 10:35 AM"
    },
    "sfomuseum:placetype": "instagram",
    "wof:name": "In 1834, the South Carolina General Assembly passed a draconian law making it illegal to teach enslaved African Americans to read and write...",
    "wof:placetype": "custom",
    "wof:placetype_alt": [
      "instagram"
    ]
  },
  "geometry": {"coordinates":[-122.386166,37.616356],"type":"Point"}
}
