{
  "type": "Feature",
  "properties": {
    "date:cessation_lower": "2022-06-09",
    "date:cessation_upper": "2022-06-09",
    "date:inception_lower": "2022-06-09",
    "date:inception_upper": "2022-06-09",
    "instagram:post": {
      "caption": {
        "body": "Founded by George T. Baker in 1934, National Airlines started as an air mail carrier, as did many airlines at that time. Initially based in St. Petersburg, it began by transporting mail between destinations within Florida. By the end of the decade, the growing company opened a service to New Orleans, called the “Buccaneer Route.”  In 1944, National was awarded a New York-Miami route; flights began the following year. Flight times on the route were shortened in 1946 when the Douglas DC-4 was introduced, allowing non-stop flights and increasing both revenue and prestige.  Expansion continued through the 1950s with the introduction of a jet airliner at the end of the decade. National had the distinction of becoming the first domestic operator of jets in the United States after leasing a Boeing 707-120 jet from Pan American—which was only flying internationally. On December 10, 1958, the airline inaugurated jet service between New York and Miami. In 1961, National's route service was extended from Houston to California cities including Los Angeles, San Diego, and San Francisco.   In 1980, Pan American World Airways purchased National Airlines to expand into the U.S. domestic market. Pan American continued to fly National’s domestic routes until it ceased operations in 1991.",
        "excerpt": "Founded by George T. Baker in 1934, National Airlines started as an air mail carrier, as did many airlines at that time.",
        "hashtags": [
          "DefunctThursday",
          "NationalAirlines",
          "AvGeek",
          "AviationHistory"
        ]
      },
      "media_id": "317323f79b4ff53e09ba5b5cad0205f6fb5cc08b",
      "path": "media/posts/202206/286798096_689005475533248_6375434125657950603_n_17961937588697537.jpg",
      "perceptual_hash": "p:d260ad9f95c068fa",
      "taken": 1654802460,
      "taken_at": "Jun 9, 2022, 7:21 PM"
    },
    "sfomuseum:placetype": "instagram",
    "wof:name": "Founded by George T. Baker in 1934, National Airlines started as an air mail carrier, as did many airlines at that time...",
    "wof:placetype": "custom",
    "wof:placetype_alt": [
      "instagram"
    ]
  },
  "geometry": {"coordinates":[-122.386166,37.616356],"type":"Point"}
}
