{
  "type": "Feature",
  "properties": {
    "instagram:post": {
      "caption": {
        "body": "\"The ocean has given me so much…it has taught me patience, taught me respect, and helped harness and control fear and turn it into excitement.\" —Ray Collins (@raycollinsphoto)",
        "users": [
          "raycollinsphoto"
        ]
      },
      "location": "San Francisco International Airport (SFO)",
      "media_id": "5e5fd9be5afd5151cfe384040d150cdc",
      "path": "photos/201611/5e5fd9be5afd5151cfe384040d150cdc.jpg",
      "taken": 1478459724,
      "taken_at": "2016-11-06T19:15:24+00:00"
    },
    "sfomuseum:placetype": "instagram",
    "wof:name": "Instagram message #%!d(string=5e5fd9be5afd5151cfe384040d150cdc)",
    "wof:placetype": "custom"
  },
  "geometry": {"coordinates":[-122.386166,37.616356],"type":"Point"}
}
