{
  "type": "Feature",
  "properties": {
    "date:cessation_lower": "2019-01-15",
    "date:cessation_upper": "2019-01-15",
    "date:inception_lower": "2019-01-15",
    "date:inception_upper": "2019-01-15",
    "instagram:post": {
      "caption": {
        "body": "A distinctly modern, consumer-based American youth culture emerged during the 1950s. On average, middle-class adolescents earned more in allowance per week than many families took in during the Great Depression, and young people became consumers for the first time. Toys and other products were marketed specifically to girls and boys, and kids personalized their rooms with a variety of items. Hula hoops, jump ropes, plastic purses, chewing-gum wrapper chains, and other fads abounded. \"The Modern Consumer: Products and Style\" is on display, post-security, in Terminal 3. http://bit.ly/1950sConsumer",
        "excerpt": "A distinctly modern, consumer-based American youth culture emerged during the 1950s.",
        "hashtags": [
          "1950sConsumer",
          "1950s",
          "50s"
        ]
      },
      "media_id": "152fcb2e58549c1560a7e15e396365ab",
      "path": "media/posts/201901/47693311_280922132594364_576958331011465531_n_18021478309047250.jpg",
      "perceptual_hash": "p:93b834c65b53646d",
      "taken": 1547574840,
      "taken_at": "Jan 15, 2019, 5:54 PM"
    },
    "sfomuseum:placetype": "instagram",
    "wof:name": "A distinctly modern, consumer-based American youth culture emerged during the 1950s...",
    "wof:placetype": "custom"
  },
  "geometry": {"coordinates":[-122.386166,37.616356],"type":"Point"}
}
