{
  "type": "Feature",
  "properties": {
    "date:cessation_lower": "2018-09-24",
    "date:cessation_upper": "2018-09-24",
    "date:inception_lower": "2018-09-24",
    "date:inception_upper": "2018-09-24",
    "instagram:post": {
      "caption": {
        "body": "This is your last week to see \"The Automatic Age: Coin-Operated Machines.\" Coin-operated machines combined mechanical novelty and automated convenience. At the drop of a coin, they vended goods, provided entertainment, and offered potential jackpot payouts and free merchandise. These intriguing devices incorporated decorative graphics and innovative mechanisms that captured the attention of people worldwide. Installed on store counters and in saloons, hotels, amusement arcades, and other public places, coin-operated machines generated revenue from clientele and passersby with minimal supervision and maintenance.  All objects are courtesy of Joe Welch American Antique Museum in San Bruno, California. \"The Automatic Age: Coin-Operated Machines\" is on display, pre-security, in the International Terminal. http://bit.ly/CoinOperated",
        "excerpt": "This is your last week to see \"The Automatic Age: Coin-Operated Machines.\"",
        "hashtags": [
          "coinoperated",
          "TheAutomaticAge",
          "coinop",
          "vintage",
          "antique",
          "gamemachines",
          "slotmachine",
          "slotmachines"
        ]
      },
      "media_id": "eeb6bf2642dc3572d10d117e80f05950",
      "path": "media/posts/201809/41555101_1114966631986592_6743716231224844441_n_17964897634125612.jpg",
      "perceptual_hash": "p:d6c3691c939517b2",
      "taken": 1537788300,
      "taken_at": "Sep 24, 2018, 11:25 AM"
    },
    "sfomuseum:placetype": "instagram",
    "wof:name": "This is your last week to see \"The Automatic Age: Coin-Operated Machines.\"..",
    "wof:placetype": "custom"
  },
  "geometry": {"coordinates":[-122.386166,37.616356],"type":"Point"}
}
