{
  "type": "Feature",
  "properties": {
    "instagram:post": {
      "caption": {
        "body": "As SFO Museum's galleries are in unconventional, always-open spaces in the Airport's terminal, we always stage our objects and test our mounts before officially installing objects. Here, life-size slot machines to be featured in an upcoming exhibition in Terminal 3 are temporarily staged in our workspace.",
        "excerpt": "As SFO Museum's galleries are in unconventional, always-open spaces in the Airport's terminal, we always stage our objects and test our mounts before officially installing objects."
      },
      "media_id": "498f265e77725c56cfa29d6c87cf4de1",
      "path": "photos/201611/498f265e77725c56cfa29d6c87cf4de1.jpg",
      "taken": 1479958761,
      "taken_at": "2016-11-24T03:39:21+00:00"
    },
    "sfomuseum:placetype": "instagram",
    "wof:name": "As SFO Museum's galleries are in unconventional, always-open spaces in the Airport's terminal, we always stage our objects and test our mounts before officially installing objects...",
    "wof:placetype": "custom"
  },
  "geometry": {"coordinates":[-122.386166,37.616356],"type":"Point"}
}
