{
  "type": "Feature",
  "properties": {
    "date:cessation_lower": "2020-03-23",
    "date:cessation_upper": "2020-03-23",
    "date:inception_lower": "2020-03-23",
    "date:inception_upper": "2020-03-23",
    "instagram:post": {
      "caption": {
        "body": "In 1971, TWA (Trans World Airlines) introduced a new group of flight attendant uniforms conceived by Rome-based fashion designer Valentino Garavani. The uniform came in three colors: purple, brown, or beige. It featured a range of wardrobe combinations in a polyester knit fabric, including a form-fitting minidress, pants, and a frock coat. The outfits came with signature Valentino buttons and matching scarves, and could be worn with pumps or go-go boots. In promotions, flight attendants were featured wearing various colors and combinations of the uniform. This promotional image shows a flight attendant wearing the beige frock coat over the minidress. Do you remember this uniform?  See “Widebody: The Launch of the Jumbojets in the Early 1970s” online at:  http://bit.ly/WidebodyAV",
        "excerpt": "In 1971, TWA (Trans World Airlines) introduced a new group of flight attendant uniforms conceived by Rome-based fashion designer Valentino Garavani.",
        "hashtags": [
          "WidebodyAV",
          "avgeek",
          "Widebody",
          "jumbojet",
          "jetage",
          "valentino",
          "fashion",
          "crewlife",
          "uniform",
          "flightattendant",
          "MuseumFromHome"
        ]
      },
      "media_id": "cff7a59bc2e1bb0c46a404e59638496e",
      "path": "media/posts/202003/90997161_677276016410855_1934048871902249841_n_18091981537158521.jpg",
      "perceptual_hash": "p:d59c33976b273830",
      "taken": 1584997800,
      "taken_at": "Mar 23, 2020 9:10 pm"
    },
    "sfomuseum:placetype": "instagram",
    "wof:name": "In 1971, TWA (Trans World Airlines) introduced a new group of flight attendant uniforms conceived by Rome-based fashion designer Valentino Garavani...",
    "wof:placetype": "custom",
    "wof:placetype_alt": [
      "instagram"
    ]
  },
  "geometry": {"coordinates":[-122.386166,37.616356],"type":"Point"}
}
