{
  "type": "Feature",
  "properties": {
    "instagram:post": {
      "caption": {
        "body": "Whoo HOO! SFO Museum’s move is well underway! Our new shiny collections storage is ready for our objects. This state-of-the-art storage room was constructed with our collection in mind and will house much of our 3D items. Stay tuned for more updates about SFO Museum’s move. ",
        "hashtags": [
          "museummonday", 
          "behindthescenes", 
          "museumlife"
        ]
      },
      "media_id": "721d6f73e57653c3936ec53b1185d04e",
      "path": "photos/201808/721d6f73e57653c3936ec53b1185d04e.jpg",
      "taken": 1533600900,
      "taken_at": "2018-08-07T00:15:00+00:00"
    },
    "sfomuseum:placetype": "instagram",
    "wof:name": "Instagram message #%!d(string=721d6f73e57653c3936ec53b1185d04e)",
    "wof:placetype": "custom"
  },
  "geometry": {"coordinates":[-122.386166,37.616356],"type":"Point"}
}
