{
  "type": "Feature",
  "properties": {
    "date:cessation_lower": "2023-12-08",
    "date:cessation_upper": "2023-12-08",
    "date:inception_lower": "2023-12-08",
    "date:inception_upper": "2023-12-08",
    "instagram:post": {
      "caption": {
        "body": "Join us for a public panel discussion and exhibition tour of “Unlocking an Archival Treasure: The Harold Bixby Collection” tomorrow, December 9, 2023, from 1:30 to 3:00, in the Louis A. Turpen Aviation Museum \u0026 Library in the International Terminal.  https://www.eventbrite.com/e/the-harold-bixby-collection-public-panel-discussion-and-exhibition-tour-tickets-764200844297  Harold McMillan Bixby (1890-1965) was a midwestern businessman and amateur pilot, whose passion for aviation led to a second career that encompassed remarkable milestones in air travel during the 1920s and 30s.  In 1927, Bixby joined a group of businessmen to help finance Charles Lindbergh’s (1902-74) historic transatlantic flight later that year. Bixby celebrated with the famous pilot after his arrival in St. Louis during the 1928 Goodwill Tour of the Americas. Bixby and Lindbergh remained lifelong friends.   “Unlocking an Archival Treasure: The Harold Bixby Collection” is on display in the Aviation Museum and Library. Located pre-security in the International Terminal, the Aviation Museum and Library is open daily from 10am to 4:30pm. https://www.sfomuseum.org/exhibitions/harold-bixby-collection",
        "excerpt": "Join us for a public panel discussion and exhibition tour of “Unlocking an Archival Treasure: The Harold Bixby Collection” tomorrow, December 9, 2023, from 1:30 to 3:00, in the Louis A. Turpen Aviation Museum \u0026 Library in the International Terminal.",
        "hashtags": [
          "BixbyCollection",
          "PanAm",
          "HaroldBixby",
          "AvGeek"
        ]
      },
      "media_id": "905f7277159ba6bcd210242a4a64ffc786b44f36",
      "path": "media/posts/202312/408530380_826822859454645_4844764076186543794_n_17894471636937440.jpg",
      "perceptual_hash": "p:c5351ac23eda3669",
      "taken": 1702054680,
      "taken_at": "Dec 08, 2023 4:58 pm"
    },
    "sfomuseum:placetype": "instagram",
    "wof:name": "Join us for a public panel discussion and exhibition tour of “Unlocking an Archival Treasure: The Harold Bixby Collection” tomorrow, December 9, 2023, from 1:30 to 3:00, in the Louis A. Turpen Aviation Museum \u0026 Library in the International Terminal...",
    "wof:placetype": "custom"
  },
  "geometry": {"coordinates":[-122.386166,37.616356],"type":"Point"}
}
