{
  "type": "Feature",
  "properties": {
    "instagram:post": {
      "caption": {
        "body": "#OnThisDay in 1964, the #Boeing 727 was introduced by Eastern Air Lines. The Boeing 727 was s a medium range, intermediate-capacity jetliner that featured a clean swept wing, a high horizontal stabilizer, and a unique tri-jet configuration. The only tri-jet to be developed by Boeing, the tri-jet design dictated that the horizontal stabilizer be placed well away from the middle engine, high on top of the vertical stabilizer. During the time of its production from the 1960s to the 1980s it was Boeing's best-selling jet with over 1,800 sold. Have you ever flown on a Boeing 727?  Image: Boeing 727-100, c. 1963. Gift of Robert W. Jackson. 2006.002.092 . . .",
        "excerpt": "#OnThisDay in 1964, the #Boeing 727 was introduced by Eastern Air Lines.",
        "hashtags": [
          "Boeing", 
          "727", 
          "avgeek"
        ]
      },
      "location": "SFO Museum",
      "media_id": "d6b7b7240c609fcb10f3fe8725d367f9",
      "path": "photos/201902/d6b7b7240c609fcb10f3fe8725d367f9.jpg",
      "taken": 1549079143,
      "taken_at": "2019-02-02T03:45:43+00:00"
    },
    "sfomuseum:placetype": "instagram",
    "wof:name": "#OnThisDay in 1964, the #Boeing 727 was introduced by Eastern Air Lines...",
    "wof:placetype": "custom"
  },
  "geometry": {"coordinates":[-122.386166,37.616356],"type":"Point"}
}
