{
  "type": "Feature",
  "properties": {
    "date:cessation_lower": "2019-01-14",
    "date:cessation_upper": "2019-01-14",
    "date:inception_lower": "2019-01-14",
    "date:inception_upper": "2019-01-14",
    "instagram:post": {
      "caption": {
        "body": "Inspired by memories of his own family vacations, Amsterdam-based filmmaker Jeroen Houben has crafted a sweet and dreamlike meditation on summer holidays, first crushes, and the courage required to reach out to someone who may care about you.  See \"Gips\" by Jeroen Houben, now playing in the Video Arts Room located pre-security in the International Terminal. http://ow.ly/mCzF30njnHE",
        "excerpt": "Inspired by memories of his own family vacations, Amsterdam-based filmmaker Jeroen Houben has crafted a sweet and dreamlike meditation on summer holidays, first crushes, and the courage required to reach out to someone who may care about you.",
        "hashtags": [
          "VideoArtsSFOM",
          "film",
          "video",
          "Gips",
          "Plaster",
          "childhood",
          "summer",
          "holidays",
          "comingofage"
        ],
        "users": [
          "jeroenhouben"
        ]
      },
      "file_hash": "15f576fb0773b070fb83b2efb114d4e7d43d296a15a6fd1d3c023b583506e01b",
      "media_id": "efe2efb062483eb98ace5671b91357ea92d82a38",
      "path": "media/other/DF468DC5BDA92E8DA1ACCF7EE05BF6BC_video_dashinit_17991782959156715.mp4",
      "taken": 1547474100,
      "taken_at": "Jan 14, 2019 1:55 pm"
    },
    "sfomuseum:placetype": "instagram",
    "wof:name": "Inspired by memories of his own family vacations, Amsterdam-based filmmaker Jeroen Houben has crafted a sweet and dreamlike meditation on summer holidays, first crushes, and the courage required to reach out to someone who may care about you...",
    "wof:placetype": "custom"
  },
  "geometry": {"coordinates":[-122.386166,37.616356],"type":"Point"}
}
