{
  "type": "Feature",
  "properties": {
    "instagram:post": {
      "caption": {
        "body": "During the late 1890s, as machining became prevalent and mechanical appliances were increasingly accessible, slot machine companies proliferated. Many of the color-wheel and roulette-based gambling devices, popularized as freestanding machines in carved, wooden cabinets, were also produced as ornate, cast-iron versions for the countertops of saloons and cigar stores. The Little Monte Carlo allowed five-way play with payouts determined by the color played. Mills Novelty Company produced this popular roulette machine from 1899 to 1915.  All objects are courtesy of the Joe Welch American Antique Museum. See \"#GamesofChance: Gambling Devices of the Mechanical Age\" on display, post-security, in Terminal 3. http://bit.ly/GamesofChance",
        "hashtags": [
          "slotmachines", 
          "vintage", 
          "gambling", 
          "castiron"
        ]
      },
      "media_id": "d709da0216ee17b29a34d2db31cb7ec6",
      "path": "photos/201706/d709da0216ee17b29a34d2db31cb7ec6.jpg",
      "taken": 1496340667,
      "taken_at": "2017-06-01T18:11:07+00:00"
    },
    "sfomuseum:placetype": "instagram",
    "wof:name": "Instagram message #%!d(string=d709da0216ee17b29a34d2db31cb7ec6)",
    "wof:placetype": "custom"
  },
  "geometry": {"coordinates":[-122.386166,37.616356],"type":"Point"}
}
