{
  "type": "Feature",
  "properties": {
    "date:cessation_lower": "2017-09-01",
    "date:cessation_upper": "2017-09-01",
    "date:inception_lower": "2017-09-01",
    "date:inception_upper": "2017-09-01",
    "instagram:post": {
      "caption": {
        "body": "Kanji, or Japanese character writing, is based on Chinese script and shares many meanings and definitions. Officially published in the Jōyō Kanji, around 2,000 Chinese-based characters are listed for use in conjunction with a distinct, Japanese kana alphabet. In 1915, Japanese printer and inventor Kyota Sugimoto (1882–1972) patented a typewriter that printed in both Chinese and Japanese. Manufactured by the Nippon Typewriter Company, the machine featured a large, sliding tray with room for 2,450 individual type-slugs. A moving carriage assembly mounted over the tray contained the typing mechanism. To operate, the typist positioned the tray and carriage along an x–y axis to select a type-slug, and depressed a button to retrieve, ink, and print.  Typewriter courtesy of Thomas S. Mullaney. Learn more about the typewriter in our exhibition, \"The Typewriter: An Innovation in Writing\", post-security, in Terminal 2. http://bit.ly/Thetypewriter",
        "excerpt": "Kanji, or Japanese character writing, is based on Chinese script and shares many meanings and definitions.",
        "hashtags": [
          "thetypewriter",
          "typewriter",
          "typewriters",
          "writing",
          "industrialdesign",
          "keyboard",
          "keyboards",
          "design",
          "innovation",
          "type",
          "typing",
          "typist",
          "oldschool",
          "writer",
          "writing",
          "vintagetypewriter",
          "vintage",
          "analog",
          "antique",
          "typewritten",
          "typewriting",
          "oldtypewriters",
          "typewritersofinstagram",
          "kanji",
          "japanese",
          "japan",
          "japanesetypewriter",
          "nippon",
          "typeslugs"
        ]
      },
      "media_id": "85f725f5848bcb1834e6a7904d21f738",
      "path": "photos/201709/85f725f5848bcb1834e6a7904d21f738.jpg",
      "perceptual_hash": "p:bcc5d03e2560cf35",
      "taken": 1504291486,
      "taken_at": "2017-09-01T18:44:46+00:00"
    },
    "sfomuseum:placetype": "instagram",
    "wof:name": "Kanji, or Japanese character writing, is based on Chinese script and shares many meanings and definitions...",
    "wof:placetype": "custom"
  },
  "geometry": {"coordinates":[-122.386166,37.616356],"type":"Point"}
}
