{
  "type": "Feature",
  "properties": {
    "date:cessation_lower": "2024-08-13",
    "date:cessation_upper": "2024-08-13",
    "date:inception_lower": "2024-08-13",
    "date:inception_upper": "2024-08-13",
    "instagram:post": {
      "caption": {
        "body": "Cheju or Jeju Island, located 50 miles off the southern peninsula of South Korea, is Korea's largest island. Seongsan Ilchulbong, a volcanic crater, pictured here, is considered one of Korea's most beautiful natural wonders. Featuring a breathtaking panoramic view of the Jeju Island, Hallasan Mountain and the surrounding ocean, millions of visitors climb to the top of the crater every year. Hallasan Mountain is the tallest peak in South Korea. Have you ever been to South Korea or Jeju Island?  📸: poster: Korean Air, Cheju Island; 1990s Transfer from San Francisco International Airport 2012.129.008  https://qr.sfomuseum.org/4cfOvgc",
        "excerpt": "Cheju or Jeju Island, located 50 miles off the southern peninsula of South Korea, is Korea's largest island.",
        "hashtags": [
          "52Posters",
          "SouthKorea",
          "KoreanAir",
          "TravelTuesday"
        ]
      },
      "media_id": "c1049c21ee9f27fff3f411021b71dc98eb50cc5d",
      "path": "media/other/455062056_1004613541675575_2872960405634685092_n_17918678501859210.jpg",
      "perceptual_hash": "p:bc9394da9a649b38",
      "taken": 1723563300,
      "taken_at": "Aug 13, 2024 3:35 pm"
    },
    "sfomuseum:placetype": "instagram",
    "wof:name": "Cheju or Jeju Island, located 50 miles off the southern peninsula of South Korea, is Korea's largest island...",
    "wof:placetype": "custom"
  },
  "geometry": {"coordinates":[-122.386166,37.616356],"type":"Point"}
}
