{
  "type": "Feature",
  "properties": {
    "date:cessation_lower": "2017-06-26",
    "date:cessation_upper": "2017-06-26",
    "date:inception_lower": "2017-06-26",
    "date:inception_upper": "2017-06-26",
    "instagram:post": {
      "caption": {
        "body": "Miniatures of the Temple of Vespasian and Titus, and those of the Temple of Castor and Pollux, were popular with visitors to these familiar ruins in Rome’s Forum. The earliest versions date to the first part of the 19th century, when archaeological excavations of these temples revealed much of their current forms. Thus, while we consider these places as ancient, it was their novelty that spurred the production of souvenirs.  All objects are from the Collection of Piraneseum. See \"All Roads Lead to #Rome: 17th–19th Century Architectural Souvenirs from the Collection of #Piraneseum\", on display, pre-security, in the International Terminal. http://bit.ly/AllRoadsRome ",
        "excerpt": "Miniatures of the Temple of Vespasian and Titus, and those of the Temple of Castor and Pollux, were popular with visitors to these familiar ruins in Rome’s Forum.",
        "hashtags": [
          "AllRoadsRome",
          "GrandTour",
          "Italy",
          "travel"
        ]
      },
      "media_id": "6d3599b4fab067154041d1c9fbb25dac",
      "path": "media/posts/201706/19425481_243133432846397_250407648602619904_n_17860361137191398.jpg",
      "perceptual_hash": "p:c3f09bb67d4942c8",
      "taken": 1498502880,
      "taken_at": "Jun 26, 2017, 6:48 PM"
    },
    "sfomuseum:placetype": "instagram",
    "wof:name": "Miniatures of the Temple of Vespasian and Titus, and those of the Temple of Castor and Pollux, were popular with visitors to these familiar ruins in Rome’s Forum...",
    "wof:placetype": "custom"
  },
  "geometry": {"coordinates":[-122.386166,37.616356],"type":"Point"}
}
