{
  "type": "Feature",
  "properties": {
    "date:cessation_lower": "2017-08-16",
    "date:cessation_upper": "2017-08-16",
    "date:inception_lower": "2017-08-16",
    "date:inception_upper": "2017-08-16",
    "instagram:post": {
      "caption": {
        "body": "Created for TWA by knitwear maker Dalton Apparel, this uniform was introduced in the summer of 1968 and worn until 1971. Made of Trevira polyester, the green collarless jacket has dropped cuffs. The short-sleeve dress, worn with a green tapered belt, has a plaid skirt with a front kick pleat and a solid top with collar. An attached neckerchief with a ring matches the skirt. \"Fashion In Flight: Airline Uniform Design\" is on display, pre-security, in the Aviation Museum. http://bit.ly/FashionInFlight1  Image: Trans World Airlines hostesses, 1968. Gift of TWA Clipped Wings International, Inc. 2002.113.397",
        "excerpt": "Created for TWA by knitwear maker Dalton Apparel, this uniform was introduced in the summer of 1968 and worn until 1971.",
        "hashtags": [
          "FashioninFlight",
          "WomenInAviation",
          "Avgeek",
          "aviationhistory",
          "crewlife",
          "paxex",
          "FlightAttendant",
          "crewlife",
          "FA",
          "fashion",
          "hostesses",
          "FlightAttendantlife",
          "Flightcrew",
          "uniform",
          "aviationgeek",
          "fashionHistory",
          "aviation",
          "dalton",
          "twa",
          "transworldairlines"
        ]
      },
      "media_id": "f978fea50d9d34894d377c14de244203",
      "path": "photos/201708/f978fea50d9d34894d377c14de244203.jpg",
      "perceptual_hash": "p:a46b6e759867c198",
      "taken": 1502922862,
      "taken_at": "2017-08-16T22:34:22+00:00"
    },
    "sfomuseum:placetype": "instagram",
    "wof:name": "Created for TWA by knitwear maker Dalton Apparel, this uniform was introduced in the summer of 1968 and worn until 1971...",
    "wof:placetype": "custom"
  },
  "geometry": {"coordinates":[-122.386166,37.616356],"type":"Point"}
}
