{
  "type": "Feature",
  "properties": {
    "date:cessation_lower": "2016-10-20",
    "date:cessation_upper": "2016-10-20",
    "date:inception_lower": "2016-10-20",
    "date:inception_upper": "2016-10-20",
    "instagram:post": {
      "caption": {
        "body": "Early airline uniforms were worn with shoes that complied with a designated type of footwear, and they were purchased individually. In the 1930s and ‘40s, sensible lace-up oxfords with low block heels provided stable footing in the cabins of the low-flying, unpressurized aircraft that often encountered turbulence. With post-War pressurized aircraft flying above the weather, and new fashion-designer outfits, slip-on shoes became a more stylish accessory. High-heel pumps were issued or designated for purchase by the 1950s, particularly the popular two-tone “spectator” shoe. Custom colored pumps and platform shoes, and modish knee-high boots completed many of the more daring uniform fashions of the 1960s and ‘70s. Such attention to footwear is still practiced by designers like Vivienne Westwood, whose Virgin Atlantic uniform offers heels in three heights. #crewlife #fashion #shoes  See more fashion in \"#FashionInFlight: A History of Airline Uniform Design\" located, pre-security, in the International Terminal. http://bit.ly/fashioninflight  United Air Lines stewardesses  1960s photograph Collection of United Airlines Archive R2016.0307.010",
        "excerpt": "Early airline uniforms were worn with shoes that complied with a designated type of footwear, and they were purchased individually."
      },
      "location": "San Francisco International Airport (SFO)",
      "media_id": "60773fa9f6b0bb301ee811c11f78fc1e",
      "path": "photos/201610/60773fa9f6b0bb301ee811c11f78fc1e.jpg",
      "perceptual_hash": "p:eddb96b48f8c4244",
      "taken": 1476930341,
      "taken_at": "2016-10-20T02:25:41+00:00"
    },
    "sfomuseum:placetype": "instagram",
    "wof:name": "Early airline uniforms were worn with shoes that complied with a designated type of footwear, and they were purchased individually...",
    "wof:placetype": "custom"
  },
  "geometry": {"coordinates":[-122.386166,37.616356],"type":"Point"}
}
