{
  "type": "Feature",
  "properties": {
    "date:cessation_lower": "2021-04-29",
    "date:cessation_upper": "2021-04-29",
    "date:inception_lower": "2021-04-29",
    "date:inception_upper": "2021-04-29",
    "instagram:post": {
      "caption": {
        "body": "College radio is a key outlet for underground genres such as instrumental rock and surf music. Throughout the 1980s, DJ Jim Dunfrund hosted “Surfwave” on KXLU-FM at Loyola Marymount University in Los Angeles. In the San Francisco Bay Area, DJ Phil Dirt featured “Surf’s Up” on KFJC-FM from Foothill College in Los Altos Hills, a tradition continued by DJ Cousin Mary every Saturday night on the KFJC Reverb Hour. We were lucky enough to have DJ Cousin Mary visit Surf’s Up! Instrumental Rock ‘n’ Roll, along with guitarist Ferenc Dobronyi of local surf music groups The TomorrowMen and Pollo del Mar, who are also featured in the exhibit.   See more of “Surf’s Up! Instrumental Rock ‘n’ Roll,” online, where you can also find a link to the exhibition playlist on Spotify. Link via bio.",
        "excerpt": "College radio is a key outlet for underground genres such as instrumental rock and surf music.",
        "hashtags": [
          "InstrumentalSurf",
          "surfrock",
          "surfmusic",
          "DJCousinMary"
        ],
        "users": [
          "kfjc897fm",
          "frankiepoolboy"
        ]
      },
      "media_id": "b73962b074281684cd62d0805cbfb9395b5891a8",
      "path": "media/posts/202104/180397131_796496717909097_8349719401272532106_n_17886336377100825.jpg",
      "perceptual_hash": "p:8f9c4eedda527801",
      "taken": 1619712660,
      "taken_at": "Apr 29, 2021 4:11 pm"
    },
    "sfomuseum:placetype": "instagram",
    "wof:name": "College radio is a key outlet for underground genres such as instrumental rock and surf music...",
    "wof:placetype": "custom",
    "wof:placetype_alt": [
      "instagram"
    ]
  },
  "geometry": {"coordinates":[-122.386166,37.616356],"type":"Point"}
}
