{
  "type": "Feature",
  "properties": {
    "date:cessation_lower": "2017-01-10",
    "date:cessation_upper": "2017-01-10",
    "date:inception_lower": "2017-01-10",
    "date:inception_upper": "2017-01-10",
    "instagram:post": {
      "caption": {
        "hashtags": [
          "TravelTuesday",
          "AvGeek",
          "AviationHistory",
          "London",
          "BOAC",
          "BEA",
          "BritishAirways"
        ]
      },
      "media_id": "1992bc804396919a739d5dc8ce473195",
      "path": "media/posts/201701/15877242_407101209681395_7471100056683151360_n_17846887090193864.jpg",
      "perceptual_hash": "p:bd694c67d3926990",
      "taken": 1484079120,
      "taken_at": "Jan 10, 2017, 8:12 PM"
    },
    "sfomuseum:placetype": "instagram",
    "wof:name": "..",
    "wof:placetype": "custom"
  },
  "geometry": {"coordinates":[-122.386166,37.616356],"type":"Point"}
}
