{
  "type": "Feature",
  "properties": {
    "instagram:post": {
      "caption": {
        "body": "SFO Museum has taken a break from social media to reflect on the police killing of unarmed people of color across the U.S. We stand in solidarity with the Black community and pledge to do better. Read more: https://sfomuseum.org/blacklivesmatter #BlackLivesMatter, now and always.",
        "excerpt": "SFO Museum has taken a break from social media to reflect on the police killing of unarmed people of color across the U.S. We stand in solidarity with the Black community and pledge to do better."
      },
      "media_id": "9d41d4294c17d871c410b747121b7514",
      "path": "photos/202007/9d41d4294c17d871c410b747121b7514.jpg",
      "taken": 1593720538,
      "taken_at": "2020-07-02T20:08:58+00:00"
    },
    "sfomuseum:placetype": "instagram",
    "wof:name": "SFO Museum has taken a break from social media to reflect on the police killing of unarmed people of color across the U.S. We stand in solidarity with the Black community and pledge to do better...",
    "wof:placetype": "custom"
  },
  "geometry": {"coordinates":[-122.386166,37.616356],"type":"Point"}
}
