{
  "type": "Feature",
  "properties": {
    "instagram:post": {
      "caption": {
        "body": "Kanban or Japanese shop signs feature imagery that allows potential customers to identify the things merchants sell in their shops. During the Meiji (1868-1912) and early Taisho (1912-26) periods, another type of shop sign developed. Rather than represent what the merchant sold inside, these shop signs display auspicious characters and symbols, such as beckoning cats, to lure customers.  This exhibition was made possible by a generous loan from Mingei International Museum. \"Maneki Neko: Japanese Beckoning Cat\" is on display post-security, in Terminal 2.  http://bit.ly/BeckoningCats",
        "hashtags": [
          "beckoningcats", 
          "beckoningcat", 
          "manekineko", 
          "catsofinstagram", 
          "cats", 
          "neko", 
          "meow", 
          "mewseum", 
          "japan", 
          "mingei", 
          "japanese", 
          "shopsign"
        ]
      },
      "media_id": "b7ba8a320395ba4e1211f36fe398cfe1",
      "path": "photos/201802/b7ba8a320395ba4e1211f36fe398cfe1.jpg",
      "taken": 1518665405,
      "taken_at": "2018-02-15T03:30:05+00:00"
    },
    "sfomuseum:placetype": "instagram",
    "wof:name": "Instagram message #%!d(string=b7ba8a320395ba4e1211f36fe398cfe1)",
    "wof:placetype": "custom"
  },
  "geometry": {"coordinates":[-122.386166,37.616356],"type":"Point"}
}
