{
  "type": "Feature",
  "properties": {
    "date:cessation_lower": "2014-09-19",
    "date:cessation_upper": "2014-09-19",
    "date:inception_lower": "2014-09-19",
    "date:inception_upper": "2014-09-19",
    "instagram:post": {
      "caption": {
        "hashtags": [
          "WhenArtRocked",
          "music",
          "posters",
          "sfhistory"
        ]
      },
      "media_id": "780a87a112d28df99f081a793b0c3394",
      "path": "photos/201409/780a87a112d28df99f081a793b0c3394.jpg",
      "perceptual_hash": "p:d6b10e52390fd8c7",
      "taken": 1411138320,
      "taken_at": "Sep 19, 2014, 2:52 PM"
    },
    "sfomuseum:placetype": "instagram",
    "wof:name": "..",
    "wof:placetype": "custom"
  },
  "geometry": {"coordinates":[-122.386166,37.616356],"type":"Point"}
}
