{
  "type": "Feature",
  "properties": {
    "date:cessation_lower": "2015-07-20",
    "date:cessation_upper": "2015-07-20",
    "date:inception_lower": "2015-07-20",
    "date:inception_upper": "2015-07-20",
    "instagram:post": {
      "caption": {
        "body": "What a whimsical video of Spirogyrate by Eric Staller! A @sfacgalleries commission found in Terminal 2 Post Security.  Thanks to @ejmahowald for the adventure!",
        "excerpt": "What a whimsical video of Spirogyrate by Eric Staller!",
        "hashtags": [
          "repost",
          "regram",
          "art",
          "sfac",
          "airportart",
          "sfo"
        ]
      },
      "file_hash": "6609bd6bee6a09e8a27f1aed53b6f155dbf49e1a0712c470811af5abde811301",
      "media_id": "782175f4591da3606d6e84c43ab7f9103c12a26b",
      "path": "media/other/4B41EFBCF40E33164E25DA6BA1A925AE_video_dashinit_17842019668062499.mp4",
      "taken": 1437398580,
      "taken_at": "Jul 20, 2015 1:23 pm"
    },
    "sfomuseum:placetype": "instagram",
    "wof:name": "What a whimsical video of Spirogyrate by Eric Staller!..",
    "wof:placetype": "custom"
  },
  "geometry": {"coordinates":[-122.386166,37.616356],"type":"Point"}
}
