{
  "type": "Feature",
  "properties": {
    "date:cessation_lower": "2019-12-06",
    "date:cessation_upper": "2019-12-06",
    "date:inception_lower": "2019-12-06",
    "date:inception_upper": "2019-12-06",
    "instagram:post": {
      "caption": {
        "body": "Can you imagine a roundtrip flight between California and the Philippine capital of Manila taking fifteen days? In 1935, the first scheduled transpacific airmail flight took eight days to reach Manila from Alameda, with stops in Honolulu, Midway Atoll, Wake Island, and Guam. After leaving Alameda on November 22, and landing in Manila, on November 29, the China Clipper started its long journey back to the United States on December 2. The trip took another four days to travel back to Alameda and landed #onthisday [Dec. 6] in 1935. The entire roundtrip flight time was 123 hours and 12 minutes. It had covered over 16,000 miles and set nineteen world records.  Learn more about early transpacific aviation in \"China Clipper\" on display, pre-security, in the Aviation Museum. http://bit.ly/chinaclipper  Image: Pan American Airways, Martin M-130 “China Clipper”, c. 1939, Gift of William T. Larkins. 2010.248.012",
        "excerpt": "Can you imagine a roundtrip flight between California and the Philippine capital of Manila taking fifteen days?",
        "hashtags": [
          "ChinaClipper",
          "aviationhistory",
          "avgeek",
          "panam"
        ]
      },
      "media_id": "4f20714a9fced045cd9554fe2b4c3472",
      "path": "media/posts/201912/74919294_152868462664519_1043468467702165238_n_17849444194743868.jpg",
      "perceptual_hash": "p:80cc375b6eb3c41b",
      "taken": 1575633060,
      "taken_at": "Dec 6, 2019, 11:51 AM"
    },
    "sfomuseum:placetype": "instagram",
    "wof:name": "Can you imagine a roundtrip flight between California and the Philippine capital of Manila taking fifteen days?..",
    "wof:placetype": "custom"
  },
  "geometry": {"coordinates":[-122.386166,37.616356],"type":"Point"}
}
