{
  "type": "Feature",
  "properties": {
    "date:cessation_lower": "2016-10-07",
    "date:cessation_upper": "2016-10-07",
    "date:inception_lower": "2016-10-07",
    "date:inception_upper": "2016-10-07",
    "instagram:post": {
      "caption": {
        "body": "Air France engaged the House of Dior to launch its new collection in 1962 as the jet age transformed world travel. Created by chief designer Marc Bohan (b. 1926), it followed his 1961 “Slim Look.” Hailed by fashion critics, this pivotal uniform elegantly married mobility with sophistication.  See more uniforms designed by Christian #Dior in \"#FashionInFlight: A History of Airline Uniform Design\", on display, pre-security, in the Aviation Museum and Library and the Main Hall of the International Terminal. The Aviation Museum and Library is open daily from 10am to 4:30pm. #fashion #hautecouture http://bit.ly/fashioninflight  Air France stewardess uniform  1962 Christian Dior Courtesy of Air France L2016.0306.001.01-.04",
        "excerpt": "Air France engaged the House of Dior to launch its new collection in 1962 as the jet age transformed world travel."
      },
      "media_id": "2a3fc206f154720f7a1d9189290a77da",
      "path": "media/posts/201610/14574112_552641861599931_8943385524010221568_n_17854730374073086.jpg",
      "perceptual_hash": "p:f0953831668cd9db",
      "taken": 1475833080,
      "taken_at": "Oct 7, 2016, 9:38 AM"
    },
    "sfomuseum:placetype": "instagram",
    "wof:name": "Air France engaged the House of Dior to launch its new collection in 1962 as the jet age transformed world travel...",
    "wof:placetype": "custom",
    "wof:placetype_alt": [
      "instagram"
    ]
  },
  "geometry": {"coordinates":[-122.386166,37.616356],"type":"Point"}
}
