{
  "type": "Feature",
  "properties": {
    "date:cessation_lower": "2022-11-15",
    "date:cessation_upper": "2022-11-15",
    "date:inception_lower": "2022-11-15",
    "date:inception_upper": "2022-11-15",
    "instagram:post": {
      "caption": {
        "body": "The Coast Guard Air Station San Francisco was commissioned #onthisday in 1940. As the “Guardians of the Golden Gate,” these dedicated officers and enlisted personnel are the ever-vigilant eyes in the sky. Their command and capabilities in aerial search and rescue and homeland security personify the Coast Guard motto Semper Paratus (Always Ready).   San Francisco Airport provided 20.53 acres at the mouth of its new man-made seaplane harbor for the Air Station site. In exchange, the federal government dredged and maintained the harbor and its channel to the bay. With a hangar, barracks, and a ramp, the new station was dedicated on February 15, 1941. Have you ever seen the Coast Guard building at SFO?",
        "excerpt": "The Coast Guard Air Station San Francisco was commissioned #onthisday in 1940.",
        "hashtags": [
          "avgeek",
          "SFOhistory",
          "CoastGuard"
        ]
      },
      "media_id": "77ee8d639e818b1d118819a959b97e5f6eda21a3",
      "path": "media/posts/202211/315610978_858966341958414_2769412634449393486_n_17971395649790066.jpg",
      "perceptual_hash": "p:91bbc6c6393be045",
      "taken": 1668530640,
      "taken_at": "Nov 15, 2022, 4:44 PM"
    },
    "sfomuseum:placetype": "instagram",
    "wof:name": "The Coast Guard Air Station San Francisco was commissioned #onthisday in 1940...",
    "wof:placetype": "custom"
  },
  "geometry": {"coordinates":[-122.386166,37.616356],"type":"Point"}
}
