{
  "type": "Feature",
  "properties": {
    "instagram:post": {
      "caption": {
        "body": "Can you see yourself in South America? Would you like a ride a llama in South America? In 1949, Pan American World Airways and Panagra (Pan American-Grace Airways) advertised their 'Round-the-Continent Air Cruise enticing passengers with next day arrivals. Have you ever been to South America?  Image: Pan American World Airways, Panagra (Pan American-Grace Airways) tourist information, South America, 1949. Gift of Jon E. Krupnick. 2008.056.0660",
        "excerpt": "Can you see yourself in South America?",
        "hashtags": [
          "TravelTuesday", 
          "SouthAmerica", 
          "PanAm", 
          "Panagra", 
          "avgeek", 
          "aviationhistory", 
          "llama"
        ]
      },
      "location": "SFO Museum",
      "media_id": "e43199642ac8eb44ca6068c55752f038",
      "path": "photos/201705/e43199642ac8eb44ca6068c55752f038.jpg",
      "taken": 1494354136,
      "taken_at": "2017-05-09T18:22:16+00:00"
    },
    "sfomuseum:placetype": "instagram",
    "wof:name": "Can you see yourself in South America?..",
    "wof:placetype": "custom"
  },
  "geometry": {"coordinates":[-122.386166,37.616356],"type":"Point"}
}
