{
  "type": "Feature",
  "properties": {
    "date:cessation_lower": "2017-05-09",
    "date:cessation_upper": "2017-05-09",
    "date:inception_lower": "2017-05-09",
    "date:inception_upper": "2017-05-09",
    "instagram:post": {
      "caption": {
        "body": "Can you see yourself in South America? Would you like a ride a llama in South America? In 1949, Pan American World Airways and Panagra (Pan American-Grace Airways) advertised their 'Round-the-Continent Air Cruise enticing passengers with next day arrivals. Have you ever been to South America?  Image: Pan American World Airways, Panagra (Pan American-Grace Airways) tourist information, South America, 1949. Gift of Jon E. Krupnick. 2008.056.0660",
        "excerpt": "Can you see yourself in South America?",
        "hashtags": [
          "TravelTuesday",
          "SouthAmerica",
          "PanAm",
          "Panagra",
          "avgeek",
          "aviationhistory",
          "llama"
        ]
      },
      "media_id": "e43199642ac8eb44ca6068c55752f038",
      "path": "media/posts/201705/18381926_428023364232618_443846528868548608_n_17866276819084271.jpg",
      "perceptual_hash": "p:a36a94b7718d6686",
      "taken": 1494325320,
      "taken_at": "May 9, 2017, 10:22 AM"
    },
    "sfomuseum:placetype": "instagram",
    "wof:name": "Can you see yourself in South America?..",
    "wof:placetype": "custom"
  },
  "geometry": {"coordinates":[-122.386166,37.616356],"type":"Point"}
}
