{
  "type": "Feature",
  "properties": {
    "date:cessation_lower": "2018-10-12",
    "date:cessation_upper": "2018-10-12",
    "date:inception_lower": "2018-10-12",
    "date:inception_upper": "2018-10-12",
    "instagram:post": {
      "caption": {
        "body": "The DC-10 was McDonnell Douglas’ first wide-body jetliner. The aircraft incorporated a tri-jet engine configuration with two engines mounted under the wings and one incorporated into the vertical stabilizer assembly. Like those on Boeing’s wide-body 747, the DC-10’s engines were high-bypass turbofans, which were capable of thrusting the aircraft to a maximum cruising speed of just over 600 miles per hour. The aircraft had a capacity of up to 400 passengers and offered similar wide-body spaciousness and comfort to the 747. The DC-10 also featured first-class and coach lounges and a lower deck galley. American Airlines introduced the DC-10-10 series in August 1971. Most international carriers chose the DC-10-30 series due to its extended transoceanic range. UTA introduced the aircraft in 1973, and by the mid-1970s, the carrier was operating it on many of its long-haul transatlantic routes to North and South America.  See \"Aviation Evolutions: The Jim Lund 1:72 Scale Model Airplane Collection\", which features more than 200 models, on display, pre-security, in the Aviation Museum. http://bit.ly/AviationEvolutions",
        "excerpt": "The DC-10 was McDonnell Douglas’ first wide-body jetliner.",
        "hashtags": [
          "AviationEvolutions",
          "jimlund",
          "avgeek",
          "aviationgeek",
          "aviation",
          "aviationhistory",
          "vintageaviation",
          "history",
          "aviationgeeks",
          "modelplane",
          "scalemodel",
          "avgeeks"
        ]
      },
      "media_id": "e112063d62601d71bfbbd49622c29a72",
      "path": "media/posts/201810/43769691_2440488452844407_2591241241635377349_n_17955678829163045.jpg",
      "perceptual_hash": "p:d98ab7359c685307",
      "taken": 1539370860,
      "taken_at": "Oct 12, 2018, 7:01 PM"
    },
    "sfomuseum:placetype": "instagram",
    "wof:name": "The DC-10 was McDonnell Douglas’ first wide-body jetliner...",
    "wof:placetype": "custom"
  },
  "geometry": {"coordinates":[-122.386166,37.616356],"type":"Point"}
}
