{
  "type": "Feature",
  "properties": {
    "date:cessation_lower": "2022-09-27",
    "date:cessation_upper": "2022-09-27",
    "date:inception_lower": "2022-09-27",
    "date:inception_upper": "2022-09-27",
    "instagram:post": {
      "caption": {
        "body": "Handkerchiefs, like samplers, display an infinite variety of handwork to showcase embroiderers’ talent and skills. Intricately embroidered handkerchiefs even made appropriate gifts for royalty. The small items sometimes served as keepsakes and were part of a genteel lady’s attire. Nineteenth-century portraits of Filipino ladies in their María Clara ensembles commonly depicted them holding the ubiquitous Spanish fan in one hand and a piña handkerchief in the other.  See \"From Pineapple to Piña: A Philippine Textile Treasure\" on display, post-security, in Harvey Milk Terminal 1 and online at: https://bit.ly/PineappletoPina",
        "excerpt": "Handkerchiefs, like samplers, display an infinite variety of handwork to showcase embroiderers’ talent and skills.",
        "hashtags": [
          "PineappletoPina",
          "piña",
          "pineapple",
          "lace",
          "fashion",
          "design",
          "Philippines"
        ]
      },
      "media_id": "f4d1b02e755b3c8bf78f87294721f1751d1bc9da",
      "path": "media/posts/202209/309060534_5813595541997686_5775714229221497119_n_17951632244138576.jpg",
      "perceptual_hash": "p:ea6d923926666d98",
      "taken": 1664271000,
      "taken_at": "Sep 27, 2022, 9:30 AM"
    },
    "sfomuseum:placetype": "instagram",
    "wof:name": "Handkerchiefs, like samplers, display an infinite variety of handwork to showcase embroiderers’ talent and skills...",
    "wof:placetype": "custom"
  },
  "geometry": {"coordinates":[-122.386166,37.616356],"type":"Point"}
}
