{
  "type": "Feature",
  "properties": {
    "instagram:post": {
      "caption": {
        "body": "When introduced in 1949 by Pan American World Airways, the Boeing 377 Stratocruiser was considered the most luxurious airliner aloft. Its unique, pressurized, “double-bubble” fuselage was equipped with two decks; the upper contained a roomy main cabin, while the lower featured the highly popular cocktail lounge. The Stratocruiser was able to cruise near the stratosphere at over 300 miles per hour. With a range of just over 4,000 miles, the airliner was well suited for transoceanic routes. Pan American World Airways launched Stratocruiser transpacific service from San Francisco to Hawai’i in April 1949, and transatlantic service to London in June 1949 as all first-class “President” service.  Image: Pan American World Airways, Boeing 377 Stratocruiser, late 1940s. Gift of the Captain John B. Russell Family. 2012.149.0846",
        "hashtags": [
          "Boeing377", 
          "377", 
          "Stratocruiser", 
          "avgeek"
        ]
      },
      "location": "San Francisco International Airport (SFO)",
      "media_id": "e19c77c46028abe1e801044d2aab1ff0",
      "path": "photos/201909/e19c77c46028abe1e801044d2aab1ff0.jpg",
      "taken": 1568923836,
      "taken_at": "2019-09-19T20:10:36+00:00"
    },
    "sfomuseum:placetype": "instagram",
    "wof:name": "Instagram message #%!d(string=e19c77c46028abe1e801044d2aab1ff0)",
    "wof:placetype": "custom"
  },
  "geometry": {"coordinates":[-122.386166,37.616356],"type":"Point"}
}
