{
  "type": "Feature",
  "properties": {
    "date:cessation_lower": "2014-07-01",
    "date:cessation_upper": "2014-07-01",
    "date:inception_lower": "2014-07-01",
    "date:inception_upper": "2014-07-01",
    "instagram:post": {
      "caption": {
        "hashtags": [
          "lace",
          "crochet"
        ]
      },
      "media_id": "bf602b2b591042e3bc4e01205e9c2154",
      "path": "photos/201406/bf602b2b591042e3bc4e01205e9c2154.jpg",
      "perceptual_hash": "p:d4a52b1a2b7b2f03",
      "taken": 1404144480,
      "taken_at": "Jun 30, 2014, 4:08 PM"
    },
    "sfomuseum:placetype": "instagram",
    "wof:name": "..",
    "wof:placetype": "custom"
  },
  "geometry": {"coordinates":[-122.386166,37.616356],"type":"Point"}
}
