{
  "type": "Feature",
  "properties": {
    "date:cessation_lower": "2017-09-26",
    "date:cessation_upper": "2017-09-26",
    "date:inception_lower": "2017-09-26",
    "date:inception_upper": "2017-09-26",
    "instagram:post": {
      "caption": {
        "body": "#OnThisDay Pan American World Airways acquired American Overseas Airlines (A.O.A.) from American Airlines in 1950. American Overseas Airlines started as American Export Airlines in 1937, and was purchased by American Airlines in 1945. A.O.A. was awarded routes to England, Iceland, Ireland, and other destinations in Europe. Once acquired, PAA obtained all of A.O.A. routes and assets including eight Boeing 377 Stratocruisers, seven Constellations, three DC-4s, and one DC-3.  Image: American Overseas Airlines (AOA) poster, Boeing 377 Stratocruiser, late 1940s. SFO Museum Collection. 1996.48.01",
        "excerpt": "#OnThisDay Pan American World Airways acquired American Overseas Airlines (A.O.A.) from American Airlines in 1950.",
        "hashtags": [
          "americanairlines",
          "americanair",
          "americanoverseasairlines",
          "aoa",
          "americanexportairlines",
          "panam",
          "panamerican",
          "paa",
          "Stratocruiser",
          "avgeek",
          "avationgeek",
          "aviation",
          "aviationhistory",
          "aviationlovers",
          "vintageaviation",
          "history",
          "avhistory",
          "aviationgeeks",
          "instaplane",
          "flying",
          "plane",
          "flight",
          "airline",
          "avgeeks",
          "aviation4u",
          "aviationdaily"
        ]
      },
      "media_id": "a312715fb8349ec547725f972bad1ddb",
      "path": "photos/201709/a312715fb8349ec547725f972bad1ddb.jpg",
      "perceptual_hash": "p:bae6c4b5e362c898",
      "taken": 1506360960,
      "taken_at": "Sep 25, 2017, 5:36 PM"
    },
    "sfomuseum:placetype": "instagram",
    "wof:name": "#OnThisDay Pan American World Airways acquired American Overseas Airlines (A.O.A.) from American Airlines in 1950...",
    "wof:placetype": "custom"
  },
  "geometry": {"coordinates":[-122.386166,37.616356],"type":"Point"}
}
