{
  "type": "Feature",
  "properties": {
    "instagram:post": {
      "caption": {
        "body": "Mario Armond Zamparelli created this highly original outfit for Hughes Airwest in 1972 to fulfill his vision of an airline uniform that he wanted “revved-up with a classic boldness in beautiful shapes streaming like light over the body.” The Sundance Yellow polyester stretch knit suit has a tightly contoured, full-zipper jacket that can be closed to the neck or opened to create a fold-down collar. The above-the-knee princess dress has a jewel collar and double –front, pleated skirt. The outfit included matching shoes or knee-high boots in crinkle leatherette. Zamparelli’s uniform collection was issued until 1977. \"#FashionInFlight: A Photo Album\" is on display, pre-security, in the Aviation Museum. http://bit.ly/FIFPhotos  Image: Hughes Airwest hostesses in uniforms by Mario Armond Zamparelli, c. 1972. The Hughes Airwest Collection/The Museum of Flight. R2016.0323.001",
        "hashtags": [
          "fashion", 
          "flightattendant", 
          "uniform", 
          "aviationhistory", 
          "avgeek", 
          "WomeninAviation", 
          "fashionHistory", 
          "aviation"
        ]
      },
      "media_id": "90e15484cf2e4f41143ab620ba4fa9a9",
      "path": "photos/201707/90e15484cf2e4f41143ab620ba4fa9a9.jpg",
      "taken": 1501087887,
      "taken_at": "2017-07-26T16:51:27+00:00"
    },
    "sfomuseum:placetype": "instagram",
    "wof:name": "Instagram message #%!d(string=90e15484cf2e4f41143ab620ba4fa9a9)",
    "wof:placetype": "custom"
  },
  "geometry": {"coordinates":[-122.386166,37.616356],"type":"Point"}
}
