{
  "type": "Feature",
  "properties": {
    "date:cessation_lower": "2016-06-24",
    "date:cessation_upper": "2016-06-24",
    "date:inception_lower": "2016-06-24",
    "date:inception_upper": "2016-06-24",
    "instagram:post": {
      "caption": {
        "body": "Pre-security, in the arrivals level of Terminal 3, we have on display a selection of work from Edward Chavez (1917-2004), a recognized master within the aircraft model-making community.",
        "excerpt": "Pre-security, in the arrivals level of Terminal 3, we have on display a selection of work from Edward Chavez (1917-2004), a recognized master within the aircraft model-making community."
      },
      "location": "San Francisco International Airport (SFO)",
      "media_id": "9057f289f67a0d41533efd74b6a55930",
      "path": "photos/201606/9057f289f67a0d41533efd74b6a55930.jpg",
      "perceptual_hash": "p:c11a3fec4d353364",
      "taken": 1466765940,
      "taken_at": "Jun 24, 2016, 10:59 AM"
    },
    "sfomuseum:placetype": "instagram",
    "wof:name": "Pre-security, in the arrivals level of Terminal 3, we have on display a selection of work from Edward Chavez (1917-2004), a recognized master within the aircraft model-making community...",
    "wof:placetype": "custom"
  },
  "geometry": {"coordinates":[-122.386166,37.616356],"type":"Point"}
}
