{
  "type": "Feature",
  "properties": {
    "date:cessation_lower": "2020-12-31",
    "date:cessation_upper": "2020-12-31",
    "date:inception_lower": "2020-12-31",
    "date:inception_upper": "2020-12-31",
    "instagram:post": {
      "caption": {
        "body": "On this last day of 2020, we wrap up SFO Museum’s 40th anniversary year with a celebration of the Aviation Museum \u0026 Library, which opened in December 2000. “History of San Francisco International Airport,” the Aviation Museum’s first exhibition, featured original documents, drawings, architectural elements, meteorological devices, building materials, and photographs that traced the development and operation of @flySFO from the opening of Mills Field in 1927 to the activation of the International Terminal in 2000. Do you remember this exhibition?",
        "excerpt": "On this last day of 2020, we wrap up SFO Museum’s 40th anniversary year with a celebration of the Aviation Museum \u0026 Library, which opened in December 2000.",
        "hashtags": [
          "SFOHistory",
          "TBTSFOM",
          "SFOMat40",
          "avgeek",
          "MuseumFromHome"
        ]
      },
      "media_id": "ef02a60ec54155c6acaa22508d427a7790716624",
      "path": "media/posts/202012/134393979_113622347213377_7280325552819813473_n_17891374453812203.jpg",
      "perceptual_hash": "p:88f2652933363be5",
      "taken": 1609449600,
      "taken_at": "Dec 31, 2020 9:20 pm"
    },
    "sfomuseum:placetype": "instagram",
    "wof:name": "On this last day of 2020, we wrap up SFO Museum’s 40th anniversary year with a celebration of the Aviation Museum \u0026 Library, which opened in December 2000...",
    "wof:placetype": "custom",
    "wof:placetype_alt": [
      "instagram"
    ]
  },
  "geometry": {"coordinates":[-122.386166,37.616356],"type":"Point"}
}
