{
  "type": "Feature",
  "properties": {
    "instagram:post": {
      "caption": {
        "body": "In the 1970s and 1980s, Pan American produced a series of children’s activity kits with the mascots Pierre and Penny Panda. With Pierre's Fabulous Flying fun kit, children could be entertained with cards, puzzles, fun facts, and other activities.  Image: Pan American World Airways children’s activity kit, 1980. Gift of the family of Armen A. Dildilian. 2015.113.014 a i",
        "hashtags": [
          "avgeek", 
          "MuseumFromHome", 
          "PAA", 
          "PanAm"
        ]
      },
      "media_id": "ab60a0472b35bda2d718473d84f6f108",
      "path": "photos/202005/ab60a0472b35bda2d718473d84f6f108.jpg",
      "taken": 1588993219,
      "taken_at": "2020-05-09T03:00:19+00:00"
    },
    "sfomuseum:placetype": "instagram",
    "wof:name": "Instagram message #%!d(string=ab60a0472b35bda2d718473d84f6f108)",
    "wof:placetype": "custom"
  },
  "geometry": {"coordinates":[-122.386166,37.616356],"type":"Point"}
}
