{
  "type": "Feature",
  "properties": {
    "date:cessation_lower": "2024-06-21",
    "date:cessation_upper": "2024-06-21",
    "date:inception_lower": "2024-06-21",
    "date:inception_upper": "2024-06-21",
    "instagram:post": {
      "caption": {
        "body": "“In keeping with physical fitness trends, I was always hoping that visitors, by viewing some forgotten object, might be exercising that area of the brain which holds onto the memory cells.”—Mickey McGowan, December 2022  The Unknown Museum, curated by Mickey McGowan, was conceived as part conceptual art, part hands-on experience. When confronted with so many common objects from years past, visitors often asked curator, Mickey McGowan, to see a specific item, and then proceeded to search for it among a multitude of similar things. The process evoked familiarity, comfort, and was thought-provoking. McGowan recalled a “special kind of laughter” heard from visitors, “not like you hear at comedy shows, but more like some incredible kind of therapeutic release, which was laughter but also joy and reminiscence–a rekindling.” These personal connections are the “secrets” behind the Unknown Museum.  A very special thank you to Mickey McGowan for making this exhibition possible. See “Recollections… from the Unknown Museum” on display, post-security, in Terminal 2. https://bit.ly/Unknown-Museum",
        "excerpt": "“In keeping with physical fitness trends, I was always hoping that visitors, by viewing some forgotten object, might be exercising that area of the brain which holds onto the memory cells.”—Mickey McGowan, December 2022  The Unknown Museum, curated by Mickey McGowan, was conceived as part conceptual art, part hands-on experience.",
        "hashtags": [
          "UnknownMuseum",
          "MickeyMcGowan",
          "BayArea",
          "BayAreaHistory"
        ]
      },
      "media_id": "1b03a5948eb7796a82284335291fd3855fe34406",
      "path": "media/posts/202406/448865300_434801282778379_609916909882884599_n_18004000691557305.jpg",
      "perceptual_hash": "p:81704a4fdeda13b5",
      "taken": 1718959500,
      "taken_at": "Jun 21, 2024 8:45 am"
    },
    "sfomuseum:placetype": "instagram",
    "wof:name": "“In keeping with physical fitness trends, I was always hoping that visitors, by viewing some forgotten object, might be exercising that area of the brain which holds onto the memory cells.”—Mickey McGowan, December 2022  The Unknown Museum, curated by Mickey McGowan, was conceived as part conceptual art, part hands-on experience...",
    "wof:placetype": "custom"
  },
  "geometry": {"coordinates":[-122.386166,37.616356],"type":"Point"}
}
