{
  "type": "Feature",
  "properties": {
    "date:cessation_lower": "2016-08-26",
    "date:cessation_upper": "2016-08-26",
    "date:inception_lower": "2016-08-26",
    "date:inception_upper": "2016-08-26",
    "instagram:post": {
      "caption": {
        "body": "San Diego-based Pacific Southwest Airlines gained notoriety in the 1970s for form-fitting dresses with dramatically raised hemlines. Cabin interiors were decorated in bright, flowery patterns complementing the pink, red, and apricot colors of the uniform to create what the company promoted as the California Look. This micro-mini dress in polyester was worn over a pair of red mini-shorts. It has a swirl pattern front and teardrop neckline. PSA uniforms of the period included perch hats in red wool felt worn at the side with hat combs, such as this heart-shaped fascinator.  See more fashions from the Bright Seventies in \"#FashionInFlight: A History of Airline Uniform Design\", on display, pre-security in the Aviation Museum and in the Main Hall of the International Terminal. http://bit.ly/fashioninflight",
        "excerpt": "San Diego-based Pacific Southwest Airlines gained notoriety in the 1970s for form-fitting dresses with dramatically raised hemlines."
      },
      "media_id": "f231081647e892def76902d462423230",
      "path": "media/other/14072944_1021473027975932_236000873_n_17861863273048846.jpg",
      "perceptual_hash": "p:dae7e0c38896bc94",
      "taken": 1472228520,
      "taken_at": "Aug 26, 2016 4:22 pm"
    },
    "sfomuseum:placetype": "instagram",
    "wof:name": "San Diego-based Pacific Southwest Airlines gained notoriety in the 1970s for form-fitting dresses with dramatically raised hemlines...",
    "wof:placetype": "custom",
    "wof:placetype_alt": [
      "instagram"
    ]
  },
  "geometry": {"coordinates":[-122.386166,37.616356],"type":"Point"}
}
