{
  "type": "Feature",
  "properties": {
    "date:cessation_lower": "2017-07-13",
    "date:cessation_upper": "2017-07-13",
    "date:inception_lower": "2017-07-13",
    "date:inception_upper": "2017-07-13",
    "instagram:post": {
      "caption": {
        "body": "What was SFO like back in the 1960s? This brochure maps out all the airlines and amenities available at the airport at the time. Did you ever visit the Aztec Bar or the Pancake Palace? How about flying on Pacific Airlines or SF\u0026O Helicopter Airlines?  Image: San Francisco International Airport (SFO) airport information, c. 1965. Gift of David A. Abercrombie, in memory of Stanley A. Abercrombie. 2001.039.697",
        "excerpt": "What was SFO like back in the 1960s?",
        "hashtags": [
          "avgeek",
          "airportmaps",
          "aviationhistory",
          "SFOHistory",
          "TBT",
          "ThrowbackThursday"
        ]
      },
      "media_id": "1c3a24dec974ce33efcdb70d25da5a9c1b490633",
      "path": "media/posts/201707/19985939_311816409265667_2900892444398714880_n_17863851760182030.jpg",
      "perceptual_hash": "p:bbc4876fa0c26974",
      "taken": 1499967600,
      "taken_at": "Jul 13, 2017, 5:40 PM"
    },
    "sfomuseum:placetype": "instagram",
    "wof:name": "What was SFO like back in the 1960s?..",
    "wof:placetype": "custom",
    "wof:placetype_alt": [
      "instagram"
    ]
  },
  "geometry": {"coordinates":[-122.386166,37.616356],"type":"Point"}
}
