{
  "type": "Feature",
  "properties": {
    "instagram:post": {
      "caption": {
        "body": "This one's for you, @zeiss_micro! A c.1865 dissecting microscope by Carl Zeiss; slides by award-winning Joseph Bourgogne.",
        "excerpt": "This one's for you, @zeiss_micro!"
      },
      "media_id": "7599584ad1b5c6f5be89797c3cc7b6c9",
      "path": "photos/201206/7599584ad1b5c6f5be89797c3cc7b6c9.jpg",
      "taken": 1339447115,
      "taken_at": "2012-06-11T20:38:35+00:00"
    },
    "sfomuseum:placetype": "instagram",
    "wof:name": "This one's for you, @zeiss_micro!..",
    "wof:placetype": "custom"
  },
  "geometry": {"coordinates":[-122.386166,37.616356],"type":"Point"}
}
