{
  "type": "Feature",
  "properties": {
    "date:cessation_lower": "2012-06-11",
    "date:cessation_upper": "2012-06-11",
    "date:inception_lower": "2012-06-11",
    "date:inception_upper": "2012-06-11",
    "instagram:post": {
      "caption": {
        "body": "This one's for you, @zeiss_micro! A c.1865 dissecting microscope by Carl Zeiss; slides by award-winning Joseph Bourgogne.",
        "excerpt": "This one's for you, @zeiss_micro!"
      },
      "media_id": "7599584ad1b5c6f5be89797c3cc7b6c9",
      "path": "media/posts/201206/11192834_818467891523776_1982521260_n_17842253173062499.jpg",
      "perceptual_hash": "p:df4082a7e03cb53d",
      "taken": 1339418280,
      "taken_at": "Jun 11, 2012, 12:38 PM"
    },
    "sfomuseum:placetype": "instagram",
    "wof:name": "This one's for you, @zeiss_micro!..",
    "wof:placetype": "custom"
  },
  "geometry": {"coordinates":[-122.386166,37.616356],"type":"Point"}
}
