{
  "type": "Feature",
  "properties": {
    "date:cessation_lower": "2017-09-28",
    "date:cessation_upper": "2017-09-28",
    "date:inception_lower": "2017-09-28",
    "date:inception_upper": "2017-09-28",
    "instagram:post": {
      "caption": {
        "body": "Pilots are outfitted with military style, two-piece suit uniforms and hats. Cuff ranks can designate captains, first officers, and other members of the flight crew. The hat badges and the wings worn on the jacket and shirt complete the outfit. Over the decades, insignia styles have evolved as aircraft and service modernized. The color and finish of United’s hat badges and wings have changed over the years, but these insignia sets have always retained their classic aeronautical bearings.  Badge courtesy of the collection of United Airlines Archives. See \"Flying the Main Line: A History of United Air Lines\", on display, post-security, in Terminal 3. http://bit.ly/TheMainLine",
        "excerpt": "Pilots are outfitted with military style, two-piece suit uniforms and hats.",
        "hashtags": [
          "avgeek",
          "united",
          "aviationhistory",
          "flyingthemainline",
          "themainline",
          "unitedairlines",
          "avationgeek",
          "aviation",
          "aviationhistory",
          "aviationlovers",
          "vintageaviation",
          "history",
          "avhistory",
          "aviationgeeks",
          "instaplane",
          "flying",
          "plane",
          "flight",
          "airline",
          "avgeeks",
          "aviation4u",
          "aviationdaily"
        ]
      },
      "media_id": "38c895774ced725d1584a5f450929ad9",
      "path": "photos/201709/38c895774ced725d1584a5f450929ad9.jpg",
      "perceptual_hash": "p:e9979468cb33382d",
      "taken": 1506563660,
      "taken_at": "2017-09-28T01:54:20+00:00"
    },
    "sfomuseum:placetype": "instagram",
    "wof:name": "Pilots are outfitted with military style, two-piece suit uniforms and hats...",
    "wof:placetype": "custom"
  },
  "geometry": {"coordinates":[-122.386166,37.616356],"type":"Point"}
}
