{
  "type": "Feature",
  "properties": {
    "date:cessation_lower": "2017-06-07",
    "date:cessation_upper": "2017-06-07",
    "date:inception_lower": "2017-06-07",
    "date:inception_upper": "2017-06-07",
    "instagram:post": {
      "caption": {
        "body": "During the 1880s, a multitude of patents for new typewriter designs were introduced. One of the most innovative was invented by James B. Hammond (1839–1913), a Civil War correspondent who became frustrated as news press staff misinterpreted and incorrectly printed his handwritten reports. While too late for wartime use, Hammond’s typewriter was one of the most enduring non-type-bar designs. Patented in 1880, it featured a curved, piano-style keyboard and printed via a type-shuttle. On a Hammond, when a key is pressed the type mechanism rotates into place and is struck by a hammer, making the impression between paper and ink ribbon.  Learn more about the history and design of #typewriters in \"The Typewriter: An Innovation in Writing\" on display, post-security, in Terminal 2. http://bit.ly/Thetypewriter",
        "excerpt": "During the 1880s, a multitude of patents for new typewriter designs were introduced.",
        "hashtags": [
          "typewriter",
          "history",
          "design",
          "hammond",
          "hammondtypewriter"
        ]
      },
      "media_id": "4d2e526da4d2bdf06ffd516305a614c3",
      "path": "media/posts/201706/19051391_217077948809916_7496678601270493184_n_17882158498012487.jpg",
      "perceptual_hash": "p:ad55d62a99354ec2",
      "taken": 1496825340,
      "taken_at": "Jun 7, 2017, 8:49 AM"
    },
    "sfomuseum:placetype": "instagram",
    "wof:name": "During the 1880s, a multitude of patents for new typewriter designs were introduced...",
    "wof:placetype": "custom"
  },
  "geometry": {"coordinates":[-122.386166,37.616356],"type":"Point"}
}
