{
  "type": "Feature",
  "properties": {
    "instagram:post": {
      "caption": {
        "body": "Flight packets given to passengers in the 1940s and 1950s consisted of various passenger information and amenities including postcards, luggage tags, route maps, and informational materials on aircraft and aviation procedures. Inside this 1948 flight packet from United Air Lines is a route map advertising: \"3 types of mainliners 3 patterns of flight 1 standard of service  To offer the fastest, most frequent and most comfortable transportation possible, United flies three types of mainliners on as many carefully planned flight patterns – long-haul coast-to-coast service, intercity flights between key cities, and segmented patterns giving frequent service to smaller cities. But on all United flights you'll enjoy “service in the Mainliner manner’ – tops in air transportation. \"  Image:  United Air Lines flight information packet, Douglas DC-6, 1948. SFO Museum Collection. 2016.103.001",
        "hashtags": [
          "avgeek", 
          "aviationhistory", 
          "united", 
          "dc6", 
          "vintage", 
          "vintageaviation", 
          "vintageads", 
          "vintangeadvertisements"
        ]
      },
      "media_id": "1b80d43276aa9b39ecbe5ee448951608",
      "path": "photos/201703/1b80d43276aa9b39ecbe5ee448951608.jpg",
      "taken": 1489946481,
      "taken_at": "2017-03-19T18:01:21+00:00"
    },
    "sfomuseum:placetype": "instagram",
    "wof:name": "Instagram message #%!d(string=1b80d43276aa9b39ecbe5ee448951608)",
    "wof:placetype": "custom"
  },
  "geometry": {"coordinates":[-122.386166,37.616356],"type":"Point"}
}
