{
  "type": "Feature",
  "properties": {
    "date:cessation_lower": "2023-08-02",
    "date:cessation_upper": "2023-08-02",
    "date:inception_lower": "2023-08-02",
    "date:inception_upper": "2023-08-02",
    "instagram:post": {
      "caption": {
        "body": "“I identify primarily as a woman and secondarily as transgender. Even though I’ve transitioned, I can’t deny or completely separate myself from the past because it did happen and those memories are with me.   I also experienced losses in my work life. I was a strategic account manager at a major corporation. I had big accounts like Walmart and Boeing. I was in the big leagues. When I decided to transition, I did it very carefully through Human Resources. I had it all planned out with management and thought I’d be supported. But even though I did it by the book, not long after I transitioned, there was a great deal of movement away from me. Almost immediately the people in my group, who were all men except for one, formed this wall. I remember one day very specifically when we were sitting in a morning meeting and the VP was looking around and said, “Does anyone want any bagels, donuts?” And, of course, everybody raises their hand. Then he goes, “Stephanie, how about you run over to Einstein’s and pick us up some?” And there I was, a high-level manager, being treated totally differently after I transitioned. “ - Stephanie, 64, St. Louis, MO, 2014  Representations of older transgender people are nearly absent from our culture and those that do exist are often one-dimensional. For over five years (2013–2018), photographer Jess T. Dugan and social worker Vanessa Fabbre traveled throughout the United States creating “To Survive on This Shore: Photographs and Interviews with Transgender and Gender Nonconforming Older Adults.”   Each portrait in “To Survive on this Shore: Photographs and Interviews with Transgender and Gender Nonconforming Older Adults” by Jess T. Dugan and Vanessa Fabbre includes a powerful interview with each of the featured individuals.   See “To Survive on this Shore: Photographs and Interviews with Transgender and Gender Nonconforming Older Adults” on display in the Ruth Kadish Gallery located in the post-security connector between Terminal 2 and Terminal 3 and online at: https://bit.ly/3rczr0P",
        "excerpt": "“I identify primarily as a woman and secondarily as transgender.",
        "hashtags": [
          "ToSurviveOnThisShore"
        ]
      },
      "media_id": "e0132a2c5e8ffaa2115dedcb2a4f14ef950a106d",
      "path": "media/posts/202308/361950988_732584682211797_3361631145090963225_n_18015081142687143.jpg",
      "perceptual_hash": "p:d87d210bda762783",
      "taken": 1690966440,
      "taken_at": "Aug 02, 2023 8:54 am"
    },
    "sfomuseum:placetype": "instagram",
    "wof:name": "“I identify primarily as a woman and secondarily as transgender...",
    "wof:placetype": "custom"
  },
  "geometry": {"coordinates":[-122.386166,37.616356],"type":"Point"}
}
