{
  "type": "Feature",
  "properties": {
    "date:cessation_lower": "2020-03-10",
    "date:cessation_upper": "2020-03-10",
    "date:inception_lower": "2020-03-10",
    "date:inception_upper": "2020-03-10",
    "instagram:post": {
      "caption": {
        "body": "The work of Nigerian photographer Andrew Esiebo is featured in our exhibition ”Extra ’O’!African Barbershop and Hairdressing Signs.” Based in Nigeria, Andrew Esiebo (b. 1978) is a visual storyteller who began his career in photography by chronicling the rapid development of urban Nigeria as well as the country’s rich culture and heritage. As his career progressed, Esiebo began to explore new creative territory, including themes ranging from popular culture to gender politics, sexuality, and migration. “His Pride” photographic essay explores male hair barbing throughout major West African cities. His photographs document a variety of hairstyles and artfully detail the spaces in which barbers operate. “Extra ’O’! African Barbershop and Hairdressing Signs” is on display, post-security, in Terminal 2. http://bit.ly/Extrao . . . #ExtraO #Africa #AfricanBarbershop #AfricanHairdessing #hair #hairstyles",
        "excerpt": "The work of Nigerian photographer Andrew Esiebo is featured in our exhibition ”Extra ’O’!African Barbershop and Hairdressing Signs.” Based in Nigeria, Andrew Esiebo (b.",
        "users": [
          "handpaintedkenya\n@andrewesiebo\n@indigoartsgallery\n@erniewolfegallery\n@thenigerbend"
        ]
      },
      "media_id": "4818a2605d0f2ab05159ca2cfbe1cc7d",
      "path": "media/posts/202003/87681387_511768159486059_708239809222280120_n_17858216722777268.jpg",
      "perceptual_hash": "p:92ba8d97b230bccc",
      "taken": 1583827140,
      "taken_at": "Mar 10, 2020, 7:59 AM"
    },
    "sfomuseum:placetype": "instagram",
    "wof:name": "The work of Nigerian photographer Andrew Esiebo is featured in our exhibition ”Extra ’O’!African Barbershop and Hairdressing Signs.” Based in Nigeria, Andrew Esiebo (b...",
    "wof:placetype": "custom",
    "wof:placetype_alt": [
      "instagram"
    ]
  },
  "geometry": {"coordinates":[-122.386166,37.616356],"type":"Point"}
}
