{
  "type": "Feature",
  "properties": {
    "instagram:post": {
      "caption": {
        "body": "Exposure to Ancient Egypt inspired the Egyptian Revival, a design style that permeated western decorative arts and furniture in the nineteenth century. Obelisks, hieroglyphs, sphinxes, pyramids, scarabs, and lotus blossoms were popular motifs. Imagery was construed and adapted in different ways, from literal interpretations to fanciful artistic motifs. In furniture, Egyptian Revival pieces rarely comprised a full suite; rather they served as statement pieces. “The Style of Display: Victorian Pedestals” is on display pre-security in the International Terminal. http://bit.ly/VictorianPedestals",
        "excerpt": "Exposure to Ancient Egypt inspired the Egyptian Revival, a design style that permeated western decorative arts and furniture in the nineteenth century.",
        "hashtags": [
          "VictorianPedestals", 
          "victorian", 
          "pedestals", 
          "victorianfurniture", 
          "victoriana", 
          "design", 
          "decorativeart", 
          "interiorstyle"
        ]
      },
      "media_id": "6c3b42ec9c9ac65f8677e9081693596d",
      "path": "photos/201906/6c3b42ec9c9ac65f8677e9081693596d.jpg",
      "taken": 1559750827,
      "taken_at": "2019-06-05T16:07:07+00:00"
    },
    "sfomuseum:placetype": "instagram",
    "wof:name": "Exposure to Ancient Egypt inspired the Egyptian Revival, a design style that permeated western decorative arts and furniture in the nineteenth century...",
    "wof:placetype": "custom"
  },
  "geometry": {"coordinates":[-122.386166,37.616356],"type":"Point"}
}
