{
  "type": "Feature",
  "properties": {
    "date:cessation_lower": "2022-05-17",
    "date:cessation_upper": "2022-05-17",
    "date:inception_lower": "2022-05-17",
    "date:inception_upper": "2022-05-17",
    "instagram:post": {
      "caption": {
        "body": "Using the language of cartography, Lordy Rodriguez reimagines six iconic San Francisco neighborhoods as independent countries in his work “Strangerhood”. The Chinatown, North Beach, The Mission, The Castro, Haight-Ashbury, and Fisherman’s Wharf neighborhoods were chosen because of their strong cultural identities and tourism economies.  In his artwork, Rodriguez explores the identity of place, encouraging the viewer to think about the signifiers of place and how they influence our perception and experience of San Francisco neighborhoods.  See “Strangerhood” by Lordy Rodriguez on display, pre-security, on the arrivals level of Terminal 3, and online at: https://bit.ly/2Izj7By",
        "excerpt": "Using the language of cartography, Lordy Rodriguez reimagines six iconic San Francisco neighborhoods as independent countries in his work “Strangerhood”.",
        "hashtags": [
          "AAPIHM",
          "LordyRodriguez",
          "publicart",
          "SanFrancisco"
        ],
        "users": [
          "sfac_public_art_collection",
          "lordyrodriguez",
          "sf_arts_commission"
        ]
      },
      "media_id": "6d092192dc45b7b8607a7e22c5c2f5173822e864",
      "path": "media/posts/202205/281570123_160841329737163_5024913793333647396_n_17935600292163731.jpg",
      "perceptual_hash": "p:bc964b3e3231cccc",
      "taken": 1652781540,
      "taken_at": "May 17, 2022, 9:59 AM"
    },
    "sfomuseum:placetype": "instagram",
    "wof:name": "Using the language of cartography, Lordy Rodriguez reimagines six iconic San Francisco neighborhoods as independent countries in his work “Strangerhood”...",
    "wof:placetype": "custom"
  },
  "geometry": {"coordinates":[-122.386166,37.616356],"type":"Point"}
}
