{
  "type": "Feature",
  "properties": {
    "date:cessation_lower": "2022-01-21",
    "date:cessation_upper": "2022-01-21",
    "date:inception_lower": "2022-01-21",
    "date:inception_upper": "2022-01-21",
    "instagram:post": {
      "caption": {
        "body": "German filmmaker Sylvia Borges was inspired by choir rehearsals in an empty parking lot during the COVID-19 pandemic to produce a film that speaks to forced separation, but also to unity and resilience during these difficult times.  See “Particles” by Sylvia Borges in the Video Arts Gallery, located pre-security, in the International Terminal with daily operating hours of 5:00am to 10:00pm, or online at: https://bit.ly/3HSTDI4",
        "excerpt": "German filmmaker Sylvia Borges was inspired by choir rehearsals in an empty parking lot during the COVID-19 pandemic to produce a film that speaks to forced separation, but also to unity and resilience during these difficult times.",
        "hashtags": [
          "VideoArts",
          "VideoArtsSFO",
          "Particles",
          "choir"
        ],
        "users": [
          "sylvia_borges_",
          "dacchord"
        ]
      },
      "media_id": "5514ef54312bf1d38e595d1be1a3775db2ab3183",
      "path": "media/posts/202201/272287114_333642455292289_654496403105528694_n_17881024523616924.jpg",
      "perceptual_hash": "p:d0f6ae688d27c0a7",
      "taken": 1642770960,
      "taken_at": "Jan 21, 2022, 1:16 PM"
    },
    "sfomuseum:placetype": "instagram",
    "wof:name": "German filmmaker Sylvia Borges was inspired by choir rehearsals in an empty parking lot during the COVID-19 pandemic to produce a film that speaks to forced separation, but also to unity and resilience during these difficult times...",
    "wof:placetype": "custom",
    "wof:placetype_alt": [
      "instagram"
    ]
  },
  "geometry": {"coordinates":[-122.386166,37.616356],"type":"Point"}
}
