{
  "type": "Feature",
  "properties": {
    "date:cessation_lower": "2017-05-16",
    "date:cessation_upper": "2017-05-16",
    "date:inception_lower": "2017-05-16",
    "date:inception_upper": "2017-05-16",
    "instagram:post": {
      "caption": {
        "body": "What does it take to fly an airplane? A lot! SAS shows us the interior of a 747 cockpit feature a multitude of buttons, knobs, and other aircraft controls, which are one group of components out of many that make flight possible.  Image: SAS (Scandinavian Airlines System) poster, Boeing 747, 1979. Gift of the William Hough Collection. 2005.133.063",
        "excerpt": "What does it take to fly an airplane?",
        "hashtags": [
          "Boeing",
          "boeing747",
          "747",
          "SAS",
          "avgeek",
          "ScandinavianAirlinesSystem",
          "Scandinavia"
        ]
      },
      "media_id": "9ed22c7f6a2dc5160376d32e73aa1e0d",
      "path": "media/posts/201705/18444938_206104989900389_5972534307242115072_n_17858997688143266.jpg",
      "perceptual_hash": "p:8aad3c6ac291575d",
      "taken": 1494929940,
      "taken_at": "May 16, 2017, 10:19 AM"
    },
    "sfomuseum:placetype": "instagram",
    "wof:name": "What does it take to fly an airplane?..",
    "wof:placetype": "custom"
  },
  "geometry": {"coordinates":[-122.386166,37.616356],"type":"Point"}
}
