{
  "type": "Feature",
  "properties": {
    "instagram:post": {
      "caption": {
        "body": "What does it take to fly an airplane? A lot! SAS shows us the interior of a 747 cockpit feature a multitude of buttons, knobs, and other aircraft controls, which are one group of components out of many that make flight possible.  Image: SAS (Scandinavian Airlines System) poster, Boeing 747, 1979. Gift of the William Hough Collection. 2005.133.063",
        "excerpt": "What does it take to fly an airplane?",
        "hashtags": [
          "Boeing", 
          "boeing747", 
          "747", 
          "SAS", 
          "avgeek", 
          "ScandinavianAirlinesSystem", 
          "Scandinavia"
        ]
      },
      "location": "SFO Museum",
      "media_id": "9ed22c7f6a2dc5160376d32e73aa1e0d",
      "path": "photos/201705/9ed22c7f6a2dc5160376d32e73aa1e0d.jpg",
      "taken": 1494958775,
      "taken_at": "2017-05-16T18:19:35+00:00"
    },
    "sfomuseum:placetype": "instagram",
    "wof:name": "What does it take to fly an airplane?..",
    "wof:placetype": "custom"
  },
  "geometry": {"coordinates":[-122.386166,37.616356],"type":"Point"}
}
