{
  "type": "Feature",
  "properties": {
    "date:cessation_lower": "2016-09-17",
    "date:cessation_upper": "2016-09-17",
    "date:inception_lower": "2016-09-17",
    "date:inception_upper": "2016-09-17",
    "instagram:post": {
      "caption": {
        "body": "Kerry Mansfield is a San Francisco-based photographer. Living in a major metropolitan area, Mansfield often seeks refuge from urban life with camera in tow. Her series Grounded explores her “impulse to escape both physically and mentally,” from the confines of the city. In these photographs, she explores the boundaries of land, sea, and sky at Fort Funston, a protected area located on the southwest edge of San Francisco overlooking the Pacific Ocean. Rather than focus on individual figures in these compositions, her photographs capture our inexplicable attraction to the outer reaches of our built environment. As the artist explains, “We all seem drawn to the seashore, the crest of a tall hill, or even the sky, dangerously out of reach.” Though Mansfield may feel self-conscious about her own small place within this vast realm, she also feels a sense of peace she cannot find when bound by city constraints.  See \"Grounded\" by #KerryMansfield, on display, pre-security in Terminal 2.",
        "excerpt": "Kerry Mansfield is a San Francisco-based photographer.",
        "hashtags": [
          "SFOMuseum",
          "photography"
        ]
      },
      "media_id": "c0097642a0543ddd190fc9eaa9d9b359",
      "path": "media/posts/201609/14294749_1797089683836456_1184463590_n_17852681887111433.jpg",
      "perceptual_hash": "p:862a226b724b5f5e",
      "taken": 1474107180,
      "taken_at": "Sep 17, 2016, 10:13 AM"
    },
    "sfomuseum:placetype": "instagram",
    "wof:name": "Kerry Mansfield is a San Francisco-based photographer...",
    "wof:placetype": "custom"
  },
  "geometry": {"coordinates":[-122.386166,37.616356],"type":"Point"}
}
