{
  "type": "Feature",
  "properties": {
    "instagram:post": {
      "caption": {
        "body": "In coordination with the naming of Terminal 1: The Harvey B. Milk Terminal, SFO Museum is pleased to announce a public call for original photographs dating between 1930 to 1980 that pertain to the life and legacy of Supervisor Harvey B. Milk. For more information and to participate, visit: http://ow.ly/RbtH50jB97D  Image courtesy of Daniel Nicoletta. . . .",
        "hashtags": [
          "HarveyMilk", 
          "Terminal1", 
          "SFO", 
          "LGBTHistory", 
          "SanFrancisco"
        ]
      },
      "location": "San Francisco International Airport (SFO)",
      "media_id": "bac42008a80c0f9a7187a7177aa6080a",
      "path": "photos/201811/bac42008a80c0f9a7187a7177aa6080a.jpg",
      "taken": 1541472105,
      "taken_at": "2018-11-06T02:41:45+00:00"
    },
    "sfomuseum:placetype": "instagram",
    "wof:name": "Instagram message #%!d(string=bac42008a80c0f9a7187a7177aa6080a)",
    "wof:placetype": "custom"
  },
  "geometry": {"coordinates":[-122.386166,37.616356],"type":"Point"}
}
