{
  "type": "Feature",
  "properties": {
    "instagram:post": {
      "caption": {
        "body": "The Lockheed L-1011 TriStar was introduced #onthisday in 1972 with Eastern Air Lines. The wide-body L-1011 was the last commercial airliner produced by Lockheed Martin. Have you ever flown on a Lockheed L-1011 TriStar?  Image:  Eastern Air Lines postcard, Lockheed L-1011 TriStar, c. 1972. Gift of the Frank J. Lichtanski Collection. 2011.061.0334",
        "excerpt": "The Lockheed L-1011 TriStar was introduced #onthisday in 1972 with Eastern Air Lines.",
        "hashtags": [
          "Lockheed", 
          "L1011", 
          "TriStar", 
          "avgeek", 
          "aviationhistory"
        ]
      },
      "media_id": "cbbc67eb71642fe4687cabb72eda445a",
      "path": "photos/201704/cbbc67eb71642fe4687cabb72eda445a.jpg",
      "taken": 1493225143,
      "taken_at": "2017-04-26T16:45:43+00:00"
    },
    "sfomuseum:placetype": "instagram",
    "wof:name": "The Lockheed L-1011 TriStar was introduced #onthisday in 1972 with Eastern Air Lines...",
    "wof:placetype": "custom"
  },
  "geometry": {"coordinates":[-122.386166,37.616356],"type":"Point"}
}
