{
  "type": "Feature",
  "properties": {
    "date:cessation_lower": "2022-06-28",
    "date:cessation_upper": "2022-06-28",
    "date:inception_lower": "2022-06-28",
    "date:inception_upper": "2022-06-28",
    "instagram:post": {
      "caption": {
        "body": "Matilde Moisant was born in Indiana and was the sister of aviators John (1868–1910) and Alfred (1862–1929) Moisant. Instructed along with her friend Harriet Quimby (1875–1912) by aviator André Houpert (1886–1963) at her brother’s Moisant Aviation School in New York, Moisant earned her pilot’s license in 1911. She was just the second licensed woman aviator in the United States at the time. That same year, she broke the women’s altitude record at Garden City, New York. She toured briefly with the Moisant exhibition team before experiencing an accident in 1912. She retired from flying shortly after.  “First Flights: Early Women Aviators and their Aircraft” is on display post-security in Terminal 3, and online at: https://bit.ly/3wzDwfL",
        "excerpt": "Matilde Moisant was born in Indiana and was the sister of aviators John (1868–1910) and Alfred (1862–1929) Moisant.",
        "hashtags": [
          "EarlyWomenAviators",
          "AvGeek",
          "AviationHistory",
          "womeninhistory",
          "aviator",
          "pilot"
        ]
      },
      "media_id": "b079d7ac3e52092340eb04e6cdb0945600471195",
      "path": "media/other/290903319_348679297397199_4718221847225668680_n_17993040631491287.jpg",
      "perceptual_hash": "p:ed843253ad2ed315",
      "taken": 1656417480,
      "taken_at": "Jun 28, 2022 11:58 am"
    },
    "sfomuseum:placetype": "instagram",
    "wof:name": "Matilde Moisant was born in Indiana and was the sister of aviators John (1868–1910) and Alfred (1862–1929) Moisant...",
    "wof:placetype": "custom",
    "wof:placetype_alt": [
      "instagram"
    ]
  },
  "geometry": {"coordinates":[-122.386166,37.616356],"type":"Point"}
}
