{
  "type": "Feature",
  "properties": {
    "date:cessation_lower": "2018-03-21",
    "date:cessation_upper": "2018-03-21",
    "date:inception_lower": "2018-03-21",
    "date:inception_upper": "2018-03-21",
    "instagram:post": {
      "caption": {
        "body": "\"The Hangar, Shrine of the Air\" was located on 2211 Union Street in Berkeley, California. For over 30 years, Mary E. Tusch lived here and invited many of the students of the United States School of Military Aeronautics on the University of California's Berkeley Campus to her home, which was across the street from the school. She was nicknamed \"Mother Tusch\" by the budding aviators, as she became like a second mother to many of them. Her love for aviation and subsequent collection of aviation related artifacts gave her home the nickname, \"The Hangar, Shrine of Air.\" In this photo you can see part of her immense collection. When she passed in 1960, her collection was donated to the Smithsonian Air and Space Museum.  Images: San Francisco Bay Area, The Hangar (interior), Berkeley, 1949. Gift of Charles Page. 2010.174.226 \u0026 San Francisco Bay Area, The Hangar, Berkeley, 1949. Gift of Charles Page. 2010.174.225",
        "excerpt": "\"The Hangar, Shrine of the Air\" was located on 2211 Union Street in Berkeley, California.",
        "hashtags": [
          "WomeninAviation",
          "Womenshistorymonth",
          "avgeek",
          "avationgeek",
          "aviation",
          "aviationhistory",
          "vintageaviation",
          "history",
          "aviationgeeks",
          "avgeeks"
        ]
      },
      "media_id": "34f22485ce476e9e65911759894f0ace",
      "path": "photos/201803/34f22485ce476e9e65911759894f0ace.jpg",
      "perceptual_hash": "p:eee6b1199159cb06",
      "taken": 1521670264,
      "taken_at": "2018-03-21T22:11:04+00:00"
    },
    "sfomuseum:placetype": "instagram",
    "wof:name": "\"The Hangar, Shrine of the Air\" was located on 2211 Union Street in Berkeley, California...",
    "wof:placetype": "custom"
  },
  "geometry": {"coordinates":[-122.386166,37.616356],"type":"Point"}
}
