{
  "type": "Feature",
  "properties": {
    "date:cessation_lower": "2024-04-05",
    "date:cessation_upper": "2024-04-05",
    "date:inception_lower": "2024-04-05",
    "date:inception_upper": "2024-04-05",
    "instagram:post": {
      "caption": {
        "body": "Please join us for a free public event to celebrate the legacy of Virgin America and the new SFO Museum exhibition \"VX Forever\". A tribute to the popular SFO-based airline Virgin America, \"VX Forever\" presents a wide array of objects that chronicle the airline’s short but vibrant history. The program will include a video message from Sir Richard Branson, presentations by Virgin America’s visionary and founding CEO, Fred Reid, VX pilot Captain Karen McNally, Head of Teammate Experience, Art Huggard, and Sales Specialist, Kevin Nguyen, as well as SFO Museum’s Aviation Curator Dennis Sharp and other guest speakers. The program will also include a dance performance by flight attendant Mikey Tongko to the VX safety video. The presentations will be followed by a curator-led exhibition tour and the viewing of other Virgin America artifacts from the SFO Museum collection not in the exhibition.  WHEN: Saturday, April 6, 2024, 1:00–3:00 PM  WHERE: Louis A. Turpen Aviation Museum \u0026 Library International Terminal, Departures, Level 3, Pre-Security  For directions and parking, visit: https://ow.ly/cNbb50R9KR0 To learn more about the exhibition VX Forever, visit: https://ow.ly/G3xJ50R9KR2",
        "excerpt": "Please join us for a free public event to celebrate the legacy of Virgin America and the new SFO Museum exhibition \"VX Forever\".",
        "hashtags": [
          "VXForever"
        ]
      },
      "media_id": "a5b67aea51c2a193c894b52b8ac23919cbc77ae6",
      "path": "media/other/435574357_425590876786061_1435805949101361567_n_18029363122819555.jpg",
      "perceptual_hash": "p:95c93a946e0bd574",
      "taken": 1712334660,
      "taken_at": "Apr 05, 2024 4:31 pm"
    },
    "sfomuseum:placetype": "instagram",
    "wof:name": "Please join us for a free public event to celebrate the legacy of Virgin America and the new SFO Museum exhibition \"VX Forever\"...",
    "wof:placetype": "custom"
  },
  "geometry": {"coordinates":[-122.386166,37.616356],"type":"Point"}
}
