{
  "type": "Feature",
  "properties": {
    "instagram:post": {
      "caption": {
        "body": "Rod Kelly’s pair of Carp vases, completed in 1987 for Garrard and Company, was the artist’s first major commercial commission. For the source material of his design, Kelly purchased two rainbow trout, froze them into contorted, curved forms, and then rendered a series of sketches. The fish are surrounded by a plant motif based on species of native grasses Kelly collected along Hampshire’s River Itchen in South East England. Kelly’s final illustration and design took a matter of days, while the chasing was accomplished over five weeks at a rate of approximately one square inch each hour.  Special thanks to The Pearson Silver Collection. \"A Sterling Renaissance: British Silver Design 1957 to 2018\" is on display, pre-security, in the International Terminal. http://bit.ly/BritishSilver",
        "excerpt": "Rod Kelly’s pair of Carp vases, completed in 1987 for Garrard and Company, was the artist’s first major commercial commission.",
        "hashtags": [
          "BritishSilver", 
          "silver", 
          "sterling", 
          "sterlingsilver", 
          "silverdesign", 
          "RodKelly", 
          "silversmith", 
          "silversmithing", 
          "vase", 
          "carp", 
          "fish"
        ]
      },
      "media_id": "c01ae75d58f6ffe5783525e205f2685d",
      "path": "photos/201902/c01ae75d58f6ffe5783525e205f2685d.jpg",
      "taken": 1549488355,
      "taken_at": "2019-02-06T21:25:55+00:00"
    },
    "sfomuseum:placetype": "instagram",
    "wof:name": "Rod Kelly’s pair of Carp vases, completed in 1987 for Garrard and Company, was the artist’s first major commercial commission...",
    "wof:placetype": "custom"
  },
  "geometry": {"coordinates":[-122.386166,37.616356],"type":"Point"}
}
