{
  "type": "Feature",
  "properties": {
    "date:cessation_lower": "2023-07-12",
    "date:cessation_upper": "2023-07-12",
    "date:inception_lower": "2023-07-12",
    "date:inception_upper": "2023-07-12",
    "instagram:post": {
      "caption": {
        "body": "Arnaldo Pomodoro first trained as an architect and was also a jewelry designer prior to becoming a sculptor. “Cilindro Costruito” (Constructed Cylinder) is a sixteen-foot tall columnar form with an erratic vertical fissure, frozen in the process of eroding, that runs the length of the sculpture. The exposed area reveals a complex, multi-faceted interiority that contrasts with the highly polished, smooth surface.  See “Cilindro Costruito” by Arnaldo Pomodoro on display, in the pre-security connector between Terminal 2 and Terminal 3, right under SFO’s air traffic control tower. https://bit.ly/3CvSTrC",
        "excerpt": "Arnaldo Pomodoro first trained as an architect and was also a jewelry designer prior to becoming a sculptor.",
        "hashtags": [
          "ArnaldoPomodoro",
          "PublicArt",
          "Sculpture",
          "Bronze"
        ]
      },
      "media_id": "b4a2f19cebdad79efc39248522ed16b2b655c032",
      "path": "media/posts/202307/359753296_728399002630365_3399177160435346302_n_18030411934495423.jpg",
      "perceptual_hash": "p:dca1f0ac287e0b5e",
      "taken": 1689172200,
      "taken_at": "Jul 12, 2023 2:30 pm"
    },
    "sfomuseum:placetype": "instagram",
    "wof:name": "Arnaldo Pomodoro first trained as an architect and was also a jewelry designer prior to becoming a sculptor...",
    "wof:placetype": "custom"
  },
  "geometry": {"coordinates":[-122.386166,37.616356],"type":"Point"}
}
