{
  "type": "Feature",
  "properties": {
    "instagram:post": {
      "caption": {
        "body": "Weaving Display by Mayan Artisan on Saturday, March 10th, at 4:15pm  San Francisco International Airport • International Terminal • FREE Pre-Security at the rear of the Main Hall Departures Lobby  In conjunction with the exhibition Empowering Threads: Textiles of Jolom Mayaetik, SFO Museum is proud to present a live display of backstrap loom weaving by Elvia Gómez López, president of Cooperativa Jolom Mayaetik in San Cristóbal de las Casas, Chiapas, Mexico. Charlene Woodcock, exhibition partner and co-editor of the new book, Weaving Chiapas: Maya Women’s Lives in a Changing World, will be on hand along with the exhibition curator. RSVP at https://empoweringthreads.eventbrite.com  Maria Gómez López and her mother Margarita López Gómez on backstrap looms, Oxchuc  2016 Courtesy of Jolom Mayaetik SCS R2017.0302.023"
      },
      "location": "San Francisco International Airport (SFO)",
      "media_id": "ed9fd568c3a9a51ec0eac1ec6ac56294",
      "path": "photos/201803/ed9fd568c3a9a51ec0eac1ec6ac56294.jpg",
      "taken": 1520443870,
      "taken_at": "2018-03-07T17:31:10+00:00"
    },
    "sfomuseum:placetype": "instagram",
    "wof:name": "Instagram message #%!d(string=ed9fd568c3a9a51ec0eac1ec6ac56294)",
    "wof:placetype": "custom"
  },
  "geometry": {"coordinates":[-122.386166,37.616356],"type":"Point"}
}
