{
  "type": "Feature",
  "properties": {
    "date:cessation_lower": "2018-01-13",
    "date:cessation_upper": "2018-01-13",
    "date:inception_lower": "2018-01-13",
    "date:inception_upper": "2018-01-13",
    "instagram:post": {
      "caption": {
        "body": "Did you know there was a Bank of America branch at SFO in the 1950s? The bank's advertisement features the newly built Central Terminal twinkling at twilight.  Image:  Bank of America advertisement, San Francisco International Airport (SFO), c. 1956. SFO Museum Collection. 2001.013.012",
        "excerpt": "Did you know there was a Bank of America branch at SFO in the 1950s?",
        "hashtags": [
          "avgeek",
          "avationgeek",
          "aviation",
          "aviationhistory",
          "vintageaviation",
          "history",
          "avhistory",
          "aviationgeeks",
          "avgeeks",
          "SFO",
          "SFOhistory",
          "illustration"
        ]
      },
      "location": "San Francisco International Airport (SFO)",
      "media_id": "626d1d6b2d7c276fb7da531486d477cb",
      "path": "photos/201801/626d1d6b2d7c276fb7da531486d477cb.jpg",
      "perceptual_hash": "p:eb40d635ce6be0c1",
      "taken": 1515776340,
      "taken_at": "Jan 12, 2018, 4:59 PM"
    },
    "sfomuseum:placetype": "instagram",
    "wof:name": "Did you know there was a Bank of America branch at SFO in the 1950s?..",
    "wof:placetype": "custom"
  },
  "geometry": {"coordinates":[-122.386166,37.616356],"type":"Point"}
}
