{
  "type": "Feature",
  "properties": {
    "instagram:post": {
      "caption": {
        "body": "Did you know there was a Bank of America branch at SFO in the 1950s? The bank's advertisement features the newly built Central Terminal twinkling at twilight.  Image:  Bank of America advertisement, San Francisco International Airport (SFO), c. 1956. SFO Museum Collection. 2001.013.012",
        "hashtags": [
          "avgeek", 
          "avationgeek", 
          "aviation", 
          "aviationhistory", 
          "vintageaviation", 
          "history", 
          "avhistory", 
          "aviationgeeks", 
          "avgeeks", 
          "SFO", 
          "SFOhistory", 
          "illustration"
        ]
      },
      "location": "San Francisco International Airport (SFO)",
      "media_id": "626d1d6b2d7c276fb7da531486d477cb",
      "path": "photos/201801/626d1d6b2d7c276fb7da531486d477cb.jpg",
      "taken": 1515805185,
      "taken_at": "2018-01-13T00:59:45+00:00"
    },
    "sfomuseum:placetype": "instagram",
    "wof:name": "Instagram message #%!d(string=626d1d6b2d7c276fb7da531486d477cb)",
    "wof:placetype": "custom"
  },
  "geometry": {"coordinates":[-122.386166,37.616356],"type":"Point"}
}
