{
  "type": "Feature",
  "properties": {
    "date:cessation_lower": "2013-12-10",
    "date:cessation_upper": "2013-12-10",
    "date:inception_lower": "2013-12-10",
    "date:inception_upper": "2013-12-10",
    "instagram:post": {
      "caption": {
        "body": "When snails, a delicacy, are found in the Luzon Cordillera, they are scooped up by the plaited sieve and placed into a #basketry container for future consumption.",
        "excerpt": "When snails, a delicacy, are found in the Luzon Cordillera, they are scooped up by the plaited sieve and placed into a #basketry container for future consumption."
      },
      "media_id": "017ceaede9770381b34e41cb06471969",
      "path": "photos/201312/017ceaede9770381b34e41cb06471969.jpg",
      "perceptual_hash": "p:ce63e09e19661f91",
      "taken": 1386674760,
      "taken_at": "Dec 10, 2013, 11:26 AM"
    },
    "sfomuseum:placetype": "instagram",
    "wof:name": "When snails, a delicacy, are found in the Luzon Cordillera, they are scooped up by the plaited sieve and placed into a #basketry container for future consumption...",
    "wof:placetype": "custom"
  },
  "geometry": {"coordinates":[-122.386166,37.616356],"type":"Point"}
}
