{
  "type": "Feature",
  "properties": {
    "instagram:post": {
      "caption": {
        "body": "When snails, a delicacy, are found in the Luzon Cordillera, they are scooped up by the plaited sieve and placed into a #basketry container for future consumption."
      },
      "media_id": "017ceaede9770381b34e41cb06471969",
      "path": "photos/201312/017ceaede9770381b34e41cb06471969.jpg",
      "taken": 1386703591,
      "taken_at": "2013-12-10T19:26:31+00:00"
    },
    "sfomuseum:placetype": "instagram",
    "wof:name": "Instagram message #%!d(string=017ceaede9770381b34e41cb06471969)",
    "wof:placetype": "custom"
  },
  "geometry": {"coordinates":[-122.386166,37.616356],"type":"Point"}
}
