{
  "type": "Feature",
  "properties": {
    "instagram:post": {
      "caption": {
        "body": "A good day at the office."
      },
      "media_id": "571730eab9e2fba3bf467fcd13843908",
      "path": "photos/201303/571730eab9e2fba3bf467fcd13843908.jpg",
      "taken": 1363279362,
      "taken_at": "2013-03-14T16:42:42+00:00"
    },
    "sfomuseum:placetype": "instagram",
    "wof:name": "Instagram message #%!d(string=571730eab9e2fba3bf467fcd13843908)",
    "wof:placetype": "custom"
  },
  "geometry": {"coordinates":[-122.386166,37.616356],"type":"Point"}
}
