{
  "type": "Feature",
  "properties": {
    "date:cessation_lower": "2013-03-14",
    "date:cessation_upper": "2013-03-14",
    "date:inception_lower": "2013-03-14",
    "date:inception_upper": "2013-03-14",
    "instagram:post": {
      "caption": {
        "body": "A good day at the office.",
        "excerpt": "A good day at the office."
      },
      "media_id": "571730eab9e2fba3bf467fcd13843908",
      "path": "media/posts/201303/11312150_1638483373031222_1243906363_n_17842307464062499.jpg",
      "perceptual_hash": "p:81954aed325a6d5e",
      "taken": 1363250520,
      "taken_at": "Mar 14, 2013, 8:42 AM"
    },
    "sfomuseum:placetype": "instagram",
    "wof:name": "A good day at the office...",
    "wof:placetype": "custom",
    "wof:placetype_alt": [
      "instagram"
    ]
  },
  "geometry": {"coordinates":[-122.386166,37.616356],"type":"Point"}
}
