{
  "type": "Feature",
  "properties": {
    "date:cessation_lower": "2018-07-25",
    "date:cessation_upper": "2018-07-25",
    "date:inception_lower": "2018-07-25",
    "date:inception_upper": "2018-07-25",
    "instagram:post": {
      "caption": {
        "body": "Modern jukeboxes trace their origins to coin-operated phonographs. Marketed as automatic phonographs, these late-nineteenth-century machines combined Thomas Alva Edison’s (1847–1931) wax cylinder phonograph with a coin-operated mechanism. Edison patented the first cylinder phonograph in 1878 after experimenting with a device that recorded audible messages from a telegraph or telephone signal. This machine utilized a metal cylinder wrapped in tinfoil and was more of a novelty, as recordings quickly degraded after a few plays. Edison’s Improved Phonograph followed a decade later with wax cylinders that greatly increased the life-span of recordings. During the 1890s, electrically operated automatic phonographs were produced by various manufacturers under license from Edison. Nicknamed “nickel-in-the-slot” machines, they appeared in arcade parlors across the United States alongside Kinetoscopes, another Edison invention that played short movies from 35 mm film.  Automatic Edison phonograph courtesy of the Joe Welch American Antique Museum. \"The Automatic Age: Coin-Operated Machines\" is on display, pre-security, in the International Terminal. http://bit.ly/CoinOperated",
        "excerpt": "Modern jukeboxes trace their origins to coin-operated phonographs.",
        "hashtags": [
          "coinoperated",
          "TheAutomaticAge",
          "coinop",
          "vintage",
          "antique",
          "gamemachines",
          "slotmachine",
          "slotmachines",
          "Edison",
          "Kinetoscopes",
          "phonograph"
        ]
      },
      "media_id": "330f503b6832cfb718f817191ae0e207",
      "path": "photos/201807/330f503b6832cfb718f817191ae0e207.jpg",
      "perceptual_hash": "p:d583286a7a85f23d",
      "taken": 1532537295,
      "taken_at": "2018-07-25T16:48:15+00:00"
    },
    "sfomuseum:placetype": "instagram",
    "wof:name": "Modern jukeboxes trace their origins to coin-operated phonographs...",
    "wof:placetype": "custom"
  },
  "geometry": {"coordinates":[-122.386166,37.616356],"type":"Point"}
}
