{
  "type": "Feature",
  "properties": {
    "date:cessation_lower": "2016-09-28",
    "date:cessation_upper": "2016-09-28",
    "date:inception_lower": "2016-09-28",
    "date:inception_upper": "2016-09-28",
    "instagram:post": {
      "caption": {
        "hashtags": [
          "TravelTuesday",
          "PanAm",
          "WorldTourismDay"
        ]
      },
      "location": "SFO Museum",
      "media_id": "b4441e00613b0de7c2867ea30174ecf6",
      "path": "photos/201609/b4441e00613b0de7c2867ea30174ecf6.jpg",
      "perceptual_hash": "p:f1934fc46e823339",
      "taken": 1474994820,
      "taken_at": "Sep 27, 2016, 4:47 PM"
    },
    "sfomuseum:placetype": "instagram",
    "wof:name": "..",
    "wof:placetype": "custom"
  },
  "geometry": {"coordinates":[-122.386166,37.616356],"type":"Point"}
}
