{
  "type": "Feature",
  "properties": {
    "date:cessation_lower": "2022-02-23",
    "date:cessation_upper": "2022-02-23",
    "date:inception_lower": "2022-02-23",
    "date:inception_upper": "2022-02-23",
    "instagram:post": {
      "caption": {
        "body": "The airline industry soared to new heights in the 1950s. Driven by great advances in aviation technology and a burgeoning consumer market, new commercial airliners introduced the future of air travel to the next generation of passengers. To keep pace with the revolution in commercial aviation, major airports around the world updated their facilities with longer runways, expansive taxiways, and modern passenger terminals. Construction of a new terminal at San Francisco Airport began in 1951. Designed in the International Style, the seven-story building employed an innovative, dual-level layout that separated departures from arrivals. Our exhibition, \"The 1954 San Francisco International Airport Terminal\" features a selection of objects and historic imagery from the first decade of operations at the 1954 Terminal building. All material is from the collection of SFO Museum.   See \"The 1954 San Francisco International Airport Terminal\" on display in the SkyTerrace and online at: http://bit.ly/SFO1954  The SkyTerrace, located pre-security in Terminal 2, is open Friday-Monday from 10:00 a.m. to 6:00 p.m. and it is free! https://bit.ly/3F20GOc",
        "excerpt": "The airline industry soared to new heights in the 1950s.",
        "hashtags": [
          "SFOHistory",
          "avgeek",
          "SFO",
          "SFHistory"
        ]
      },
      "media_id": "7f0a43e8341bccdf0cddd724d333be2feede4f02",
      "path": "media/posts/202202/274502024_655109089108758_98377069711801737_n_17998799689413082.jpg",
      "perceptual_hash": "p:fb2bea0c34446e3c",
      "taken": 1645636260,
      "taken_at": "Feb 23, 2022, 5:11 PM"
    },
    "sfomuseum:placetype": "instagram",
    "wof:name": "The airline industry soared to new heights in the 1950s...",
    "wof:placetype": "custom"
  },
  "geometry": {"coordinates":[-122.386166,37.616356],"type":"Point"}
}
