{
  "type": "Feature",
  "properties": {
    "date:cessation_lower": "2016-11-30",
    "date:cessation_upper": "2016-11-30",
    "date:inception_lower": "2016-11-30",
    "date:inception_upper": "2016-11-30",
    "instagram:post": {
      "caption": {
        "body": "Exhibition rotations are a team effort as objects are transported through the terminal to the gallery, unloaded, arranged for an assembly-line fashion of installation. Take a ride on a rack as we sail through Terminal 2 to install @SFOMuseum's most recent exhibition, The Mysterious Talking Board: #OuijaAndBeyond.  Learn more about #Ouija boards in \"The Mysterious Talking Board: #OuijaAndBeyond\", located post-security, in Terminal 2. http://bit.ly/OuijaAndBeyond  G O O D B Y E",
        "excerpt": "Exhibition rotations are a team effort as objects are transported through the terminal to the gallery, unloaded, arranged for an assembly-line fashion of installation."
      },
      "file_hash": "2d0965c26686c5ea8e74b10cbcd42067461b35bdf6bb5dedd99fd11cfccd65ac",
      "media_id": "f8094fe42df16298b71055c5e07cfb52f7437e39",
      "path": "media/posts/201611/6941892CCD6F111CB9EEDB019216188A_video_dashinit_17845326091143940.mp4",
      "taken": 1480499340,
      "taken_at": "Nov 30, 2016 9:49 am"
    },
    "sfomuseum:placetype": "instagram",
    "wof:name": "Exhibition rotations are a team effort as objects are transported through the terminal to the gallery, unloaded, arranged for an assembly-line fashion of installation...",
    "wof:placetype": "custom"
  },
  "geometry": {"coordinates":[-122.386166,37.616356],"type":"Point"}
}
