{
  "type": "Feature",
  "properties": {
    "instagram:post": {
      "caption": {
        "body": "#Onthisday in 2003, the last scheduled eastbound transatlantic Concorde flight took off from New York bound for London. British Airways had announced in April 2003 that they would be retiring their Concordes. The Concorde could reach supersonic speeds of up to Mach II (around 1,450 miles an hour) and could travel from New York to London in under 4 hours. Tickets cost up to $9,000 round-trip. Did you ever fly on a Concorde?  Image: British Airways, Concorde, c. 2000. Gift of David Robinson. 2010.044.002",
        "excerpt": "#Onthisday in 2003, the last scheduled eastbound transatlantic Concorde flight took off from New York bound for London.",
        "hashtags": [
          "concorde", 
          "onthisday", 
          "britishairways", 
          "aviationhistory", 
          "avgeeks"
        ]
      },
      "location": "SFO Museum",
      "media_id": "9e011ca70a31fb79b5a57f7d55fe121e",
      "path": "photos/201910/9e011ca70a31fb79b5a57f7d55fe121e.jpg",
      "taken": 1571940970,
      "taken_at": "2019-10-24T18:16:10+00:00"
    },
    "sfomuseum:placetype": "instagram",
    "wof:name": "#Onthisday in 2003, the last scheduled eastbound transatlantic Concorde flight took off from New York bound for London...",
    "wof:placetype": "custom"
  },
  "geometry": {"coordinates":[-122.386166,37.616356],"type":"Point"}
}
