{
  "type": "Feature",
  "properties": {
    "date:cessation_lower": "2017-03-22",
    "date:cessation_upper": "2017-03-22",
    "date:inception_lower": "2017-03-22",
    "date:inception_upper": "2017-03-22",
    "instagram:post": {
      "caption": {
        "body": "“When using the Mystifying Oracle—extinguish all lights. Questions may be asked—and out of the darkness your answers are spelled out in tiny flashes of light. The effect is weird and mysterious as your destiny is flashed before you.” Mystifying Oracle Ouija Electric advertisement 1933  The William Fuld Manufacturing Company produced a number of interesting boards, perhaps none more so than the exceedingly rare Mystifying Oracle Electric, which they offered in the 1930s. The oversized board and planchette are made of sheet metal and finished in a faux mahogany. The board displays an unusual, scattered alphabet layout with a Grecian-inspired border pattern. Its most unusual feature, however, is a remarkable light-up planchette, powered by a dry-cell battery. An electric bulb cleverly illuminates letters through the viewing window when the electric switch, located on the underside of the #planchette, comes into contact with bumps on the board.  All objects are courtesy of Gene Orlando, Museum of Talking Boards, and Robert Murch, The Talking Board Historical Society. See more #OuijaBoards in \"The Mysterious Talking Board: #OuijaAndBeyond\" on display, post-security, in Terminal 2. http://bit.ly/OuijaAndBeyond . . . #OuijaBoard #TalkingBoard #MystifyingOracle #WilliamFuld  G O O D B Y E",
        "excerpt": "“When using the Mystifying Oracle—extinguish all lights."
      },
      "media_id": "980c045b8b5efcee732aab05d59ecb99",
      "path": "photos/201703/980c045b8b5efcee732aab05d59ecb99.jpg",
      "perceptual_hash": "p:ffca806590b5c17a",
      "taken": 1490123220,
      "taken_at": "Mar 21, 2017, 7:07 PM"
    },
    "sfomuseum:placetype": "instagram",
    "wof:name": "“When using the Mystifying Oracle—extinguish all lights...",
    "wof:placetype": "custom"
  },
  "geometry": {"coordinates":[-122.386166,37.616356],"type":"Point"}
}
