{
  "type": "Feature",
  "properties": {
    "date:cessation_lower": "2021-10-04",
    "date:cessation_upper": "2021-10-04",
    "date:inception_lower": "2021-10-04",
    "date:inception_upper": "2021-10-04",
    "instagram:post": {
      "caption": {
        "body": "Artist Stacy Speyer began making this series of geometric metal sculptures as an artist-in-residence at the Exploratorium. The Greek term combines ‘poly’ meaning many and ‘hedra’ for faces or sides; hence, polyhedra are three-dimensional shapes made of polygon faces joined at the edges and corners. Speyer created these three polyhedra—a dodecahedron, a hexahedron, and a rhombic triacontahedron, by bending the corners (vertices), bolting them to the edges of each polyhedron, and leaving the faces open.   See “Mathematics: Modern and Vintage” is on display post-security in Terminal 2 and online at: https://bit.ly/MathAtSFO",
        "excerpt": "Artist Stacy Speyer began making this series of geometric metal sculptures as an artist-in-residence at the Exploratorium.",
        "hashtags": [
          "MathAtSFO",
          "Mathematics",
          "Math",
          "StacySpeyer",
          "metal",
          "sculpture"
        ],
        "users": [
          "cubesandthings",
          "exploratorium"
        ]
      },
      "media_id": "e71e80536afbb1958c8ab85ef67a94ec84fe43f9",
      "path": "media/posts/202110/244333635_392435049038074_408088229517564310_n_18205599886103897.jpg",
      "perceptual_hash": "p:cf4aaa215eb1e586",
      "taken": 1633364220,
      "taken_at": "Oct 4, 2021, 4:17 PM"
    },
    "sfomuseum:placetype": "instagram",
    "wof:name": "Artist Stacy Speyer began making this series of geometric metal sculptures as an artist-in-residence at the Exploratorium...",
    "wof:placetype": "custom",
    "wof:placetype_alt": [
      "instagram"
    ]
  },
  "geometry": {"coordinates":[-122.386166,37.616356],"type":"Point"}
}
