{
  "type": "Feature",
  "properties": {
    "date:cessation_lower": "2018-09-19",
    "date:cessation_upper": "2018-09-19",
    "date:inception_lower": "2018-09-19",
    "date:inception_upper": "2018-09-19",
    "instagram:post": {
      "caption": {
        "body": "\"I had only to resort to that often-abandoned aspect of my work which goes back to 1928 when I first made the three-dimensional out of a two-dimensional plate. The way pointed to an aesthetic of the flat enhanced by a technology not otherwise practical…these sculptures are like short poems pertaining to California where I was born, and to the world I have known.\" Isamu Noguchi, November 11, 1982  Thank you to The Isamu Noguchi Foundation and Garden Museum for their generous loan. See \"Isamu Noguchi: Inside and Out\" on display, pre-security, in the International Terminal. http://bit.ly/NoguchiSFO",
        "excerpt": "\"I had only to resort to that often-abandoned aspect of my work which goes back to 1928 when I first made the three-dimensional out of a two-dimensional plate.",
        "hashtags": [
          "NoguchiSFO",
          "IsamuNoguchi",
          "noguchi",
          "sculpture",
          "art",
          "modernart",
          "design",
          "industrialdesign"
        ]
      },
      "location": "San Francisco International Airport (SFO)",
      "media_id": "77c66dd9f722721bf131a3e650872c35",
      "path": "photos/201809/77c66dd9f722721bf131a3e650872c35.jpg",
      "perceptual_hash": "p:91670ed891d93e4e",
      "taken": 1537352220,
      "taken_at": "Sep 19, 2018, 10:17 AM"
    },
    "sfomuseum:placetype": "instagram",
    "wof:name": "\"I had only to resort to that often-abandoned aspect of my work which goes back to 1928 when I first made the three-dimensional out of a two-dimensional plate...",
    "wof:placetype": "custom"
  },
  "geometry": {"coordinates":[-122.386166,37.616356],"type":"Point"}
}
