{
  "type": "Feature",
  "properties": {
    "date:cessation_lower": "2022-01-14",
    "date:cessation_upper": "2022-01-14",
    "date:inception_lower": "2022-01-14",
    "date:inception_upper": "2022-01-14",
    "instagram:post": {
      "caption": {
        "body": "British documentary filmmaker Ellen Evans profiles Kath Holden, who reflects on her life and art in the precious world of miniatures, where her creations stand apart from the genteel museum pieces of her contemporaries.   See “Life In Miniature” by Ellen Evans in the Video Arts Gallery, located pre-security, in the International Terminal with daily operating hours of 5:00am to 10:00pm or online at: https://bit.ly/3zrlRXs",
        "excerpt": "British documentary filmmaker Ellen Evans profiles Kath Holden, who reflects on her life and art in the precious world of miniatures, where her creations stand apart from the genteel museum pieces of her contemporaries.",
        "hashtags": [
          "VideoArts",
          "VideoArtsSFO",
          "EllenEvans",
          "LifeInMiniature",
          "KathHolden",
          "miniatures"
        ],
        "users": [
          "ellenfevans"
        ]
      },
      "media_id": "2508101466fbb85668afe1bb7a40d1cf9f12c95b",
      "path": "media/posts/202201/271804823_377102487508005_130436884015821329_n_17875091306631423.jpg",
      "perceptual_hash": "p:d0f6ae688d27c0a7",
      "taken": 1642178640,
      "taken_at": "Jan 14, 2022, 4:44 PM"
    },
    "sfomuseum:placetype": "instagram",
    "wof:name": "British documentary filmmaker Ellen Evans profiles Kath Holden, who reflects on her life and art in the precious world of miniatures, where her creations stand apart from the genteel museum pieces of her contemporaries...",
    "wof:placetype": "custom"
  },
  "geometry": {"coordinates":[-122.386166,37.616356],"type":"Point"}
}
