{
  "type": "Feature",
  "properties": {
    "instagram:post": {
      "caption": {
        "body": "Learn about Bay Area Coast Guard history in our photography exhibition, “United States Coast Guard Air Station San Francisco: Honoring the Guardians of the Golden Gate 75th”, located pre-security, in the Aviation Museum and Library in the International Terminal. The Aviation Museum and Library is open from Sunday through Friday, 10am to 4:30pm. See more at our online exhibition: http://www.flysfo.com/museum/exhibitions/united-states-coast-guard-air-station-san-francisco  A Sikorsky R-6A Hoverfly helicopter is displayed on a flatbed truck during the Moose Parade sponsored by the Loyal Order of Moose in San Francisco  1949  SFO Museum Gift of United States Coast Guard, Air Station San Francisco 2014.114.023"
      },
      "location": "Aviation Museum and Library - San Francisco International Airport (SFO)",
      "media_id": "eae565d38127fd74fd2cf4b54d500dc9",
      "path": "photos/201603/eae565d38127fd74fd2cf4b54d500dc9.jpg",
      "taken": 1459015308,
      "taken_at": "2016-03-26T18:01:48+00:00"
    },
    "sfomuseum:placetype": "instagram",
    "wof:name": "Instagram message #%!d(string=eae565d38127fd74fd2cf4b54d500dc9)",
    "wof:placetype": "custom"
  },
  "geometry": {"coordinates":[-122.386166,37.616356],"type":"Point"}
}
