{
  "type": "Feature",
  "properties": {
    "date:cessation_lower": "2016-03-26",
    "date:cessation_upper": "2016-03-26",
    "date:inception_lower": "2016-03-26",
    "date:inception_upper": "2016-03-26",
    "instagram:post": {
      "caption": {
        "body": "Learn about Bay Area Coast Guard history in our photography exhibition, “United States Coast Guard Air Station San Francisco: Honoring the Guardians of the Golden Gate 75th”, located pre-security, in the Aviation Museum and Library in the International Terminal. The Aviation Museum and Library is open from Sunday through Friday, 10am to 4:30pm. See more at our online exhibition: http://www.flysfo.com/museum/exhibitions/united-states-coast-guard-air-station-san-francisco  A Sikorsky R-6A Hoverfly helicopter is displayed on a flatbed truck during the Moose Parade sponsored by the Loyal Order of Moose in San Francisco  1949  SFO Museum Gift of United States Coast Guard, Air Station San Francisco 2014.114.023",
        "excerpt": "Learn about Bay Area Coast Guard history in our photography exhibition, “United States Coast Guard Air Station San Francisco: Honoring the Guardians of the Golden Gate 75th”, located pre-security, in the Aviation Museum and Library in the International Terminal."
      },
      "media_id": "eae565d38127fd74fd2cf4b54d500dc9",
      "path": "media/posts/201603/1169132_445632225635195_189482741_n_17854494931052795.jpg",
      "perceptual_hash": "p:aa2b9535d492b2d3",
      "taken": 1458986460,
      "taken_at": "Mar 26, 2016, 10:01 AM"
    },
    "sfomuseum:placetype": "instagram",
    "wof:name": "Learn about Bay Area Coast Guard history in our photography exhibition, “United States Coast Guard Air Station San Francisco: Honoring the Guardians of the Golden Gate 75th”, located pre-security, in the Aviation Museum and Library in the International Terminal...",
    "wof:placetype": "custom",
    "wof:placetype_alt": [
      "instagram"
    ]
  },
  "geometry": {"coordinates":[-122.386166,37.616356],"type":"Point"}
}
