{
  "type": "Feature",
  "properties": {
    "instagram:post": {
      "caption": {
        "body": "The pottery and cultures of Central and South America inspired many of Marguerite Wildenhain’s ceramics. She sketched figures of indigenous peoples and landscapes that she observed on her trips, then carved and painted these scenes on bowls, vases, tiles, and wall plaques, as well as sculpting figurines. Many of her works portray village life, the Aymara and Quechua Indians of Peru, sheep herds, and other animals of the Andes.  See more South American influenced pottery in \"A Potter's Life: Marguerite Wildenhain at #PondFarm\", on display, post-security, in Terminal 2.  http://bit.ly/PondFarm\""
      },
      "location": "San Francisco International Airport (SFO)",
      "media_id": "2e195fde937b0e3301df3cb4bc67e9d4",
      "path": "photos/201605/2e195fde937b0e3301df3cb4bc67e9d4.jpg",
      "taken": 1464311164,
      "taken_at": "2016-05-27T01:06:04+00:00"
    },
    "sfomuseum:placetype": "instagram",
    "wof:name": "Instagram message #%!d(string=2e195fde937b0e3301df3cb4bc67e9d4)",
    "wof:placetype": "custom"
  },
  "geometry": {"coordinates":[-122.386166,37.616356],"type":"Point"}
}
