{
  "type": "Feature",
  "properties": {
    "date:cessation_lower": "2013-05-23",
    "date:cessation_upper": "2013-05-23",
    "date:inception_lower": "2013-05-23",
    "date:inception_upper": "2013-05-23",
    "instagram:post": {
      "caption": {
        "body": "An eagle's head ornament from the barkentine, Charles F. Crocker (built in Alameda in 1890)",
        "excerpt": "An eagle's head ornament from the barkentine, Charles F. Crocker (built in Alameda in 1890)"
      },
      "media_id": "8fe571ab18dbc2ace55bae8ff7e0636f",
      "path": "media/posts/201305/11247742_817122858343011_1496607383_n_17842324927062499.jpg",
      "perceptual_hash": "p:9fd431316d899636",
      "taken": 1369316040,
      "taken_at": "May 23, 2013, 1:34 PM"
    },
    "sfomuseum:placetype": "instagram",
    "wof:name": "An eagle's head ornament from the barkentine, Charles F. Crocker (built in Alameda in 1890)..",
    "wof:placetype": "custom"
  },
  "geometry": {"coordinates":[-122.386166,37.616356],"type":"Point"}
}
