{
  "type": "Feature",
  "properties": {
    "instagram:post": {
      "caption": {
        "body": "Longhorn beetles belong to the family Cerambycidae and derive their name from their long antennae. Most longhorn beetle eggs are laid under pieces of bark. Their larvae feed inside the wood of dead and dying trees, including roots, trunks, and branches. Larvae first feed on the cambium (new growth layer under the bark) before boring deeper into the wood. Most species only attack trees that are weakened by disease, drought, or fire. But some species, such as the Asian longhorn beetle (Anoplophora glabripennis Motschulsky, 1853), which has invaded northeastern North America, can attack the healthy trees of many species. The intricate patterns on the elytra (wings) of many species help them to blend in with the bark of the trees on which they feed.  See “The Intriguing World of Insects” on display, pre-security, in the International Terminal. http://bit.ly/IntriguingInsects",
        "excerpt": "Longhorn beetles belong to the family Cerambycidae and derive their name from their long antennae.",
        "hashtags": [
          "IntriguingInsects", 
          "WorldofInsects", 
          "insects", 
          "Entomology", 
          "Berkeley", 
          "UCBerkeley", 
          "beetle", 
          "Cerambycidae", 
          "Longhornbeetles"
        ]
      },
      "media_id": "84af621daeddf261af4a6e05da74a6b3",
      "path": "photos/201907/84af621daeddf261af4a6e05da74a6b3.jpg",
      "taken": 1562114951,
      "taken_at": "2019-07-03T00:49:11+00:00"
    },
    "sfomuseum:placetype": "instagram",
    "wof:name": "Longhorn beetles belong to the family Cerambycidae and derive their name from their long antennae...",
    "wof:placetype": "custom"
  },
  "geometry": {"coordinates":[-122.386166,37.616356],"type":"Point"}
}
