{
  "type": "Feature",
  "properties": {
    "instagram:post": {
      "caption": {
        "body": "United Air Lines stewardesses stand in formation to receive their wings from Don G. Maggerell, Vice-President, Passenger Service, in front of a Douglas DC-3 airliner. Stewardesses received their uniform insignia upon graduation from their training program and prior to their first flight. #WomenInAviation #WomensHistoryMonth  United Air Lines stewardess wings ceremony  early 1940s  SFO Museum Collection Gift of United Airlines Archives 1999.047.318"
      },
      "location": "San Francisco International Airport (SFO)",
      "media_id": "9107c0d95f2762f69842353266fb676d",
      "path": "photos/201603/9107c0d95f2762f69842353266fb676d.jpg",
      "taken": 1458178572,
      "taken_at": "2016-03-17T01:36:12+00:00"
    },
    "sfomuseum:placetype": "instagram",
    "wof:name": "Instagram message #%!d(string=9107c0d95f2762f69842353266fb676d)",
    "wof:placetype": "custom"
  },
  "geometry": {"coordinates":[-122.386166,37.616356],"type":"Point"}
}
