{
  "type": "Feature",
  "properties": {
    "date:cessation_lower": "2016-03-16",
    "date:cessation_upper": "2016-03-16",
    "date:inception_lower": "2016-03-16",
    "date:inception_upper": "2016-03-16",
    "instagram:post": {
      "caption": {
        "body": "United Air Lines stewardesses stand in formation to receive their wings from Don G. Maggerell, Vice-President, Passenger Service, in front of a Douglas DC-3 airliner. Stewardesses received their uniform insignia upon graduation from their training program and prior to their first flight. #WomenInAviation #WomensHistoryMonth  United Air Lines stewardess wings ceremony  early 1940s  SFO Museum Collection Gift of United Airlines Archives 1999.047.318",
        "excerpt": "United Air Lines stewardesses stand in formation to receive their wings from Don G. Maggerell, Vice-President, Passenger Service, in front of a Douglas DC-3 airliner."
      },
      "media_id": "9107c0d95f2762f69842353266fb676d",
      "path": "media/other/926517_252919481710866_340848064_n_17854778746027358.jpg",
      "perceptual_hash": "p:da9c952e8547ba49",
      "taken": 1458149760,
      "taken_at": "Mar 16, 2016 5:36 pm"
    },
    "sfomuseum:placetype": "instagram",
    "wof:name": "United Air Lines stewardesses stand in formation to receive their wings from Don G. Maggerell, Vice-President, Passenger Service, in front of a Douglas DC-3 airliner...",
    "wof:placetype": "custom",
    "wof:placetype_alt": [
      "instagram"
    ]
  },
  "geometry": {"coordinates":[-122.386166,37.616356],"type":"Point"}
}
