{
  "type": "Feature",
  "properties": {
    "date:cessation_lower": "2016-01-23",
    "date:cessation_upper": "2016-01-23",
    "date:inception_lower": "2016-01-23",
    "date:inception_upper": "2016-01-23",
    "instagram:post": {
      "caption": {
        "body": "Open wide! Did you know that Boeing 747 freighters specifically designed for cargo can open from their nose cones?",
        "excerpt": "Open wide!"
      },
      "media_id": "efc8f3684e02440cbf378f4cf7098c9e",
      "path": "media/posts/201601/12407665_1010111292401803_225123633_n_17844094993112077.jpg",
      "perceptual_hash": "p:ebca9225c53dc16a",
      "taken": 1453546980,
      "taken_at": "Jan 23, 2016, 11:03 AM"
    },
    "sfomuseum:placetype": "instagram",
    "wof:name": "Open wide!..",
    "wof:placetype": "custom"
  },
  "geometry": {"coordinates":[-122.386166,37.616356],"type":"Point"}
}
