{
  "type": "Feature",
  "properties": {
    "date:cessation_lower": "2016-05-06",
    "date:cessation_upper": "2016-05-06",
    "date:inception_lower": "2016-05-06",
    "date:inception_upper": "2016-05-06",
    "instagram:post": {
      "caption": {
        "body": "A Boeing 247 at \"San Francisco's Busy Airport, Mills Field,\" circa 1935.",
        "excerpt": "A Boeing 247 at \"San Francisco's Busy Airport, Mills Field,\" circa 1935."
      },
      "location": "San Francisco International Airport (SFO)",
      "media_id": "275c37494e7f5dcf5243b55b0d19d13b",
      "path": "photos/201605/275c37494e7f5dcf5243b55b0d19d13b.jpg",
      "perceptual_hash": "p:bbc70857aee0198e",
      "taken": 1462471200,
      "taken_at": "May 5, 2016, 6:00 PM"
    },
    "sfomuseum:placetype": "instagram",
    "wof:name": "A Boeing 247 at \"San Francisco's Busy Airport, Mills Field,\" circa 1935...",
    "wof:placetype": "custom"
  },
  "geometry": {"coordinates":[-122.386166,37.616356],"type":"Point"}
}
