{
  "type": "Feature",
  "properties": {
    "date:cessation_lower": "2018-08-29",
    "date:cessation_upper": "2018-08-29",
    "date:inception_lower": "2018-08-29",
    "date:inception_upper": "2018-08-29",
    "instagram:post": {
      "caption": {
        "body": "The Prison Arts Project started in 1977 as the original model for Arts in Corrections, a statewide California prison arts program which helped lower recidivism (return-to-prison rates) and improve the quality of life for tens of thousands of incarcerated people, their families, and the larger community. San Quentin State Prison’s program offers fourteen classes in visual arts, writing, and music, taught by twelve professional artists. For this exhibition, artists produced a variety of works focusing on birds. They often represent freedom, aspiration, and transcendence.  See \"Free Flying\" by people incarcerated in San Quentin State Prison, located pre-security in Terminal 3. http://bit.ly/2N3dICE",
        "excerpt": "The Prison Arts Project started in 1977 as the original model for Arts in Corrections, a statewide California prison arts program which helped lower recidivism (return-to-prison rates) and improve the quality of life for tens of thousands of incarcerated people, their families, and the larger community.",
        "hashtags": [
          "SanQuentinStatePrison",
          "arts",
          "SanQuentin",
          "ArtsInCorrections",
          "prisonart",
          "arttherapy"
        ]
      },
      "media_id": "dc1759e85c4e28498983202b1ca342b2",
      "path": "photos/201808/dc1759e85c4e28498983202b1ca342b2.jpg",
      "perceptual_hash": "p:bfd685ed86939280",
      "taken": 1535576923,
      "taken_at": "2018-08-29T21:08:43+00:00"
    },
    "sfomuseum:placetype": "instagram",
    "wof:name": "The Prison Arts Project started in 1977 as the original model for Arts in Corrections, a statewide California prison arts program which helped lower recidivism (return-to-prison rates) and improve the quality of life for tens of thousands of incarcerated people, their families, and the larger community...",
    "wof:placetype": "custom"
  },
  "geometry": {"coordinates":[-122.386166,37.616356],"type":"Point"}
}
