{
  "type": "Feature",
  "properties": {
    "instagram:post": {
      "caption": {
        "body": "In May of 1967, Elaine Mayes was a young freelance photographer living in San Francisco when Hullabaloo magazine assigned her to document a three-day concert scheduled for June 16th through June 18th at the Monterey County Fairgrounds, one hundred miles south of the city. The Monterey International Pop Music Festival was organized to showcase rock music and soul music as art forms. Mayes managed to photograph nearly every performer, many of whom would profoundly affect the course of rock music and popular culture. Mayes’ photographs offer a remarkable level of intimacy with performers at this seminal event, remembered by Mayes as “among the best experiences of my life.” See \"It Happened in Monterey\" photographs by Elaine Mayes, post-security, in Terminal 3. http://bit.ly/ElaineMayes",
        "hashtags": [
          "ElaineMayes", 
          "airportart", 
          "publicart", 
          "summeroflove", 
          "rock", 
          "soul", 
          "SanFrancisco", 
          "Monterey", 
          "MontereyPop", 
          "JanisJoplin", 
          "BigBrotherandtheHoldingCompany", 
          "fineart", 
          "fineartphotography", 
          "MuseumWeek", 
          "musicMW", 
          "WomenMW"
        ]
      },
      "media_id": "6d712fb41a574fdb9448ff83f5d37f8b",
      "path": "photos/201706/6d712fb41a574fdb9448ff83f5d37f8b.jpg",
      "taken": 1498109699,
      "taken_at": "2017-06-22T05:34:59+00:00"
    },
    "sfomuseum:placetype": "instagram",
    "wof:name": "Instagram message #%!d(string=6d712fb41a574fdb9448ff83f5d37f8b)",
    "wof:placetype": "custom"
  },
  "geometry": {"coordinates":[-122.386166,37.616356],"type":"Point"}
}
