{
  "type": "Feature",
  "properties": {
    "date:cessation_lower": "2023-07-24",
    "date:cessation_upper": "2023-07-24",
    "date:inception_lower": "2023-07-24",
    "date:inception_upper": "2023-07-24",
    "instagram:post": {
      "caption": {
        "body": "What a beautiful bag for your motion discomfort. Did you know we have over 600 airsickness bags on our online database? From advertisements, instructions, patterns, or logos, these bags feature a variety of different graphic designs.   airsickness bag: Eastern Air Lines; c. 1980 Gift of The Henry Steiner Air Sickness Bag Collection 1998.157.113 https://bit.ly/44u4aVM",
        "excerpt": "What a beautiful bag for your motion discomfort.",
        "hashtags": [
          "52Objects"
        ]
      },
      "media_id": "cc0fe7ea1cdc498d427440805b7dd3675ac8f663",
      "path": "media/other/361913341_732598658877066_9054266729649809105_n_18011941039699179.jpg",
      "perceptual_hash": "p:bc9e9a86ca69926c",
      "taken": 1690187580,
      "taken_at": "Jul 24, 2023 8:33 am"
    },
    "sfomuseum:placetype": "instagram",
    "wof:name": "What a beautiful bag for your motion discomfort...",
    "wof:placetype": "custom"
  },
  "geometry": {"coordinates":[-122.386166,37.616356],"type":"Point"}
}
