{
  "type": "Feature",
  "properties": {
    "date:cessation_lower": "2023-12-11",
    "date:cessation_upper": "2023-12-11",
    "date:inception_lower": "2023-12-11",
    "date:inception_upper": "2023-12-11",
    "instagram:post": {
      "caption": {
        "body": "San Francisco International Airport’s International Terminal officially opened to the public on December 10, 2000. The largest public works project in Northern California at the time, the leader of the Joint Venture Architects group, Skidmore, Owings \u0026 Merrill, envisioned the International Terminal would become the signature structure of SFO. With 24 additional gates and 2.5 million square feet, the International Terminal doubled the overall passenger terminal square footage.  #52Objects #InternationalTerminal #SFOHistory #SFOMuseum   📸: photograph: San Francisco International Airport (SFO), International Terminal construction; 1999 Gift of Edith Lauterbach 2006.028.176.008 https://collection.sfomuseum.org/objects/1762832617/",
        "excerpt": "San Francisco International Airport’s International Terminal officially opened to the public on December 10, 2000."
      },
      "media_id": "a070394595a6843fad9479e0f134bff074dc9575",
      "path": "media/other/409794275_1602765383801020_7310327299247928132_n_17996589347166158.jpg",
      "perceptual_hash": "p:a1d4ba0974bbd52a",
      "taken": 1702312980,
      "taken_at": "Dec 11, 2023 4:43 pm"
    },
    "sfomuseum:placetype": "instagram",
    "wof:name": "San Francisco International Airport’s International Terminal officially opened to the public on December 10, 2000...",
    "wof:placetype": "custom"
  },
  "geometry": {"coordinates":[-122.386166,37.616356],"type":"Point"}
}
