{
  "type": "Feature",
  "properties": {
    "date:cessation_lower": "2021-12-02",
    "date:cessation_upper": "2021-12-02",
    "date:inception_lower": "2021-12-02",
    "date:inception_upper": "2021-12-02",
    "instagram:post": {
      "caption": {
        "body": "Nimisha Doongarwal (@nimishart) collects grouped inventories of fragments—paintings, photographs, fabrics, and digital prints—to create her artwork. Each piece starts with a carefully curated collection of these mixed media. Doongarwal then creates her collages by tearing and layering prints and further embellishing them with paint, stamps, and fabric. Every conceptual portrait takes on a new, abstract identity and tells a unique story by creating visual links to history and contemporary reality. Her work explores the varying relationships between the past and popular culture by referencing social issues such as racism, gender inequality, and immigration.  “Identity” by Nimisha Doongarwal is on display pre-security in Harvey Milk Terminal 1 and online at: https://bit.ly/3HAiyAX",
        "excerpt": "Nimisha Doongarwal (@nimishart) collects grouped inventories of fragments—paintings, photographs, fabrics, and digital prints—to create her artwork.",
        "hashtags": [
          "Identity",
          "NimishaDoongarwal",
          "StudentArtSFO"
        ]
      },
      "media_id": "f3af85fac06fc97ec0016f59e5e33447f5088365",
      "path": "media/posts/202112/262708795_252741106842138_1064709383333409876_n_17956754686531471.jpg",
      "perceptual_hash": "p:b9e503aec41bd076",
      "taken": 1638447600,
      "taken_at": "Dec 2, 2021, 12:20 PM"
    },
    "sfomuseum:placetype": "instagram",
    "wof:name": "Nimisha Doongarwal (@nimishart) collects grouped inventories of fragments—paintings, photographs, fabrics, and digital prints—to create her artwork...",
    "wof:placetype": "custom"
  },
  "geometry": {"coordinates":[-122.386166,37.616356],"type":"Point"}
}
