{
  "type": "Feature",
  "properties": {
    "date:cessation_lower": "2022-05-24",
    "date:cessation_upper": "2022-05-24",
    "date:inception_lower": "2022-05-24",
    "date:inception_upper": "2022-05-24",
    "instagram:post": {
      "caption": {
        "body": "It’s happening!! The long-awaited re-opening of our Aviation Museum and Library will take place next week!   Some of the final objects to be reinstalled are model aircraft suspended from the ceiling. Our preparators took great care in re-hanging models of the Pan Am Clipper (a Sikorsky S-42) and the China Clipper (a Martin M-130).  The Aviation Museum and Library will reopen Wednesday, June 1st at 10am. We can’t wait to welcome you in. https://bit.ly/AMLSFOM",
        "excerpt": "It’s happening!!",
        "hashtags": [
          "AvGeek",
          "BehindTheScenes",
          "SneakPeek",
          "AviationHistory"
        ]
      },
      "media_id": "0891f568066b1765c8933492e2c48c359323e5e8",
      "path": "media/posts/202205/283606793_1172651806834095_1362788517897555464_n_18177919540203918.jpg",
      "perceptual_hash": "p:f292498d874a36f3",
      "taken": 1653411720,
      "taken_at": "May 24, 2022 5:02 pm"
    },
    "sfomuseum:placetype": "instagram",
    "wof:name": "It’s happening!!..",
    "wof:placetype": "custom",
    "wof:placetype_alt": [
      "instagram"
    ]
  },
  "geometry": {"coordinates":[-122.386166,37.616356],"type":"Point"}
}
