{
  "type": "Feature",
  "properties": {
    "instagram:post": {
      "caption": {
        "body": "United Air Lines introduced the company’s first passenger recognition program in 1939. The 100,000 Mile Club campaign was conducted by United’s public contact personnel and awarded personalized plaques, with stars indicating additional 100K miles flown, to the airline’s frequent fliers. Membership reached the thousands by the 1950s.  How many miles have you flown on United?  See \"Flying the Main Line: A History of United Air Lines\", on display, post-security, in Terminal 3. http://bit.ly/TheMainLine  Image: United Air Lines 100,000 Mile Club member plaque, 1965. Gift of John M. Burnard. 2004.093.004",
        "excerpt": "United Air Lines introduced the company’s first passenger recognition program in 1939.",
        "hashtags": [
          "avgeek", 
          "united", 
          "aviationhistory", 
          "flyingthemainline", 
          "themainline", 
          "unitedairlines", 
          "aviationgeek", 
          "aviation", 
          "frequentflyer", 
          "100000mileclub", 
          "1965"
        ]
      },
      "media_id": "3ccf956430cc331589fae1bb50ac55ee",
      "path": "photos/201710/3ccf956430cc331589fae1bb50ac55ee.jpg",
      "taken": 1507349858,
      "taken_at": "2017-10-07T04:17:38+00:00"
    },
    "sfomuseum:placetype": "instagram",
    "wof:name": "United Air Lines introduced the company’s first passenger recognition program in 1939...",
    "wof:placetype": "custom"
  },
  "geometry": {"coordinates":[-122.386166,37.616356],"type":"Point"}
}
