{
  "type": "Feature",
  "properties": {
    "instagram:post": {
      "caption": {
        "body": "In his series, \"Standard Stars\", Eric William Carroll examines and engages with an archive of decaying astronomical glass plate negatives held by the Pisgah Astronomical Research Institute in Rosman, North Carolina. The institute’s Astronomical Photographic Data Archive (APDA) contains one of the largest collections of astronomical glass plates and represents nearly 150 years of efforts to study, catalog, and define the cosmos. Working directly with the photographic plates, Carroll composes new images from the emulsion that has peeled and separated from the glass backing over time. In revisiting the APDA and drawing focus on the deteriorating plates, Standard Stars recontextualizes the fragile objects to ask larger questions about the history of photography and the nature of obsolescence. \"Standard Stars\" by Eric William Carroll is on display pre-security, in Terminal 1. http://bit.ly/2CMrEez",
        "hashtags": [
          "EricCarroll", 
          "StandardStars", 
          "astronomy", 
          "photography", 
          "cosmos", 
          "decay", 
          "glassplatenegative", 
          "negatives"
        ],
        "users": [
          "ericwilliamcarroll"
        ]
      },
      "location": "San Francisco International Airport (SFO)",
      "media_id": "85129b0117818f1ef9d9885aceaf3518",
      "path": "photos/201901/85129b0117818f1ef9d9885aceaf3518.jpg",
      "taken": 1547435843,
      "taken_at": "2019-01-14T03:17:23+00:00"
    },
    "sfomuseum:placetype": "instagram",
    "wof:name": "Instagram message #%!d(string=85129b0117818f1ef9d9885aceaf3518)",
    "wof:placetype": "custom"
  },
  "geometry": {"coordinates":[-122.386166,37.616356],"type":"Point"}
}
