{
  "type": "Feature",
  "properties": {
    "date:cessation_lower": "2022-05-10",
    "date:cessation_upper": "2022-05-10",
    "date:inception_lower": "2022-05-10",
    "date:inception_upper": "2022-05-10",
    "instagram:post": {
      "caption": {
        "body": "Introduced in 1959, the Douglas DC-8 was United Air Lines’ first jet airliner to be launched into service and the second American jetliner to be launched into service after Boeing’s 707. Branded the “Jet Mainliner” by United, it was a major advancement in airliner design and officially launched the airline into the jet age. To help promote the new airliner to the traveling public, United had Pacific Miniatures of Alhambra, California, create several large cutaway models to highlight the DC-8’s new features and amenities, particularly its spacious and luxurious cabin interior. Created to be an easily viewable, three-dimensional presentation of the Jet Mainliner in miniature, the cutaway model contains a highly detailed cockpit and cabin interior with minute features that accurately replicate the actual United DC-8 as launched in 1959.  See “Jet Mainliner in Miniature: The United Air Lines Douglas DC-8 Cutaway Model” on display, pre-security, in the Aviation Museum and Library and online at: https://bit.ly/3AEyqiS",
        "excerpt": "Introduced in 1959, the Douglas DC-8 was United Air Lines’ first jet airliner to be launched into service and the second American jetliner to be launched into service after Boeing’s 707.",
        "hashtags": [
          "jetage",
          "aircraftmodels",
          "avgeek",
          "united",
          "dc8"
        ]
      },
      "media_id": "42e774063ea4fd6d982d3ae65f96d9ae92196899",
      "path": "media/posts/202205/280533613_1064582954129547_6140307298485196914_n_17904865301576621.jpg",
      "perceptual_hash": "p:95466b7e3f30b80c",
      "taken": 1652195760,
      "taken_at": "May 10, 2022 3:16 pm"
    },
    "sfomuseum:placetype": "instagram",
    "wof:name": "Introduced in 1959, the Douglas DC-8 was United Air Lines’ first jet airliner to be launched into service and the second American jetliner to be launched into service after Boeing’s 707...",
    "wof:placetype": "custom",
    "wof:placetype_alt": [
      "instagram"
    ]
  },
  "geometry": {"coordinates":[-122.386166,37.616356],"type":"Point"}
}
