{
  "type": "Feature",
  "properties": {
    "date:cessation_lower": "2021-04-19",
    "date:cessation_upper": "2021-04-19",
    "date:inception_lower": "2021-04-19",
    "date:inception_upper": "2021-04-19",
    "instagram:post": {
      "caption": {
        "body": "New blog alert! What's it like for a designer and the child of an air traffic controller to work at a museum within an airport? Natalia Gajos, our Digital Design Assistant, describes what two years at SFO Museum and San Francisco International Airport has meant to her.  Read Natalia's story here: https://www.sfomuseum.org/about/blog/change-plans   Link also in bio.",
        "excerpt": "New blog alert!",
        "hashtags": [
          "MuseumMonday",
          "museumlife",
          "museum",
          "blog"
        ]
      },
      "media_id": "01cd470101c4d0e9f15de9c3d6f76f1184b43dda",
      "path": "media/other/175798845_288873762830556_185116011118288332_n_17874547418288805.jpg",
      "perceptual_hash": "p:fce304787700a87f",
      "taken": 1618846500,
      "taken_at": "Apr 19, 2021 3:35 pm"
    },
    "sfomuseum:placetype": "instagram",
    "wof:name": "New blog alert!..",
    "wof:placetype": "custom",
    "wof:placetype_alt": [
      "instagram"
    ]
  },
  "geometry": {"coordinates":[-122.386166,37.616356],"type":"Point"}
}
