{
  "type": "Feature",
  "properties": {
    "date:cessation_lower": "2019-01-16",
    "date:cessation_upper": "2019-01-16",
    "date:inception_lower": "2019-01-16",
    "date:inception_upper": "2019-01-16",
    "instagram:post": {
      "caption": {
        "body": "The lap steel guitar developed in Hawai’i in the late-nineteenth and early-twentieth centuries and is attributed to an adolescent named Joseph Kekuku (1874–1932). He began playing a regular guitar on his lap and sliding a piece of metal along its strings. By plucking the strings with one hand and changing the pitch of the strings with the use of a metal bar or slide, he created an entirely new sound. Kekuku spent several years perfecting the technique, which his classmates soon learned. The new form of guitar playing quickly spread throughout the islands, transforming island guitar music as well as the music of the continental United States. \"Down-Home Music: The Story of Arhoolie Records\" is on display, post-security, in Terminal 2. http://bit.ly/StoryofArhoolie",
        "excerpt": "The lap steel guitar developed in Hawai’i in the late-nineteenth and early-twentieth centuries and is attributed to an adolescent named Joseph Kekuku (1874–1932).",
        "hashtags": [
          "storyofarhoolie",
          "arhoolie",
          "arhoolierecords",
          "ChrisStrachwitz",
          "hawaii",
          "music",
          "steelguitar",
          "guitar",
          "recordalbum",
          "albumcover"
        ]
      },
      "media_id": "7889ba5ca573480736d2763b28d14f4f",
      "path": "media/other/49296896_289204318456383_989780347563371086_n_17905364995283399.jpg",
      "perceptual_hash": "p:b69079a6bcf34470",
      "taken": 1547637000,
      "taken_at": "Jan 16, 2019 11:10 am"
    },
    "sfomuseum:placetype": "instagram",
    "wof:name": "The lap steel guitar developed in Hawai’i in the late-nineteenth and early-twentieth centuries and is attributed to an adolescent named Joseph Kekuku (1874–1932)...",
    "wof:placetype": "custom",
    "wof:placetype_alt": [
      "instagram"
    ]
  },
  "geometry": {"coordinates":[-122.386166,37.616356],"type":"Point"}
}
