{
  "type": "Feature",
  "properties": {
    "date:cessation_lower": "2018-02-26",
    "date:cessation_upper": "2018-02-26",
    "date:inception_lower": "2018-02-26",
    "date:inception_upper": "2018-02-26",
    "instagram:post": {
      "caption": {
        "body": "Artist and filmmaker Marco Brambilla pays tribute to the golden age of cinema in his reworking of the well-known scene of Gene Kelly and Leslie Caron during the musical finale of the 1951 film, An American in Paris. \"Celluloid (An American in Paris, 1951)\" by Marco Brambilla, is now playing in the Video Arts Gallery located, pre-security, in the International Terminal.",
        "excerpt": "Artist and filmmaker Marco Brambilla pays tribute to the golden age of cinema in his reworking of the well-known scene of Gene Kelly and Leslie Caron during the musical finale of the 1951 film, An American in Paris."
      },
      "file_hash": "bdbb4f10fd78eb58a2efa44910897f4207407e61b3b9b534fa097b4b534e0ffd",
      "media_id": "4dc5ad4f09861d0fb04ae6b1e603f50cc23d90f1",
      "path": "media/other/ED4FB6F651E845BE09C429E60BC11FA8_video_dashinit_17926230376022101.mp4",
      "taken": 1519681140,
      "taken_at": "Feb 26, 2018 9:39 pm"
    },
    "sfomuseum:placetype": "instagram",
    "wof:name": "Artist and filmmaker Marco Brambilla pays tribute to the golden age of cinema in his reworking of the well-known scene of Gene Kelly and Leslie Caron during the musical finale of the 1951 film, An American in Paris...",
    "wof:placetype": "custom"
  },
  "geometry": {"coordinates":[-122.386166,37.616356],"type":"Point"}
}
