{
  "type": "Feature",
  "properties": {
    "date:cessation_lower": "2017-04-26",
    "date:cessation_upper": "2017-04-26",
    "date:inception_lower": "2017-04-26",
    "date:inception_upper": "2017-04-26",
    "instagram:post": {
      "caption": {
        "body": "George Petty became famous as a pinup artist in the 1930s and 40s. He also sketched a TWA hostess dressed in the winter blue uniform introduced in 1938, giving the uniform the nickname “Petty Girl.” The uniform was first worn in 1938 at the opening of New York’s LaGuardia Airport.  Image: Transcontinental \u0026 Western Air (TWA) calendar, Douglas DC-3, 1941. Gift of Captain Jon Simmonds. 2016.080.011",
        "excerpt": "George Petty became famous as a pinup artist in the 1930s and 40s.",
        "hashtags": [
          "pettygirl",
          "TWA",
          "georgepetty",
          "fashioninflight",
          "womeninaviation",
          "avgeek",
          "aviationhistory"
        ]
      },
      "media_id": "c657c3caf81c7eff6155bed382810f18",
      "path": "media/posts/201704/18095199_1420935181261985_620675383326408704_n_17854373128193872.jpg",
      "perceptual_hash": "p:b08b9cc3c36b333c",
      "taken": 1493230620,
      "taken_at": "Apr 26, 2017, 6:17 PM"
    },
    "sfomuseum:placetype": "instagram",
    "wof:name": "George Petty became famous as a pinup artist in the 1930s and 40s...",
    "wof:placetype": "custom"
  },
  "geometry": {"coordinates":[-122.386166,37.616356],"type":"Point"}
}
