{
  "type": "Feature",
  "properties": {
    "date:cessation_lower": "2024-01-24",
    "date:cessation_upper": "2024-01-24",
    "date:inception_lower": "2024-01-24",
    "date:inception_upper": "2024-01-24",
    "instagram:post": {
      "caption": {
        "body": "Virgin America was founded in 2004 by the Virgin Group to offer a more pleasurable domestic airline flying experience to the traveling public. Headquartered in nearby Burlingame, California, the carrier built a large and particularly loyal customer base through a unique blend of style, equipment, and services. These included leather seats, cabin mood lighting, premium entertainment systems with a broad range of audiovisual programming, full-service meals, and friendly, enthusiastic flight and ground crews dressed in hip, casual uniforms. The airline primarily focused on offering superior economy services while also providing competitive first-class amenities. The carrier’s flight crews were known for fostering a fun, relaxed, and enjoyable cabin atmosphere that was reminiscent of earlier California carriers, such as PSA (Pacific Southwest Airlines) and Hughes Airwest.  See \"VX Forever: The Legacy of Virgin America\" on display in the Aviation Museum and Library, located pre-security, in the International Terminal, open daily from 10am to 4:30pm. https://www.sfomuseum.org/exhibitions/vx-forever",
        "excerpt": "Virgin America was founded in 2004 by the Virgin Group to offer a more pleasurable domestic airline flying experience to the traveling public.",
        "hashtags": [
          "VXForever",
          "AvGeek",
          "VirginAmerica"
        ]
      },
      "media_id": "9240940bafcd91fcaede514b1eb2bf6e51f963c2",
      "path": "media/posts/202401/421743112_860086302794967_7617428602282207276_n_17875070129982800.jpg",
      "perceptual_hash": "p:9f8c70f32c4c9363",
      "taken": 1706115240,
      "taken_at": "Jan 24, 2024 4:54 pm"
    },
    "sfomuseum:placetype": "instagram",
    "wof:name": "Virgin America was founded in 2004 by the Virgin Group to offer a more pleasurable domestic airline flying experience to the traveling public...",
    "wof:placetype": "custom"
  },
  "geometry": {"coordinates":[-122.386166,37.616356],"type":"Point"}
}
