{
  "type": "Feature",
  "properties": {
    "date:cessation_lower": "2018-08-10",
    "date:cessation_upper": "2018-08-10",
    "date:inception_lower": "2018-08-10",
    "date:inception_upper": "2018-08-10",
    "instagram:post": {
      "caption": {
        "body": "Pinball games trace their origins to bagatelle, a fashionable eighteenth-century French table game. Bagatelle was developed from billiards, and utilized an inclined playing field with central pockets shrouded by pins. Using a cue and ball, bagatelle players deflected indirect shots towards an arched backstop. Skilled shots made their way directly into high-scoring pockets, while others bounced downward from pin to pin, left to chance for a score or additional shot from pockets in the lower trough. Bagatelle was also found in taverns, home parlors, and saloons throughout England and the United States. In 1901, Caille Brothers of Detroit patented Log Cabin, a nickel-operated bagatelle game and trade stimulator. Log Cabin features a spring-loaded plunger for shooting and pioneered the mechanical ball lift—an important feature of modern pinball machines. This version of Log Cabin offered $1 for the central shot, or between two and five cigars from alternating pockets in the lower trough.  Pinball game is courtesy of Joe Welch American Antique Museum. \"The Automatic Age: Coin-Operated Machines\" is on display, pre-security, in the International Terminal. http://bit.ly/CoinOperated",
        "excerpt": "Pinball games trace their origins to bagatelle, a fashionable eighteenth-century French table game.",
        "hashtags": [
          "coinoperated",
          "TheAutomaticAge",
          "coinop",
          "vintage",
          "antique",
          "gamemachines",
          "slotmachine",
          "slotmachines",
          "bagatelle",
          "pinball",
          "games",
          "tablegames"
        ]
      },
      "media_id": "c59b9ea5e3ca7762c680d127c276a2ca",
      "path": "media/posts/201808/38019743_221457698539642_8262861875948027904_n_17933697652171789.jpg",
      "perceptual_hash": "p:ee4ac43f9ce098d1",
      "taken": 1533916260,
      "taken_at": "Aug 10, 2018, 3:51 PM"
    },
    "sfomuseum:placetype": "instagram",
    "wof:name": "Pinball games trace their origins to bagatelle, a fashionable eighteenth-century French table game...",
    "wof:placetype": "custom"
  },
  "geometry": {"coordinates":[-122.386166,37.616356],"type":"Point"}
}
