{
  "type": "Feature",
  "properties": {
    "date:cessation_lower": "2018-05-24",
    "date:cessation_upper": "2018-05-24",
    "date:inception_lower": "2018-05-24",
    "date:inception_upper": "2018-05-24",
    "instagram:post": {
      "caption": {
        "body": "#OnThisDay in 1960, the Pan American Worldport terminal opened at Idlewild Airport, now called John F. Kennedy International Airport in New York City. #PanAm operated out of the Worldport terminal until the airline ceased operations in 1991. Delta Airlines took over Worldport until May of 2013; the demolition of the terminal began the following month. Did you ever travel through the Worldport?  Image:  Pan American World Airways brochure, John F. Kennedy International Airport (JFK), 1972. In memory of Jane Anne Thoe-Meyer. 2016.117.090",
        "excerpt": "#OnThisDay in 1960, the Pan American Worldport terminal opened at Idlewild Airport, now called John F. Kennedy International Airport in New York City.",
        "hashtags": [
          "worldport",
          "PanAm",
          "PAA",
          "avgeek",
          "avationgeek",
          "aviation",
          "aviationhistory",
          "vintageaviation",
          "history",
          "avhistory",
          "aviationgeeks",
          "avgeeks"
        ]
      },
      "location": "San Francisco International Airport (SFO)",
      "media_id": "a81c2cef6e7e13255bc932ad72038dae",
      "path": "photos/201805/a81c2cef6e7e13255bc932ad72038dae.jpg",
      "perceptual_hash": "p:e5989bc63269cd31",
      "taken": 1527163980,
      "taken_at": "May 24, 2018, 12:13 PM"
    },
    "sfomuseum:placetype": "instagram",
    "wof:name": "#OnThisDay in 1960, the Pan American Worldport terminal opened at Idlewild Airport, now called John F. Kennedy International Airport in New York City...",
    "wof:placetype": "custom"
  },
  "geometry": {"coordinates":[-122.386166,37.616356],"type":"Point"}
}
