{
  "type": "Feature",
  "properties": {
    "instagram:post": {
      "caption": {
        "body": "#OnThisDay in 1927, Charles A. Lindbergh landed in Paris, France, making aviation history. The Ryan NYP “Spirit of St. Louis” was built by Ryan Airlines in San Diego specifically for Lindbergh to fly across the Atlantic Ocean and win the New York–Paris Orteig Prize. On May 20, 1927, from Roosevelt Field, New York, Lindbergh flew a solo, non-stop, transatlantic flight of approximately 3,600 miles that lasted over thirty-three hours. He arrived the next day at Le Bourget Airport, Paris. By completing this first solo, non-stop, transatlantic flight, Lindbergh immediately became an international aviation superstar.  See \"Aviation Evolutions: The Jim Lund 1:72 Scale Model Airplane Collection\", which features more than 200 models, on display, pre-security, in the Aviation Museum. http://bit.ly/AviationEvolutions",
        "hashtags": [
          "AviationEvolutions", 
          "JimLund", 
          "CharlesLindbergh", 
          "LuckyLindy", 
          "Lindbergh", 
          "RyanNYP", 
          "SpiritofStLouis", 
          "RyanAirlines", 
          "Paris", 
          "NewYork", 
          "avgeek", 
          "avationgeek", 
          "aviation", 
          "aviationhistory", 
          "vintageaviation", 
          "history", 
          "avhistory", 
          "aviationgeeks", 
          "modelplane", 
          "avgeeks", 
          "modelaircraft", 
          "airplane", 
          "aircraft"
        ]
      },
      "location": "San Francisco International Airport (SFO)",
      "media_id": "30835a1ba0f8696483c1fb378f5ba806",
      "path": "photos/201805/30835a1ba0f8696483c1fb378f5ba806.jpg",
      "taken": 1526930197,
      "taken_at": "2018-05-21T19:16:37+00:00"
    },
    "sfomuseum:placetype": "instagram",
    "wof:name": "Instagram message #%!d(string=30835a1ba0f8696483c1fb378f5ba806)",
    "wof:placetype": "custom"
  },
  "geometry": {"coordinates":[-122.386166,37.616356],"type":"Point"}
}
