{
  "type": "Feature",
  "properties": {
    "date:cessation_lower": "2015-12-07",
    "date:cessation_upper": "2015-12-07",
    "date:inception_lower": "2015-12-07",
    "date:inception_upper": "2015-12-07",
    "instagram:post": {
      "caption": {
        "body": "For the next month, passengers can enjoy live music playing in SFO's terminals as part of the Sounds of the Season program. In the 1940s, Pan American hired Lord Caresser, a Trinidadian Calypso singer, to greet passengers at Picaro Airport near Port of Spain, Trinidad, with songs about travelers or current news. The group adopted the name Pan-ypsoes for the gig.  Lord Caresser and his calypso group performing at Picaro Airport, Trinidad, for Pan American Airways early 1940s SFO Museum Collection 2014.061.005",
        "excerpt": "For the next month, passengers can enjoy live music playing in SFO's terminals as part of the Sounds of the Season program."
      },
      "media_id": "3e1b406cac52958f8ade3b0510b57389",
      "path": "media/other/12317935_155012691522739_649607149_n_17850620677048556.jpg",
      "perceptual_hash": "p:c8d5b3a8e1689736",
      "taken": 1449489420,
      "taken_at": "Dec 07, 2015 11:57 am"
    },
    "sfomuseum:placetype": "instagram",
    "wof:name": "For the next month, passengers can enjoy live music playing in SFO's terminals as part of the Sounds of the Season program...",
    "wof:placetype": "custom",
    "wof:placetype_alt": [
      "instagram"
    ]
  },
  "geometry": {"coordinates":[-122.386166,37.616356],"type":"Point"}
}
