{
  "type": "Feature",
  "properties": {
    "instagram:post": {
      "caption": {
        "body": "For the next month, passengers can enjoy live music playing in SFO's terminals as part of the Sounds of the Season program. In the 1940s, Pan American hired Lord Caresser, a Trinidadian Calypso singer, to greet passengers at Picaro Airport near Port of Spain, Trinidad, with songs about travelers or current news. The group adopted the name Pan-ypsoes for the gig.  Lord Caresser and his calypso group performing at Picaro Airport, Trinidad, for Pan American Airways early 1940s SFO Museum Collection 2014.061.005",
        "excerpt": "For the next month, passengers can enjoy live music playing in SFO's terminals as part of the Sounds of the Season program."
      },
      "location": "SFO Museum",
      "media_id": "3e1b406cac52958f8ade3b0510b57389",
      "path": "photos/201512/3e1b406cac52958f8ade3b0510b57389.jpg",
      "taken": 1449518230,
      "taken_at": "2015-12-07T19:57:10+00:00"
    },
    "sfomuseum:placetype": "instagram",
    "wof:name": "For the next month, passengers can enjoy live music playing in SFO's terminals as part of the Sounds of the Season program...",
    "wof:placetype": "custom"
  },
  "geometry": {"coordinates":[-122.386166,37.616356],"type":"Point"}
}
