{
  "type": "Feature",
  "properties": {
    "date:cessation_lower": "2014-07-29",
    "date:cessation_upper": "2014-07-29",
    "date:inception_lower": "2014-07-29",
    "date:inception_upper": "2014-07-29",
    "instagram:post": {
      "caption": {
        "hashtags": [
          "Tiffany",
          "glass"
        ]
      },
      "media_id": "8ab2b4c542ad9e06807f6e57f413d292",
      "path": "media/posts/201407/10518138_276890779165542_13756397_n_17842458337062499.jpg",
      "perceptual_hash": "p:95487f275ac82f86",
      "taken": 1406631180,
      "taken_at": "Jul 29, 2014, 10:53 AM"
    },
    "sfomuseum:placetype": "instagram",
    "wof:name": "..",
    "wof:placetype": "custom"
  },
  "geometry": {"coordinates":[-122.386166,37.616356],"type":"Point"}
}
