{
  "type": "Feature",
  "properties": {
    "date:cessation_lower": "2016-01-13",
    "date:cessation_upper": "2016-01-13",
    "date:inception_lower": "2016-01-13",
    "date:inception_upper": "2016-01-13",
    "instagram:post": {
      "caption": {
        "hashtags": [
          "WomenInAviation"
        ]
      },
      "media_id": "f7750c41ccc23cc4f5935677530cc775d37c9dd8",
      "path": "media/posts/201601/12519188_1683408041904212_448233985_n_17846747497067495.jpg",
      "perceptual_hash": "p:898586ca2eecd673",
      "taken": 1452715320,
      "taken_at": "Jan 13, 2016, 8:02 PM"
    },
    "sfomuseum:placetype": "instagram",
    "wof:name": "..",
    "wof:placetype": "custom"
  },
  "geometry": {"coordinates":[-122.386166,37.616356],"type":"Point"}
}
