{
  "type": "Feature",
  "properties": {
    "instagram:post": {
      "caption": {
        "body": "#Onthisday in 1929, Charles Lindbergh piloted a Ford 5-AT Tri-Motor, named \"Mexico\" and painted with C.M.A. and Pan American Airways markings, on the first southbound airmail service from Brownsville Municipal Airport in Brownsville, Texas, to Mexico City, via Tampico. Located at the southernmost point of Texas, near the Mexico–United States border, the Brownsville Municipal Airport served as Pan American Airways’ Western Division base for destinations to Mexico by its Mexican subsidiary Compañía Mexicana de Aviación or C.M.A. Charles Lindbergh completed this inaugural flight only two days after the Brownsville Airport opened.  Image: Brownsville Municipal Airport, Brownsville, Texas, c. 1929. Gift of Jon E. Krupnick. 2010.281.006.025 - A large crowd welcomes Charles Lindbergh at Brownsville Municipal Airport before his inaugural airmail flight to Mexico City, 1929. Gift of Jon E. Krupnick. 2010.281.006.008 ",
        "excerpt": "#Onthisday in 1929, Charles Lindbergh piloted a Ford 5-AT Tri-Motor, named \"Mexico\" and painted with C.M.A. and Pan American Airways markings, on the first southbound airmail service from Brownsville Municipal Airport in Brownsville, Texas, to Mexico City, via Tampico.",
        "hashtags": [
          "avgeek", 
          "Brownsville", 
          "airport", 
          "Texas", 
          "PAA", 
          "panam", 
          "CharlesLindbergh", 
          "aviationhistory"
        ]
      },
      "media_id": "565de87bda5d0513b610297a5c5b0547",
      "path": "photos/201903/565de87bda5d0513b610297a5c5b0547.jpg",
      "taken": 1552255248,
      "taken_at": "2019-03-10T22:00:48+00:00"
    },
    "sfomuseum:placetype": "instagram",
    "wof:name": "#Onthisday in 1929, Charles Lindbergh piloted a Ford 5-AT Tri-Motor, named \"Mexico\" and painted with C.M.A. and Pan American Airways markings, on the first southbound airmail service from Brownsville Municipal Airport in Brownsville, Texas, to Mexico City, via Tampico...",
    "wof:placetype": "custom"
  },
  "geometry": {"coordinates":[-122.386166,37.616356],"type":"Point"}
}
