{
  "type": "Feature",
  "properties": {
    "date:cessation_lower": "2016-04-05",
    "date:cessation_upper": "2016-04-05",
    "date:inception_lower": "2016-04-05",
    "date:inception_upper": "2016-04-05",
    "instagram:post": {
      "caption": {
        "hashtags": [
          "TravelTuesday"
        ]
      },
      "media_id": "b01429bf99b8f03bce33ea36d972a7a0",
      "path": "media/posts/201604/12950428_1684991638421518_939647646_n_17846455516121584.jpg",
      "perceptual_hash": "p:9b649a93659b9463",
      "taken": 1459872480,
      "taken_at": "Apr 5, 2016, 4:08 PM"
    },
    "sfomuseum:placetype": "instagram",
    "wof:name": "..",
    "wof:placetype": "custom",
    "wof:placetype_alt": [
      "instagram"
    ]
  },
  "geometry": {"coordinates":[-122.386166,37.616356],"type":"Point"}
}
