{
  "type": "Feature",
  "properties": {
    "date:cessation_lower": "2022-06-23",
    "date:cessation_upper": "2022-06-23",
    "date:inception_lower": "2022-06-23",
    "date:inception_upper": "2022-06-23",
    "instagram:post": {
      "caption": {
        "body": "London-based filmmaker Balan Evans reveals the fierce determination, resilience, and hope of the LGBTQ community in Sierra Leone, where homosexuality is illegal.   See “Queen Harold” by Balan Evan in the Video Arts Gallery, located pre-security in the International Terminal with daily operating hours of 7:00am to 10:00pm, or online at: https://bit.ly/3mdjjXm",
        "excerpt": "London-based filmmaker Balan Evans reveals the fierce determination, resilience, and hope of the LGBTQ community in Sierra Leone, where homosexuality is illegal.",
        "hashtags": [
          "VideoArts",
          "VideoArtsSFO",
          "pride",
          "QueenHarold",
          "LGBT",
          "SierraLeone"
        ],
        "users": [
          "balan.evans"
        ]
      },
      "file_hash": "100e5170c98777e0e01c33251b837636b0f726831e3a87082c112f39eafbfa50",
      "media_id": "a78ec96dc2132bdecbb5876ca81e141b8e3d204a",
      "path": "media/posts/202206/289825226_365886725651392_5223896279226483861_n_17915470700422452.mp4",
      "taken": 1655987580,
      "taken_at": "Jun 23, 2022, 12:33 PM"
    },
    "sfomuseum:placetype": "instagram",
    "wof:name": "London-based filmmaker Balan Evans reveals the fierce determination, resilience, and hope of the LGBTQ community in Sierra Leone, where homosexuality is illegal...",
    "wof:placetype": "custom"
  },
  "geometry": {"coordinates":[-122.386166,37.616356],"type":"Point"}
}
