{
  "type": "Feature",
  "properties": {
    "date:cessation_lower": "2024-01-31",
    "date:cessation_upper": "2024-01-31",
    "date:inception_lower": "2024-01-31",
    "date:inception_upper": "2024-01-31",
    "instagram:post": {
      "caption": {
        "body": "Introduced in 1955, the Lockheed L-1049G Super Constellation, also known as the “Super G,” was a longer-range upgrade variant of the Super Constellation. Equipped with wingtip fuel tanks, it was primarily designed for operation on transatlantic routes. It was followed in 1957 by the improved L-1649 Starliner, the final version of the Constellation. Passengers flying between the U.S. and Europe could expect to spend many long hours sitting in the cabins of these propliners. Cruising at around 300 miles per hour, a flight with refueling stops between London and Los Angeles could require more than twenty hours. Henry Dreyfuss Associates designed the cabin interiors for these Lockheed airliners in a multitude of harmonized color and fabric combinations. In order to minimize the claustrophobic effects of viewing down a long tube they divided it into four separate sections, which included a roomy first class lounge.   See “Remain Seated: Airliner Passenger Chairs,” on display, pre-security in the Aviation Museum and Library, located on the departures level of the International Terminal and online at: https://bit.ly/AirlinerChairs",
        "excerpt": "Introduced in 1955, the Lockheed L-1049G Super Constellation, also known as the “Super G,” was a longer-range upgrade variant of the Super Constellation.",
        "hashtags": [
          "AirlinerChairs",
          "AircraftInteriors",
          "AvGeek"
        ]
      },
      "media_id": "3f0cf4a22a6498b00b4233eecd0e8c72c7770587",
      "path": "media/posts/202401/424687491_865225915614339_1378872985451997209_n_18174397135295973.jpg",
      "perceptual_hash": "p:a4c09b0bcfb4ce99",
      "taken": 1706721480,
      "taken_at": "Jan 31, 2024 5:18 pm"
    },
    "sfomuseum:placetype": "instagram",
    "wof:name": "Introduced in 1955, the Lockheed L-1049G Super Constellation, also known as the “Super G,” was a longer-range upgrade variant of the Super Constellation...",
    "wof:placetype": "custom"
  },
  "geometry": {"coordinates":[-122.386166,37.616356],"type":"Point"}
}
