{
  "type": "Feature",
  "properties": {
    "date:cessation_lower": "2021-06-01",
    "date:cessation_upper": "2021-06-01",
    "date:inception_lower": "2021-06-01",
    "date:inception_upper": "2021-06-01",
    "instagram:post": {
      "caption": {
        "body": "Harvey Milk (1930–78) made history in 1977 when he became the first openly gay individual elected to public office in the state of California. He would serve just eleven months on the San Francisco Board of Supervisors before his assassination on November 27, 1978. Today, Harvey Milk’s legacy is felt in the gains for LGBTQ rights made during the four decades since his tragic death, including the 2015 United States Supreme Court ruling recognizing same-sex marriage as a legal right.   Learn more about Harvey Milk's life and legacy in our exhibition, \"Messenger of Hope,\" which is on view pre-security in Harvey Milk Terminal 1. Not traveling? The exhibition catalog is available to read online! https://www.sfomuseum.org/exhibitions/harvey-milk-messenger-hope \u003c— link in bio",
        "excerpt": "Harvey Milk (1930–78) made history in 1977 when he became the first openly gay individual elected to public office in the state of California.",
        "hashtags": [
          "Pride2021",
          "Pride",
          "HarveyMilk"
        ]
      },
      "media_id": "3f0fa7fb1959fbee03f27f5969d53d9d0dc481b2",
      "path": "media/posts/202106/195759107_309625974090506_3428675703724570475_n_17917734922702136.jpg",
      "perceptual_hash": "p:d2b9e493eea70819",
      "taken": 1622562480,
      "taken_at": "Jun 1, 2021, 3:48 PM"
    },
    "sfomuseum:placetype": "instagram",
    "wof:name": "Harvey Milk (1930–78) made history in 1977 when he became the first openly gay individual elected to public office in the state of California...",
    "wof:placetype": "custom"
  },
  "geometry": {"coordinates":[-122.386166,37.616356],"type":"Point"}
}
