{
  "type": "Feature",
  "properties": {
    "date:cessation_lower": "2016-11-15",
    "date:cessation_upper": "2016-11-15",
    "date:inception_lower": "2016-11-15",
    "date:inception_upper": "2016-11-15",
    "instagram:post": {
      "caption": {
        "hashtags": [
          "TravelTuesday"
        ]
      },
      "media_id": "341a9030e4343d6be34a5cb8916c4d2c",
      "path": "media/posts/201611/15034665_1513689451980736_786845468985393152_n_17865351280014150.jpg",
      "perceptual_hash": "p:c6c0b91fc86656d9",
      "taken": 1479236280,
      "taken_at": "Nov 15, 2016 6:58 pm"
    },
    "sfomuseum:placetype": "instagram",
    "wof:name": "..",
    "wof:placetype": "custom",
    "wof:placetype_alt": [
      "instagram"
    ]
  },
  "geometry": {"coordinates":[-122.386166,37.616356],"type":"Point"}
}
