{
  "type": "Feature",
  "properties": {
    "date:cessation_lower": "2018-09-06",
    "date:cessation_upper": "2018-09-06",
    "date:inception_lower": "2018-09-06",
    "date:inception_upper": "2018-09-06",
    "instagram:post": {
      "caption": {
        "body": "Richard E. Byrd was a famous aviator who explored the North and South Poles in the early 20th century. He was reportedly the first person to fly over the North and South Poles, though the former claim is disputed. His trips to Antarctica were widely reported on and documented, including the famous flight over the South Pole. \"With Byrd at the South Pole,\" was released in 1930, documenting the 14 months Byrd and his crew spent in the Antarctic. As a result of his accomplishments, the United States Navy promoted him to the rank of Rear Admiral; he was nicknamed the Admiral of the Antarctic.  Richard Evelyn Byrd film production, portrait of Admiral Richard Evelyn Byrd c. 1930 SFO Museum Collection 2007.077.017.044",
        "excerpt": "Richard E. Byrd was a famous aviator who explored the North and South Poles in the early 20th century."
      },
      "media_id": "9a201ce0ed65f04ab345e68b86a68ddf",
      "path": "media/posts/201809/40470295_230432971151110_1992099565648212520_n_17903716117235635.jpg",
      "perceptual_hash": "p:b8edf060b0a693b6",
      "taken": 1536252360,
      "taken_at": "Sep 6, 2018, 4:46 PM"
    },
    "sfomuseum:placetype": "instagram",
    "wof:name": "Richard E. Byrd was a famous aviator who explored the North and South Poles in the early 20th century...",
    "wof:placetype": "custom"
  },
  "geometry": {"coordinates":[-122.386166,37.616356],"type":"Point"}
}
