{
  "type": "Feature",
  "properties": {
    "date:cessation_lower": "2020-10-15",
    "date:cessation_upper": "2020-10-15",
    "date:inception_lower": "2020-10-15",
    "date:inception_upper": "2020-10-15",
    "instagram:post": {
      "caption": {
        "body": "In honor of our 40th anniversary, every week this year we are highlighting one of our past exhibitions. In 2001, we presented “Chicken or the Egg” which featured items relating to the popularity of chickens, roosters, and eggs. Do you remember this exhibition?",
        "excerpt": "In honor of our 40th anniversary, every week this year we are highlighting one of our past exhibitions.",
        "hashtags": [
          "SFOMat40",
          "TBTSFOM",
          "MuseumFromHome"
        ]
      },
      "media_id": "99121c5d5e6b624686f2a755a08073472004067a",
      "path": "media/posts/202010/121571516_849170659160432_655177170811513488_n_17903694613545197.jpg",
      "perceptual_hash": "p:803f4abf7cc0526e",
      "taken": 1602776340,
      "taken_at": "Oct 15, 2020, 3:39 PM"
    },
    "sfomuseum:placetype": "instagram",
    "wof:name": "In honor of our 40th anniversary, every week this year we are highlighting one of our past exhibitions...",
    "wof:placetype": "custom"
  },
  "geometry": {"coordinates":[-122.386166,37.616356],"type":"Point"}
}
