{
  "type": "Feature",
  "properties": {
    "date:cessation_lower": "2018-03-27",
    "date:cessation_upper": "2018-03-27",
    "date:inception_lower": "2018-03-27",
    "date:inception_upper": "2018-03-27",
    "instagram:post": {
      "caption": {
        "body": "In the 1930s and 1940s, flights from San Francisco to Hong Kong required multiple stops along the way. \"China Clipper\", our exhibition detailing the arduous journey, is on display in the Aviation Museum and Library. In 1937, a trip from San Francisco (which actually departed from Alameda) to Hong Kong took at least a week with stops in Honolulu, Midway Island, Wake Island, Guam, and Manila. The flight from San Francisco to Hong Kong cost $1,710 round trip, which has the same buying power as about $29,700 in today's money. Have you ever been to Hong Kong? Learn more about #PanAm's #ChinaClipper in \"China Clipper\", on display, pre-security in the Aviation Museum and Library. http://bit.ly/chinaclipper  Image: Pan American Airways route map, transpacific route, c. 1937. SFO Museum Collection. 1998.139.006",
        "excerpt": "In the 1930s and 1940s, flights from San Francisco to Hong Kong required multiple stops along the way.",
        "hashtags": [
          "avgeek",
          "avationgeek",
          "aviation",
          "aviationhistory",
          "vintageaviation",
          "history",
          "avhistory",
          "aviationgeeks",
          "avgeeks",
          "map",
          "routemap",
          "travelTuesday"
        ]
      },
      "location": "San Francisco International Airport (SFO)",
      "media_id": "1dabb9929baf1795cba72d8136862056",
      "path": "photos/201803/1dabb9929baf1795cba72d8136862056.jpg",
      "perceptual_hash": "p:c2aa2db230f5d656",
      "taken": 1522148760,
      "taken_at": "Mar 27, 2018, 11:06 AM"
    },
    "sfomuseum:placetype": "instagram",
    "wof:name": "In the 1930s and 1940s, flights from San Francisco to Hong Kong required multiple stops along the way...",
    "wof:placetype": "custom"
  },
  "geometry": {"coordinates":[-122.386166,37.616356],"type":"Point"}
}
