{
  "type": "Feature",
  "properties": {
    "date:cessation_lower": "2017-08-27",
    "date:cessation_upper": "2017-08-27",
    "date:inception_lower": "2017-08-27",
    "date:inception_upper": "2017-08-27",
    "instagram:post": {
      "caption": {
        "body": "#Onthisday in 1954, the new Terminal Building at SFO was dedicated. The upper level was for departures and the lower level was for arrivals, each with its own roadway. A spacious restaurant named the International Room provided panoramic views of the airfield. In addition to the new radar, radio, and lighting systems, airfield improvements at the time included parallel runways for simultaneous take-off and landings.  As SFO had reached 2 million passengers by 1952, this new facility could accommodate several million additional passengers. The dedication ceremony for the new Terminal was a three-day event that drew hundreds of thousands of visitors.  Later called the Central Terminal, the building has been modified several times over the years and, now named Terminal 2, it is still part of SFO.  Image: San Francisco International Airport (SFO), dedication events for new Terminal Building, 1954. SFO Museum Collection. 2011.032.0392",
        "excerpt": "#Onthisday in 1954, the new Terminal Building at SFO was dedicated.",
        "hashtags": [
          "SFOHistory",
          "SFO",
          "avgeek",
          "avationgeek",
          "aviation",
          "aviationhistory",
          "aviationlovers",
          "vintageaviation",
          "history",
          "avhistory",
          "aviationgeeks",
          "instaplane",
          "flying",
          "plane",
          "flight",
          "airline",
          "avgeeks",
          "aviation4u",
          "aviationdaily"
        ]
      },
      "media_id": "87452b091d9aacdddf9ece5b5e1463dc",
      "path": "photos/201708/87452b091d9aacdddf9ece5b5e1463dc.jpg",
      "perceptual_hash": "p:c6e6a91819eb6365",
      "taken": 1503865511,
      "taken_at": "2017-08-27T20:25:11+00:00"
    },
    "sfomuseum:placetype": "instagram",
    "wof:name": "#Onthisday in 1954, the new Terminal Building at SFO was dedicated...",
    "wof:placetype": "custom"
  },
  "geometry": {"coordinates":[-122.386166,37.616356],"type":"Point"}
}
