{
  "type": "Feature",
  "properties": {
    "date:cessation_lower": "2015-08-31",
    "date:cessation_upper": "2015-08-31",
    "date:inception_lower": "2015-08-31",
    "date:inception_upper": "2015-08-31",
    "instagram:post": {
      "caption": {
        "body": "The new pre-security connector between Terminal 2 \u0026 Terminal 3 at SFO opens tomorrow to the public featuring our new photography exhibit, On Approach by Cris Benton. Benton, a retired UC Berkeley professor, uses a kite-lofted camera to create amazing aerial photographic documentation of the South Bay's salt ponds. Benton’s On Approach allows us to leave our earthly bonds and see the salt ponds from a fresh perspective—a portrait of ecological transformation and resilience.",
        "excerpt": "The new pre-security connector between Terminal 2 \u0026 Terminal 3 at SFO opens tomorrow to the public featuring our new photography exhibit, On Approach by Cris Benton."
      },
      "media_id": "21adb5760b2842f8ea19ff659696272a",
      "path": "media/posts/201508/11257761_499599496873374_1319919654_n_17843081776062499.jpg",
      "perceptual_hash": "p:af1ad0e5c1a02bde",
      "taken": 1441012680,
      "taken_at": "Aug 31, 2015, 9:18 AM"
    },
    "sfomuseum:placetype": "instagram",
    "wof:name": "The new pre-security connector between Terminal 2 \u0026 Terminal 3 at SFO opens tomorrow to the public featuring our new photography exhibit, On Approach by Cris Benton...",
    "wof:placetype": "custom",
    "wof:placetype_alt": [
      "instagram"
    ]
  },
  "geometry": {"coordinates":[-122.386166,37.616356],"type":"Point"}
}
