{
  "type": "Feature",
  "properties": {
    "instagram:post": {
      "caption": {
        "body": "The new pre-security connector between Terminal 2 \u0026 Terminal 3 at SFO opens tomorrow to the public featuring our new photography exhibit, On Approach by Cris Benton. Benton, a retired UC Berkeley professor, uses a kite-lofted camera to create amazing aerial photographic documentation of the South Bay's salt ponds. Benton’s On Approach allows us to leave our earthly bonds and see the salt ponds from a fresh perspective—a portrait of ecological transformation and resilience.",
        "excerpt": "The new pre-security connector between Terminal 2 \u0026 Terminal 3 at SFO opens tomorrow to the public featuring our new photography exhibit, On Approach by Cris Benton."
      },
      "location": "San Francisco International Airport (SFO)",
      "media_id": "21adb5760b2842f8ea19ff659696272a",
      "path": "photos/201508/21adb5760b2842f8ea19ff659696272a.jpg",
      "taken": 1441041507,
      "taken_at": "2015-08-31T17:18:27+00:00"
    },
    "sfomuseum:placetype": "instagram",
    "wof:name": "The new pre-security connector between Terminal 2 \u0026 Terminal 3 at SFO opens tomorrow to the public featuring our new photography exhibit, On Approach by Cris Benton...",
    "wof:placetype": "custom"
  },
  "geometry": {"coordinates":[-122.386166,37.616356],"type":"Point"}
}
