{
  "type": "Feature",
  "properties": {
    "date:cessation_lower": "2019-09-12",
    "date:cessation_upper": "2019-09-12",
    "date:inception_lower": "2019-09-12",
    "date:inception_upper": "2019-09-12",
    "instagram:post": {
      "caption": {
        "body": "Modern, mid-century entertaining called for contemporary and expressive dinnerware. In 1954, two California-based manufacturers introduced a selection of progressive earthenware lines. The quintessentially modern Starburst design was a transfer-printed pattern created by Mary C.L. Brown (1913–65) to decorate George James’ (1921–2003) futuristic line of Eclipse dinnerware for Franciscan. Around the same time, Metlox added the California Mobile series to their Poppytrail earthenware. Designed by Frank Irwin (1922–2002), California Mobile was a decal pattern applied to Metlox’ Freeform range of sculpturally squared plates and boomerang-shaped dishes. \"The Modern Consumer: Products and Style\" is on display, post-security, in Terminal 3. http://bit.ly/1950sConsumer",
        "excerpt": "Modern, mid-century entertaining called for contemporary and expressive dinnerware.",
        "hashtags": [
          "1950sConsumer",
          "1950s",
          "vintage",
          "50s",
          "midcentury",
          "dinnerware",
          "ceramics"
        ]
      },
      "media_id": "78464dfddc023855ce9900e76d4d942a",
      "path": "media/posts/201909/68908087_957526844583211_473288477148753109_n_18088712029079669.jpg",
      "perceptual_hash": "p:869bed78f48926c1",
      "taken": 1568304300,
      "taken_at": "Sep 12, 2019, 4:05 PM"
    },
    "sfomuseum:placetype": "instagram",
    "wof:name": "Modern, mid-century entertaining called for contemporary and expressive dinnerware...",
    "wof:placetype": "custom"
  },
  "geometry": {"coordinates":[-122.386166,37.616356],"type":"Point"}
}
