{
  "type": "Feature",
  "properties": {
    "date:cessation_lower": "2021-07-02",
    "date:cessation_upper": "2021-07-02",
    "date:inception_lower": "2021-07-02",
    "date:inception_upper": "2021-07-02",
    "instagram:post": {
      "caption": {
        "body": "Word of the day: phillumenist - a collector of matchbooks or matchboxes, \"lover of light.\" Matchbooks have long been a popular and inexpensive promotional item for companies to manufacture. Although their production has declined dramatically since a heyday in the 1940s-50s, their retro appeal is fueling a resurgence as an advertising item.   Have a happy and safe 4th of July weekend!",
        "excerpt": "Word of the day: phillumenist - a collector of matchbooks or matchboxes, \"lover of light.\"",
        "hashtags": [
          "avgeek",
          "matchbook",
          "graphicdesign",
          "phillumenist"
        ]
      },
      "media_id": "afb2066d7330991f4cb4402d8c92ca1c8ce5914e",
      "path": "media/posts/202107/209569186_110681141170992_1360684201798469152_n_17913125107851650.jpg",
      "perceptual_hash": "p:a63165643966d99b",
      "taken": 1625239320,
      "taken_at": "Jul 2, 2021, 3:22 PM"
    },
    "sfomuseum:placetype": "instagram",
    "wof:name": "Word of the day: phillumenist - a collector of matchbooks or matchboxes, \"lover of light.\"..",
    "wof:placetype": "custom"
  },
  "geometry": {"coordinates":[-122.386166,37.616356],"type":"Point"}
}
