{
  "type": "Feature",
  "properties": {
    "date:cessation_lower": "2019-02-22",
    "date:cessation_upper": "2019-02-22",
    "date:inception_lower": "2019-02-22",
    "date:inception_upper": "2019-02-22",
    "instagram:post": {
      "caption": {
        "body": "Santiago Jiménez, Sr. (1913–84), born in San Antonio, Texas, began to play the accordion at the age of eight. His father Patricio, born in Eagle Pass, Texas, also played the accordion. Jiménez, Sr., was known for his use of the two-row button accordion even after the still popular three-row instruments were introduced. During the 1930s, he and Narciso Martínez pioneered the use of the accordion in Texas-Mexican music. Jiménez, Sr. enjoyed a long recording career into the 1950s and ’60s. Flaco Jiménez and his brother, Santiago Jiménez, Jr., continued in their father’s footsteps—both continue to perform today. \"Down-Home Music: The Story of Arhoolie Records\" is on display, post-security, in Terminal 2. http://bit.ly/StoryofArhoolie",
        "excerpt": "Santiago Jiménez, Sr. (1913–84), born in San Antonio, Texas, began to play the accordion at the age of eight.",
        "hashtags": [
          "storyofarhoolie",
          "arhoolie",
          "arhoolierecords",
          "ChrisStrachwitz",
          "SantiagoJiménez",
          "accordion",
          "NarcisoMartínez",
          "TexasMexican",
          "Mexican",
          "MexicanAmerican",
          "texas",
          "music",
          "recordalbum"
        ]
      },
      "file_hash": "38b099cb09910a26391ca0b66fb8b539584cd54c6a7ddad672bfe1207dde930c",
      "media_id": "73bce77253b4826d5ab381aa8284d1d2f1f32648",
      "path": "media/other/B544EA93895F68548F983D6CBD8656B7_video_dashinit_18002687017166037.mp4",
      "taken": 1550828700,
      "taken_at": "Feb 22, 2019 9:45 am"
    },
    "sfomuseum:placetype": "instagram",
    "wof:name": "Santiago Jiménez, Sr. (1913–84), born in San Antonio, Texas, began to play the accordion at the age of eight...",
    "wof:placetype": "custom"
  },
  "geometry": {"coordinates":[-122.386166,37.616356],"type":"Point"}
}
