{
  "type": "Feature",
  "properties": {
    "date:cessation_lower": "2019-08-15",
    "date:cessation_upper": "2019-08-15",
    "date:inception_lower": "2019-08-15",
    "date:inception_upper": "2019-08-15",
    "instagram:post": {
      "caption": {
        "body": "Dung beetles, June bugs, chafers, and scarabs all belong to the beetle family Scarabaeidae. They all have lamellate antennae, which means the ends of their antennae can spread like fingers. Goliath beetles are the largest insects on Earth in terms of body mass. Some species, such as rose beetles and chafers, can be abundant pests in gardens, feeding on roots as larvae and on leaves and flowers as adults. Dung beetles and other detritivores are responsible for recycling nutrients and preventing animal waste from building up and breeding pest flies. In places where cows and other large mammals are not native, dung beetles have been purposely introduced to help control their waste.  See “The Intriguing World of Insects” on display, pre-security, in the International Terminal. http://bit.ly/IntriguingInsects",
        "excerpt": "Dung beetles, June bugs, chafers, and scarabs all belong to the beetle family Scarabaeidae.",
        "hashtags": [
          "IntriguingInsects",
          "WorldofInsects",
          "insects",
          "entomology",
          "Scarabaeidae",
          "dungbeetles",
          "beetles",
          "beetle"
        ]
      },
      "media_id": "c10f59d531685843f5f6d0955349163d",
      "path": "photos/201908/c10f59d531685843f5f6d0955349163d.jpg",
      "perceptual_hash": "p:9ea5c3daa5642c1b",
      "taken": 1565856300,
      "taken_at": "Aug 15, 2019, 8:05 AM"
    },
    "sfomuseum:placetype": "instagram",
    "wof:name": "Dung beetles, June bugs, chafers, and scarabs all belong to the beetle family Scarabaeidae...",
    "wof:placetype": "custom",
    "wof:placetype_alt": [
      "instagram"
    ]
  },
  "geometry": {"coordinates":[-122.386166,37.616356],"type":"Point"}
}
