{
  "type": "Feature",
  "properties": {
    "date:cessation_lower": "2019-09-18",
    "date:cessation_upper": "2019-09-18",
    "date:inception_lower": "2019-09-18",
    "date:inception_upper": "2019-09-18",
    "instagram:post": {
      "caption": {
        "body": "It's Ask a Curator day! What would you like to know about SFO Museum? Questions will be answered by Curators, Registrars, Conservators, and other museum staff. Reply below with your questions!",
        "excerpt": "It's Ask a Curator day!",
        "hashtags": [
          "AskACurator",
          "museum",
          "museumlife"
        ]
      },
      "media_id": "3675ad80090695827b8e3809f0ec0f00",
      "path": "photos/201909/3675ad80090695827b8e3809f0ec0f00.jpg",
      "perceptual_hash": "p:cbe0b64fa9d28516",
      "taken": 1568798580,
      "taken_at": "Sep 18, 2019, 9:23 AM"
    },
    "sfomuseum:placetype": "instagram",
    "wof:name": "It's Ask a Curator day!..",
    "wof:placetype": "custom"
  },
  "geometry": {"coordinates":[-122.386166,37.616356],"type":"Point"}
}
