{
  "type": "Feature",
  "properties": {
    "date:cessation_lower": "2012-07-10",
    "date:cessation_upper": "2012-07-10",
    "date:inception_lower": "2012-07-10",
    "date:inception_upper": "2012-07-10",
    "instagram:post": {
      "caption": {
        "body": "We're sad to see the motorcycles go, but here's a sneak peak for what comes next!",
        "excerpt": "We're sad to see the motorcycles go, but here's a sneak peak for what comes next!"
      },
      "media_id": "6de0bfd45674a9e83456674e3d44fe00",
      "path": "media/other/11176284_382196118632585_1795090672_n_17842257307062499.jpg",
      "perceptual_hash": "p:859666c2b08ae7bd",
      "taken": 1341916920,
      "taken_at": "Jul 10, 2012 10:42 am"
    },
    "sfomuseum:placetype": "instagram",
    "wof:name": "We're sad to see the motorcycles go, but here's a sneak peak for what comes next!..",
    "wof:placetype": "custom",
    "wof:placetype_alt": [
      "instagram"
    ]
  },
  "geometry": {"coordinates":[-122.386166,37.616356],"type":"Point"}
}
