{
  "type": "Feature",
  "properties": {
    "date:cessation_lower": "2017-03-09",
    "date:cessation_upper": "2017-03-09",
    "date:inception_lower": "2017-03-09",
    "date:inception_upper": "2017-03-09",
    "instagram:post": {
      "caption": {
        "body": "Under the wing of a Stearman 4D, these two aviatrixes, clad in aviator helmets and goggles, were part of an air show held at SFO on November 20, 1932. The show featured races, acrobatics, and stunts.  Image:  San Francisco Airport, aviatrixes, 1932. SFO Museum Collection. 2011.032.0121",
        "excerpt": "Under the wing of a Stearman 4D, these two aviatrixes, clad in aviator helmets and goggles, were part of an air show held at SFO on November 20, 1932.",
        "hashtags": [
          "WomenInAviation",
          "Aviatrix",
          "aviatrixes",
          "ThrowbackThursday",
          "TBT",
          "WomensHistoryMonth",
          "SFOHistory",
          "SFHistory",
          "avgeek",
          "aviationhistory"
        ]
      },
      "media_id": "c427a4dfa5b77b3c700c36b146e2a18f",
      "path": "media/posts/201703/17126477_1794726257513522_4606531245923368960_n_17874435034009701.jpg",
      "perceptual_hash": "p:d4687b0d952e13f4",
      "taken": 1489052700,
      "taken_at": "Mar 09, 2017 9:45 am"
    },
    "sfomuseum:placetype": "instagram",
    "wof:name": "Under the wing of a Stearman 4D, these two aviatrixes, clad in aviator helmets and goggles, were part of an air show held at SFO on November 20, 1932...",
    "wof:placetype": "custom",
    "wof:placetype_alt": [
      "instagram"
    ]
  },
  "geometry": {"coordinates":[-122.386166,37.616356],"type":"Point"}
}
