{
  "type": "Feature",
  "properties": {
    "instagram:post": {
      "caption": {
        "body": "Under the wing of a Stearman 4D, these two aviatrixes, clad in aviator helmets and goggles, were part of an air show held at SFO on November 20, 1932. The show featured races, acrobatics, and stunts.  Image:  San Francisco Airport, aviatrixes, 1932. SFO Museum Collection. 2011.032.0121",
        "hashtags": [
          "WomenInAviation", 
          "Aviatrix", 
          "aviatrixes", 
          "ThrowbackThursday", 
          "TBT", 
          "WomensHistoryMonth", 
          "SFOHistory", 
          "SFHistory", 
          "avgeek", 
          "aviationhistory"
        ]
      },
      "location": "San Francisco International Airport (SFO)",
      "media_id": "c427a4dfa5b77b3c700c36b146e2a18f",
      "path": "photos/201703/c427a4dfa5b77b3c700c36b146e2a18f.jpg",
      "taken": 1489081520,
      "taken_at": "2017-03-09T17:45:20+00:00"
    },
    "sfomuseum:placetype": "instagram",
    "wof:name": "Instagram message #%!d(string=c427a4dfa5b77b3c700c36b146e2a18f)",
    "wof:placetype": "custom"
  },
  "geometry": {"coordinates":[-122.386166,37.616356],"type":"Point"}
}
