{
  "type": "Feature",
  "properties": {
    "date:cessation_lower": "2018-11-16",
    "date:cessation_upper": "2018-11-16",
    "date:inception_lower": "2018-11-16",
    "date:inception_upper": "2018-11-16",
    "instagram:post": {
      "caption": {
        "body": "Advertised as the quietest widebody jet airliner in service, the Lockheed L-1011 TriStar took off on its maiden flight #onthisday in 1970. The TriStar trijet was the last commercial airliner produced by the Lockheed Corporation. An advanced feature of the L-1011 was the autoland system which fully automated the landing procedure and allowed the plane to land in unfavorable weather conditions. Only 250 L-1011 TriStar jets were produced and production halted in 1982. Did you ever fly on a Lockheed L-1011 TriStar?  Image: Pan American World Airways postcard, Lockheed L-1011-500 TriStar. Gift of the William Hough Collection. 2008.055.523",
        "excerpt": "Advertised as the quietest widebody jet airliner in service, the Lockheed L-1011 TriStar took off on its maiden flight #onthisday in 1970.",
        "hashtags": [
          "lockheed",
          "L1011",
          "tristar",
          "trijet",
          "autoland",
          "panamerican",
          "avgeek",
          "avationgeek",
          "aviation",
          "aviationhistory",
          "aviationgeeks",
          "plane",
          "avgeeks"
        ]
      },
      "media_id": "a03b00885ba17ec5565c59e81dff4415",
      "path": "media/other/46063028_252653822076626_6181616793162661142_n_17922439084246448.jpg",
      "perceptual_hash": "p:97e26a9d9463299c",
      "taken": 1542385620,
      "taken_at": "Nov 16, 2018 4:27 pm"
    },
    "sfomuseum:placetype": "instagram",
    "wof:name": "Advertised as the quietest widebody jet airliner in service, the Lockheed L-1011 TriStar took off on its maiden flight #onthisday in 1970...",
    "wof:placetype": "custom",
    "wof:placetype_alt": [
      "instagram"
    ]
  },
  "geometry": {"coordinates":[-122.386166,37.616356],"type":"Point"}
}
