{
  "type": "Feature",
  "properties": {
    "date:cessation_lower": "2013-12-27",
    "date:cessation_upper": "2013-12-27",
    "date:inception_lower": "2013-12-27",
    "date:inception_upper": "2013-12-27",
    "instagram:post": {
      "caption": {
        "hashtags": [
          "sfmaps",
          "maps"
        ]
      },
      "media_id": "14c63fe460609a5ac9fc1cacd8cf8345",
      "path": "media/posts/201312/11422018_402589873258272_1255341651_n_17842387831062499.jpg",
      "perceptual_hash": "p:c0c52e6c334fbe1a",
      "taken": 1388143320,
      "taken_at": "Dec 27, 2013, 11:22 AM"
    },
    "sfomuseum:placetype": "instagram",
    "wof:name": "..",
    "wof:placetype": "custom"
  },
  "geometry": {"coordinates":[-122.386166,37.616356],"type":"Point"}
}
