{
  "type": "Feature",
  "properties": {
    "instagram:post": {
      "caption": {
        "hashtags": [
          "sfmaps", 
          "maps"
        ]
      },
      "media_id": "14c63fe460609a5ac9fc1cacd8cf8345",
      "path": "photos/201312/14c63fe460609a5ac9fc1cacd8cf8345.jpg",
      "taken": 1388172138,
      "taken_at": "2013-12-27T19:22:18+00:00"
    },
    "sfomuseum:placetype": "instagram",
    "wof:name": "Instagram message #%!d(string=14c63fe460609a5ac9fc1cacd8cf8345)",
    "wof:placetype": "custom"
  },
  "geometry": {"coordinates":[-122.386166,37.616356],"type":"Point"}
}
