{
  "type": "Feature",
  "properties": {
    "date:cessation_lower": "2021-04-15",
    "date:cessation_upper": "2021-04-15",
    "date:inception_lower": "2021-04-15",
    "date:inception_upper": "2021-04-15",
    "instagram:post": {
      "caption": {
        "body": "In the United States, the 1970s were primarily a dormant period for instrumental rock until the end of the decade, when in 1979, Jon \u0026 The Nightriders unleashed a surf music revival with their self-titled 7” EP. Fronted by surf music historian John Blair (b. 1947), Jon \u0026 The Nightriders followed with Surf Beat ’80 and continued the group’s dedication to reviving the traditional emotion and tone of instrumental surf music. Somewhat surprisingly, surf music was welcomed amidst the punk, garage, and new wave movements in such diverse venues as the historic Whisky A Go-Go on Hollywood’s Sunset Strip, the Orange County amusement park Knott’s Berry Farm, and the Los Angeles punk-rock-haven Madame Wong’s West.  See more of “Surf’s Up! Instrumental Rock ‘n’ Roll,” online, where you can also find a link to the exhibition playlist on Spotify. Link in bio.",
        "excerpt": "In the United States, the 1970s were primarily a dormant period for instrumental rock until the end of the decade, when in 1979, Jon \u0026 The Nightriders unleashed a surf music revival with their self-titled 7” EP.",
        "hashtags": [
          "InstrumentalSurf",
          "SurfRock",
          "jonandthenightriders",
          "surf",
          "surfmusic"
        ]
      },
      "media_id": "edc2deafdfa98663525def37e4ead907aaf17758",
      "path": "media/posts/202104/174341280_359416318794712_6225673103366830673_n_17898337312878220.jpg",
      "perceptual_hash": "p:80205e3bc3bfc9b6",
      "taken": 1618503120,
      "taken_at": "Apr 15, 2021 4:12 pm"
    },
    "sfomuseum:placetype": "instagram",
    "wof:name": "In the United States, the 1970s were primarily a dormant period for instrumental rock until the end of the decade, when in 1979, Jon \u0026 The Nightriders unleashed a surf music revival with their self-titled 7” EP...",
    "wof:placetype": "custom",
    "wof:placetype_alt": [
      "instagram"
    ]
  },
  "geometry": {"coordinates":[-122.386166,37.616356],"type":"Point"}
}
