{
  "type": "Feature",
  "properties": {
    "date:cessation_lower": "2018-05-16",
    "date:cessation_upper": "2018-05-16",
    "date:inception_lower": "2018-05-16",
    "date:inception_upper": "2018-05-16",
    "instagram:post": {
      "caption": {
        "body": "\"Perspectives in Line and Space\" features works made by student artists from the seventh and eighth grades at Aptos Middle School. Students used their understanding of perspective drawing and shading techniques to produce a range of works, including landscapes, still lifes and, portraits.  See \"Perspectives in Line and Space\" in the arrivals level of Terminal 1. http://bit.ly/2wlpbqc",
        "excerpt": "\"Perspectives in Line and Space\" features works made by student artists from the seventh and eighth grades at Aptos Middle School.",
        "hashtags": [
          "studentart",
          "lines",
          "space",
          "aptos",
          "sfusd",
          "middleschool",
          "arteducation",
          "arted"
        ]
      },
      "media_id": "62fa86250e8ce08decab0ada3709773d",
      "path": "media/posts/201805/32343979_607229476320113_7239381073505812480_n_17937588238073476.jpg",
      "perceptual_hash": "p:a9af921af2f29611",
      "taken": 1526502420,
      "taken_at": "May 16, 2018, 8:27 PM"
    },
    "sfomuseum:placetype": "instagram",
    "wof:name": "\"Perspectives in Line and Space\" features works made by student artists from the seventh and eighth grades at Aptos Middle School...",
    "wof:placetype": "custom",
    "wof:placetype_alt": [
      "instagram"
    ]
  },
  "geometry": {"coordinates":[-122.386166,37.616356],"type":"Point"}
}
