{
  "type": "Feature",
  "properties": {
    "instagram:post": {
      "caption": {
        "body": "\"Perspectives in Line and Space\" features works made by student artists from the seventh and eighth grades at Aptos Middle School. Students used their understanding of perspective drawing and shading techniques to produce a range of works, including landscapes, still lifes and, portraits.  See \"Perspectives in Line and Space\" in the arrivals level of Terminal 1. http://bit.ly/2wlpbqc",
        "hashtags": [
          "studentart", 
          "lines", 
          "space", 
          "aptos", 
          "sfusd", 
          "middleschool", 
          "arteducation", 
          "arted"
        ]
      },
      "location": "San Francisco International Airport (SFO)",
      "media_id": "62fa86250e8ce08decab0ada3709773d",
      "path": "photos/201805/62fa86250e8ce08decab0ada3709773d.jpg",
      "taken": 1526531231,
      "taken_at": "2018-05-17T04:27:11+00:00"
    },
    "sfomuseum:placetype": "instagram",
    "wof:name": "Instagram message #%!d(string=62fa86250e8ce08decab0ada3709773d)",
    "wof:placetype": "custom"
  },
  "geometry": {"coordinates":[-122.386166,37.616356],"type":"Point"}
}
