{
  "type": "Feature",
  "properties": {
    "date:cessation_lower": "2015-10-19",
    "date:cessation_upper": "2015-10-19",
    "date:inception_lower": "2015-10-19",
    "date:inception_upper": "2015-10-19",
    "instagram:post": {
      "caption": {
        "hashtags": [
          "KirksMonsters",
          "KirkHammett",
          "MonsterMonday"
        ],
        "users": [
          "KirkHammett"
        ]
      },
      "media_id": "99d794811cbe186ee4c70704be93d036",
      "path": "media/posts/201510/12135355_441617479362979_1850025727_n_17844446257062499.jpg",
      "perceptual_hash": "p:c71c38e30f877338",
      "taken": 1445281860,
      "taken_at": "Oct 19, 2015, 7:11 PM"
    },
    "sfomuseum:placetype": "instagram",
    "wof:name": "..",
    "wof:placetype": "custom"
  },
  "geometry": {"coordinates":[-122.386166,37.616356],"type":"Point"}
}
