{
  "type": "Feature",
  "properties": {
    "instagram:post": {
      "caption": {
        "body": "Cleveland Chenier, the older brother of the \"King of Zydeco\" Clifton Chenier, played the rubboard in Clifton's zydeco band. The rubboard is a rhythm instrument made from a corrugated steel board. Although he was not the first to play a rubboard, his younger brother Clifton was the first to design this instrument to fit like a vest over his chest, a style which came to be emulated by other zydeco musicians who followed after him. Cleveland, considered the most innovative and accomplished rubboard player, beat and scraped the instrument with bottle openers—six on each hand—to create varied sounds. \"Down-Home Music: The Story of Arhoolie Records\" is on display, post-security, in Terminal 2. http://bit.ly/StoryofArhoolie",
        "excerpt": "Cleveland Chenier, the older brother of the \"King of Zydeco\" Clifton Chenier, played the rubboard in Clifton's zydeco band.",
        "hashtags": [
          "storyofarhoolie", 
          "arhoolie", 
          "arhoolierecords", 
          "ChrisStrachwitz", 
          "CliftonChenier", 
          "ClevelandChenier", 
          "rubboard", 
          "zydeco", 
          "music"
        ]
      },
      "media_id": "54738681b45624c7210bc416caa209d1",
      "path": "photos/201901/54738681b45624c7210bc416caa209d1.jpg",
      "taken": 1546563175,
      "taken_at": "2019-01-04T00:52:55+00:00"
    },
    "sfomuseum:placetype": "instagram",
    "wof:name": "Cleveland Chenier, the older brother of the \"King of Zydeco\" Clifton Chenier, played the rubboard in Clifton's zydeco band...",
    "wof:placetype": "custom"
  },
  "geometry": {"coordinates":[-122.386166,37.616356],"type":"Point"}
}
