{
  "type": "Feature",
  "properties": {
    "date:cessation_lower": "2017-06-20",
    "date:cessation_upper": "2017-06-20",
    "date:inception_lower": "2017-06-20",
    "date:inception_upper": "2017-06-20",
    "instagram:post": {
      "caption": {
        "body": "The Airport is hosting a ground-breaking ceremony today for a new hotel. In the 1960s, the airport's previous hotel featured 380 rooms and a night club favored by airline staff and locals called the Tiger A Go-Go. The San Francisco Airport Hilton was the first of the Hilton chain to be located at an airport. It was demolished in the 1990s to make way for the International Terminal. Do you remember the old airport hotel?  Image: San Francisco International Airport (SFO), aerial, Hilton Hotel, 1962. SFO Museum Collection. 2011.032.0740",
        "excerpt": "The Airport is hosting a ground-breaking ceremony today for a new hotel.",
        "hashtags": [
          "hilton",
          "grandhyatt",
          "hyatt",
          "hotels",
          "sfohistory",
          "avgeek",
          "aviationhistory",
          "sfhistory",
          "tigeragogo"
        ]
      },
      "media_id": "5aa352816a477d8577c025ad7bd3df3ac083613f",
      "path": "media/posts/201706/19367707_142087499682163_8382047630728888320_n_17858925760193930.jpg",
      "perceptual_hash": "p:81da6e819d7bc3e0",
      "taken": 1497947820,
      "taken_at": "Jun 20, 2017, 8:37 AM"
    },
    "sfomuseum:placetype": "instagram",
    "wof:name": "The Airport is hosting a ground-breaking ceremony today for a new hotel...",
    "wof:placetype": "custom"
  },
  "geometry": {"coordinates":[-122.386166,37.616356],"type":"Point"}
}
