{
  "type": "Feature",
  "properties": {
    "date:cessation_lower": "2019-06-14",
    "date:cessation_upper": "2019-06-14",
    "date:inception_lower": "2019-06-14",
    "date:inception_upper": "2019-06-14",
    "instagram:post": {
      "caption": {
        "body": "The cockchafer beetle (Melolontha melolontha Linnaeus, 1758) is a well-known plant pest in Europe, and one of the first beetle species named by Carl von Linné (a.k.a. Linnaeus), the Swedish biologist who created the binomial system for naming species. This papier-mâché model was made by the manufactory of French surgeon Dr. Louis Auzoux in 1881 as a teaching tool for entomology students. All of the internal and external organs are labeled with their proper names in a style he called anatomie clastique (“broken in pieces”). Auzoux created similar models of humans, horses, and other animals.  See “The Intriguing World of Insects” on display, pre-security, in the International Terminal. http://bit.ly/IntriguingInsects",
        "excerpt": "The cockchafer beetle (Melolontha melolontha Linnaeus, 1758) is a well-known plant pest in Europe, and one of the first beetle species named by Carl von Linné (a.k.a. Linnaeus), the Swedish biologist who created the binomial system for naming species.",
        "hashtags": [
          "IntriguingInsects",
          "WorldofInsects",
          "insects",
          "Entomology",
          "Berkeley",
          "UCBerkeley",
          "cockchaferbeetle",
          "beetle",
          "bugs",
          "Linnaeus"
        ]
      },
      "media_id": "292fb7efe8fd7638bd39d9d2aafe243e",
      "path": "photos/201906/292fb7efe8fd7638bd39d9d2aafe243e.jpg",
      "perceptual_hash": "p:e21196ce6938ce67",
      "taken": 1560446940,
      "taken_at": "Jun 13, 2019, 5:29 PM"
    },
    "sfomuseum:placetype": "instagram",
    "wof:name": "The cockchafer beetle (Melolontha melolontha Linnaeus, 1758) is a well-known plant pest in Europe, and one of the first beetle species named by Carl von Linné (a.k.a. Linnaeus), the Swedish biologist who created the binomial system for naming species...",
    "wof:placetype": "custom"
  },
  "geometry": {"coordinates":[-122.386166,37.616356],"type":"Point"}
}
