{
  "type": "Feature",
  "properties": {
    "date:cessation_lower": "2021-05-11",
    "date:cessation_upper": "2021-05-11",
    "date:inception_lower": "2021-05-11",
    "date:inception_upper": "2021-05-11",
    "instagram:post": {
      "caption": {
        "body": "United Air Lines highlighted many of their destinations in a series of advertisements placed in Time magazine in late 1944 and 1945. Naturally, we're partial to the San Francisco ad, but check them all out and don't miss the one celebrating the route's first 25 years!  📸: advertisements: United Air Lines, Time Magazine | San Francisco, Los Angeles, Seattle, Chicago, Boston, 25-years; 1945 Purchases 2017.112.026, .028, .030-033",
        "excerpt": "United Air Lines highlighted many of their destinations in a series of advertisements placed in Time magazine in late 1944 and 1945.",
        "hashtags": [
          "aviationhistory",
          "unitedairlines",
          "avgeek",
          "traveltuesday"
        ]
      },
      "media_id": "1a3d736c1eadecdec262993c760b6cf1b805f530",
      "path": "media/posts/202105/185446471_896060437914831_6389828444605137735_n_17900750725880286.jpg",
      "perceptual_hash": "p:fa1f94b0c9a762c8",
      "taken": 1620750000,
      "taken_at": "May 11, 2021, 4:20 PM"
    },
    "sfomuseum:placetype": "instagram",
    "wof:name": "United Air Lines highlighted many of their destinations in a series of advertisements placed in Time magazine in late 1944 and 1945...",
    "wof:placetype": "custom"
  },
  "geometry": {"coordinates":[-122.386166,37.616356],"type":"Point"}
}
