{
  "type": "Feature",
  "properties": {
    "date:cessation_lower": "2019-03-20",
    "date:cessation_upper": "2019-03-20",
    "date:inception_lower": "2019-03-20",
    "date:inception_upper": "2019-03-20",
    "instagram:post": {
      "caption": {
        "body": "Native Hawaiian surfing originated approximately one thousand years ago, imported from Tahiti by the Polynesian people who settled the Hawaiian Islands. He‘e nalu, which translates to “wave sliding,” is a culturally distinct form of surfing that grew into a popular pastime for men and women of all ages in Hawai‘i.  Photo courtesy of the Bernice Pauahi Bishop Museum. \"Reflections in Wood — Surfboards and Shapers\" is on display, pre-security, in the International Terminal! http://bit.ly/SurfboardsAndShapers",
        "excerpt": "Native Hawaiian surfing originated approximately one thousand years ago, imported from Tahiti by the Polynesian people who settled the Hawaiian Islands.",
        "hashtags": [
          "SurfboardsandShapers",
          "surfers",
          "shapers",
          "surf",
          "surfing",
          "surflife",
          "surfer",
          "hawaii"
        ]
      },
      "media_id": "9061a8ea727a3d4e71e8d6e6b696219a",
      "path": "media/posts/201903/54446588_168424617501558_5001620943974890188_n_18046312396019452.jpg",
      "perceptual_hash": "p:af95946ac069993e",
      "taken": 1553106660,
      "taken_at": "Mar 20, 2019, 6:31 PM"
    },
    "sfomuseum:placetype": "instagram",
    "wof:name": "Native Hawaiian surfing originated approximately one thousand years ago, imported from Tahiti by the Polynesian people who settled the Hawaiian Islands...",
    "wof:placetype": "custom",
    "wof:placetype_alt": [
      "instagram"
    ]
  },
  "geometry": {"coordinates":[-122.386166,37.616356],"type":"Point"}
}
