{
  "type": "Feature",
  "properties": {
    "instagram:post": {
      "caption": {
        "body": "Native Hawaiian surfing originated approximately one thousand years ago, imported from Tahiti by the Polynesian people who settled the Hawaiian Islands. He‘e nalu, which translates to “wave sliding,” is a culturally distinct form of surfing that grew into a popular pastime for men and women of all ages in Hawai‘i.  Photo courtesy of the Bernice Pauahi Bishop Museum. \"Reflections in Wood — Surfboards and Shapers\" is on display, pre-security, in the International Terminal! http://bit.ly/SurfboardsAndShapers",
        "hashtags": [
          "SurfboardsandShapers", 
          "surfers", 
          "shapers", 
          "surf", 
          "surfing", 
          "surflife", 
          "surfer", 
          "hawaii"
        ]
      },
      "location": "San Francisco International Airport (SFO)",
      "media_id": "9061a8ea727a3d4e71e8d6e6b696219a",
      "path": "photos/201903/9061a8ea727a3d4e71e8d6e6b696219a.jpg",
      "taken": 1553135461,
      "taken_at": "2019-03-21T02:31:01+00:00"
    },
    "sfomuseum:placetype": "instagram",
    "wof:name": "Instagram message #%!d(string=9061a8ea727a3d4e71e8d6e6b696219a)",
    "wof:placetype": "custom"
  },
  "geometry": {"coordinates":[-122.386166,37.616356],"type":"Point"}
}
