{
  "type": "Feature",
  "properties": {
    "instagram:post": {
      "caption": {
        "body": "Nicholas Arioli’s CG animated short explores the significance of the term “life savings” through the experience of a naïve young boy who opens a lemonade stand to finance his dreams of space travel, an aspiration long-held by the filmmaker.  See \"Coin Operated\" by Nicholas Arioli, now playing in the Video Arts gallery, located pre-security in the International Terminal. ",
        "excerpt": "Nicholas Arioli’s CG animated short explores the significance of the term “life savings” through the experience of a naïve young boy who opens a lemonade stand to finance his dreams of space travel, an aspiration long-held by the filmmaker.",
        "hashtags": [
          "VideoArtsSFOM", 
          "video", 
          "film", 
          "animation", 
          "illustration", 
          "space", 
          "spacetravel", 
          "computergenerated", 
          "lemonadestand", 
          "lemonade", 
          "lifesavings"
        ]
      },
      "location": "SFO Museum",
      "media_id": "75c4756415707a584b4aea55cb203121",
      "path": "photos/201808/75c4756415707a584b4aea55cb203121.jpg",
      "taken": 1534205533,
      "taken_at": "2018-08-14T00:12:13+00:00"
    },
    "sfomuseum:placetype": "instagram",
    "wof:name": "Nicholas Arioli’s CG animated short explores the significance of the term “life savings” through the experience of a naïve young boy who opens a lemonade stand to finance his dreams of space travel, an aspiration long-held by the filmmaker...",
    "wof:placetype": "custom"
  },
  "geometry": {"coordinates":[-122.386166,37.616356],"type":"Point"}
}
