{
  "type": "Feature",
  "properties": {
    "instagram:post": {
      "caption": {
        "body": "#OnThisDay in 1959, the inaugural jetliner flight from SFO to New York departed. Operated by TWA (Trans World Airlines), this Boeing 707 flight officially launched SFO into the jet age. The speed of commercial jet aircraft enabled airlines to offer customers dramatically reduced flying times. It was the capacity and efficiency of the jets, however, that dramatically reduced per-passenger costs. This in turn spurred a wave of economy fare programs. Have you ever flown on a Boeing 707?  Image: San Francisco International Airport (SFO), Terminal Building and TWA (Trans World Airlines), Boeing 707, 1959. SFO Museum Collection. 2011.032.0526",
        "excerpt": "#OnThisDay in 1959, the inaugural jetliner flight from SFO to New York departed.",
        "hashtags": [
          "707", 
          "Boeing", 
          "avgeek", 
          "jetage", 
          "SFO", 
          "TWA", 
          "TransWorldAirlines"
        ]
      },
      "location": "San Francisco International Airport (SFO)",
      "media_id": "27a4090b9436fd3a10942ebc3b89d072",
      "path": "photos/201903/27a4090b9436fd3a10942ebc3b89d072.jpg",
      "taken": 1553121115,
      "taken_at": "2019-03-20T22:31:55+00:00"
    },
    "sfomuseum:placetype": "instagram",
    "wof:name": "#OnThisDay in 1959, the inaugural jetliner flight from SFO to New York departed...",
    "wof:placetype": "custom"
  },
  "geometry": {"coordinates":[-122.386166,37.616356],"type":"Point"}
}
