{
  "type": "Feature",
  "properties": {
    "instagram:post": {
      "caption": {
        "body": "This is your last week to check out our Typewriters exhibition! Have you ever wondered what Chinese typewriters look like? With over 2,000 different character slugs, the machine features d a large, sliding tray from which the typist could choose characters from. To operate, the typist positioned the tray and carriage along an x-y axis to select a type-slug, and depressed a button to retrieve, ink, and print.  Learn more about the typewriter in \"The Typewriter: An Innovation in Writing\" on display, post-security, in Terminal 2. http://bit.ly/Thetypewriter",
        "hashtags": [
          "thetypewriter", 
          "typewriter", 
          "typewriters", 
          "industrialdesign", 
          "QWERTY", 
          "keyboard", 
          "keyboards", 
          "design", 
          "innovation", 
          "type", 
          "oldschool", 
          "writer", 
          "writing", 
          "vintagetypewriter", 
          "vintage", 
          "analog", 
          "antique", 
          "oldtypewriters", 
          "typewritersofinstagram", 
          "chinesetypewriter"
        ]
      },
      "media_id": "f4810c8311732a677b08b4794f6483c6",
      "path": "photos/201801/f4810c8311732a677b08b4794f6483c6.jpg",
      "taken": 1516743372,
      "taken_at": "2018-01-23T21:36:12+00:00"
    },
    "sfomuseum:placetype": "instagram",
    "wof:name": "Instagram message #%!d(string=f4810c8311732a677b08b4794f6483c6)",
    "wof:placetype": "custom"
  },
  "geometry": {"coordinates":[-122.386166,37.616356],"type":"Point"}
}
