{
  "type": "Feature",
  "properties": {
    "instagram:post": {
      "caption": {
        "body": "The toad, or \"sapo\", is an important and commonly interpreted symbol in Mayan weaving. The sapo symbolizes fertility and life in Mayan culture and comes to life at the start of each rainy season, when fields planted with new crops are filled with toads mating and singing in the rain, calling for another successful harvest.  Learn more about \"Empowering Threads: Textiles of Jolom Mayaetik\" on display, pre-security, in the International Terminal. http://bit.ly/EmpoweringThreads",
        "excerpt": "The toad, or \"sapo\", is an important and commonly interpreted symbol in Mayan weaving.",
        "hashtags": [
          "EmpoweringThreads", 
          "mayantextiles", 
          "textile", 
          "textiles", 
          "mayan", 
          "mexico", 
          "mexican", 
          "mexicanhistory", 
          "mayanhistory", 
          "JolomMayaetik", 
          "weavers", 
          "weaving", 
          "mayanculture", 
          "handwoven", 
          "sewing", 
          "empoweringwomen", 
          "toad", 
          "sapo", 
          "patterns"
        ]
      },
      "media_id": "c9147fb6fddc0cd78fb34b38d6ed8148",
      "path": "photos/201803/c9147fb6fddc0cd78fb34b38d6ed8148.jpg",
      "taken": 1521763187,
      "taken_at": "2018-03-22T23:59:47+00:00"
    },
    "sfomuseum:placetype": "instagram",
    "wof:name": "The toad, or \"sapo\", is an important and commonly interpreted symbol in Mayan weaving...",
    "wof:placetype": "custom"
  },
  "geometry": {"coordinates":[-122.386166,37.616356],"type":"Point"}
}
