{
  "type": "Feature",
  "properties": {
    "instagram:post": {
      "caption": {
        "body": "Finishing up the installation of 'The Douglas DC-3: Legacy of an Airline Legend' at the #Aviation Museum."
      },
      "media_id": "e01f57ebbe16dd8504588872060dba91",
      "path": "photos/201305/e01f57ebbe16dd8504588872060dba91.jpg",
      "taken": 1367529535,
      "taken_at": "2013-05-02T21:18:55+00:00"
    },
    "sfomuseum:placetype": "instagram",
    "wof:name": "Instagram message #%!d(string=e01f57ebbe16dd8504588872060dba91)",
    "wof:placetype": "custom"
  },
  "geometry": {"coordinates":[-122.386166,37.616356],"type":"Point"}
}
