{
  "type": "Feature",
  "properties": {
    "instagram:post": {
      "caption": {
        "body": "We are so sad to hear about the passing of the great Bay Area photorealist painter, Robert Bechtle. \"San Francisco Nova\" shows Benton Avenue in San Francisco, one of the familiar local neighborhoods Bechtle frequently painted, and is part of @flySFO's public art collection. This fantastic artwork is one of many he painted of San Francisco, and is on display post-security in Terminal 3, Boarding Area E. Robert Bechtle was 88. Rest In Peace."
      },
      "media_id": "7175c126f8bc995f6c70cf33446c61f7",
      "path": "photos/202010/7175c126f8bc995f6c70cf33446c61f7.jpg",
      "taken": 1601676452,
      "taken_at": "2020-10-02T22:07:32+00:00"
    },
    "sfomuseum:placetype": "instagram",
    "wof:name": "Instagram message #%!d(string=7175c126f8bc995f6c70cf33446c61f7)",
    "wof:placetype": "custom"
  },
  "geometry": {"coordinates":[-122.386166,37.616356],"type":"Point"}
}
