{
  "type": "Feature",
  "properties": {
    "date:cessation_lower": "2022-02-01",
    "date:cessation_upper": "2022-02-01",
    "date:inception_lower": "2022-02-01",
    "date:inception_upper": "2022-02-01",
    "instagram:post": {
      "caption": {
        "body": "#Onthisday in 1964, Eastern Air Lines first introduced the Boeing 727. The aircraft was a medium range, intermediate-capacity jetliner that could serve regional airports with short runways. It featured a clean swept wing, a high horizontal stabilizer, and a unique tri-jet configuration, which was influenced by the Hawker Siddeley Trident. This design dictated that the horizontal stabilizer be placed well away from the middle engine, high on top of the vertical stabilizer.   The only tri-jet to be developed by Boeing, the 727 was the result of a request from Eastern Air Lines, United Air Lines, and American Airlines for a medium-range airliner with less capacity than both the Boeing 707 and Douglas DC-8 that could serve smaller regional airports with short runways. At the aft underbelly was a uniquely located passenger door and air stair that allowed passengers to exit from the back of the aircraft.",
        "excerpt": "#Onthisday in 1964, Eastern Air Lines first introduced the Boeing 727.",
        "hashtags": [
          "avgeek",
          "Boeing",
          "727",
          "Eastern"
        ]
      },
      "media_id": "fa87bb153e6ba3caa405cfcf0515d665938af91f",
      "path": "media/posts/202202/273024905_943352999718603_412889619112515343_n_17964101725545160.jpg",
      "perceptual_hash": "p:87d038aec7d16837",
      "taken": 1643732580,
      "taken_at": "Feb 1, 2022, 4:23 PM"
    },
    "sfomuseum:placetype": "instagram",
    "wof:name": "#Onthisday in 1964, Eastern Air Lines first introduced the Boeing 727...",
    "wof:placetype": "custom"
  },
  "geometry": {"coordinates":[-122.386166,37.616356],"type":"Point"}
}
