{
  "type": "Feature",
  "properties": {
    "instagram:post": {
      "caption": {
        "body": "During World War II, Pan American Airways moved their flying boat operations from Treasure Island to SFO's seaplane harbor. After the war, when land planes became widely used, Pan Am built new facilities here. This photo shows Pan Am's SFO base in 1959, with that of United Air Lines in the background. #ThrowbackThursday #PanAm #AvGeek #SFOHistory #AviationHistory  Pan Am base at SFO, 1959 SFO Museum Collection 1997.52.051.008 a"
      },
      "location": "San Francisco International Airport (SFO)",
      "media_id": "cc8524a5bf7564b297d3a9e5506ac3ff",
      "path": "photos/201701/cc8524a5bf7564b297d3a9e5506ac3ff.jpg",
      "taken": 1484248385,
      "taken_at": "2017-01-12T19:13:05+00:00"
    },
    "sfomuseum:placetype": "instagram",
    "wof:name": "Instagram message #%!d(string=cc8524a5bf7564b297d3a9e5506ac3ff)",
    "wof:placetype": "custom"
  },
  "geometry": {"coordinates":[-122.386166,37.616356],"type":"Point"}
}
