{
  "type": "Feature",
  "properties": {
    "date:cessation_lower": "2020-12-30",
    "date:cessation_upper": "2020-12-30",
    "date:inception_lower": "2020-12-30",
    "date:inception_upper": "2020-12-30",
    "instagram:post": {
      "caption": {
        "body": "#OnThisDay in 1934, the Martin M-130 took its first test flight in Baltimore, Maryland. Designed under chief engineer Lassiter C. Milburn and the largest commercial airplane when delivered in 1935, only three Martin M-130 flying boats were built. They were named \"Hawaii Clipper\", \"Philippine Clipper\", and \"China Clipper\". When the \"China Clipper\" inaugurated service to Asia, the name became synonymous in the public’s mind with all of Pan American’s Pacific flying boats. Its distinguishing characteristics were sleek lines and the stabilizing seawings, or “sponsons,” at the waterline braced by cross struts.   Image: Pan American Airways, Martin M-130 “Hawaii Clipper, \"1934. Gift of the Captain John B. Russell Family. 2012.149.0913",
        "excerpt": "#OnThisDay in 1934, the Martin M-130 took its first test flight in Baltimore, Maryland.",
        "hashtags": [
          "avgeek",
          "aviationhistory",
          "MuseumFromHome"
        ]
      },
      "media_id": "23e9d3d2380056200d6f76da99d5ba2b55b06159",
      "path": "media/posts/202012/133968228_684693552203262_8478673929880660653_n_17947374025406680.jpg",
      "perceptual_hash": "p:8ab4f4435c78e32d",
      "taken": 1609332060,
      "taken_at": "Dec 30, 2020, 12:41 PM"
    },
    "sfomuseum:placetype": "instagram",
    "wof:name": "#OnThisDay in 1934, the Martin M-130 took its first test flight in Baltimore, Maryland...",
    "wof:placetype": "custom",
    "wof:placetype_alt": [
      "instagram"
    ]
  },
  "geometry": {"coordinates":[-122.386166,37.616356],"type":"Point"}
}
