{
  "type": "Feature",
  "properties": {
    "date:cessation_lower": "2018-04-02",
    "date:cessation_upper": "2018-04-02",
    "date:inception_lower": "2018-04-02",
    "date:inception_upper": "2018-04-02",
    "instagram:post": {
      "caption": {
        "body": "Produced while attending Chapman University's Dodge College of Film and Media Arts, Tom Teller's animated film features a lonely dishwashing robot who, through a chance encounter, becomes enlightened to the larger world beyond his four walls",
        "excerpt": "Produced while attending Chapman University's Dodge College of Film and Media Arts, Tom Teller's animated film features a lonely dishwashing robot who, through a chance encounter, becomes enlightened to the larger world beyond his four walls",
        "hashtags": [
          "robot",
          "video",
          "videoartsSFOM",
          "animation"
        ]
      },
      "file_hash": "86ebf4cf148f2405af4e5097b1dd274b507b604d7afcbbd6b9ea2c28b087425d",
      "media_id": "69975af5c166ae14ab11f7538baf1b90dc0adf75",
      "path": "media/other/82474A7E8ACC175611632C4B7DE4B287_video_dashinit_17910111766187902.mp4",
      "taken": 1522666680,
      "taken_at": "Apr 02, 2018 10:58 am"
    },
    "sfomuseum:placetype": "instagram",
    "wof:name": "Produced while attending Chapman University's Dodge College of Film and Media Arts, Tom Teller's animated film features a lonely dishwashing robot who, through a chance encounter, becomes enlightened to the larger world beyond his four walls..",
    "wof:placetype": "custom"
  },
  "geometry": {"coordinates":[-122.386166,37.616356],"type":"Point"}
}
