{
  "type": "Feature",
  "properties": {
    "date:cessation_lower": "2018-01-03",
    "date:cessation_upper": "2018-01-03",
    "date:inception_lower": "2018-01-03",
    "date:inception_upper": "2018-01-03",
    "instagram:post": {
      "caption": {
        "body": "“To be an artisan, to be a weaver signifies tradition, the culture. We wear our dress. I never have taken it off.…In many municipalities, they no longer wear their dress or know how it was. If it is lost, the tradition is not known anymore… It is very important to learn to weave because it signifies not losing our culture. Because if we do not do our weaving, the culture is lost. —Celia Sántiz Ruíz, Past President, Jolom Mayaetik  Learn more about \"Empowering Threads: Textiles of Jolom Mayaetik\" on display, pre-security, in the International Terminal. http://bit.ly/EmpoweringThreads",
        "excerpt": "“To be an artisan, to be a weaver signifies tradition, the culture.",
        "hashtags": [
          "EmpoweringThreads",
          "mayantextiles",
          "textile",
          "textiles",
          "mayan",
          "mexico",
          "mexican",
          "mexicanhistory",
          "mayanhistory",
          "JolomMayaetik",
          "weavers",
          "weaving",
          "blouses",
          "huipiles",
          "looms",
          "backstraploom",
          "mayanculture",
          "handwoven",
          "sewing",
          "cooperativa",
          "artesanaschiapanecas",
          "chiapas",
          "cojinesartesanales",
          "artesanias",
          "empoweringwomen"
        ]
      },
      "media_id": "3eebb38b1b6b8efc7dd87beebf75ef75",
      "path": "media/posts/201801/25036724_901456640027947_4201450563587538944_n_17889888508158733.jpg",
      "perceptual_hash": "p:e9138731a739ce58",
      "taken": 1514999880,
      "taken_at": "Jan 3, 2018, 5:18 PM"
    },
    "sfomuseum:placetype": "instagram",
    "wof:name": "“To be an artisan, to be a weaver signifies tradition, the culture...",
    "wof:placetype": "custom",
    "wof:placetype_alt": [
      "instagram"
    ]
  },
  "geometry": {"coordinates":[-122.386166,37.616356],"type":"Point"}
}
