{
  "type": "Feature",
  "properties": {
    "date:cessation_lower": "2018-08-29",
    "date:cessation_upper": "2018-08-29",
    "date:inception_lower": "2018-08-29",
    "date:inception_upper": "2018-08-29",
    "instagram:post": {
      "caption": {
        "body": "Masterminded by advertising executive Mary Wells Lawrence and unveiled in 1965, Braniff’s revolutionary new identity shocked the airline industry. For “The End of the Plain Plane” campaign, designer Alexander Girard (1907–1993) introduced a vivid color pallet, while Italian-born fashion impresario Emilio Pucci (1914–1992) re-conceptualized the airline uniform. Pucci’s 1965 Gemini IV Collection was multi-layered for inflight quick-change combinations of suits, tunics, and culottes. Pucci then introduced this 1966 Supersonic Derby outfit. The harlequin-print nylon jersey, tights, and bowler hat have Central American instruments and pre-Columbian art motifs. Footwear designer Beth Levine (1914–2006) created the striped calfskin boots.  Image: Braniff International, Anne Karin Austreim Walker, 1968. Gift of Sandra C. A. Thomas, in memory of Anne Karin Walker. 2015.062.035",
        "excerpt": "Masterminded by advertising executive Mary Wells Lawrence and unveiled in 1965, Braniff’s revolutionary new identity shocked the airline industry.",
        "hashtags": [
          "avgeek",
          "aviationgeek",
          "aviation",
          "aviationhistory",
          "aviationlovers",
          "vintageaviation",
          "history",
          "aviationgeeks",
          "avgeeks",
          "braniff",
          "pucci",
          "emiliopucci",
          "fashion"
        ]
      },
      "media_id": "e88f1d077c2c502f4ad0e4cc2e0705a9",
      "path": "media/posts/201808/40304936_1905171246264173_4244180158128324608_n_17867763184274148.jpg",
      "perceptual_hash": "p:87d3fa763318e068",
      "taken": 1535560020,
      "taken_at": "Aug 29, 2018, 4:27 PM"
    },
    "sfomuseum:placetype": "instagram",
    "wof:name": "Masterminded by advertising executive Mary Wells Lawrence and unveiled in 1965, Braniff’s revolutionary new identity shocked the airline industry...",
    "wof:placetype": "custom"
  },
  "geometry": {"coordinates":[-122.386166,37.616356],"type":"Point"}
}
