{
  "type": "Feature",
  "properties": {
    "instagram:post": {
      "caption": {
        "body": "Coast Guard Air Station San Francisco was commissioned November 15, 1940, on the eve of World War II.  San Francisco Airport (SFO) provided 20.53 acres at the mouth of its new man-made seaplane harbor for the Air Station site. In exchange, the federal government dredged and maintained the harbor and its channel to the bay. With a hangar, barracks, and a ramp, the new station was dedicated on February 15, 1941.  The \"United States Coast Guard Air Station San Francisco: Honoring the Guardians of the Golden Gate 75th\" exhibition of photography is on display pre-security, in the Aviation Museum and Library in the International Terminal. The Aviation Museum and Library is open from Sunday through Friday, 10am to 4:30pm.  Northwest aerial view of the newly completed Coast Guard Air Station San Francisco  c. 1940  SFO Museum Collection Gift of United States Coast Guard, Air Station San Francisco 2014.114.019",
        "excerpt": "Coast Guard Air Station San Francisco was commissioned November 15, 1940, on the eve of World War II."
      },
      "location": "San Francisco International Airport (SFO)",
      "media_id": "2d9565adbd5c74bbe8e0605417d0d37a",
      "path": "photos/201512/2d9565adbd5c74bbe8e0605417d0d37a.jpg",
      "taken": 1450638228,
      "taken_at": "2015-12-20T19:03:48+00:00"
    },
    "sfomuseum:placetype": "instagram",
    "wof:name": "Coast Guard Air Station San Francisco was commissioned November 15, 1940, on the eve of World War II...",
    "wof:placetype": "custom"
  },
  "geometry": {"coordinates":[-122.386166,37.616356],"type":"Point"}
}
