{
  "type": "Feature",
  "properties": {
    "date:cessation_lower": "2016-01-22",
    "date:cessation_upper": "2016-01-22",
    "date:inception_lower": "2016-01-22",
    "date:inception_upper": "2016-01-22",
    "instagram:post": {
      "caption": {
        "body": "#Onthisday in 1970, the first scheduled Pan American World Airways Boeing 747 wide-body jet took off from New York’s John F. Kennedy International Airport at 1:52AM. At the time of production, the Boeing 747 could carry 360-450 passengers, depending on seat configurations. It was also twice as big as the previous Boeing generation and 80% larger than the Douglas DC-8-63, the largest commercial aircraft at the time.",
        "excerpt": "#Onthisday in 1970, the first scheduled Pan American World Airways Boeing 747 wide-body jet took off from New York’s John F. Kennedy International Airport at 1:52AM."
      },
      "media_id": "8dba105cbfaff34d49c090b15162cf78",
      "path": "media/posts/201601/12547443_494160480766571_733556143_n_17844066043099513.jpg",
      "perceptual_hash": "p:edd2da192ae46c0d",
      "taken": 1453456320,
      "taken_at": "Jan 22, 2016, 9:52 AM"
    },
    "sfomuseum:placetype": "instagram",
    "wof:name": "#Onthisday in 1970, the first scheduled Pan American World Airways Boeing 747 wide-body jet took off from New York’s John F. Kennedy International Airport at 1:52AM...",
    "wof:placetype": "custom"
  },
  "geometry": {"coordinates":[-122.386166,37.616356],"type":"Point"}
}
