{
  "type": "Feature",
  "properties": {
    "instagram:post": {
      "caption": {
        "body": "#Onthisday in 1970, the first scheduled Pan American World Airways Boeing 747 wide-body jet took off from New York’s John F. Kennedy International Airport at 1:52AM. At the time of production, the Boeing 747 could carry 360-450 passengers, depending on seat configurations. It was also twice as big as the previous Boeing generation and 80% larger than the Douglas DC-8-63, the largest commercial aircraft at the time."
      },
      "location": "San Francisco International Airport (SFO)",
      "media_id": "8dba105cbfaff34d49c090b15162cf78",
      "path": "photos/201601/8dba105cbfaff34d49c090b15162cf78.jpg",
      "taken": 1453485127,
      "taken_at": "2016-01-22T17:52:07+00:00"
    },
    "sfomuseum:placetype": "instagram",
    "wof:name": "Instagram message #%!d(string=8dba105cbfaff34d49c090b15162cf78)",
    "wof:placetype": "custom"
  },
  "geometry": {"coordinates":[-122.386166,37.616356],"type":"Point"}
}
