{
  "type": "Feature",
  "properties": {
    "date:cessation_lower": "2021-01-22",
    "date:cessation_upper": "2021-01-22",
    "date:inception_lower": "2021-01-22",
    "date:inception_upper": "2021-01-22",
    "instagram:post": {
      "caption": {
        "body": "During the summer of 1961, Dick Dale and his Del-Tones played dances known as “stomps” to thousands of teenagers in Southern California. As crowds grew at the cavernous Rendezvous Ballroom adjacent to Balboa Beach, Dale and his group played at increasingly higher volumes, which caused amplifiers to malfunction on a regular basis. With a trail of burned-out gear in his wake, Dale worked with Leo Fender (1909–91) to design modified speakers and increase the power output of the Showman amplifier. Dale also road-tested Fender’s new Reverb unit, which produced a watery, echo-like effect that became synonymous with surf music.  See “Surf’s Up! Instrumental Rock ‘n’ Roll” online at: https://bit.ly/InstrumentalSurf",
        "excerpt": "During the summer of 1961, Dick Dale and his Del-Tones played dances known as “stomps” to thousands of teenagers in Southern California.",
        "hashtags": [
          "InstrumentalSurf",
          "SurfRock",
          "InstrumentalRock",
          "DickDale"
        ]
      },
      "media_id": "ee38f0dcadb1647215c4200d3105eca71f29eb94",
      "path": "media/posts/202101/141226615_1139420499821628_7269786513461419040_n_17914663120575919.jpg",
      "perceptual_hash": "p:9508c993d7efca81",
      "taken": 1611315900,
      "taken_at": "Jan 22, 2021 11:45 am"
    },
    "sfomuseum:placetype": "instagram",
    "wof:name": "During the summer of 1961, Dick Dale and his Del-Tones played dances known as “stomps” to thousands of teenagers in Southern California...",
    "wof:placetype": "custom",
    "wof:placetype_alt": [
      "instagram"
    ]
  },
  "geometry": {"coordinates":[-122.386166,37.616356],"type":"Point"}
}
