{
  "type": "Feature",
  "properties": {
    "date:cessation_lower": "2018-10-15",
    "date:cessation_upper": "2018-10-15",
    "date:inception_lower": "2018-10-15",
    "date:inception_upper": "2018-10-15",
    "instagram:post": {
      "caption": {
        "body": "Interdisciplinary artist Maria Ferreira employs microscopy to reveal the geometric gardens, iridescent waves, and spiraling sand dunes of crystal structures invisible to the unaided eye, blurring the lines between the physical and the abstract.  See \"Lattice\" by Maria Ferreira, now playing in the Video Arts gallery, located pre-security in the International Terminal. http://bit.ly/2CljcmT",
        "excerpt": "Interdisciplinary artist Maria Ferreira employs microscopy to reveal the geometric gardens, iridescent waves, and spiraling sand dunes of crystal structures invisible to the unaided eye, blurring the lines between the physical and the abstract.",
        "hashtags": [
          "VideoArtsSFOM",
          "video",
          "film",
          "experimental",
          "microscopy",
          "geometric",
          "waves",
          "sanddunes",
          "crystal",
          "foodculture",
          "abstract",
          "microsope"
        ]
      },
      "file_hash": "8c48e75db69d7362df48cc8a874beeef236b8c2040948093b64f65fd6706ef50",
      "media_id": "1db2c2f68a5fa0030dc7a99ff5f9db743d2a0f62",
      "path": "media/other/6246531C85CFF76888911782A410DC86_video_dashinit_17974147474117232.mp4",
      "taken": 1539617280,
      "taken_at": "Oct 15, 2018 3:28 pm"
    },
    "sfomuseum:placetype": "instagram",
    "wof:name": "Interdisciplinary artist Maria Ferreira employs microscopy to reveal the geometric gardens, iridescent waves, and spiraling sand dunes of crystal structures invisible to the unaided eye, blurring the lines between the physical and the abstract...",
    "wof:placetype": "custom"
  },
  "geometry": {"coordinates":[-122.386166,37.616356],"type":"Point"}
}
