{
  "type": "Feature",
  "properties": {
    "date:cessation_lower": "2016-09-11",
    "date:cessation_upper": "2016-09-11",
    "date:inception_lower": "2016-09-11",
    "date:inception_upper": "2016-09-11",
    "instagram:post": {
      "caption": {
        "body": "Our online database contains brochures on the various topics that airlines have covered over the years. The collection includes route maps, information on tourist destinations and aircraft types, and other passenger information, including tongue-in-cheek brochures like this one from Pacific Southwest Airlines (PSA). See more on our website: http://bit.ly/2bA1v6B  Pacific Southwest Airlines (PSA) brochure, How to be a PSA passenger 1970 SFO Museum Collection Gift of the William Hough Collection 2007.011.285",
        "excerpt": "Our online database contains brochures on the various topics that airlines have covered over the years."
      },
      "media_id": "3b2ac709aab5ceea65a9939c38be0536",
      "path": "media/posts/201609/14156198_340755802934978_1168721241_n_17853401113078904.jpg",
      "perceptual_hash": "p:ff68c2c78734b098",
      "taken": 1473596160,
      "taken_at": "Sep 11, 2016, 12:16 PM"
    },
    "sfomuseum:placetype": "instagram",
    "wof:name": "Our online database contains brochures on the various topics that airlines have covered over the years...",
    "wof:placetype": "custom"
  },
  "geometry": {"coordinates":[-122.386166,37.616356],"type":"Point"}
}
