{
  "type": "Feature",
  "properties": {
    "date:cessation_lower": "2019-12-09",
    "date:cessation_upper": "2019-12-09",
    "date:inception_lower": "2019-12-09",
    "date:inception_upper": "2019-12-09",
    "instagram:post": {
      "caption": {
        "body": "NOW PLAYING: Berkeley-based filmmaker Kevin Gordon profiles Stockton, California’s Michael Chicago, the son of a Filipino immigrant mother and an alcoholic father, who escaped a difficult home life through Turfing, a form of street dancing with roots in Oakland.  See \"TURF Fever\" by Kevin Gordon, now playing in the Video Arts Room located pre-security in the International Terminal. http://bit.ly/2PysMHI",
        "excerpt": "NOW PLAYING: Berkeley-based filmmaker Kevin Gordon profiles Stockton, California’s Michael Chicago, the son of a Filipino immigrant mother and an alcoholic father, who escaped a difficult home life through Turfing, a form of street dancing with roots in Oakland.",
        "hashtags": [
          "VideoArtsSFOM",
          "film",
          "video",
          "Sub64Films",
          "MichaelChicago",
          "TurfDancing",
          "StocktonProud",
          "TURFinc",
          "Stockton",
          "California",
          "dance",
          "dancing"
        ]
      },
      "file_hash": "361e576bdfd0759b40b4bc4656b831b9efc86032bd0e8784a44bc5efb05f7938",
      "media_id": "7d6bb784f1f3969c5018156a6863795768ef2528",
      "path": "media/posts/201912/79705959_245587289743791_7289465837049706982_n_18034363156225230.mp4",
      "taken": 1575913320,
      "taken_at": "Dec 9, 2019, 5:42 PM"
    },
    "sfomuseum:placetype": "instagram",
    "wof:name": "NOW PLAYING: Berkeley-based filmmaker Kevin Gordon profiles Stockton, California’s Michael Chicago, the son of a Filipino immigrant mother and an alcoholic father, who escaped a difficult home life through Turfing, a form of street dancing with roots in Oakland...",
    "wof:placetype": "custom",
    "wof:placetype_alt": [
      "instagram"
    ]
  },
  "geometry": {"coordinates":[-122.386166,37.616356],"type":"Point"}
}
