{
  "type": "Feature",
  "properties": {
    "date:cessation_lower": "2020-08-12",
    "date:cessation_upper": "2020-08-12",
    "date:inception_lower": "2020-08-12",
    "date:inception_upper": "2020-08-12",
    "instagram:post": {
      "caption": {
        "body": "What did it take to mount and install the thirty-two lengths of wallpaper that make up the complete set of Zuber’s “Les Vues d’Amérique du Nord (Views of North America)”? A lot! Check out this video that shows the work by wallpaper installation specialists and SFO Museum staff in the paper mounting, review, and exhibition installation.  The first edition of Views of North America was offered in 1834 and designed by Jean-Julien Deltil (1791–1863). The entire panoramic wallpaper requires 1,690 printing blocks, 223 colors, and thirty-two lengths totaling forty-nine feet.  “Zuber: The Art of French Scenic Wallpaper” is online at:http://bit.ly/ZuberScenicWallpaper. https://www.youtube.com/watch?v=XKA0zYj8P_s",
        "excerpt": "What did it take to mount and install the thirty-two lengths of wallpaper that make up the complete set of Zuber’s “Les Vues d’Amérique du Nord (Views of North America)”?",
        "hashtags": [
          "Zuber",
          "WallpaperWednesday",
          "MuseumFromHome"
        ]
      },
      "file_hash": "edc125c829d21a2b84e5170f1e6c885daa68477ea56e7384a4ec7c2bf3fbc756",
      "media_id": "309bf5c0a41b3b5e14499f3c01a6e97a606bd3d8",
      "path": "media/posts/202008/117645597_725970914914384_9187034441423527054_n_17854077488179715.mp4",
      "taken": 1597245480,
      "taken_at": "Aug 12, 2020, 3:18 PM"
    },
    "sfomuseum:placetype": "instagram",
    "wof:name": "What did it take to mount and install the thirty-two lengths of wallpaper that make up the complete set of Zuber’s “Les Vues d’Amérique du Nord (Views of North America)”?..",
    "wof:placetype": "custom",
    "wof:placetype_alt": [
      "instagram"
    ]
  },
  "geometry": {"coordinates":[-122.386166,37.616356],"type":"Point"}
}
