{
  "type": "Feature",
  "properties": {
    "date:cessation_lower": "2018-12-14",
    "date:cessation_upper": "2018-12-14",
    "date:inception_lower": "2018-12-14",
    "date:inception_upper": "2018-12-14",
    "instagram:post": {
      "caption": {
        "body": "Have you ever seen the cockpit of the Concorde? Operated by a crew of three, the captain, the first officer, and the flight engineer, the Concorde's cockpit was divided into three different sections designed for each operator. The Front Dash Panel Controls, operated by the pilot and the first officer, are shown in this photo. The flight engineers station behind them is not shown. Noteworthy in this photo is that the pilot in the first officers seat is also a captain with four stripes on his epaulettes. Starting in April we will also have a whole photography show on airline cockpits! Stay tuned!  Image:  Concorde promotional print, c. 1980. Gift of the William Hough Collection. 2016.097.007 . . .",
        "excerpt": "Have you ever seen the cockpit of the Concorde?",
        "hashtags": [
          "Concorde",
          "BritishAirways",
          "AirFrance",
          "cockpit",
          "captain",
          "firstofficer",
          "flightengineer",
          "flightdeck"
        ]
      },
      "location": "SFO Museum",
      "media_id": "4ddc8c4137c8d093b0c7a1339acd1d7d",
      "path": "photos/201812/4ddc8c4137c8d093b0c7a1339acd1d7d.jpg",
      "perceptual_hash": "p:f13e87639e8dd240",
      "taken": 1544723640,
      "taken_at": "Dec 13, 2018, 5:54 PM"
    },
    "sfomuseum:placetype": "instagram",
    "wof:name": "Have you ever seen the cockpit of the Concorde?..",
    "wof:placetype": "custom"
  },
  "geometry": {"coordinates":[-122.386166,37.616356],"type":"Point"}
}
