{
  "type": "Feature",
  "properties": {
    "date:cessation_lower": "2022-11-16",
    "date:cessation_upper": "2022-11-16",
    "date:inception_lower": "2022-11-16",
    "date:inception_upper": "2022-11-16",
    "instagram:post": {
      "caption": {
        "body": "Many of Bradbury \u0026 Bradbury Art Wallpapers’ patterns are initially hand painted on acetate or by cutting a stencil. For every pattern created, a separate stencil or silkscreen must be prepared for each different color. Silkscreens require a coating of photo-sensitive emulsion, essentially creating a large piece of film. The screen and artwork are sandwiched in a large vacuum frame and exposed to light. Areas exposed to the light become impervious; the other areas are washed away. Paint is forced through the stencil using a plastic-bladed squeegee. The printer must skip every other repeat to prevent the silkscreen frame from falling in wet ink. Each screen lays down one color at a time. St. James, which has seventeen colors, requires seventeen different prints with seventeen separate screens, each of which must perfectly align with the next one. Printing tables are ninety feet long and hold six rolls of wallpaper. A complex pattern for an average size Victorian room can require over one thousand individual impressions!  Special thank you to Bradbury \u0026 Bradbury Art Wallpapers (@bradburywallpaper) for making this exhibition possible. “The Victorian Papered Wall” is on display pre-security in the International Terminal and online at: https://bit.ly/VictorianPaperedWall",
        "excerpt": "Many of Bradbury \u0026 Bradbury Art Wallpapers’ patterns are initially hand painted on acetate or by cutting a stencil.",
        "hashtags": [
          "VictorianPaperedWall",
          "Wallpaper",
          "WallpaperWednesday",
          "design"
        ]
      },
      "media_id": "ea215e86419817a4df7b4c846885564bec018406",
      "path": "media/posts/202211/315545585_113704614888056_8597249610219752639_n_18262554544109405.jpg",
      "perceptual_hash": "p:bad66d88c415d23e",
      "taken": 1668606300,
      "taken_at": "Nov 16, 2022, 1:45 PM"
    },
    "sfomuseum:placetype": "instagram",
    "wof:name": "Many of Bradbury \u0026 Bradbury Art Wallpapers’ patterns are initially hand painted on acetate or by cutting a stencil...",
    "wof:placetype": "custom"
  },
  "geometry": {"coordinates":[-122.386166,37.616356],"type":"Point"}
}
