{
  "type": "Feature",
  "properties": {
    "date:cessation_lower": "2023-12-27",
    "date:cessation_upper": "2023-12-27",
    "date:inception_lower": "2023-12-27",
    "date:inception_upper": "2023-12-27",
    "instagram:post": {
      "caption": {
        "body": "In the bustling streets of La Paz and the sprawling suburbs of El Alto, Bolivia, nearly three thousand shoe shiners emerge each day in search of clients. What characterizes this group is the use of ski masks to obscure their identities, combat discrimination, and maintain their anonymity even among family and neighbors. The masks serve as both a unifying symbol and a form of resistance against societal exclusion, empowering them to confront prejudices related to their occupation. Their story, captured in Federico Estol’s series, \"Héroes del Brillo (Shine Heroes)\", is a poignant reminder of the daily challenges many face in their pursuit of dignity and respect. Their experience is not isolated but reflects broader global issues of labor discrimination and stigmatization.  See “Héroes del Brillo” by Federico Estol, on display, pre-security in Terminal 3.  https://www.sfomuseum.org/exhibitions/heroes-del-brillo",
        "excerpt": "In the bustling streets of La Paz and the sprawling suburbs of El Alto, Bolivia, nearly three thousand shoe shiners emerge each day in search of clients.",
        "hashtags": [
          "LaPaz",
          "ElAlto",
          "Bolvia",
          "HéroesdelBrillo",
          "A3HumanRightsDay",
          "HumanRights75"
        ],
        "users": [
          "federicoestol"
        ]
      },
      "media_id": "afefe7a8ed64a129cc81d7c74d22373080f62efd",
      "path": "media/posts/202312/413005153_840331784770419_1440464151766621363_n_18080172133378954.jpg",
      "perceptual_hash": "p:a84cd515baade255",
      "taken": 1703697540,
      "taken_at": "Dec 27, 2023 5:19 pm"
    },
    "sfomuseum:placetype": "instagram",
    "wof:name": "In the bustling streets of La Paz and the sprawling suburbs of El Alto, Bolivia, nearly three thousand shoe shiners emerge each day in search of clients...",
    "wof:placetype": "custom"
  },
  "geometry": {"coordinates":[-122.386166,37.616356],"type":"Point"}
}
