{
  "type": "Feature",
  "properties": {
    "date:cessation_lower": "2024-04-02",
    "date:cessation_upper": "2024-04-02",
    "date:inception_lower": "2024-04-02",
    "date:inception_upper": "2024-04-02",
    "instagram:post": {
      "caption": {
        "body": "Unknown Museum’s “resident curator,” Mickey McGowan developed a unique  interpretation practice that recalled high school science fair displays. He arranged toys and other common mid-century objects in chrome-plated aquariums from the same era; only a typewritten notecard offered a title or brief explanation. Other items were displayed in “specimen jars” with simple, descriptive labels.  A very special thank you to Mickey McGowan for making this exhibition possible. See “Recollections… from the Unknown Museum” on display, post-security, in Terminal 2. https://ow.ly/oRgR50R75QA",
        "excerpt": "Unknown Museum’s “resident curator,” Mickey McGowan developed a unique  interpretation practice that recalled high school science fair displays.",
        "hashtags": [
          "UnknownMuseum",
          "MickeyMcGowan",
          "BayArea",
          "BayAreaHistory"
        ]
      },
      "media_id": "2e9873d86fd7a4889873d48bfe58cede5598fd5d",
      "path": "media/posts/202404/435318824_456220536738658_8017409143323174313_n_18044049763673173.jpg",
      "perceptual_hash": "p:c747433f6a52a6a4",
      "taken": 1712072100,
      "taken_at": "Apr 02, 2024 3:35 pm"
    },
    "sfomuseum:placetype": "instagram",
    "wof:name": "Unknown Museum’s “resident curator,” Mickey McGowan developed a unique  interpretation practice that recalled high school science fair displays...",
    "wof:placetype": "custom"
  },
  "geometry": {"coordinates":[-122.386166,37.616356],"type":"Point"}
}
