{
  "type": "Feature",
  "properties": {
    "date:cessation_lower": "2018-08-02",
    "date:cessation_upper": "2018-08-02",
    "date:inception_lower": "2018-08-02",
    "date:inception_upper": "2018-08-02",
    "instagram:post": {
      "caption": {
        "body": "Émile Gallé (1846-1904) combined natural motifs with modern techniques and was one of Art Nouveau’s most significant figures. World renowned for his exquisite art glass, Gallé’s firm also produced ceramic and wooden items, often with the cat as his subject. Life-sized ceramic sculptures are his most famous feline creations and are simply referred to as Gallé cats. Made from faience, a tin-glazed earthenware, they feature colorful, whimsical designs and glass eyes colored by green sulfur. Gallé cats are prized for their magnetic smiles, and some include a locket framing a humorous picture of a dog.  See \"Caticons: The Cat in Art\" is on display, pre-security, in the International Terminal. http://bit.ly/Caticons",
        "excerpt": "Émile Gallé (1846-1904) combined natural motifs with modern techniques and was one of Art Nouveau’s most significant figures.",
        "hashtags": [
          "caticons",
          "art",
          "catsofinstagram",
          "cats",
          "meow",
          "mewseum",
          "cat",
          "artnouveau",
          "faience",
          "pottery"
        ]
      },
      "media_id": "e3709688d7826f0f6784573909e30058",
      "path": "photos/201808/e3709688d7826f0f6784573909e30058.jpg",
      "perceptual_hash": "p:f8944b99bc3c66c2",
      "taken": 1533249178,
      "taken_at": "2018-08-02T22:32:58+00:00"
    },
    "sfomuseum:placetype": "instagram",
    "wof:name": "Émile Gallé (1846-1904) combined natural motifs with modern techniques and was one of Art Nouveau’s most significant figures...",
    "wof:placetype": "custom"
  },
  "geometry": {"coordinates":[-122.386166,37.616356],"type":"Point"}
}
