{
  "type": "Feature",
  "properties": {
    "date:cessation_lower": "2016-07-15",
    "date:cessation_upper": "2016-07-15",
    "date:inception_lower": "2016-07-15",
    "date:inception_upper": "2016-07-15",
    "instagram:post": {
      "caption": {
        "body": "With airport planners projecting annual passenger traffic at SFO to reach 23 million, a series of design, engineering, and construction projects were proposed during the late 1960s and early ‘70s. In 1973, a comprehensive master plan to meet the demand was approved. A new master plan was undertaken in the 1990s to create the International Terminal Complex, which opened in 2000. It completed the circular configuration of SFO. Last year, 50 million passengers were served throughout our four terminals. #SFOHistory #ThrowbackThursday  Presentation of an SFO Master Plan 1968 SFO Museum Collection 2011.032.1692",
        "excerpt": "With airport planners projecting annual passenger traffic at SFO to reach 23 million, a series of design, engineering, and construction projects were proposed during the late 1960s and early ‘70s."
      },
      "location": "San Francisco International Airport (SFO)",
      "media_id": "0549bf7b79dbc193dc1fb203d3fafc1e",
      "path": "photos/201607/0549bf7b79dbc193dc1fb203d3fafc1e.jpg",
      "perceptual_hash": "p:8db31903d92bd339",
      "taken": 1468552823,
      "taken_at": "2016-07-15T03:20:23+00:00"
    },
    "sfomuseum:placetype": "instagram",
    "wof:name": "With airport planners projecting annual passenger traffic at SFO to reach 23 million, a series of design, engineering, and construction projects were proposed during the late 1960s and early ‘70s...",
    "wof:placetype": "custom"
  },
  "geometry": {"coordinates":[-122.386166,37.616356],"type":"Point"}
}
