{
  "type": "Feature",
  "properties": {
    "date:cessation_lower": "2020-08-31",
    "date:cessation_upper": "2020-08-31",
    "date:inception_lower": "2020-08-31",
    "date:inception_upper": "2020-08-31",
    "instagram:post": {
      "caption": {
        "body": "What was the museum up to while International Terminal A has been closed? We did some housekeeping! Cleaning “Salty Peanuts” by Mildred Howard took our crew of two over four hours to complete. In ordinary times, this type of cleaning takes place late at night, usually after midnight, when there are few people around.   International Terminal side A reopens tomorrow!",
        "excerpt": "What was the museum up to while International Terminal A has been closed?",
        "hashtags": [
          "MuseumFromHome",
          "MuseumMonday",
          "publicart"
        ]
      },
      "file_hash": "9859a1055fb80cf4f2337d89fad18e02a9b044dc1e341d4aac29a83f018c6f6f",
      "media_id": "6b11066329f1ba41584c5e7d632b378db0183143",
      "path": "media/other/A44AF5FA8EB74C37E5E055E6B319F9B7_video_dashinit_18129281824119100.mp4",
      "taken": 1598870820,
      "taken_at": "Aug 31, 2020 10:47 am"
    },
    "sfomuseum:placetype": "instagram",
    "wof:name": "What was the museum up to while International Terminal A has been closed?..",
    "wof:placetype": "custom"
  },
  "geometry": {"coordinates":[-122.386166,37.616356],"type":"Point"}
}
