{
  "type": "Feature",
  "properties": {
    "date:cessation_lower": "2018-09-26",
    "date:cessation_upper": "2018-09-26",
    "date:inception_lower": "2018-09-26",
    "date:inception_upper": "2018-09-26",
    "instagram:post": {
      "caption": {
        "body": "Cast your mind far, far back to the days before cell phones... When travelling internationally, how would you make a phone call? Perhaps you used a pre-paid phone card. United Airlines offered these calling cards to passengers through their mileage reward programs. Do you remember using phone cards?  United Airlines, Mileage Plus mileage program phone card 1997 SFO Museum Collection Gift of Kurt Bodden 2016.043.014 - United Airlines, Mileage Plus mileage program phone card 1997 SFO Museum Collection Gift of Kurt Bodden 2016.043.017",
        "excerpt": "Cast your mind far, far back to the days before cell phones..."
      },
      "media_id": "f34715f2a0cc713ed3452fcac7a09546",
      "path": "media/posts/201809/41345112_157865155147712_639002959834053988_n_17957873827188244.jpg",
      "perceptual_hash": "p:cf16c9216ade90b5",
      "taken": 1537952280,
      "taken_at": "Sep 26, 2018, 8:58 AM"
    },
    "sfomuseum:placetype": "instagram",
    "wof:name": "Cast your mind far, far back to the days before cell phones.....",
    "wof:placetype": "custom"
  },
  "geometry": {"coordinates":[-122.386166,37.616356],"type":"Point"}
}
