{
  "type": "Feature",
  "properties": {
    "date:cessation_lower": "2021-05-25",
    "date:cessation_upper": "2021-05-25",
    "date:inception_lower": "2021-05-25",
    "date:inception_upper": "2021-05-25",
    "instagram:post": {
      "caption": {
        "body": "Are you as excited as we are that the Sky Terrace @flysfo is reopening? Starting this week, hours will be Fridays, Saturdays, Sundays, and Mondays from 10am-6pm. Get a great view of the airfield and check out our exhibition on the 1954 Terminal!  As the airline industry soared to new heights in the late 1940s and 1950s, construction of a new terminal at San Francisco Airport began in 1951. Designed in the International Style, the seven-story building employed an innovative, dual-level layout that separated departures from arrivals. Dedicated roadways streamlined traffic to the terminal, and restaurants and amenities such as the Pancake Palace and International Room filled the bustling passenger areas.   Learn more about the 1954 Terminal online at: http://bit.ly/SFO1954 \u003c-- also via bio.  Or visit in person 😷 at Sky Terrace starting this Friday at 10am! It's free and will be open to the public.",
        "excerpt": "Are you as excited as we are that the Sky Terrace @flysfo is reopening?",
        "hashtags": [
          "SFO1954",
          "SFOHistory",
          "SkyTerrace",
          "airport",
          "avgeek"
        ]
      },
      "media_id": "4aee9d4552eeb1808c66258f810a2906e8785ab7",
      "path": "media/posts/202105/191738448_755202518488312_4921255407204104723_n_17907347239807574.jpg",
      "perceptual_hash": "p:c8acde4b53d29c15",
      "taken": 1621959960,
      "taken_at": "May 25, 2021, 4:26 PM"
    },
    "sfomuseum:placetype": "instagram",
    "wof:name": "Are you as excited as we are that the Sky Terrace @flysfo is reopening?..",
    "wof:placetype": "custom",
    "wof:placetype_alt": [
      "instagram"
    ]
  },
  "geometry": {"coordinates":[-122.386166,37.616356],"type":"Point"}
}
