{
  "type": "Feature",
  "properties": {
    "date:cessation_lower": "2018-11-13",
    "date:cessation_upper": "2018-11-13",
    "date:inception_lower": "2018-11-13",
    "date:inception_upper": "2018-11-13",
    "instagram:post": {
      "caption": {
        "body": "What is it like to be an immigrant? Filmmaker Borbála Tompa animates the fears, challenges, and aspirations of five immigrants in Budapest whose futures remain undetermined.  See \"Random Walks\" by Borbála Tompa, now playing, in the Video Arts Room located pre-security in the International Terminal. https://www.flysfo.com/museum/video-arts/random-walks",
        "excerpt": "What is it like to be an immigrant?",
        "hashtags": [
          "VideoArtsSFOM",
          "film",
          "video",
          "BorbálaTompa",
          "animation",
          "randomwalks",
          "immigration",
          "immigrants",
          "Budapest",
          "Hungary"
        ]
      },
      "file_hash": "0780c38b111c6d8d047f864f645d070131d7f5501e15cd06f71f184d273583d5",
      "media_id": "e2d4c4d2b3bb78d9a0917272f9ce681630db4400",
      "path": "media/posts/201811/45769455_494698431025380_5728288941814375597_n_17999868046019421.mp4",
      "taken": 1542115380,
      "taken_at": "Nov 13, 2018, 1:23 PM"
    },
    "sfomuseum:placetype": "instagram",
    "wof:name": "What is it like to be an immigrant?..",
    "wof:placetype": "custom",
    "wof:placetype_alt": [
      "instagram"
    ]
  },
  "geometry": {"coordinates":[-122.386166,37.616356],"type":"Point"}
}
