{
  "type": "Feature",
  "properties": {
    "date:cessation_lower": "2019-02-20",
    "date:cessation_upper": "2019-02-20",
    "date:inception_lower": "2019-02-20",
    "date:inception_upper": "2019-02-20",
    "instagram:post": {
      "caption": {
        "body": "This photo from 1959 shows a group of stewardesses in front of United Air Lines' training center in Cheyenne, Wyoming. They're wearing a new uniform, released that same year, designed by Raymond Loewy as part of his complete re-branding of United's identity for the jet age.  Image: United Air Lines stewardesses with Susan F. Robbins, 2nd from right, 1959.  Gift of Eric Barclay. 2016.028.006",
        "excerpt": "This photo from 1959 shows a group of stewardesses in front of United Air Lines' training center in Cheyenne, Wyoming.",
        "hashtags": [
          "avgeek",
          "unitedairlines",
          "unitedair",
          "united",
          "Cheyenne",
          "stewardess",
          "FA",
          "crewlife",
          "uniform"
        ]
      },
      "media_id": "045323d44e3f14ab0459a9b3220caa15",
      "path": "media/other/51232309_2384876711741014_5954640099336946629_n_17960077399242408.jpg",
      "perceptual_hash": "p:ebd4946bc03ccac3",
      "taken": 1550673720,
      "taken_at": "Feb 20, 2019 2:42 pm"
    },
    "sfomuseum:placetype": "instagram",
    "wof:name": "This photo from 1959 shows a group of stewardesses in front of United Air Lines' training center in Cheyenne, Wyoming...",
    "wof:placetype": "custom",
    "wof:placetype_alt": [
      "instagram"
    ]
  },
  "geometry": {"coordinates":[-122.386166,37.616356],"type":"Point"}
}
