{
  "type": "Feature",
  "properties": {
    "date:cessation_lower": "2017-01-16",
    "date:cessation_upper": "2017-01-16",
    "date:inception_lower": "2017-01-16",
    "date:inception_upper": "2017-01-16",
    "instagram:post": {
      "caption": {
        "body": "The Aviation Museum and Library is closed today to observe Dr. Martin Luther King, Jr. Day. All other exhibitions around the airport are open everyday, twenty-four hours a day. See what's currently on display: http://bit.ly/SFOMuseum",
        "excerpt": "The Aviation Museum and Library is closed today to observe Dr. Martin Luther King, Jr. Day."
      },
      "location": "San Francisco International Airport (SFO)",
      "media_id": "c7d5eca2c8c0d2331170301a2bb354a8",
      "path": "photos/201701/c7d5eca2c8c0d2331170301a2bb354a8.jpg",
      "perceptual_hash": "p:96c03ba7583b6d92",
      "taken": 1484575440,
      "taken_at": "Jan 16, 2017, 2:04 PM"
    },
    "sfomuseum:placetype": "instagram",
    "wof:name": "The Aviation Museum and Library is closed today to observe Dr. Martin Luther King, Jr. Day...",
    "wof:placetype": "custom"
  },
  "geometry": {"coordinates":[-122.386166,37.616356],"type":"Point"}
}
