{
  "type": "Feature",
  "properties": {
    "date:cessation_lower": "2015-10-14",
    "date:cessation_upper": "2015-10-14",
    "date:inception_lower": "2015-10-14",
    "date:inception_upper": "2015-10-14",
    "instagram:post": {
      "caption": {
        "body": "Our newest Student Art Show is from the San Francisco Waldorf High School. ‘Investigative Learning: Art, Nature, and Science’ was inspired by the integration of artistic expression across different academic subjects. Students explored a variety of disciplines ranging from agriculture and anatomy to geography and architecture. ‘Investigative Learning: Art, Nature, and Science’ is located, pre-security, in the Arrivals level of Terminal 1.",
        "excerpt": "Our newest Student Art Show is from the San Francisco Waldorf High School."
      },
      "media_id": "dfa492eefe29b420cfd0f668a2499fd4",
      "path": "media/posts/201510/12145141_451603191691798_990882180_n_17844223297062499.jpg",
      "perceptual_hash": "p:873c68cbb037c3ca",
      "taken": 1444814400,
      "taken_at": "Oct 14, 2015, 9:20 AM"
    },
    "sfomuseum:placetype": "instagram",
    "wof:name": "Our newest Student Art Show is from the San Francisco Waldorf High School...",
    "wof:placetype": "custom"
  },
  "geometry": {"coordinates":[-122.386166,37.616356],"type":"Point"}
}
