{
  "type": "Feature",
  "properties": {
    "instagram:post": {
      "caption": {
        "body": "Our newest Student Art Show is from the San Francisco Waldorf High School. ‘Investigative Learning: Art, Nature, and Science’ was inspired by the integration of artistic expression across different academic subjects. Students explored a variety of disciplines ranging from agriculture and anatomy to geography and architecture. ‘Investigative Learning: Art, Nature, and Science’ is located, pre-security, in the Arrivals level of Terminal 1."
      },
      "location": "San Francisco International Airport (SFO)",
      "media_id": "dfa492eefe29b420cfd0f668a2499fd4",
      "path": "photos/201510/dfa492eefe29b420cfd0f668a2499fd4.jpg",
      "taken": 1444843222,
      "taken_at": "2015-10-14T17:20:22+00:00"
    },
    "sfomuseum:placetype": "instagram",
    "wof:name": "Instagram message #%!d(string=dfa492eefe29b420cfd0f668a2499fd4)",
    "wof:placetype": "custom"
  },
  "geometry": {"coordinates":[-122.386166,37.616356],"type":"Point"}
}
