{
  "type": "Feature",
  "properties": {
    "date:cessation_lower": "2019-07-03",
    "date:cessation_upper": "2019-07-03",
    "date:inception_lower": "2019-07-03",
    "date:inception_upper": "2019-07-03",
    "instagram:post": {
      "caption": {
        "body": "This Renaissance Revival pedestal exhibits both veneering and marquetry. A veneer consists of a very fine sheet of wood applied to the surface of furniture. Marquetry entails cutting wood veneers, in various colors and grain patterns, into decorative designs and adhering them to a piece of furniture or decorative art object. Materials such as mother-of-pearl, ivory, tortoise shell, and fine metals might also be applied. “The Style of Display: Victorian Pedestals” is on display pre-security in the International Terminal. http://bit.ly/VictorianPedestals",
        "excerpt": "This Renaissance Revival pedestal exhibits both veneering and marquetry.",
        "hashtags": [
          "VictorianPedestals",
          "victorian",
          "pedestals",
          "victorianfurniture",
          "victoriana",
          "design",
          "decorativeart",
          "interiorstyle"
        ]
      },
      "media_id": "fcfd7b0bc59b3e1dd4519b19af00468a",
      "path": "photos/201907/fcfd7b0bc59b3e1dd4519b19af00468a.jpg",
      "perceptual_hash": "p:d36c667392d194b8",
      "taken": 1562167740,
      "taken_at": "Jul 3, 2019, 3:29 PM"
    },
    "sfomuseum:placetype": "instagram",
    "wof:name": "This Renaissance Revival pedestal exhibits both veneering and marquetry...",
    "wof:placetype": "custom"
  },
  "geometry": {"coordinates":[-122.386166,37.616356],"type":"Point"}
}
