{
  "type": "Feature",
  "properties": {
    "instagram:post": {
      "caption": {
        "body": "Victorian silver plate designers often combined elements of Gothic, Rococo, and Italian Renaissance styles with Greek and Egyptian Revival influences to create contemporary interpretations of historical styles. Items were decorated with many motifs including floral patterns, animals, ancient Egyptian figures, and Roman goddesses. In this fruit bowl by the Middletown Silver Company, two Renaissance putti figures sit atop a barge adorned with shells inset with smaller putti at the base.   See “Eclectic Taste: Victorian Silver Plate” online at https://bit.ly/VictorianSP",
        "hashtags": [
          "VictorianSilverPlate", 
          "silverplate", 
          "silver", 
          "victorian", 
          "MuseumFromHome"
        ]
      },
      "media_id": "9bbc5abf2fb8afdfc735d16e4133059d",
      "path": "photos/202009/9bbc5abf2fb8afdfc735d16e4133059d.jpg",
      "taken": 1600121559,
      "taken_at": "2020-09-14T22:12:39+00:00"
    },
    "sfomuseum:placetype": "instagram",
    "wof:name": "Instagram message #%!d(string=9bbc5abf2fb8afdfc735d16e4133059d)",
    "wof:placetype": "custom"
  },
  "geometry": {"coordinates":[-122.386166,37.616356],"type":"Point"}
}
