{
  "type": "Feature",
  "properties": {
    "date:cessation_lower": "2018-10-30",
    "date:cessation_upper": "2018-10-30",
    "date:inception_lower": "2018-10-30",
    "date:inception_upper": "2018-10-30",
    "instagram:post": {
      "caption": {
        "body": "The streets of San Francisco’s Mission District come alive in Ramin Talaie’s documentation of the city’s annual celebration of Día de Muertos (Day of the Dead), a public holiday observed throughout Mexico and by people of Mexican ancestry everywhere.  See \"Día De Los Muerto\" by Ramin Talaie, now playing in the Video Arts gallery, located pre-security in the International Terminal. https://www.flysfo.com/museum/video-arts/d%C3%ADa-de-los-muerto",
        "excerpt": "The streets of San Francisco’s Mission District come alive in Ramin Talaie’s documentation of the city’s annual celebration of Día de Muertos (Day of the Dead), a public holiday observed throughout Mexico and by people of Mexican ancestry everywhere.",
        "hashtags": [
          "VideoArtsSFOM",
          "video",
          "film",
          "documentary",
          "diadelosmuerto",
          "DíadeMuertos",
          "missiondistrict",
          "sanfrancisco",
          "mission",
          "mexican",
          "mexico",
          "mexicanamerican",
          "dayofthedead"
        ]
      },
      "location": "San Francisco International Airport (SFO)",
      "media_id": "eeb3b49278ded955eaf4e7f8824912ed",
      "path": "photos/201810/eeb3b49278ded955eaf4e7f8824912ed.jpg",
      "perceptual_hash": "p:95b9bf9832883a6c",
      "taken": 1540917776,
      "taken_at": "2018-10-30T16:42:56+00:00"
    },
    "sfomuseum:placetype": "instagram",
    "wof:name": "The streets of San Francisco’s Mission District come alive in Ramin Talaie’s documentation of the city’s annual celebration of Día de Muertos (Day of the Dead), a public holiday observed throughout Mexico and by people of Mexican ancestry everywhere...",
    "wof:placetype": "custom"
  },
  "geometry": {"coordinates":[-122.386166,37.616356],"type":"Point"}
}
