{
  "type": "Feature",
  "properties": {
    "date:cessation_lower": "2018-11-25",
    "date:cessation_upper": "2018-11-25",
    "date:inception_lower": "2018-11-25",
    "date:inception_upper": "2018-11-25",
    "instagram:post": {
      "caption": {
        "body": "#Onthisday in 1935, the first airfield expansion was completed at SFO extending Runway “C” from 1,900 to 3,000 feet.  The airport’s first reclamation project took two years and augmented the airfield with 38 additional acres. The extension enabled the development of a runway with an orientation that could take better advantage of the prevailing west-northwest winds.  Image: San Francisco Airport, aerial, 1937. SFO Museum Collection. 2011.032.0172 . . .",
        "excerpt": "#Onthisday in 1935, the first airfield expansion was completed at SFO extending Runway “C” from 1,900 to 3,000 feet.",
        "hashtags": [
          "avgeek",
          "SFOHistory",
          "SFO",
          "airport",
          "runways",
          "airfield",
          "SanFrancisco",
          "SanFranciscoHistory",
          "1930s"
        ]
      },
      "media_id": "5e75bdb64d0a4e80d81d6b5076c3f91d",
      "path": "media/posts/201811/44883115_502678650217254_2523058855672969076_n_17973311419155745.jpg",
      "perceptual_hash": "p:de1d6d4a4926a595",
      "taken": 1543151040,
      "taken_at": "Nov 25, 2018, 1:04 PM"
    },
    "sfomuseum:placetype": "instagram",
    "wof:name": "#Onthisday in 1935, the first airfield expansion was completed at SFO extending Runway “C” from 1,900 to 3,000 feet...",
    "wof:placetype": "custom",
    "wof:placetype_alt": [
      "instagram"
    ]
  },
  "geometry": {"coordinates":[-122.386166,37.616356],"type":"Point"}
}
