{
  "type": "Feature",
  "properties": {
    "instagram:post": {
      "caption": {
        "body": "On March 16, 1947, the Convair 240 made its maiden flight. The Convair 240 was the first postwar commercial airliner developed by Convair of San Diego. It was designed to be a pressurized, mid-range replacement for the DC-3 that was easy to service and turnover between flights. It featured a built-in, drop-down stairway for quick passenger loading, petal-style engine cowlings for rapid maintenance, and tricycle-configuration landing gear. It could carry forty passengers comfortably and had a range of up to 1,200 miles.  Introduced by American Airlines in 1948, 176 were produced for numerous airlines worldwide.  Image: American Airlines, Convair 240, c. 1948. SFO Museum Collection. 2008.128.006",
        "hashtags": [
          "convair", 
          "avgeek", 
          "museumfromhome"
        ]
      },
      "location": "SFO Museum",
      "media_id": "c386ea8d9bb2629606c62c1a02403775",
      "path": "photos/202003/c386ea8d9bb2629606c62c1a02403775.jpg",
      "taken": 1584551634,
      "taken_at": "2020-03-18T17:13:54+00:00"
    },
    "sfomuseum:placetype": "instagram",
    "wof:name": "Instagram message #%!d(string=c386ea8d9bb2629606c62c1a02403775)",
    "wof:placetype": "custom"
  },
  "geometry": {"coordinates":[-122.386166,37.616356],"type":"Point"}
}
