{
  "type": "Feature",
  "properties": {
    "date:cessation_lower": "2020-03-18",
    "date:cessation_upper": "2020-03-18",
    "date:inception_lower": "2020-03-18",
    "date:inception_upper": "2020-03-18",
    "instagram:post": {
      "caption": {
        "body": "On March 16, 1947, the Convair 240 made its maiden flight. The Convair 240 was the first postwar commercial airliner developed by Convair of San Diego. It was designed to be a pressurized, mid-range replacement for the DC-3 that was easy to service and turnover between flights. It featured a built-in, drop-down stairway for quick passenger loading, petal-style engine cowlings for rapid maintenance, and tricycle-configuration landing gear. It could carry forty passengers comfortably and had a range of up to 1,200 miles.  Introduced by American Airlines in 1948, 176 were produced for numerous airlines worldwide.  Image: American Airlines, Convair 240, c. 1948. SFO Museum Collection. 2008.128.006",
        "excerpt": "On March 16, 1947, the Convair 240 made its maiden flight.",
        "hashtags": [
          "convair",
          "avgeek",
          "museumfromhome"
        ]
      },
      "media_id": "c386ea8d9bb2629606c62c1a02403775",
      "path": "media/posts/202003/90044548_647384532729357_633885208199520981_n_18104400676125673.jpg",
      "perceptual_hash": "p:c07eabc09766e8b1",
      "taken": 1584522780,
      "taken_at": "Mar 18, 2020, 9:13 AM"
    },
    "sfomuseum:placetype": "instagram",
    "wof:name": "On March 16, 1947, the Convair 240 made its maiden flight...",
    "wof:placetype": "custom",
    "wof:placetype_alt": [
      "instagram"
    ]
  },
  "geometry": {"coordinates":[-122.386166,37.616356],"type":"Point"}
}
