{
  "type": "Feature",
  "properties": {
    "date:cessation_lower": "2015-09-14",
    "date:cessation_upper": "2015-09-14",
    "date:inception_lower": "2015-09-14",
    "date:inception_upper": "2015-09-14",
    "instagram:post": {
      "caption": {
        "hashtags": [
          "museummonday",
          "behindthescenes"
        ]
      },
      "file_hash": "809871b6bb82290d178b058a7b3b8524dbb6685d462084cc79f9b2e3d73b1ea6",
      "media_id": "85582da433466f0a85d6a2d357fe47c789f05fb1",
      "path": "media/posts/201509/11932184_840882912695781_2056836831_n_17843774899062499.mp4",
      "taken": 1442251140,
      "taken_at": "Sep 14, 2015, 5:19 PM"
    },
    "sfomuseum:placetype": "instagram",
    "wof:name": "..",
    "wof:placetype": "custom",
    "wof:placetype_alt": [
      "instagram"
    ]
  },
  "geometry": {"coordinates":[-122.386166,37.616356],"type":"Point"}
}
