{
  "type": "Feature",
  "properties": {
    "instagram:post": {
      "caption": {
        "body": "United Air Lines produced this 1957 flight attendant employee pamphlet that introduces potential applicants to the profession. \"You, as a United Air Lines stewardess, will have many of the same duties and responsibilities as if you were entertaining in your own home – making advance preparations, greeting guests and doing all possible to make them welcome.  Your “guests” will include a wide variety of interesting people, possibly a business man from Bombay, a military family moving from New York to Seattle, even your next-door-neighbor.  Visiting with passengers aloft, you will soon realize your position as a stewardess offers new opportunities to increase your knowledge of the world. As you say goodbye to your passengers when they reach their destinations, you will have a deep feeling of satisfaction and pride in your career as a stewardess.\" Image:  United Air Lines employee pamphlet, stewardess, 1957. Gift of Eric Barclay. 2016.028.003",
        "excerpt": "United Air Lines produced this 1957 flight attendant employee pamphlet that introduces potential applicants to the profession.",
        "hashtags": [
          "United", 
          "crewlife", 
          "paxex", 
          "FlightAttendant", 
          "crewlife", 
          "FA", 
          "fashioninflight", 
          "hostesses", 
          "FlightAttendantlife", 
          "FlightAttendanttraining", 
          "Flightcrew", 
          "avgeek", 
          "aviationhistory", 
          "WomenInAviation", 
          "Womenshistorymonth"
        ]
      },
      "media_id": "b66b5014a93d98cd84d409b14cde6279",
      "path": "photos/201703/b66b5014a93d98cd84d409b14cde6279.jpg",
      "taken": 1490237033,
      "taken_at": "2017-03-23T02:43:53+00:00"
    },
    "sfomuseum:placetype": "instagram",
    "wof:name": "United Air Lines produced this 1957 flight attendant employee pamphlet that introduces potential applicants to the profession...",
    "wof:placetype": "custom"
  },
  "geometry": {"coordinates":[-122.386166,37.616356],"type":"Point"}
}
