{
  "type": "Feature",
  "properties": {
    "date:cessation_lower": "2015-10-27",
    "date:cessation_upper": "2015-10-27",
    "date:inception_lower": "2015-10-27",
    "date:inception_upper": "2015-10-27",
    "instagram:post": {
      "caption": {
        "hashtags": [
          "KirksMonsters",
          "KirkHammett",
          "HappyHalloween"
        ],
        "users": [
          "KirkHammett"
        ]
      },
      "location": "San Francisco International Airport (SFO)",
      "media_id": "6c7f9d0a52298ca6ccbb8dc5b5a9db2d",
      "path": "photos/201510/6c7f9d0a52298ca6ccbb8dc5b5a9db2d.jpg",
      "perceptual_hash": "p:be7e45a151e6521a",
      "taken": 1445938980,
      "taken_at": "Oct 27, 2015, 9:43 AM"
    },
    "sfomuseum:placetype": "instagram",
    "wof:name": "..",
    "wof:placetype": "custom"
  },
  "geometry": {"coordinates":[-122.386166,37.616356],"type":"Point"}
}
