{
  "type": "Feature",
  "properties": {
    "instagram:post": {
      "caption": {
        "body": "Hughes Airwest, the airline with the slogan, \"the top banana in the west\", did not literally fly bananas, but this imaginative 1970s poster does feature a flying banana. Did you ever fly on Hughes Airwest?  See more banana-related Hughes Airwest objects in \"Catch our Style\", on display until the end of the month, pre-security, in the Aviation Museum and Library. The Aviation Museum and Library is located in the International Terminal and open daily, from 10am to 4:30pm, excluding holidays. http://bit.ly/CatchOurStyle  Hughes Airwest poster 1970s SFO Museum Collection Gift of Thomas G. Dragges 2001.135.074"
      },
      "location": "SFO Museum",
      "media_id": "cd8d58a7cb6d51c3e766de12d12743a2",
      "path": "photos/201605/cd8d58a7cb6d51c3e766de12d12743a2.jpg",
      "taken": 1463853949,
      "taken_at": "2016-05-21T18:05:49+00:00"
    },
    "sfomuseum:placetype": "instagram",
    "wof:name": "Instagram message #%!d(string=cd8d58a7cb6d51c3e766de12d12743a2)",
    "wof:placetype": "custom"
  },
  "geometry": {"coordinates":[-122.386166,37.616356],"type":"Point"}
}
