{
  "type": "Feature",
  "properties": {
    "date:cessation_lower": "2022-09-20",
    "date:cessation_upper": "2022-09-20",
    "date:inception_lower": "2022-09-20",
    "date:inception_upper": "2022-09-20",
    "instagram:post": {
      "caption": {
        "body": "Dorr Bothwell (1902–2000) was a Symbolist painter, printmaker, and art teacher who experimented with a variety of media and artistic ideas. Born Doris Hodgson Bothwell in San Francisco, she moved to San Diego as a young girl and took art lessons with her family’s neighbor, the painter and sculptor Anna Marie Valentien (1862–1947). In the early 1920s Bothwell returned to San Francisco and studied at the California School of Fine Arts (now the San Francisco Art Institute) with Rudolph Schaeffer (1886-1988). After her first exhibition entry was rejected in 1924, female colleagues suggested to Bothwell she not sign her full first name to avoid gender discrimination from male reviewers. Instead, Bothwell legally changed her first name to Dorr, a nickname from childhood that she preferred.  See “California Modernist Women: Groundbreaking Creativity” on display, post-security, in Harvey Milk Terminal 1 and online at: https://bit.ly/CaliforniaModernistWomen",
        "excerpt": "Dorr Bothwell (1902–2000) was a Symbolist painter, printmaker, and art teacher who experimented with a variety of media and artistic ideas.",
        "hashtags": [
          "CaliforniaModernistWomen",
          "DorrBothwell",
          "California",
          "womenartists",
          "modernism"
        ]
      },
      "media_id": "4228c16d0ed3262c72252cec1c01cd1483550c96",
      "path": "media/posts/202209/307881005_163870389576112_6105835032633337673_n_18183985825236803.jpg",
      "perceptual_hash": "p:f47ea388cd81837c",
      "taken": 1663682700,
      "taken_at": "Sep 20, 2022, 2:05 PM"
    },
    "sfomuseum:placetype": "instagram",
    "wof:name": "Dorr Bothwell (1902–2000) was a Symbolist painter, printmaker, and art teacher who experimented with a variety of media and artistic ideas...",
    "wof:placetype": "custom"
  },
  "geometry": {"coordinates":[-122.386166,37.616356],"type":"Point"}
}
