{
  "type": "Feature",
  "properties": {
    "date:cessation_lower": "2017-03-01",
    "date:cessation_upper": "2017-03-01",
    "date:inception_lower": "2017-03-01",
    "date:inception_upper": "2017-03-01",
    "instagram:post": {
      "caption": {
        "hashtags": [
          "A380",
          "Emirates?",
          "TravelTuesday"
        ]
      },
      "location": "San Francisco International Airport (SFO)",
      "media_id": "4fb7a3c08ec4b1917fe914a7f1bdffb2",
      "path": "photos/201702/4fb7a3c08ec4b1917fe914a7f1bdffb2.jpg",
      "perceptual_hash": "p:8a4ab4b5a57bca52",
      "taken": 1488338660,
      "taken_at": "2017-03-01T03:24:20+00:00"
    },
    "sfomuseum:placetype": "instagram",
    "wof:name": "..",
    "wof:placetype": "custom"
  },
  "geometry": {"coordinates":[-122.386166,37.616356],"type":"Point"}
}
