{
  "type": "Feature",
  "properties": {
    "instagram:post": {
      "caption": {
        "body": "Born in Bergamo, Italy in 1606, painter Viviano Codazzi reached Naples by the 1620s, where he demonstrated remarkable skill with \"quadratura\"—architectural perspective. Codazzi pursued an illusionistic realism, employing his skills of perspective, architectural rendering, and strong lighting to create a picture of a very real place, even if the viewpoint was impossible and the details inaccurate. Codazzi’s body of work largely consists of medium-size architectural paintings. This large, impressive picture of the Colosseum is characteristic of the painter’s mature work of the 1650s. The highly realized figure group is by Michelangelo Cerquozzi (1602–60), with whom Codazzi collaborated on many pictures.",
        "excerpt": "Born in Bergamo, Italy in 1606, painter Viviano Codazzi reached Naples by the 1620s, where he demonstrated remarkable skill with \"quadratura\"—architectural perspective.",
        "hashtags": [
          "Rome:", 
          "Piraneseum\",", 
          "AllRoadsRome", 
          "GrandTour", 
          "Italy", 
          "travel"
        ]
      },
      "location": "San Francisco International Airport (SFO)",
      "media_id": "624ff6cf5df946bb33b71067876f22c7",
      "path": "photos/201703/624ff6cf5df946bb33b71067876f22c7.jpg",
      "taken": 1488423679,
      "taken_at": "2017-03-02T03:01:19+00:00"
    },
    "sfomuseum:placetype": "instagram",
    "wof:name": "Born in Bergamo, Italy in 1606, painter Viviano Codazzi reached Naples by the 1620s, where he demonstrated remarkable skill with \"quadratura\"—architectural perspective...",
    "wof:placetype": "custom"
  },
  "geometry": {"coordinates":[-122.386166,37.616356],"type":"Point"}
}
