{
  "type": "Feature",
  "properties": {
    "date:cessation_lower": "2018-03-10",
    "date:cessation_upper": "2018-03-10",
    "date:inception_lower": "2018-03-10",
    "date:inception_upper": "2018-03-10",
    "instagram:post": {
      "caption": {
        "body": "For centuries, people have traveled the seas exploring new territories, engaging in trade, fishing, and whaling. Mariners spent long periods of time confined to a ship surrounded by the sea. In the days of sailing ships, a stint aboard might last weeks, months, or years. A seaman had to be a jack-of-all-trades in order to perform his duties. To pass the time during slow periods and calm seas, sailors adapted their varied skill sets to a number of handicrafts. Using their imagination, men transformed wood, bone, and rope into a variety of folk art.  Block with painted schooner \"Aurora\" courtesy of the collection of the San Francisco Maritime National Historical Park (@sfmaritimenps). See \"#AmericanFolkArt: An Enduring Legacy\", on display, pre-security, in the International Terminal. http://bit.ly/AmericanFolkArt",
        "excerpt": "For centuries, people have traveled the seas exploring new territories, engaging in trade, fishing, and whaling.",
        "hashtags": [
          "AmericanFolkArt",
          "folkart",
          "american",
          "history",
          "americana",
          "maritime"
        ]
      },
      "location": "San Francisco International Airport (SFO)",
      "media_id": "ec191fc665f9990d3a4bcb79ffd83f72",
      "path": "photos/201803/ec191fc665f9990d3a4bcb79ffd83f72.jpg",
      "perceptual_hash": "p:eb9794601a4f63f0",
      "taken": 1520628480,
      "taken_at": "Mar 9, 2018, 8:48 PM"
    },
    "sfomuseum:placetype": "instagram",
    "wof:name": "For centuries, people have traveled the seas exploring new territories, engaging in trade, fishing, and whaling...",
    "wof:placetype": "custom"
  },
  "geometry": {"coordinates":[-122.386166,37.616356],"type":"Point"}
}
