{
  "type": "Feature",
  "properties": {
    "date:cessation_lower": "2016-08-16",
    "date:cessation_upper": "2016-08-16",
    "date:inception_lower": "2016-08-16",
    "date:inception_upper": "2016-08-16",
    "instagram:post": {
      "caption": {
        "hashtags": [
          "avgeek"
        ],
        "users": [
          "Wired"
        ]
      },
      "media_id": "4557a4cacd07d774686f734afaeb9baf",
      "path": "media/other/13248778_317112245300828_1237654801_n_17850898819119595.jpg",
      "perceptual_hash": "p:9f9deee2a1c1b028",
      "taken": 1471338960,
      "taken_at": "Aug 16, 2016 9:16 am"
    },
    "sfomuseum:placetype": "instagram",
    "wof:name": "..",
    "wof:placetype": "custom",
    "wof:placetype_alt": [
      "instagram"
    ]
  },
  "geometry": {"coordinates":[-122.386166,37.616356],"type":"Point"}
}
