{
  "type": "Feature",
  "properties": {
    "instagram:post": {
      "caption": {
        "hashtags": [
          "WomeninAviation"
        ]
      },
      "location": "San Francisco International Airport (SFO)",
      "media_id": "1d29eb3e8a4cb313827d033bca075766",
      "path": "photos/201510/1d29eb3e8a4cb313827d033bca075766.jpg",
      "taken": 1445484482,
      "taken_at": "2015-10-22T03:28:02+00:00"
    },
    "sfomuseum:placetype": "instagram",
    "wof:name": "Instagram message #%!d(string=1d29eb3e8a4cb313827d033bca075766)",
    "wof:placetype": "custom"
  },
  "geometry": {"coordinates":[-122.386166,37.616356],"type":"Point"}
}
