{
  "type": "Feature",
  "properties": {
    "date:cessation_lower": "2023-08-16",
    "date:cessation_upper": "2023-08-16",
    "date:inception_lower": "2023-08-16",
    "date:inception_upper": "2023-08-16",
    "instagram:post": {
      "caption": {
        "body": "“But what does it mean to have a trans man in lesbian space? As I would have conversations with folks I would be a little confused because I’d think, “You led me to this door and now you don’t want me to open it? You don’t want me to step through it? You brought me right here and now I’m just supposed to stare at this shut door? That doesn’t make sense. Why don’t I crack it open a little bit?” So ultimately that’s what I did. It made complete sense to me that somebody might do a gender transition, and it moved forward in what would seem to me like a trajectory. What I didn’t quite realize is that it wasn’t that way for them. My sheer presence was disruptive, and I started to push back and challenge that. I’m so impressed with so many of them because we would duke it out. We would sit there for three hours and there would be anger and tears and confusion and laughter and love.” - Aidan, 52, Burien, WA, 2016  Representations of older transgender people are nearly absent from our culture and those that do exist are often one-dimensional. For over five years (2013–2018), photographer Jess T. Dugan and social worker Vanessa Fabbre traveled throughout the United States creating “To Survive on This Shore: Photographs and Interviews with Transgender and Gender Nonconforming Older Adults.”   Each portrait in “To Survive on this Shore: Photographs and Interviews with Transgender and Gender Nonconforming Older Adults” by Jess T. Dugan and Vanessa Fabbre includes a powerful interview with each of the featured individuals.   See “To Survive on this Shore: Photographs and Interviews with Transgender and Gender Nonconforming Older Adults” on display in the Ruth Kadish Gallery located in the post-security connector between Terminal 2 and Terminal 3 and online at: https://bit.ly/46z9t7N",
        "excerpt": "“But what does it mean to have a trans man in lesbian space?"
      },
      "media_id": "8235e5925a9f98443633d88f731afd3aa56869d3",
      "path": "media/posts/202308/366379470_750882920381973_8366356963505827183_n_17999339831007606.jpg",
      "perceptual_hash": "p:d87d210bda762783",
      "taken": 1692199920,
      "taken_at": "Aug 16, 2023 3:32 pm"
    },
    "sfomuseum:placetype": "instagram",
    "wof:name": "“But what does it mean to have a trans man in lesbian space?..",
    "wof:placetype": "custom"
  },
  "geometry": {"coordinates":[-122.386166,37.616356],"type":"Point"}
}
