{
  "type": "Feature",
  "properties": {
    "date:cessation_lower": "2017-07-04",
    "date:cessation_upper": "2017-07-04",
    "date:inception_lower": "2017-07-04",
    "date:inception_upper": "2017-07-04",
    "instagram:post": {
      "caption": {
        "body": "Straw, the byproduct of rice and other plant life, served as one of the most plentiful materials for crafting items in Japan. Some of the many items made from straw include clothing, shoes, hats, and containers. The oldest style of shoes still worn in Japan consists of sandals made of straw twisted into ropes and plaited to form the sandal’s sole, with the ropes acting as straps. Known as waraji, they were traditionally worn by peasants and probably introduced from China in the eighth century. In addition to sandals, straw boots are called fukagutsu. They are still worn today in snowy, mountainous regions of Japan. They differ stylistically in height and shape depending on the area where they are made and the amount of snowfall.  Shoes courtesy of the Mingei International Museum. See more shoes from all over the world in \"Stepping Out: Shoes in World Culture\" on display, pre-security, in the International Terminal. http://bit.ly/ShoesinCulture",
        "excerpt": "Straw, the byproduct of rice and other plant life, served as one of the most plentiful materials for crafting items in Japan.",
        "hashtags": [
          "ShoesinCulture",
          "shoes",
          "instashoes",
          "footwearfriday",
          "fridayfootwear",
          "japan",
          "strawshoes",
          "straw",
          "waraji",
          "fukagutsu",
          "snowshoes",
          "snow",
          "china",
          "sandals",
          "shoes",
          "shoestagram",
          "shoeswag",
          "shoesoftheday",
          "shoedesign",
          "instashoes",
          "shoefashion",
          "shoeslover"
        ]
      },
      "media_id": "1c58bb9c0c0e2641b8832543e8be087e",
      "path": "media/posts/201707/19624221_1727418210886918_5530963913471950848_n_17887308007063773.jpg",
      "perceptual_hash": "p:9b14c06ba7d41b6e",
      "taken": 1499194440,
      "taken_at": "Jul 04, 2017 6:54 pm"
    },
    "sfomuseum:placetype": "instagram",
    "wof:name": "Straw, the byproduct of rice and other plant life, served as one of the most plentiful materials for crafting items in Japan...",
    "wof:placetype": "custom",
    "wof:placetype_alt": [
      "instagram"
    ]
  },
  "geometry": {"coordinates":[-122.386166,37.616356],"type":"Point"}
}
