{
  "type": "Feature",
  "properties": {
    "date:cessation_lower": "2015-08-04",
    "date:cessation_upper": "2015-08-04",
    "date:inception_lower": "2015-08-04",
    "date:inception_upper": "2015-08-04",
    "instagram:post": {
      "caption": {
        "body": "For all the Kirk Hammett and #classicmonsters fans out there! We hope you enjoy this rocking photo collage of @kirkhammett's Classic Monster exhibition by @footefoto. ・・・",
        "excerpt": "For all the Kirk Hammett and #classicmonsters fans out there!",
        "hashtags": [
          "tbt",
          "kirkhammett",
          "metallica",
          "classicmonsters",
          "sfomuseum",
          "flysfo",
          "sanfrancisco"
        ],
        "users": [
          "sfomuseum"
        ]
      },
      "location": "San Francisco International Airport (SFO)",
      "media_id": "a69accb710911f87068b3cd5cd734883",
      "path": "photos/201508/a69accb710911f87068b3cd5cd734883.jpg",
      "perceptual_hash": "p:8ba75a1be298e748",
      "taken": 1438628940,
      "taken_at": "Aug 3, 2015, 7:09 PM"
    },
    "sfomuseum:placetype": "instagram",
    "wof:name": "For all the Kirk Hammett and #classicmonsters fans out there!..",
    "wof:placetype": "custom"
  },
  "geometry": {"coordinates":[-122.386166,37.616356],"type":"Point"}
}
