{
  "type": "Feature",
  "properties": {
    "date:cessation_lower": "2018-08-21",
    "date:cessation_upper": "2018-08-21",
    "date:inception_lower": "2018-08-21",
    "date:inception_upper": "2018-08-21",
    "instagram:post": {
      "caption": {
        "body": "With a deceptively simple concept, filmmakers Alex Gorosh and Wylie Overstreet invite passersby in Los Angeles to gaze upon what they’ve looked at all their lives but never seen, evoking a common response of wonder and revealing our shared humanity.  See \"A New View of the Moon\" by Alex Gorosh and Wylie Overstreet, now playing in the Video Arts gallery, located pre-security in the International Terminal. http://bit.ly/2BzNiEk",
        "excerpt": "With a deceptively simple concept, filmmakers Alex Gorosh and Wylie Overstreet invite passersby in Los Angeles to gaze upon what they’ve looked at all their lives but never seen, evoking a common response of wonder and revealing our shared humanity.",
        "hashtags": [
          "VideoArtsSFOM",
          "video",
          "film",
          "documentary",
          "moon",
          "lunar",
          "telescope",
          "street",
          "gaze",
          "LA",
          "losangeles"
        ]
      },
      "file_hash": "91e0df6c977b86f3ceed5cee2967c793cb0c35b67632d6c3c826b977cdab61cc",
      "media_id": "a15479e2130fbb10be152b1145102539d5645af6",
      "path": "media/posts/201808/39113178_532712350499681_4325394869290370146_n_17971758031039880.mp4",
      "taken": 1534857840,
      "taken_at": "Aug 21, 2018, 1:24 PM"
    },
    "sfomuseum:placetype": "instagram",
    "wof:name": "With a deceptively simple concept, filmmakers Alex Gorosh and Wylie Overstreet invite passersby in Los Angeles to gaze upon what they’ve looked at all their lives but never seen, evoking a common response of wonder and revealing our shared humanity...",
    "wof:placetype": "custom"
  },
  "geometry": {"coordinates":[-122.386166,37.616356],"type":"Point"}
}
