{
  "type": "Feature",
  "properties": {
    "instagram:post": {
      "caption": {
        "body": "No sign of her yet, but happy 115th birthday to Amelia Earhart!",
        "excerpt": "No sign of her yet, but happy 115th birthday to Amelia Earhart!"
      },
      "media_id": "d0c7e1cf49bcf6cc91892e5d944b5874",
      "path": "photos/201207/d0c7e1cf49bcf6cc91892e5d944b5874.jpg",
      "taken": 1343150061,
      "taken_at": "2012-07-24T17:14:21+00:00"
    },
    "sfomuseum:placetype": "instagram",
    "wof:name": "No sign of her yet, but happy 115th birthday to Amelia Earhart!..",
    "wof:placetype": "custom"
  },
  "geometry": {"coordinates":[-122.386166,37.616356],"type":"Point"}
}
