{
  "type": "Feature",
  "properties": {
    "instagram:post": {
      "caption": {
        "hashtags": [
          "TravelTuesday"
        ]
      },
      "location": "San Francisco International Airport (SFO)",
      "media_id": "41bc77695997262d1899bc0e1f4a855a",
      "path": "photos/201510/41bc77695997262d1899bc0e1f4a855a.jpg",
      "taken": 1445400124,
      "taken_at": "2015-10-21T04:02:04+00:00"
    },
    "sfomuseum:placetype": "instagram",
    "wof:name": "Instagram message #%!d(string=41bc77695997262d1899bc0e1f4a855a)",
    "wof:placetype": "custom"
  },
  "geometry": {"coordinates":[-122.386166,37.616356],"type":"Point"}
}
