{
  "type": "Feature",
  "properties": {
    "date:cessation_lower": "2023-06-07",
    "date:cessation_upper": "2023-06-07",
    "date:inception_lower": "2023-06-07",
    "date:inception_upper": "2023-06-07",
    "instagram:post": {
      "caption": {
        "body": "We are saddened to learn about the passing of artist Jim Melchert (1930-2023), a central figure in the Bay Area art community. Melchert began his career teaching ceramics at Carthage College in the 1950s. Originally trained in fine art, Melchert enrolled in a summer class taught by ceramicist Peter Voulkos, leading Melchert to develop an interest in abstract expressionism. Melchert moved to the Bay Area in the late 1950s and began teaching first at UC Berkeley then the San Francisco Art Institute. In 1976, Melchert became the director of the visual arts program at the National Endowment for the Arts in Washington, D.C., the first artist to be appointed to the position. Then in 1981, he was named director of the American Academy in Rome, where he cultivated an interest in ceramic tiles. His piece \"Riven/River,\" a fantastic example of his signature abstract expressionism style incorporated into ceramic tiles, is located the post-security connector between Harvey Milk Terminal 1 and Terminal 2. https://bit.ly/3IYl4mM",
        "excerpt": "We are saddened to learn about the passing of artist Jim Melchert (1930-2023), a central figure in the Bay Area art community.",
        "hashtags": [
          "JimMelchert"
        ],
        "users": [
          "sf_arts_commission"
        ]
      },
      "media_id": "3419fd8e428a1a184d35e3ad96943839705b4728",
      "path": "media/posts/202306/352666597_613607230717996_1209713451663491246_n_18215908312241207.jpg",
      "perceptual_hash": "p:96ef77036c38c1c4",
      "taken": 1686139800,
      "taken_at": "Jun 07, 2023 12:10 pm"
    },
    "sfomuseum:placetype": "instagram",
    "wof:name": "We are saddened to learn about the passing of artist Jim Melchert (1930-2023), a central figure in the Bay Area art community...",
    "wof:placetype": "custom",
    "wof:placetype_alt": [
      "instagram"
    ]
  },
  "geometry": {"coordinates":[-122.386166,37.616356],"type":"Point"}
}
