{
  "type": "Feature",
  "properties": {
    "date:cessation_lower": "2016-10-31",
    "date:cessation_upper": "2016-10-31",
    "date:inception_lower": "2016-10-31",
    "date:inception_upper": "2016-10-31",
    "instagram:post": {
      "caption": {
        "body": "#HappyHalloween! How are you celebrating this #spoopy holiday? Trying to commune with the spirits? Try a #Ouija Board! See more #Halloween themed shenanigans in \"The Mysterious Talking Board: #OuijaAndBeyond\", post-security, in Terminal 2. http://bit.ly/OuijaAndBeyond",
        "excerpt": "#HappyHalloween!"
      },
      "location": "San Francisco International Airport",
      "media_id": "18341db2ba32f6fec2529f3664efdcd7",
      "path": "photos/201610/18341db2ba32f6fec2529f3664efdcd7.jpg",
      "perceptual_hash": "p:ee3bf8f9850603a4",
      "taken": 1477906560,
      "taken_at": "Oct 31, 2016, 9:36 AM"
    },
    "sfomuseum:placetype": "instagram",
    "wof:name": "#HappyHalloween!..",
    "wof:placetype": "custom"
  },
  "geometry": {"coordinates":[-122.386166,37.616356],"type":"Point"}
}
