{
  "type": "Feature",
  "properties": {
    "instagram:post": {
      "caption": {
        "body": "#HappyHalloween! How are you celebrating this #spoopy holiday? Trying to commune with the spirits? Try a #Ouija Board! See more #Halloween themed shenanigans in \"The Mysterious Talking Board: #OuijaAndBeyond\", post-security, in Terminal 2. http://bit.ly/OuijaAndBeyond",
        "excerpt": "#HappyHalloween!"
      },
      "location": "San Francisco International Airport",
      "media_id": "18341db2ba32f6fec2529f3664efdcd7",
      "path": "photos/201610/18341db2ba32f6fec2529f3664efdcd7.jpg",
      "taken": 1477935413,
      "taken_at": "2016-10-31T17:36:53+00:00"
    },
    "sfomuseum:placetype": "instagram",
    "wof:name": "#HappyHalloween!..",
    "wof:placetype": "custom"
  },
  "geometry": {"coordinates":[-122.386166,37.616356],"type":"Point"}
}
