{
  "type": "Feature",
  "properties": {
    "date:cessation_lower": "2018-07-16",
    "date:cessation_upper": "2018-07-16",
    "date:inception_lower": "2018-07-16",
    "date:inception_upper": "2018-07-16",
    "instagram:post": {
      "caption": {
        "body": "Filmmaker Naghmeh Farzaneh, who left Iran for the United States during the “Arab Spring” of 2010–12, communicates the anxiety, alienation, and complex range of emotions shared with other immigrants in this beautifully composed, hand-drawn animation.  See \"Scent of Geranium\" by Naghmeh Farzaneh, now playing in the Video Arts gallery, located pre-security in the International Terminal. http://bit.ly/2uCDEd9",
        "excerpt": "Filmmaker Naghmeh Farzaneh, who left Iran for the United States during the “Arab Spring” of 2010–12, communicates the anxiety, alienation, and complex range of emotions shared with other immigrants in this beautifully composed, hand-drawn animation.",
        "hashtags": [
          "VideoArtsSFOM",
          "video",
          "film",
          "Tehran",
          "Iran",
          "arabspring",
          "animation",
          "immigration",
          "immigrant",
          "alienation",
          "anxiety",
          "ESL"
        ]
      },
      "file_hash": "c4e4825e9991f2775b6a735b06bcc0bca0b7c71bee7755b9df20767bfe1766f3",
      "media_id": "1e02fe623840c548052ad1f2bd58589f9212ec7f",
      "path": "media/other/CF467E3EF8D10FD010F78FDEC31ADD9E_video_dashinit_17890353382225899.mp4",
      "taken": 1531756980,
      "taken_at": "Jul 16, 2018 4:03 pm"
    },
    "sfomuseum:placetype": "instagram",
    "wof:name": "Filmmaker Naghmeh Farzaneh, who left Iran for the United States during the “Arab Spring” of 2010–12, communicates the anxiety, alienation, and complex range of emotions shared with other immigrants in this beautifully composed, hand-drawn animation...",
    "wof:placetype": "custom"
  },
  "geometry": {"coordinates":[-122.386166,37.616356],"type":"Point"}
}
