{
  "type": "Feature",
  "properties": {
    "date:cessation_lower": "2015-08-10",
    "date:cessation_upper": "2015-08-10",
    "date:inception_lower": "2015-08-10",
    "date:inception_upper": "2015-08-10",
    "instagram:post": {
      "caption": {
        "body": "What a beautiful collection of photos of our collection! Thanks for visiting!  #Repost by @every1ismyfriend ・・・",
        "excerpt": "What a beautiful collection of photos of our collection!",
        "hashtags": [
          "SFO",
          "sfo",
          "airports",
          "museums",
          "archives",
          "libraries"
        ]
      },
      "location": "San Francisco International Airport (SFO)",
      "media_id": "2f79707f493871653cddfbb520883360",
      "path": "photos/201508/2f79707f493871653cddfbb520883360.jpg",
      "perceptual_hash": "p:ee9bc4e49291e16c",
      "taken": 1439205900,
      "taken_at": "Aug 10, 2015, 11:25 AM"
    },
    "sfomuseum:placetype": "instagram",
    "wof:name": "What a beautiful collection of photos of our collection!..",
    "wof:placetype": "custom"
  },
  "geometry": {"coordinates":[-122.386166,37.616356],"type":"Point"}
}
