{
  "type": "Feature",
  "properties": {
    "instagram:post": {
      "caption": {
        "body": "What a beautiful collection of photos of our collection! Thanks for visiting!  #Repost by @every1ismyfriend ・・・",
        "hashtags": [
          "SFO", 
          "sfo", 
          "airports", 
          "museums", 
          "archives", 
          "libraries"
        ]
      },
      "location": "San Francisco International Airport (SFO)",
      "media_id": "2f79707f493871653cddfbb520883360",
      "path": "photos/201508/2f79707f493871653cddfbb520883360.jpg",
      "taken": 1439234722,
      "taken_at": "2015-08-10T19:25:22+00:00"
    },
    "sfomuseum:placetype": "instagram",
    "wof:name": "Instagram message #%!d(string=2f79707f493871653cddfbb520883360)",
    "wof:placetype": "custom"
  },
  "geometry": {"coordinates":[-122.386166,37.616356],"type":"Point"}
}
