{
  "type": "Feature",
  "properties": {
    "date:cessation_lower": "2024-07-16",
    "date:cessation_upper": "2024-07-16",
    "date:inception_lower": "2024-07-16",
    "date:inception_upper": "2024-07-16",
    "instagram:post": {
      "caption": {
        "body": "Designed in the early 1940s under the leadership of Lockheed’s chief engineer Clarence \"Kelly\" Johnson (1910–90), with direction from TWA’s (Transcontinental \u0026 Western Air) owner Howard Hughes (1905–76), the Lockheed L-049 Constellation was introduced as a commercial airliner shortly after World War II. It was an advanced, large-capacity propliner featuring a unique, aerodynamic, dolphin-shaped fuselage with a distinctive triple tail. Introduced in 1951, the TWA (Trans World Airlines) Lockheed L-1049 Super Constellation was a larger, long-range upgrade of the Constellation. The L-1049G Super Constellation was introduced four years later. It was designed for even longer-range flights and included wingtip tanks for extra fuel, radar equipment, and more powerful engines. Promoted by TWA as the “Super G,” the airline touted its technology, speed, exceptional comfort, and smooth flying characteristics. The airliner could accommodate between sixty-two and ninety-five passengers depending on the class configuration. During the mid-1950s, the Super G served as TWA’s premier long-distance transoceanic airliner on routes to Europe and beyond.   See “A Cut Above: Airplane Models from the SFO Museum Collection” on display, pre-security, in the Mayor Edwin M. Lee International Terminal Departures Hall and online at: https://bit.ly/CutAboveModels  📸: TWA (Trans World Airlines) Lockheed L-1049G Super Constellation model aircraft  1990s Gary Field scale 1:32 metal, paint Collection of SFO Museum Gift of the San Francisco Aeronautical Society 2018.127.007 a c  L2024.0401.002 a d  https://bit.ly/3zWfIXq",
        "excerpt": "Designed in the early 1940s under the leadership of Lockheed’s chief engineer Clarence \"Kelly\" Johnson (1910–90), with direction from TWA’s (Transcontinental \u0026 Western Air) owner Howard Hughes (1905–76), the Lockheed L-049 Constellation was introduced as a commercial airliner shortly after World War II.",
        "hashtags": [
          "CutAboveModels"
        ]
      },
      "media_id": "2d280a9fc65b6bedee0d439702dc7ebf186d6e6e",
      "path": "media/posts/202407/451404968_984842776985985_3398501638933538100_n_17856420333213400.jpg",
      "perceptual_hash": "p:abfa940708d43f63",
      "taken": 1721143980,
      "taken_at": "Jul 16, 2024 3:33 pm"
    },
    "sfomuseum:placetype": "instagram",
    "wof:name": "Designed in the early 1940s under the leadership of Lockheed’s chief engineer Clarence \"Kelly\" Johnson (1910–90), with direction from TWA’s (Transcontinental \u0026 Western Air) owner Howard Hughes (1905–76), the Lockheed L-049 Constellation was introduced as a commercial airliner shortly after World War II...",
    "wof:placetype": "custom"
  },
  "geometry": {"coordinates":[-122.386166,37.616356],"type":"Point"}
}
