{
  "type": "Feature",
  "properties": {
    "instagram:post": {
      "caption": {
        "hashtags": [
          "ILoveYouCA", 
          "owlpuns", 
          "birdpuns", 
          "naturalhistory"
        ]
      },
      "location": "San Francisco International Airport (SFO)",
      "media_id": "1c7ac5ad40b2d5c9f3662e0b178509a5",
      "path": "photos/201507/1c7ac5ad40b2d5c9f3662e0b178509a5.jpg",
      "taken": 1436831667,
      "taken_at": "2015-07-13T23:54:27+00:00"
    },
    "sfomuseum:placetype": "instagram",
    "wof:name": "..",
    "wof:placetype": "custom"
  },
  "geometry": {"coordinates":[-122.386166,37.616356],"type":"Point"}
}
