{
  "type": "Feature",
  "properties": {
    "instagram:post": {
      "caption": {
        "body": "Horse racing is one of the world's oldest sports. Its roots trace back to the Olympic Games in Greece, when chariot racing was introduced around 640 BCE. Modern flat-track racing gained popularity in England during the late 18th century with inauguration of The Derby Stakes (1780), and then in the United States with the Belmont Stakes (1867) and Kentucky Derby (1875). Counter games and trade stimulators capitalized on the popularity of horse racing. Patented in 1929, Good Luck Race Horse is a dial machine based on earlier wheel-mechanism trade stimulators from the 1890s. Good Luck Race Horse featured six horses and a six-to-one odds of a prize from the operator or merchant.  All objects are courtesy of Joe Welch American Antique Museum in San Bruno, California. \"The Automatic Age: Coin-Operated Machines\" is on display, pre-security, in the International Terminal. http://bit.ly/CoinOperated",
        "hashtags": [
          "coinoperated", 
          "TheAutomaticAge", 
          "coinop", 
          "vintage", 
          "antique", 
          "gamemachines", 
          "slotmachine", 
          "slotmachines", 
          "horseracing", 
          "goodluck"
        ]
      },
      "media_id": "cc6549b9104d7cb15df2a82cbc9858ab",
      "path": "photos/201801/cc6549b9104d7cb15df2a82cbc9858ab.jpg",
      "taken": 1517448606,
      "taken_at": "2018-02-01T01:30:06+00:00"
    },
    "sfomuseum:placetype": "instagram",
    "wof:name": "Instagram message #%!d(string=cc6549b9104d7cb15df2a82cbc9858ab)",
    "wof:placetype": "custom"
  },
  "geometry": {"coordinates":[-122.386166,37.616356],"type":"Point"}
}
