{
  "type": "Feature",
  "properties": {
    "instagram:post": {
      "caption": {
        "body": "One of the many types of promotional items given away by airlines are sewing kits. Do you have any from your flights?"
      },
      "location": "San Francisco International Airport (SFO)",
      "media_id": "79d9e2e88c72027812d3c28f51e09fad",
      "path": "photos/201604/79d9e2e88c72027812d3c28f51e09fad.jpg",
      "taken": 1461260251,
      "taken_at": "2016-04-21T17:37:31+00:00"
    },
    "sfomuseum:placetype": "instagram",
    "wof:name": "Instagram message #%!d(string=79d9e2e88c72027812d3c28f51e09fad)",
    "wof:placetype": "custom"
  },
  "geometry": {"coordinates":[-122.386166,37.616356],"type":"Point"}
}
