{
  "type": "Feature",
  "properties": {
    "date:cessation_lower": "2016-04-21",
    "date:cessation_upper": "2016-04-21",
    "date:inception_lower": "2016-04-21",
    "date:inception_upper": "2016-04-21",
    "instagram:post": {
      "caption": {
        "body": "One of the many types of promotional items given away by airlines are sewing kits. Do you have any from your flights?",
        "excerpt": "One of the many types of promotional items given away by airlines are sewing kits."
      },
      "media_id": "79d9e2e88c72027812d3c28f51e09fad",
      "path": "media/posts/201604/12445862_1734792453432444_843784761_n_17847563491077051.jpg",
      "perceptual_hash": "p:dfbcc843c0c02f37",
      "taken": 1461231420,
      "taken_at": "Apr 21, 2016, 9:37 AM"
    },
    "sfomuseum:placetype": "instagram",
    "wof:name": "One of the many types of promotional items given away by airlines are sewing kits...",
    "wof:placetype": "custom",
    "wof:placetype_alt": [
      "instagram"
    ]
  },
  "geometry": {"coordinates":[-122.386166,37.616356],"type":"Point"}
}
