{
  "type": "Feature",
  "properties": {
    "date:cessation_lower": "2013-10-29",
    "date:cessation_upper": "2013-10-29",
    "date:inception_lower": "2013-10-29",
    "date:inception_upper": "2013-10-29",
    "instagram:post": {
      "caption": {
        "hashtags": [
          "AirportPlay"
        ]
      },
      "media_id": "5833ec0901749a322db870150bec01e0",
      "path": "photos/201310/5833ec0901749a322db870150bec01e0.jpg",
      "perceptual_hash": "p:c1400fd73a9b79c5",
      "taken": 1383089762,
      "taken_at": "2013-10-29T23:36:02+00:00"
    },
    "sfomuseum:placetype": "instagram",
    "wof:name": "..",
    "wof:placetype": "custom"
  },
  "geometry": {"coordinates":[-122.386166,37.616356],"type":"Point"}
}
