{
  "type": "Feature",
  "properties": {
    "instagram:post": {
      "caption": {
        "body": "Today marks the 50th anniversary of the song \"San Francisco (Be Sure to Wear Flowers in Your Hair)\" by Scott McKenzie, which was released #onthisday in 1967. To celebrate The Summer of Love, SFO Museum is presenting \"It Happened in Monterey\", photographs by Elaine Mayes from The Monterey International Pop Music Festival in May 1967. The Monterey Pop Festival was organized to showcase rock music and soul music as art forms, bringing together acts from the United Kingdom and major regional music centers in the United States—Los Angeles, Memphis, New York City, and of course, San Francisco. Mayes managed to photograph nearly every performer, many of whom would profoundly affect the course of rock music and popular culture. Mayes’ photographs offer a remarkable level of intimacy with performers at this seminal event, remembered by Mayes as “among the best experiences of my life.” See \"It Happened in Monterey\" photographs by Elaine Mayes, post-security, in Terminal 3. http://bit.ly/ElaineMayes",
        "excerpt": "Today marks the 50th anniversary of the song \"San Francisco (Be Sure to Wear Flowers in Your Hair)\" by Scott McKenzie, which was released #onthisday in 1967.",
        "hashtags": [
          "ElaineMayes", 
          "airportart", 
          "publicart", 
          "summeroflove", 
          "rock", 
          "soul", 
          "SanFrancisco", 
          "Monterey", 
          "MontereyPop", 
          "JimiHendrix", 
          "ScottMcKenzie", 
          "FlowersinYourHair", 
          "TheMamasandthePapas", 
          "KeithMoon", 
          "theWho", 
          "OtisRedding", 
          "GraceSlick", 
          "JeffersonAirplane", 
          "PaulSimon", 
          "ArtGarfunkel", 
          "SimonandGarfunkel", 
          "PeteTownsend", 
          "LouRawls", 
          "JerryGarcia", 
          "TheGratefulDead", 
          "PaulKantner", 
          "JanisJoplin", 
          "RaviShankar", 
          "RogerDaltrey"
        ]
      },
      "media_id": "ea1ec845d56f7f6a59caeb3ac5db26e1",
      "path": "photos/201705/ea1ec845d56f7f6a59caeb3ac5db26e1.jpg",
      "taken": 1494743275,
      "taken_at": "2017-05-14T06:27:55+00:00"
    },
    "sfomuseum:placetype": "instagram",
    "wof:name": "Today marks the 50th anniversary of the song \"San Francisco (Be Sure to Wear Flowers in Your Hair)\" by Scott McKenzie, which was released #onthisday in 1967...",
    "wof:placetype": "custom"
  },
  "geometry": {"coordinates":[-122.386166,37.616356],"type":"Point"}
}
