{
  "type": "Feature",
  "properties": {
    "date:cessation_lower": "2014-11-26",
    "date:cessation_upper": "2014-11-26",
    "date:inception_lower": "2014-11-26",
    "date:inception_upper": "2014-11-26",
    "instagram:post": {
      "caption": {
        "hashtags": [
          "StudioGlass",
          "glass"
        ]
      },
      "media_id": "a7babd99f374e467dfff7f90187b8c2d",
      "path": "media/posts/201411/927429_1594110074144050_948706996_n_17842497673062499.jpg",
      "perceptual_hash": "p:bf17c069c6609b5a",
      "taken": 1417010040,
      "taken_at": "Nov 26, 2014, 1:54 PM"
    },
    "sfomuseum:placetype": "instagram",
    "wof:name": "..",
    "wof:placetype": "custom",
    "wof:placetype_alt": [
      "instagram"
    ]
  },
  "geometry": {"coordinates":[-122.386166,37.616356],"type":"Point"}
}
