{
  "type": "Feature",
  "properties": {
    "date:cessation_lower": "2016-02-01",
    "date:cessation_upper": "2016-02-01",
    "date:inception_lower": "2016-02-01",
    "date:inception_upper": "2016-02-01",
    "instagram:post": {
      "caption": {
        "hashtags": [
          "TheNationsGame",
          "SuperBowl50",
          "SB50"
        ]
      },
      "media_id": "e9cfab5c7372e40ad6fc22f9a7e016bc",
      "path": "media/posts/201602/12424363_143517192696876_2083978644_n_17844179521124597.jpg",
      "perceptual_hash": "p:80e7f6e0e034bd71",
      "taken": 1454354880,
      "taken_at": "Feb 1, 2016, 7:28 PM"
    },
    "sfomuseum:placetype": "instagram",
    "wof:name": "..",
    "wof:placetype": "custom"
  },
  "geometry": {"coordinates":[-122.386166,37.616356],"type":"Point"}
}
