{
  "type": "Feature",
  "properties": {
    "instagram:post": {
      "caption": {
        "body": "“Two miles a minute” is how Pan American advertised their services in 1931. At around 120 miles per hour, flying was still faster than any other mode of transportation at the time. Commercial planes now fly around 600 miles per hour. Have you ever flown on a trimotor aircraft?",
        "hashtags": [
          "panam", 
          "PAA", 
          "luggagelabel", 
          "trimotor", 
          "1930s"
        ]
      },
      "location": "San Francisco International Airport (SFO)",
      "media_id": "5a72d380bac5c1c7ae80a80f175fb99b",
      "path": "photos/201906/5a72d380bac5c1c7ae80a80f175fb99b.jpg",
      "taken": 1560391586,
      "taken_at": "2019-06-13T02:06:26+00:00"
    },
    "sfomuseum:placetype": "instagram",
    "wof:name": "Instagram message #%!d(string=5a72d380bac5c1c7ae80a80f175fb99b)",
    "wof:placetype": "custom"
  },
  "geometry": {"coordinates":[-122.386166,37.616356],"type":"Point"}
}
