{
  "type": "Feature",
  "properties": {
    "date:cessation_lower": "2019-06-12",
    "date:cessation_upper": "2019-06-12",
    "date:inception_lower": "2019-06-12",
    "date:inception_upper": "2019-06-12",
    "instagram:post": {
      "caption": {
        "body": "“Two miles a minute” is how Pan American advertised their services in 1931. At around 120 miles per hour, flying was still faster than any other mode of transportation at the time. Commercial planes now fly around 600 miles per hour. Have you ever flown on a trimotor aircraft?",
        "excerpt": "“Two miles a minute” is how Pan American advertised their services in 1931.",
        "hashtags": [
          "panam",
          "PAA",
          "luggagelabel",
          "trimotor",
          "1930s"
        ]
      },
      "media_id": "5a72d380bac5c1c7ae80a80f175fb99b",
      "path": "media/posts/201906/61446858_150872949409978_8920047130301618773_n_18030567268194948.jpg",
      "perceptual_hash": "p:af3fe04ed216b640",
      "taken": 1560362760,
      "taken_at": "Jun 12, 2019, 6:06 PM"
    },
    "sfomuseum:placetype": "instagram",
    "wof:name": "“Two miles a minute” is how Pan American advertised their services in 1931...",
    "wof:placetype": "custom"
  },
  "geometry": {"coordinates":[-122.386166,37.616356],"type":"Point"}
}
