{
  "type": "Feature",
  "properties": {
    "date:cessation_lower": "2017-02-23",
    "date:cessation_upper": "2017-02-23",
    "date:inception_lower": "2017-02-23",
    "date:inception_upper": "2017-02-23",
    "instagram:post": {
      "caption": {
        "body": "The Lockheed Electra 10, built and designed to compete with the Boeing 247 and the Douglas DC-2, made its first flight #onthisday in 1934. #Aviationhistory #Avgeek  Image: Braniff Airways postcard, Lockheed Electra, 1940s. Gift of Captain Jon Simmonds. 2015.057.340",
        "excerpt": "The Lockheed Electra 10, built and designed to compete with the Boeing 247 and the Douglas DC-2, made its first flight #onthisday in 1934."
      },
      "location": "SFO Museum",
      "media_id": "f5eea8f11796894e84baa22c6616d848",
      "path": "photos/201702/f5eea8f11796894e84baa22c6616d848.jpg",
      "perceptual_hash": "p:a407fba4c65aa4cb",
      "taken": 1487845320,
      "taken_at": "Feb 23, 2017, 10:22 AM"
    },
    "sfomuseum:placetype": "instagram",
    "wof:name": "The Lockheed Electra 10, built and designed to compete with the Boeing 247 and the Douglas DC-2, made its first flight #onthisday in 1934...",
    "wof:placetype": "custom"
  },
  "geometry": {"coordinates":[-122.386166,37.616356],"type":"Point"}
}
