{
  "type": "Feature",
  "properties": {
    "date:cessation_lower": "2017-10-23",
    "date:cessation_upper": "2017-10-23",
    "date:inception_lower": "2017-10-23",
    "date:inception_upper": "2017-10-23",
    "instagram:post": {
      "caption": {
        "body": "Blueprint of Power by Nomi Talisman and Dee Hibbert-Jones is now on view in our video arts room. In this video project by artists Nomi Talisman and Dee Hibbert-Jones, a walk through the Slovakian city of Žilina reveals how the its architecture is tightly connected to history, politics, and the different regimes that have ruled this city.  The Video Arts room is located pre-security, in the International Terminal. http://bit.ly/2xS7Aqq",
        "excerpt": "Blueprint of Power by Nomi Talisman and Dee Hibbert-Jones is now on view in our video arts room.",
        "hashtags": [
          "videoartsSFOM",
          "videoarts",
          "video",
          "fineart",
          "publicart",
          "blueprintofpower",
          "NomiTalisman",
          "DeeHibbertJones",
          "Slovakia",
          "Žilina",
          "architecture",
          "animation",
          "experimental"
        ]
      },
      "file_hash": "0083316055068c2e476615f15dc44a3ee65cd06a685c5bcdb709041354e9df23",
      "media_id": "b54819a12685b8c8be7546c0421e0f2e61df5d43",
      "path": "media/posts/201710/22832154_1487436218030093_1712524849575886848_n_17878602511144472.mp4",
      "taken": 1508749380,
      "taken_at": "Oct 23, 2017, 9:03 AM"
    },
    "sfomuseum:placetype": "instagram",
    "wof:name": "Blueprint of Power by Nomi Talisman and Dee Hibbert-Jones is now on view in our video arts room...",
    "wof:placetype": "custom",
    "wof:placetype_alt": [
      "instagram"
    ]
  },
  "geometry": {"coordinates":[-122.386166,37.616356],"type":"Point"}
}
