{
  "type": "Feature",
  "properties": {
    "date:cessation_lower": "2018-01-27",
    "date:cessation_upper": "2018-01-27",
    "date:inception_lower": "2018-01-27",
    "date:inception_upper": "2018-01-27",
    "instagram:post": {
      "caption": {
        "body": "United Air Lines introduced hot meal service on Douglas DST (Douglas Sleeper Transport) and DC-3 flights in the late 1930s. The DC-3 was one of the first airliners to be equipped with a galley. Meals on short, daytime flights were served with paper or plastic cups and plates to reduce weight. Ceramic wares were specifically designed to be light, yet sturdy, for inflight use. Silver-plated flatware was offered with most types of meal service. One set featured the same \"Embossed\" art deco pattern incorporated on the airline's blue plastic dishes.  See \"Flying the Main Line: A History of United Airlines\", on display, post-security, in Terminal 3. http://bit.ly/TheMainLine",
        "excerpt": "United Air Lines introduced hot meal service on Douglas DST (Douglas Sleeper Transport) and DC-3 flights in the late 1930s.",
        "hashtags": [
          "FlyingTheMainLine",
          "TheMainLine",
          "avgeek",
          "united",
          "aviationhistory",
          "unitedairlines",
          "aviationgeek",
          "aviation",
          "tablesetting",
          "dinnerware",
          "onthetable"
        ]
      },
      "media_id": "3212eecefc608f1a59aad6f33a55afd0",
      "path": "photos/201801/3212eecefc608f1a59aad6f33a55afd0.jpg",
      "perceptual_hash": "p:853972cac3868f73",
      "taken": 1517032361,
      "taken_at": "2018-01-27T05:52:41+00:00"
    },
    "sfomuseum:placetype": "instagram",
    "wof:name": "United Air Lines introduced hot meal service on Douglas DST (Douglas Sleeper Transport) and DC-3 flights in the late 1930s...",
    "wof:placetype": "custom"
  },
  "geometry": {"coordinates":[-122.386166,37.616356],"type":"Point"}
}
