{
  "type": "Feature",
  "properties": {
    "instagram:post": {
      "caption": {
        "hashtags": [
          "sfac", 
          "loveletters"
        ]
      },
      "media_id": "2b1ac3cd8e351a6c5fc751cdd262628f",
      "path": "photos/201406/2b1ac3cd8e351a6c5fc751cdd262628f.jpg",
      "taken": 1403823656,
      "taken_at": "2014-06-26T23:00:56+00:00"
    },
    "sfomuseum:placetype": "instagram",
    "wof:name": "Instagram message #%!d(string=2b1ac3cd8e351a6c5fc751cdd262628f)",
    "wof:placetype": "custom"
  },
  "geometry": {"coordinates":[-122.386166,37.616356],"type":"Point"}
}
