{
  "type": "Feature",
  "properties": {
    "instagram:post": {
      "caption": {
        "body": "What did Terminal 2 look like in the 1980s? Quite a bit different than today. Before the existing International Terminal of today, Terminal 2 served as the International Terminal. Have you ever flown out of Terminal 2?  Image: SFO International Terminal Customs arrival area overlook and exhibition gallery, c. 1983. SFO Museum Collection. 2011.032.2759",
        "hashtags": [
          "avgeek", 
          "SFOHistory", 
          "Terminal2", 
          "SFHistory", 
          "airport"
        ]
      },
      "location": "San Francisco International Airport (SFO)",
      "media_id": "c675df11fd58ca39643eee911b6eb378",
      "path": "photos/201901/c675df11fd58ca39643eee911b6eb378.jpg",
      "taken": 1547157681,
      "taken_at": "2019-01-10T22:01:21+00:00"
    },
    "sfomuseum:placetype": "instagram",
    "wof:name": "Instagram message #%!d(string=c675df11fd58ca39643eee911b6eb378)",
    "wof:placetype": "custom"
  },
  "geometry": {"coordinates":[-122.386166,37.616356],"type":"Point"}
}
