{
  "type": "Feature",
  "properties": {
    "date:cessation_lower": "2019-01-10",
    "date:cessation_upper": "2019-01-10",
    "date:inception_lower": "2019-01-10",
    "date:inception_upper": "2019-01-10",
    "instagram:post": {
      "caption": {
        "body": "What did Terminal 2 look like in the 1980s? Quite a bit different than today. Before the existing International Terminal of today, Terminal 2 served as the International Terminal. Have you ever flown out of Terminal 2?  Image: SFO International Terminal Customs arrival area overlook and exhibition gallery, c. 1983. SFO Museum Collection. 2011.032.2759",
        "excerpt": "What did Terminal 2 look like in the 1980s?",
        "hashtags": [
          "avgeek",
          "SFOHistory",
          "Terminal2",
          "SFHistory",
          "airport"
        ]
      },
      "media_id": "c675df11fd58ca39643eee911b6eb378",
      "path": "media/other/50247621_582318892181731_6014681125249037907_n_17921390995267062.jpg",
      "perceptual_hash": "p:d6c4abc87cd1e0b1",
      "taken": 1547128860,
      "taken_at": "Jan 10, 2019 2:01 pm"
    },
    "sfomuseum:placetype": "instagram",
    "wof:name": "What did Terminal 2 look like in the 1980s?..",
    "wof:placetype": "custom",
    "wof:placetype_alt": [
      "instagram"
    ]
  },
  "geometry": {"coordinates":[-122.386166,37.616356],"type":"Point"}
}
