{
  "type": "Feature",
  "properties": {
    "date:cessation_lower": "2019-11-01",
    "date:cessation_upper": "2019-11-01",
    "date:inception_lower": "2019-11-01",
    "date:inception_upper": "2019-11-01",
    "instagram:post": {
      "caption": {
        "body": "Celebrate Native American Heritage Month at SFO with a visit to the Video Arts gallery in the International Terminal Departures Lobby. SFO Museum is currently screening four film shorts by Native American and First Nations filmmakers, with a rotation of Native American and First Nations programming throughout the month of November.  NOW PLAYING: Toronto-based filmmaker Chrisann Hessing profiles Joshua DePerry, aka DJ Classic Roots, who merges the sounds and dance of his Anishinaabe culture with techno music as he inspires indigenous youths to look to the future without forgetting their past.  See \"Turning Tables\" by Chrisann Hessing, now playing in the Video Arts Room located pre-security in the International Terminal. http://bit.ly/2p2pWBT",
        "excerpt": "Celebrate Native American Heritage Month at SFO with a visit to the Video Arts gallery in the International Terminal Departures Lobby.",
        "hashtags": [
          "VideoArtsSFOM",
          "film",
          "video",
          "TurningTables",
          "JoshuaDePerry",
          "PowwowStep",
          "DJClassicRoots",
          "FirstNations",
          "Anishinaabe",
          "Ojibwe",
          "NativeFilm"
        ]
      },
      "file_hash": "c5f63a447a4500c2857f9d64f17dd6db914bcf4133df2814d5cdfdd5a74a8be5",
      "media_id": "9dbc2f6e88081d940a19c2fa0d6b887bca6ecbe4",
      "path": "media/posts/201911/76834773_408296026745819_5719623330522598966_n_17854710850621662.mp4",
      "taken": 1572627840,
      "taken_at": "Nov 1, 2019, 5:04 PM"
    },
    "sfomuseum:placetype": "instagram",
    "wof:name": "Celebrate Native American Heritage Month at SFO with a visit to the Video Arts gallery in the International Terminal Departures Lobby...",
    "wof:placetype": "custom"
  },
  "geometry": {"coordinates":[-122.386166,37.616356],"type":"Point"}
}
