{
  "type": "Feature",
  "properties": {
    "date:cessation_lower": "2018-07-18",
    "date:cessation_upper": "2018-07-18",
    "date:inception_lower": "2018-07-18",
    "date:inception_upper": "2018-07-18",
    "instagram:post": {
      "caption": {
        "body": "The Convair 240 was the first postwar commercial airliner developed by the Consolidated Vultee Company, or Convair, of San Diego. It was designed to be a pressurized, mid-range DC-3 replacement that was easy to service and turnover between flights. It featured a built-in, drop-down stairway for quick passenger loading, petal-style engine cowlings for rapid maintenance, and tricycle-configuration landing gear. It could carry forty passengers comfortably and had a range of up to 1,200 miles.  First flown in 1947, it was introduced by American Airlines in 1948. 176 were produced for numerous airlines worldwide, including Pan American World Airways, which operated a fleet of twenty of the type.  See \"Aviation Evolutions: The Jim Lund 1:72 Scale Model Airplane Collection\", which features more than 200 models, on display, pre-security, in the Aviation Museum. http://bit.ly/AviationEvolutions",
        "excerpt": "The Convair 240 was the first postwar commercial airliner developed by the Consolidated Vultee Company, or Convair, of San Diego.",
        "hashtags": [
          "AviationEvolutions",
          "jimlund",
          "avgeek",
          "avationgeek",
          "aviation",
          "aviationhistory",
          "vintageaviation",
          "history",
          "avhistory",
          "aviationgeeks",
          "modelplane",
          "avgeeks",
          "modelaircraft",
          "airplane",
          "aircraft",
          "convair",
          "convair240"
        ]
      },
      "media_id": "21d1cbef8a2d1d90ad910428aaeb9c1e",
      "path": "media/posts/201807/37113338_347511339115796_2427125816136564736_n_17853532552277160.jpg",
      "perceptual_hash": "p:8d97f274ad1a5614",
      "taken": 1531903680,
      "taken_at": "Jul 18, 2018, 8:48 AM"
    },
    "sfomuseum:placetype": "instagram",
    "wof:name": "The Convair 240 was the first postwar commercial airliner developed by the Consolidated Vultee Company, or Convair, of San Diego...",
    "wof:placetype": "custom"
  },
  "geometry": {"coordinates":[-122.386166,37.616356],"type":"Point"}
}
