{
  "type": "Feature",
  "properties": {
    "date:cessation_lower": "2019-02-28",
    "date:cessation_upper": "2019-02-28",
    "date:inception_lower": "2019-02-28",
    "date:inception_upper": "2019-02-28",
    "instagram:post": {
      "caption": {
        "body": "Terminal 2, previously known as the Central Terminal, opened in 1954. Here are views of the terminal from just before its opening, the 1980s, and 2012",
        "excerpt": "Terminal 2, previously known as the Central Terminal, opened in 1954.",
        "hashtags": [
          "ThrowbackThursday",
          "SFOHistory",
          "SFHistory",
          "avgeek",
          "airport",
          "airportarchitecture",
          "architecture"
        ]
      },
      "media_id": "476b00ac97e938327fd1524157f54f8a",
      "path": "media/posts/201902/52416027_121582422308423_4922023139502110937_n_18012271033186322.jpg",
      "perceptual_hash": "p:ccf0e148e2695e37",
      "taken": 1551376020,
      "taken_at": "Feb 28, 2019, 5:47 PM"
    },
    "sfomuseum:placetype": "instagram",
    "wof:name": "Terminal 2, previously known as the Central Terminal, opened in 1954...",
    "wof:placetype": "custom",
    "wof:placetype_alt": [
      "instagram"
    ]
  },
  "geometry": {"coordinates":[-122.386166,37.616356],"type":"Point"}
}
