{
  "type": "Feature",
  "properties": {
    "instagram:post": {
      "caption": {
        "body": "Terminal 2, previously known as the Central Terminal, opened in 1954. Here are views of the terminal from just before its opening, the 1980s, and 2012",
        "hashtags": [
          "ThrowbackThursday", 
          "SFOHistory", 
          "SFHistory", 
          "avgeek", 
          "airport", 
          "airportarchitecture", 
          "architecture"
        ]
      },
      "media_id": "476b00ac97e938327fd1524157f54f8a",
      "path": "photos/201902/476b00ac97e938327fd1524157f54f8a.jpg",
      "taken": 1551404840,
      "taken_at": "2019-03-01T01:47:20+00:00"
    },
    "sfomuseum:placetype": "instagram",
    "wof:name": "Instagram message #%!d(string=476b00ac97e938327fd1524157f54f8a)",
    "wof:placetype": "custom"
  },
  "geometry": {"coordinates":[-122.386166,37.616356],"type":"Point"}
}
