{
  "type": "Feature",
  "properties": {
    "instagram:post": {
      "caption": {
        "hashtags": [
          "behindthescenes", 
          "sneakpeek", 
          "HarveyMilk", 
          "HarveyMilkDay", 
          "HBD", 
          "onthisday", 
          "SFhistory"
        ]
      },
      "location": "San Francisco International Airport",
      "media_id": "60539bdf8f9cba007c9af571fb8ae755",
      "path": "photos/201905/60539bdf8f9cba007c9af571fb8ae755.jpg",
      "taken": 1558570159,
      "taken_at": "2019-05-23T00:09:19+00:00"
    },
    "sfomuseum:placetype": "instagram",
    "wof:name": "Instagram message #%!d(string=60539bdf8f9cba007c9af571fb8ae755)",
    "wof:placetype": "custom"
  },
  "geometry": {"coordinates":[-122.386166,37.616356],"type":"Point"}
}
