{
  "type": "Feature",
  "properties": {
    "date:cessation_lower": "2019-05-22",
    "date:cessation_upper": "2019-05-22",
    "date:inception_lower": "2019-05-22",
    "date:inception_upper": "2019-05-22",
    "instagram:post": {
      "caption": {
        "hashtags": [
          "behindthescenes",
          "sneakpeek",
          "HarveyMilk",
          "HarveyMilkDay",
          "HBD",
          "onthisday",
          "SFhistory"
        ]
      },
      "media_id": "60539bdf8f9cba007c9af571fb8ae755",
      "path": "media/posts/201905/60260586_286634908881457_3179708676083024505_n_18070285123055353.jpg",
      "perceptual_hash": "p:ab9d9562f485c839",
      "taken": 1558541340,
      "taken_at": "May 22, 2019, 4:09 PM"
    },
    "sfomuseum:placetype": "instagram",
    "wof:name": "..",
    "wof:placetype": "custom",
    "wof:placetype_alt": [
      "instagram"
    ]
  },
  "geometry": {"coordinates":[-122.386166,37.616356],"type":"Point"}
}
