{
  "type": "Feature",
  "properties": {
    "date:cessation_lower": "2022-09-30",
    "date:cessation_upper": "2022-09-30",
    "date:inception_lower": "2022-09-30",
    "date:inception_upper": "2022-09-30",
    "instagram:post": {
      "caption": {
        "body": "Japan’s outstanding metallurgy inspired Western silver manufacturers to reconsider their design and production processes. Traditionally, the West valued silver and gold above all other metals. The Japanese, on the other hand, used iron, zinc, bismuth, gold, silver, copper, and bronze. Metalsmiths combined different metals using techniques such as inlay, applied castings, and mechanical fusion.  The sides of this footed dish are intricately worked. The “outer” layer of hexagonal hammering appears torn away to reveal differing patterns beneath. Multi-colored gold butterflies and foliage accent the piece.  See “Japonisme: A Passion for Japan” on display, post-security, in Terminal 2 and online at: https://bit.ly/JaponismeSFO",
        "excerpt": "Japan’s outstanding metallurgy inspired Western silver manufacturers to reconsider their design and production processes.",
        "hashtags": [
          "Japonisme",
          "Japan",
          "Design",
          "silver",
          "decorativearts"
        ]
      },
      "media_id": "bf20783d0c4f2d714e8144d9478c53bf24db9cfc",
      "path": "media/posts/202209/309693829_135497262323361_826877468040860246_n_17957753536917942.jpg",
      "perceptual_hash": "p:830b70745f62787b",
      "taken": 1664539740,
      "taken_at": "Sep 30, 2022, 12:09 PM"
    },
    "sfomuseum:placetype": "instagram",
    "wof:name": "Japan’s outstanding metallurgy inspired Western silver manufacturers to reconsider their design and production processes...",
    "wof:placetype": "custom"
  },
  "geometry": {"coordinates":[-122.386166,37.616356],"type":"Point"}
}
