{
  "type": "Feature",
  "properties": {
    "date:cessation_lower": "2024-03-06",
    "date:cessation_upper": "2024-03-06",
    "date:inception_lower": "2024-03-06",
    "date:inception_upper": "2024-03-06",
    "instagram:post": {
      "caption": {
        "body": "Every March, SFO Museum highlights women artists for International Women’s History Month using the hashtag #5WomenArtists. Started by the National Museum of Women in the Arts (@womeninthearts), #5WomenArtists calls attention to the fact that women are underrepresented in the art world and that many people can’t name even five female artists.  Alicia McCarthy is a key member of the Mission School, a movement that emerged in the 1990’s in San Francisco and drew inspiration from graffiti, street art, and the use of non-traditional materials.  In creating “MMXX,” McCarthy worked closely with Lineman Architectural Glass in Oakland to translate her distinctive aesthetics of repetition, variation, and chance into glass using a combination of techniques.  By painting, airbrushing, and sandblasting the different surfaces of the artwork’s layered assembly, she adds depth and dimension to the work’s radiating design.  See “MMXX” by Alicia McCarthy on display, post-security in the International Terminal. https://ow.ly/fyse50QNaN0",
        "excerpt": "Every March, SFO Museum highlights women artists for International Women’s History Month using the hashtag #5WomenArtists.",
        "hashtags": [
          "AliciaMcCarthy",
          "5WomenArtists",
          "WomensHistoryMonth",
          "SFAC"
        ],
        "users": [
          "sf_arts_commission"
        ]
      },
      "media_id": "39d4a7353ed50d4749fafc19615a07703665bc3d",
      "path": "media/posts/202403/431300649_310834934973754_3482975785158097869_n_18082904467441296.jpg",
      "perceptual_hash": "p:d6da95c4359a6235",
      "taken": 1709741760,
      "taken_at": "Mar 06, 2024 4:16 pm"
    },
    "sfomuseum:placetype": "instagram",
    "wof:name": "Every March, SFO Museum highlights women artists for International Women’s History Month using the hashtag #5WomenArtists...",
    "wof:placetype": "custom"
  },
  "geometry": {"coordinates":[-122.386166,37.616356],"type":"Point"}
}
