{
  "type": "Feature",
  "properties": {
    "date:cessation_lower": "2015-12-21",
    "date:cessation_upper": "2015-12-21",
    "date:inception_lower": "2015-12-21",
    "date:inception_upper": "2015-12-21",
    "instagram:post": {
      "caption": {
        "hashtags": [
          "OnThisDay"
        ]
      },
      "media_id": "1281f9bdbf01d5d5f65e95812ae98baf",
      "path": "media/other/12346113_203171096688514_250360491_n_17852289049003092.jpg",
      "perceptual_hash": "p:c493ec817eec815d",
      "taken": 1450696500,
      "taken_at": "Dec 21, 2015 11:15 am"
    },
    "sfomuseum:placetype": "instagram",
    "wof:name": "..",
    "wof:placetype": "custom",
    "wof:placetype_alt": [
      "instagram"
    ]
  },
  "geometry": {"coordinates":[-122.386166,37.616356],"type":"Point"}
}
