{
  "type": "Feature",
  "properties": {
    "date:cessation_lower": "2020-04-06",
    "date:cessation_upper": "2020-04-06",
    "date:inception_lower": "2020-04-06",
    "date:inception_upper": "2020-04-06",
    "instagram:post": {
      "caption": {
        "body": "#Onthisday in 1926, Walter T. Varney, a flight school and air taxi operator from San Francisco, launched his air mail service. His company, Varney Air Lines, was acquired by United Aircraft and Transport Corporation in 1930. United Airlines originated from a merger of several early air transport companies, including Varney Air Lines.  Image: Leon D. Cuddleback, chief pilot for Varney Air Lines, c. 1926. Gift of United Airlines Archives. 1999.047.184",
        "excerpt": "#Onthisday in 1926, Walter T. Varney, a flight school and air taxi operator from San Francisco, launched his air mail service.",
        "hashtags": [
          "united",
          "MuseumFromHome",
          "avgeek"
        ]
      },
      "media_id": "a78613329c8ea0e7e35677325e47b905",
      "path": "photos/202004/a78613329c8ea0e7e35677325e47b905.jpg",
      "perceptual_hash": "p:ae5a95e5893ac21e",
      "taken": 1586180700,
      "taken_at": "Apr 6, 2020, 1:45 PM"
    },
    "sfomuseum:placetype": "instagram",
    "wof:name": "#Onthisday in 1926, Walter T. Varney, a flight school and air taxi operator from San Francisco, launched his air mail service...",
    "wof:placetype": "custom"
  },
  "geometry": {"coordinates":[-122.386166,37.616356],"type":"Point"}
}
