{
  "type": "Feature",
  "properties": {
    "date:cessation_lower": "2018-12-20",
    "date:cessation_upper": "2018-12-20",
    "date:inception_lower": "2018-12-20",
    "date:inception_upper": "2018-12-20",
    "instagram:post": {
      "caption": {
        "body": "One of the greatest advances in commercial aviation was the successful introduction of jet airliners during the late 1950s. Although introduced after the British de Havilland Comet and the Soviet Tupolev Tu-104, the Boeing 707 was the first commercial jetliner to provide regular, sustained commercial airline service and thus revolutionized the airline industry, while effectively ushering in the jet age of air travel. #OnThisDay in 1957, the first Boeing 707 took flight from Renton Municipal Airport. N708PA, the aircraft that took this first test flight, was delivered to Pan American World Airways on November 30, 1958. Pan American inaugurated 707 service in October 1958. By October 1983, Pan American and TWA (Trans World Airlines) retired their Boeing 707s. Did you ever fly on a Boeing 707?  Boeing 707-120, first flight, Renton Municipal Airport 1957 SFO Museum Collection The Estate of Fred Nott  2004.016.156",
        "excerpt": "One of the greatest advances in commercial aviation was the successful introduction of jet airliners during the late 1950s."
      },
      "media_id": "851f47b62ee8c0a9eb68b2df0f00b60c",
      "path": "media/posts/201812/45634499_303347136972974_739989316367876948_n_17984381707193039.jpg",
      "perceptual_hash": "p:a7da502fd3582457",
      "taken": 1545316020,
      "taken_at": "Dec 20, 2018, 2:27 PM"
    },
    "sfomuseum:placetype": "instagram",
    "wof:name": "One of the greatest advances in commercial aviation was the successful introduction of jet airliners during the late 1950s...",
    "wof:placetype": "custom"
  },
  "geometry": {"coordinates":[-122.386166,37.616356],"type":"Point"}
}
