{
  "type": "Feature",
  "properties": {
    "date:cessation_lower": "2013-02-28",
    "date:cessation_upper": "2013-02-28",
    "date:inception_lower": "2013-02-28",
    "date:inception_upper": "2013-02-28",
    "instagram:post": {
      "caption": {
        "body": "In addition to making their own textiles, the Shakers crafted the related production tools.",
        "excerpt": "In addition to making their own textiles, the Shakers crafted the related production tools."
      },
      "media_id": "c512059ad6bf40cbed38b84622d687b7",
      "path": "media/posts/201302/11261688_815156725229030_1483791184_n_17842304482062499.jpg",
      "perceptual_hash": "p:81bc63603f5a6ae3",
      "taken": 1362060780,
      "taken_at": "Feb 28, 2013, 2:13 PM"
    },
    "sfomuseum:placetype": "instagram",
    "wof:name": "In addition to making their own textiles, the Shakers crafted the related production tools...",
    "wof:placetype": "custom"
  },
  "geometry": {"coordinates":[-122.386166,37.616356],"type":"Point"}
}
