{
  "type": "Feature",
  "properties": {
    "instagram:post": {
      "caption": {
        "body": "Art found in ancient sites throughout the Chiapas highlands preserves images of early attire and the oldest symbols utilized in contemporary Mayan weaving. A stone carving from a lintel at the Bonampak temple complex shows one of the most common ancient designs, known today as the cruz or feathered cross. The symbol decorates a long and elaborate huipil worn by Lady K'ab'al Xook, queen of Yaxchilán, who is performing a bloodletting ritual with her husband, Shield Jaguar II in the year 709CE. Glyphs on the lintel identify dates along with the king and queen, yet do not give a name or interpretation of the cruz symbol. While the true meaning of the feathered cross is lost to time, its design survives in weaving as a representation of Mayan antiquity.  Learn more about \"Empowering Threads: Textiles of Jolom Mayaetik\" on display, pre-security, in the International Terminal. http://bit.ly/EmpoweringThreads",
        "excerpt": "Art found in ancient sites throughout the Chiapas highlands preserves images of early attire and the oldest symbols utilized in contemporary Mayan weaving.",
        "hashtags": [
          "EmpoweringThreads", 
          "mayantextiles", 
          "textile", 
          "textiles", 
          "mayan", 
          "mexico", 
          "mexican", 
          "mexicanhistory", 
          "mayanhistory", 
          "JolomMayaetik", 
          "weavers", 
          "weaving", 
          "blouses", 
          "huipiles", 
          "looms", 
          "backstraploom", 
          "mayanculture", 
          "handwoven", 
          "sewing", 
          "cooperativa", 
          "artesanaschiapanecas", 
          "chiapas", 
          "cojinesartesanales", 
          "artesanias", 
          "empoweringwomen"
        ]
      },
      "media_id": "16cebd469deac510302eb37de0dc0bf8",
      "path": "photos/201712/16cebd469deac510302eb37de0dc0bf8.jpg",
      "taken": 1512694377,
      "taken_at": "2017-12-08T00:52:57+00:00"
    },
    "sfomuseum:placetype": "instagram",
    "wof:name": "Art found in ancient sites throughout the Chiapas highlands preserves images of early attire and the oldest symbols utilized in contemporary Mayan weaving...",
    "wof:placetype": "custom"
  },
  "geometry": {"coordinates":[-122.386166,37.616356],"type":"Point"}
}
