{
  "type": "Feature",
  "properties": {
    "instagram:post": {
      "caption": {
        "body": "In 1935, in response to a request for a large-capacity, long-range airliner from United Air Lines, Douglas began developing the DC-4. Soon, American Airlines, Eastern Air Lines, and Pan American Airways expressed interest. The prototype was a large, pressurized, four-engine airliner with a capacity for fifty-two passengers. It also featured a low-profile triple tail in order to fit into aircraft hangers of the period. It first flew in 1938. However, the aircraft was deemed too large and complicated, with performance was well below expectations. As a result, it was completely redesigned. A smaller, less complicated, unpressurized design was developed instead, which became the DC-4. The original prototype, then re-designated the DC-4E to differentiate between the two, was sold to the Empire of Japan.  See \"Aviation Evolutions: The Jim Lund 1:72 Scale Model Airplane Collection\", which features more than 200 models, on display, pre-security, in the Aviation Museum. http://bit.ly/AviationEvolutions",
        "excerpt": "In 1935, in response to a request for a large-capacity, long-range airliner from United Air Lines, Douglas began developing the DC-4.",
        "hashtags": [
          "AviationEvolutions", 
          "jimlund", 
          "avgeek", 
          "avationgeek", 
          "aviation", 
          "aviationhistory", 
          "aviationlovers", 
          "vintageaviation", 
          "history", 
          "avhistory", 
          "aviationgeeks", 
          "instaplane", 
          "flying", 
          "modelplane", 
          "flight", 
          "airline", 
          "avgeeks", 
          "aviation4u", 
          "aviationdaily", 
          "modelaricraft", 
          "airplane", 
          "aircraft"
        ]
      },
      "media_id": "d2dc624b859f69c701b3d116213520f8",
      "path": "photos/201711/d2dc624b859f69c701b3d116213520f8.jpg",
      "taken": 1511985486,
      "taken_at": "2017-11-29T19:58:06+00:00"
    },
    "sfomuseum:placetype": "instagram",
    "wof:name": "In 1935, in response to a request for a large-capacity, long-range airliner from United Air Lines, Douglas began developing the DC-4...",
    "wof:placetype": "custom"
  },
  "geometry": {"coordinates":[-122.386166,37.616356],"type":"Point"}
}
