{
  "type": "Feature",
  "properties": {
    "date:cessation_lower": "2017-08-26",
    "date:cessation_upper": "2017-08-26",
    "date:inception_lower": "2017-08-26",
    "date:inception_upper": "2017-08-26",
    "instagram:post": {
      "caption": {
        "body": "It is the second week of installation for our \"#EmpoweringThreads: #Textiles of Jolom Mayaetik\" exhibition. It will open in its entirety on Saturday.  A unique and dedicated community of Mayan artisans are weaving brilliantly colored textiles in Los Altos de Chiapas, México. Working on backstrap looms, these weavers are utilizing methods passed down through generations to combine old-world symbolism with new colors and designs. Traditional Mayan weaving is produced on the backstrap loom, a simple and portable device used for centuries that creates complex work in the hands of a skilled artisan. In the past, weavers made woven items for themselves, for family members, and to trade. Now they are also produced for sale, and backstrap weaving has become a primary means for indigenous women to earn supplementary income.  See \"#EmpoweringThreads: #Textiles of Jolom Mayaetik\" on display, pre-security, in the International Terminal. http://bit.ly/EmpoweringThreads",
        "excerpt": "It is the second week of installation for our \"#EmpoweringThreads: #Textiles of Jolom Mayaetik\" exhibition.",
        "hashtags": [
          "mayantextiles",
          "textile",
          "textiles",
          "mayan",
          "mexico",
          "mexican",
          "mexicanhistory",
          "mayanhistory",
          "JolomMayaetik",
          "weavers",
          "weaving",
          "blouses",
          "huipiles",
          "looms",
          "backstraploom",
          "mayanculture",
          "handwoven",
          "sewing"
        ]
      },
      "media_id": "f2e9598027c7501afc94f27bd5c82bce",
      "path": "media/posts/201708/21041706_1796577077269930_4021130587912798208_n_17872036447147631.jpg",
      "perceptual_hash": "p:84527e528cacb9dd",
      "taken": 1503774600,
      "taken_at": "Aug 26, 2017, 7:10 PM"
    },
    "sfomuseum:placetype": "instagram",
    "wof:name": "It is the second week of installation for our \"#EmpoweringThreads: #Textiles of Jolom Mayaetik\" exhibition...",
    "wof:placetype": "custom"
  },
  "geometry": {"coordinates":[-122.386166,37.616356],"type":"Point"}
}
