{
  "type": "Feature",
  "properties": {
    "date:cessation_lower": "2024-01-16",
    "date:cessation_upper": "2024-01-16",
    "date:inception_lower": "2024-01-16",
    "date:inception_upper": "2024-01-16",
    "instagram:post": {
      "caption": {
        "body": "The first Pan American Airways scheduled passenger flight took off on this day in 1928 from Key West, Florida, to Havana, Cuba. The eight-passenger, three-engine, Fokker F-VIIa/3m made the 90-mile trip in just under 90 minutes. The one-way fare was $50 or about $887 today, adjusted for inflation.  model airplane: Pan American Airways, Fokker F.VllA-3m General Machado; 1980 Gift of Jim Lund 2014.173.001 https://collection.sfomuseum.org/objects/1880318919/",
        "excerpt": "The first Pan American Airways scheduled passenger flight took off on this day in 1928 from Key West, Florida, to Havana, Cuba."
      },
      "media_id": "043916d9e7cf9207a80a44cc79f0048a9fea3076",
      "path": "media/other/420197895_854035760066688_6935323140923803687_n_17958964889601251.jpg",
      "perceptual_hash": "p:b89dc73438caa617",
      "taken": 1705425900,
      "taken_at": "Jan 16, 2024 5:25 pm"
    },
    "sfomuseum:placetype": "instagram",
    "wof:name": "The first Pan American Airways scheduled passenger flight took off on this day in 1928 from Key West, Florida, to Havana, Cuba...",
    "wof:placetype": "custom"
  },
  "geometry": {"coordinates":[-122.386166,37.616356],"type":"Point"}
}
