{
  "type": "Feature",
  "properties": {
    "date:cessation_lower": "2023-05-10",
    "date:cessation_upper": "2023-05-10",
    "date:inception_lower": "2023-05-10",
    "date:inception_upper": "2023-05-10",
    "instagram:post": {
      "caption": {
        "body": "“Well, it’s not terribly complicated. I have always identified on the masculine spectrum and have used the words FTM, trans man, gay man, male to identify myself. Before I transitioned, I was with a woman in a butch/femme lesbian relationship. I identified as a leather dyke back then, and was definitely butch. In October of 1990, I went to a conference, heard of female-to-male, which I didn’t even know was possible, and went through an identity crisis. I started testosterone in February of 1991. I did not lose a lot of friends, but in the beginning it was a little rocky. It was different back then. There was no internet. You found out about groups through the backs of magazines. For a while, I refused to identify as either/or. I identified as sort of both, what we would call “queer” these days. For all intents and purposes, I still identify as queer, but my identity doesn’t come up for the most part. I get seen as male. I spend most of my time, in terms of sexualized spaces, with other gay men.   I don’t have any concerns about aging, per se, because I don’t think our issues are terribly different from anybody else who’s aging. I think the greatest fear for me is the greatest fear for anybody who’s in a couple, that my partner will pass away. I’m also worried about the lack of nursing homes and long term care facilities geared toward our community. Right now, if something happened and I needed to be in a home, finding a place where I would be comfortable would be a challenge. I’m hopeful that in the next twenty years, something will change, preferably sooner rather than later.” - Mike, 55, Palm Springs, CA, 2017  See “To Survive on this Shore: Photographs and Interviews with Transgender and Gender Nonconforming Older Adults” on display in the Ruth Kadish Gallery located in the post-security connector between Terminal 2 and Terminal 3 and online at: http://bit.ly/436W6tV",
        "excerpt": "“Well, it’s not terribly complicated.",
        "hashtags": [
          "JessTDugan",
          "VanessaFabbre",
          "ToSurviveOnThisShore",
          "Trans",
          "Transgender",
          "GenderNonconforming"
        ]
      },
      "media_id": "cebf14a1d94362d48d390f54abf6cda8e4a975da",
      "path": "media/posts/202305/345859168_949764146071256_3383156441630700352_n_18021043936541167.jpg",
      "perceptual_hash": "p:d87d210bda762783",
      "taken": 1683713820,
      "taken_at": "May 10, 2023 10:17 am"
    },
    "sfomuseum:placetype": "instagram",
    "wof:name": "“Well, it’s not terribly complicated...",
    "wof:placetype": "custom",
    "wof:placetype_alt": [
      "instagram"
    ]
  },
  "geometry": {"coordinates":[-122.386166,37.616356],"type":"Point"}
}
