{
  "type": "Feature",
  "properties": {
    "date:cessation_lower": "2017-01-28",
    "date:cessation_upper": "2017-01-28",
    "date:inception_lower": "2017-01-28",
    "date:inception_upper": "2017-01-28",
    "instagram:post": {
      "caption": {
        "body": "This c. 1936 postcard features a rendering of the San Francisco - Oakland Bay Bridge superimposed on a photographic image of San Francisco. The back of the postcard reads: \"The concrete and reinforcing steel used in constructing the bridge is sufficient to build 35 Russ Buildings (San Francisco), 35 City Halls (Los Angeles); or 35 L.C. Smith Buildings (Seattle). The total length of the 2 1/4\" suspender ropes will be 43 miles, and the total length of cable wire used will be 70,815 miles – nearly three times the circumference of the earth.  The bridge, which is the largest in the world and which cost $77,600,000 is being built for the California Toll Bridge Authority, of which Governor Frank Merriam is Chairman, by the State Department of Public Works, of which Earl Lee Kelly is Director and C.H. Purcell is Chief Engineer.  The bridge is financed entirely without taxation, its cost defrayed by sale of 4 3/4 per cent bonds issued against the prospective revenues of the bridge. These bonds have been purchased at a discount increasing the yield to 5 per cent by the Federal Reconstruction Finance Corporation and may eventually to be sold to the public.  In addition to the bonds purchased by the Reconstruction Finance Corporation, financing came from the State Gas Tax Fund to be repaid out of tolls before the bridge becomes free to the public. Like a State highway, the completed bridge will be maintained out of the State Highway Fund.\" #SFHistory  San Francisco - Oakland Bay Bridge, J. C. Bardell c. 1936 SFO Museum Collection Gift of Teresa Damgaard 2010.245.003",
        "excerpt": "This c. 1936 postcard features a rendering of the San Francisco - Oakland Bay Bridge superimposed on a photographic image of San Francisco."
      },
      "location": "SFO Museum",
      "media_id": "43bf488eb426eab11026da7fb879c115",
      "path": "photos/201701/43bf488eb426eab11026da7fb879c115.jpg",
      "perceptual_hash": "p:c09fc390be7bc720",
      "taken": 1485572201,
      "taken_at": "2017-01-28T02:56:41+00:00"
    },
    "sfomuseum:placetype": "instagram",
    "wof:name": "This c. 1936 postcard features a rendering of the San Francisco - Oakland Bay Bridge superimposed on a photographic image of San Francisco...",
    "wof:placetype": "custom"
  },
  "geometry": {"coordinates":[-122.386166,37.616356],"type":"Point"}
}
