{
  "type": "Feature",
  "properties": {
    "date:cessation_lower": "2024-11-11",
    "date:cessation_upper": "2024-11-11",
    "date:inception_lower": "2024-11-11",
    "date:inception_upper": "2024-11-11",
    "instagram:post": {
      "caption": {
        "body": "The Aviation Museum and Library is closed today to observe Veterans Day and will reopen tomorrow, November 12th at 10am. All other exhibitions located in the airport terminals are still available to view: https://bit.ly/SFOMExhibits",
        "excerpt": "The Aviation Museum and Library is closed today to observe Veterans Day and will reopen tomorrow, November 12th at 10am.",
        "hashtags": [
          "VeteransDay"
        ]
      },
      "media_id": "c681c224b5162daa655aeb2d80c1fc5d905a2cf7",
      "path": "media/other/466802869_584417743960655_5642168335780731591_n_18037392773251274.jpg",
      "perceptual_hash": "p:860b799572ccc739",
      "taken": 1731312300,
      "taken_at": "Nov 11, 2024 8:05 am"
    },
    "sfomuseum:placetype": "instagram",
    "wof:name": "The Aviation Museum and Library is closed today to observe Veterans Day and will reopen tomorrow, November 12th at 10am...",
    "wof:placetype": "custom"
  },
  "geometry": {"coordinates":[-122.386166,37.616356],"type":"Point"}
}
