{
  "type": "Feature",
  "properties": {
    "date:cessation_lower": "2021-11-19",
    "date:cessation_upper": "2021-11-19",
    "date:inception_lower": "2021-11-19",
    "date:inception_upper": "2021-11-19",
    "instagram:post": {
      "caption": {
        "body": "Thomas Chandler and other potters of Edgefield, South Carolina, often mixed different clays together to achieve the proper balance and ground their clays in a pug mill to obtain the right consistency for turning. The potter weighed the necessary amount of clay according to the size of the vessel that they wanted to produce, kneaded the clay, then formed the clay into a ball. The clay was then ready to be turned on a “kick” or treadle wheel. Lastly, the dried wares were coated with an alkaline glaze solution.   “Stoneware Stories: Folk Pottery of Edgefield, South Carolina” is on display pre-security in the International Terminal Main Hall, near the security checkpoint for the A gates. See it online at http://bit.ly/StonewareStories",
        "excerpt": "Thomas Chandler and other potters of Edgefield, South Carolina, often mixed different clays together to achieve the proper balance and ground their clays in a pug mill to obtain the right consistency for turning.",
        "hashtags": [
          "StonewareStories",
          "ThomasChandler",
          "Edgefield",
          "Ceramics"
        ]
      },
      "media_id": "5f63bfcc86bd356b07878dba8390fcedb5bf8fe9",
      "path": "media/posts/202111/259191374_402031954986603_7287005342191813343_n_18089164969303228.jpg",
      "perceptual_hash": "p:f0368d31968bf2d4",
      "taken": 1637338680,
      "taken_at": "Nov 19, 2021, 4:18 PM"
    },
    "sfomuseum:placetype": "instagram",
    "wof:name": "Thomas Chandler and other potters of Edgefield, South Carolina, often mixed different clays together to achieve the proper balance and ground their clays in a pug mill to obtain the right consistency for turning...",
    "wof:placetype": "custom",
    "wof:placetype_alt": [
      "instagram"
    ]
  },
  "geometry": {"coordinates":[-122.386166,37.616356],"type":"Point"}
}
