{
  "type": "Feature",
  "properties": {
    "instagram:post": {
      "caption": {
        "body": "The Lockheed Model 12 Electra was similar to the Model 10 Electra in design, but smaller and faster. Most airlines rejected the aircraft, primarily because of its low capacity of only six passengers. The few exceptions were Continental Air Lines, which operated a fleet of three Model 12 types, and British West Indian Airways. However, the aircraft was successful as a fast company and government transport, and as a military transport and bomber trainer.  See \"Aviation Evolutions: The Jim Lund 1:72 Scale Model Airplane Collection\", which features more than 200 models on display, pre-security in the Aviation Museum. http://bit.ly/AviationEvolutions",
        "hashtags": [
          "AviationEvolutions", 
          "JimLund", 
          "Lockheed", 
          "Electra", 
          "Continental", 
          "avgeek", 
          "avationgeek", 
          "aviation", 
          "aviationhistory", 
          "aviationlovers", 
          "vintageaviation", 
          "history", 
          "avhistory", 
          "aviationgeeks", 
          "instaplane", 
          "flying", 
          "modelplane", 
          "flight", 
          "airline", 
          "avgeeks", 
          "aviation4u", 
          "aviationdaily", 
          "modelaircraft", 
          "airplane", 
          "aircraft"
        ]
      },
      "media_id": "d16973bf45e36bf941205b10d66bf640",
      "path": "photos/201804/d16973bf45e36bf941205b10d66bf640.jpg",
      "taken": 1524764682,
      "taken_at": "2018-04-26T17:44:42+00:00"
    },
    "sfomuseum:placetype": "instagram",
    "wof:name": "Instagram message #%!d(string=d16973bf45e36bf941205b10d66bf640)",
    "wof:placetype": "custom"
  },
  "geometry": {"coordinates":[-122.386166,37.616356],"type":"Point"}
}
