{
  "type": "Feature",
  "properties": {
    "instagram:post": {
      "caption": {
        "body": "Stuart Rome has worked as a photographer since the 1970s. His Oculus series is composed of images taken from within giant redwoods and sequoias. Rome places himself within the trees and uses the openings at the top as apertures, framing the sky.  Check out Stuart Rome’s Oculus, post-security, in Terminal 3.",
        "excerpt": "Stuart Rome has worked as a photographer since the 1970s."
      },
      "location": "San Francisco International Airport (SFO)",
      "media_id": "6fda6c0a6b0d22d9be1bb955ef374d25",
      "path": "photos/201601/6fda6c0a6b0d22d9be1bb955ef374d25.jpg",
      "taken": 1451763520,
      "taken_at": "2016-01-02T19:38:40+00:00"
    },
    "sfomuseum:placetype": "instagram",
    "wof:name": "Stuart Rome has worked as a photographer since the 1970s...",
    "wof:placetype": "custom"
  },
  "geometry": {"coordinates":[-122.386166,37.616356],"type":"Point"}
}
