{
  "type": "Feature",
  "properties": {
    "instagram:post": {
      "caption": {
        "body": "Dorothy Hope Parkinson Kewin (1922-1976) was the first Pan American World Airways stewardess officially assigned to Pacific route service. #PanAm  Pan American World Airways, Hope Parkinson 1940s SFO Museum Collection Gift of Thomas Kewin 2015.151.002"
      },
      "location": "SFO Museum",
      "media_id": "ef066168786c6ff4085944dc77f18d0c",
      "path": "photos/201604/ef066168786c6ff4085944dc77f18d0c.jpg",
      "taken": 1461811051,
      "taken_at": "2016-04-28T02:37:31+00:00"
    },
    "sfomuseum:placetype": "instagram",
    "wof:name": "Instagram message #%!d(string=ef066168786c6ff4085944dc77f18d0c)",
    "wof:placetype": "custom"
  },
  "geometry": {"coordinates":[-122.386166,37.616356],"type":"Point"}
}
