{
  "type": "Feature",
  "properties": {
    "date:cessation_lower": "2020-11-16",
    "date:cessation_upper": "2020-11-16",
    "date:inception_lower": "2020-11-16",
    "date:inception_upper": "2020-11-16",
    "instagram:post": {
      "caption": {
        "body": "Advertised as the quietest widebody jet airliner in service, the Lockheed L-1011 TriStar took off on its maiden flight #onthisday in 1970. The TriStar trijet was the last commercial airliner produced by the Lockheed Corporation. An advanced feature of the L-1011 was the autoland system, which fully automated the landing procedure and allowed the plane to land in unfavorable weather conditions. Only 250 L-1011 TriStar jets were produced and production halted in 1982. Did you ever fly on a Lockheed L-1011 TriStar?  Image: Pacific Southwest Airlines (PSA) postcard, L-1011 TriStar. Gift of Ruth Y. Tamura. 1998.153.011",
        "excerpt": "Advertised as the quietest widebody jet airliner in service, the Lockheed L-1011 TriStar took off on its maiden flight #onthisday in 1970.",
        "hashtags": [
          "avgeek",
          "MuseumFromHome",
          "Lockheed"
        ]
      },
      "media_id": "9d05813fe0310cf4f6b796268862f314cd8a3381",
      "path": "media/posts/202011/125380616_302682054179506_6039066138895511024_n_17948392591376541.jpg",
      "perceptual_hash": "p:831d166ef33a9c85",
      "taken": 1605552420,
      "taken_at": "Nov 16, 2020, 6:47 PM"
    },
    "sfomuseum:placetype": "instagram",
    "wof:name": "Advertised as the quietest widebody jet airliner in service, the Lockheed L-1011 TriStar took off on its maiden flight #onthisday in 1970...",
    "wof:placetype": "custom",
    "wof:placetype_alt": [
      "instagram"
    ]
  },
  "geometry": {"coordinates":[-122.386166,37.616356],"type":"Point"}
}
