{
  "type": "Feature",
  "properties": {
    "instagram:post": {
      "caption": {
        "body": "This 1950s Pan American World Airways drinks and distractions menu in English and French was for the Rainbow class, a reduced-priced, tourist-class service. Cocktails and other drinks were offered for 50 cents and a wide array of games and service items were available for free. What would you have ordered from this menu? #avgeek #panam #aviationhistory  Image: Pan American World Airways menu, Rainbow (Economy) Class, 1950s, Gift of Thomas G. Dragges, 2014.095.202"
      },
      "location": "San Francisco International Airport (SFO)",
      "media_id": "0e7863964286455ab4e345ad17818e05",
      "path": "photos/201702/0e7863964286455ab4e345ad17818e05.jpg",
      "taken": 1486144080,
      "taken_at": "2017-02-03T17:48:00+00:00"
    },
    "sfomuseum:placetype": "instagram",
    "wof:name": "Instagram message #%!d(string=0e7863964286455ab4e345ad17818e05)",
    "wof:placetype": "custom"
  },
  "geometry": {"coordinates":[-122.386166,37.616356],"type":"Point"}
}
