{
  "type": "Feature",
  "properties": {
    "date:cessation_lower": "2024-09-24",
    "date:cessation_upper": "2024-09-24",
    "date:inception_lower": "2024-09-24",
    "date:inception_upper": "2024-09-24",
    "instagram:post": {
      "caption": {
        "body": "Do you ever wonder how SFO Museum creates our exhibitions? We mockup every exhibition in our exhibition design lab before installation in our galleries. All exhibitions are planned and designed in stages. For the initial layout stage, armed with the list of objects, our exhibition designer and curators decide on how objects will be placed and grouped together to tell a cohesive story. Then, our exhibition designer begins working on the layout of the objects; in this instance, using paper facsimiles and cardboard cut outs in the place of 3D objects.  This includes considering the height of an object in relation to other objects, its angle, and what pieces should be grouped together on platforms or risers. As the exhibition design for our upcoming show evolved and progressed, our designer switched out the facsimiles for the actual objects that will be on display.  Kudos to our exhibition design team!  Stay tuned to see more behind the scenes from our upcoming exhibition, “San Francisco: City of the World!”",
        "excerpt": "Do you ever wonder how SFO Museum creates our exhibitions?",
        "hashtags": [
          "behindthescenes",
          "sneakpeek",
          "SFCityoftheWorld"
        ]
      },
      "media_id": "c319f05de3a0742aae99558c891d9e218630b7d7",
      "path": "media/posts/202409/461053044_1037055438431385_4855852387193071393_n_17939697917873069.jpg",
      "perceptual_hash": "p:f4f452703c87d2a9",
      "taken": 1727193600,
      "taken_at": "Sep 24, 2024 4:00 pm"
    },
    "sfomuseum:placetype": "instagram",
    "wof:name": "Do you ever wonder how SFO Museum creates our exhibitions?..",
    "wof:placetype": "custom"
  },
  "geometry": {"coordinates":[-122.386166,37.616356],"type":"Point"}
}
