{
  "type": "Feature",
  "properties": {
    "date:cessation_lower": "2018-02-15",
    "date:cessation_upper": "2018-02-15",
    "date:inception_lower": "2018-02-15",
    "date:inception_upper": "2018-02-15",
    "instagram:post": {
      "caption": {
        "body": "The universe is central to Mayan mythology and often appears symbolically in traditional weaving. Illustrated by a diamond motif sometimes referred to as the \"Grand Design,\" its four sides represent the boundaries of space and time. Smaller diamonds at the points of the symbol mark cardinal directions, with curl motifs that extend from the central diamond to recreate movement of the sun across the sky. Implemented in rows, the universe design shows the continuation of time through its repetition.  Learn more about \"Empowering Threads: Textiles of Jolom Mayaetik\" on display, pre-security, in the International Terminal. http://bit.ly/EmpoweringThreads",
        "excerpt": "The universe is central to Mayan mythology and often appears symbolically in traditional weaving.",
        "hashtags": [
          "EmpoweringThreads",
          "mayantextiles",
          "textile",
          "universe",
          "mythology"
        ]
      },
      "media_id": "313ab57e10a9e5458e0da65e4cc81f4d158d51fd",
      "path": "media/posts/201802/27578700_151307312250097_9181664854983835648_n_17911736647106267.jpg",
      "perceptual_hash": "p:d6a8a921de765629",
      "taken": 1518698820,
      "taken_at": "Feb 15, 2018, 12:47 PM"
    },
    "sfomuseum:placetype": "instagram",
    "wof:name": "The universe is central to Mayan mythology and often appears symbolically in traditional weaving...",
    "wof:placetype": "custom"
  },
  "geometry": {"coordinates":[-122.386166,37.616356],"type":"Point"}
}
