{
  "type": "Feature",
  "properties": {
    "date:cessation_lower": "2019-04-04",
    "date:cessation_upper": "2019-04-04",
    "date:inception_lower": "2019-04-04",
    "date:inception_upper": "2019-04-04",
    "instagram:post": {
      "caption": {
        "body": "During the late 1930s, appliances for the office and home underwent a major streamline design transformation. Even sewing machines were streamlined. The clean, airplane-like shape of the Sears Kenmore Imperial Model 117.59, designed by John Richard Morgan (1903–1986), presented a sharp contrast from the multifaceted, complex appearance of earlier sewing machine designs. \"Streamlines: Air Age Aesthetics for Industrial Design\" is on display, pre-security, in the Aviation Museum and Library in the International Terminal. http://bit.ly/Streamlines  Image: Sears Kenmore Imperial Model 117.59 rotary sewing machine and cabinet,  c. 1942, Collection of The Museum of American Heritage, Palo Alto, California. L2018.0215.008.01–.03",
        "excerpt": "During the late 1930s, appliances for the office and home underwent a major streamline design transformation.",
        "hashtags": [
          "StreamlinesAesthetics",
          "streamline",
          "design",
          "industrialdesign"
        ]
      },
      "media_id": "6ef730d90df8175adf1274ea96c85ed9",
      "path": "photos/201904/6ef730d90df8175adf1274ea96c85ed9.jpg",
      "perceptual_hash": "p:ca96693ec14e3de0",
      "taken": 1554390420,
      "taken_at": "Apr 4, 2019, 3:07 PM"
    },
    "sfomuseum:placetype": "instagram",
    "wof:name": "During the late 1930s, appliances for the office and home underwent a major streamline design transformation...",
    "wof:placetype": "custom",
    "wof:placetype_alt": [
      "instagram"
    ]
  },
  "geometry": {"coordinates":[-122.386166,37.616356],"type":"Point"}
}
