{
  "type": "Feature",
  "properties": {
    "date:cessation_lower": "2020-08-07",
    "date:cessation_upper": "2020-08-07",
    "date:inception_lower": "2020-08-07",
    "date:inception_upper": "2020-08-07",
    "instagram:post": {
      "caption": {
        "body": "What was happening #onthisday in 1970 at the airport? This photograph taken by Marshall Moxom shows the entrance road and directional signs at San Francisco International Airport. Following the construction of the International Terminal, the entrance to the airport looks much different now. Do you remember this entrance?   Image: San Francisco International Airport (SFO), approach roads, 1970. SFO Museum Collections. 2011.032.2130",
        "excerpt": "What was happening #onthisday in 1970 at the airport?",
        "hashtags": [
          "FBF",
          "FlashbackFriday",
          "SFOHistory",
          "SFO",
          "MuseumFromHome"
        ]
      },
      "media_id": "ca0f8b14a97749c816793fe9a0a93bf7",
      "path": "media/other/117117434_1240453432964108_7051570958224789263_n_17868360889928604.jpg",
      "perceptual_hash": "p:c917562f99f68816",
      "taken": 1596815700,
      "taken_at": "Aug 07, 2020 3:55 pm"
    },
    "sfomuseum:placetype": "instagram",
    "wof:name": "What was happening #onthisday in 1970 at the airport?..",
    "wof:placetype": "custom",
    "wof:placetype_alt": [
      "instagram"
    ]
  },
  "geometry": {"coordinates":[-122.386166,37.616356],"type":"Point"}
}
