{
  "type": "Feature",
  "properties": {
    "date:cessation_lower": "2019-10-23",
    "date:cessation_upper": "2019-10-23",
    "date:inception_lower": "2019-10-23",
    "date:inception_upper": "2019-10-23",
    "instagram:post": {
      "caption": {
        "body": "Zuber et Cie currently produces fourteen scenic wallpaper sets using original antique printing blocks. It often takes more than one thousand blocks to create a scenic paper set. For instance, if there are several colors on one leaf in a scenic paper, each color is applied with a separate woodblock by hand. Printing blocks were created in layers in order to prevent the blocks from warping. Whitewood or pine was used underneath, and sycamore or pear tree wood was preferred as the top carved layer due to the fineness of the grain. “Zuber: The Art of French Scenic Wallpaper” is on display, pre-security in the International Terminal. http://bit.ly/ZuberScenicWallpaper",
        "excerpt": "Zuber et Cie currently produces fourteen scenic wallpaper sets using original antique printing blocks.",
        "hashtags": [
          "ZuberScenicWallpaper",
          "wallpaper",
          "zuber",
          "scenicwallpaper",
          "interiordesign",
          "museum",
          "design"
        ],
        "users": [
          "ZuberOfficial"
        ]
      },
      "media_id": "64d5a6f95ee553004d37aa58b5d7040f",
      "path": "media/posts/201910/73282018_122660352132027_5601453178590293191_n_17868613282496768.jpg",
      "perceptual_hash": "p:edec52668c1c8ed8",
      "taken": 1571850240,
      "taken_at": "Oct 23, 2019, 5:04 PM"
    },
    "sfomuseum:placetype": "instagram",
    "wof:name": "Zuber et Cie currently produces fourteen scenic wallpaper sets using original antique printing blocks...",
    "wof:placetype": "custom",
    "wof:placetype_alt": [
      "instagram"
    ]
  },
  "geometry": {"coordinates":[-122.386166,37.616356],"type":"Point"}
}
