{
  "type": "Feature",
  "properties": {
    "date:cessation_lower": "2017-01-09",
    "date:cessation_upper": "2017-01-09",
    "date:inception_lower": "2017-01-09",
    "date:inception_upper": "2017-01-09",
    "instagram:post": {
      "caption": {
        "body": "“Artists frequently try to use old techniques on a new medium. I tried to discover the possibilities within the medium itself.” – Zahara Schatz  Trained as a painter, Zahara Schatz (1916–99) translated modern art into laminated plastics. In her Berkeley studio, she created two-dimensional “planar layered paintings,” molded sculpture, lighting, jewelry, and architectural elements in translucent Plexiglas. This aircraft-surplus plastic was readily available after the Second World War, and offered fantastic optical clarity for exploration in color and reflection. Her artwork plays upon viewing angles and varying sources of light, changing in appearance with movement of perspective and illumination.",
        "excerpt": "“Artists frequently try to use old techniques on a new medium.",
        "hashtags": [
          "midcentury",
          "modern",
          "design",
          "ZaharaSchatz"
        ]
      },
      "location": "San Francisco International Airport (SFO)",
      "media_id": "4198c460fe4e7b530d65f76f58c5dc47",
      "path": "photos/201701/4198c460fe4e7b530d65f76f58c5dc47.jpg",
      "perceptual_hash": "p:85d3561e4bc43d39",
      "taken": 1483961520,
      "taken_at": "Jan 9, 2017, 11:32 AM"
    },
    "sfomuseum:placetype": "instagram",
    "wof:name": "“Artists frequently try to use old techniques on a new medium...",
    "wof:placetype": "custom"
  },
  "geometry": {"coordinates":[-122.386166,37.616356],"type":"Point"}
}
