{
  "type": "Feature",
  "properties": {
    "instagram:post": {
      "caption": {
        "body": "American carved stone books first appeared around 1860. Stonecutters, many of whom worked in gravestone shops, created these intriguing items in their leisure hours. Stone books, usually carved in a closed position, are small, typically three- to six-inches in height. Marble, especially white, was used most often because it was readily available and easily carved. Given to loved ones as gifts, stone books typically served as objects of remembrance. Makers embellished books with a variety of religious and secular inscriptions and imagery-both incised or carved in relief. Some recurring motifs include crosses, clasped hands, hearts, horseshoes, and lambs.  Books courtesy of the collection Ian Berke. See \"#AmericanFolkArt: An Enduring Legacy\", on display, pre-security, in the International Terminal. http://bit.ly/AmericanFolkArt",
        "excerpt": "American carved stone books first appeared around 1860.",
        "hashtags": [
          "AmericanFolkArt", 
          "folkart", 
          "stonebooks", 
          "american", 
          "history", 
          "americana", 
          "folkartdesign", 
          "folkarts", 
          "folkartantiques", 
          "folkartantique", 
          "marble", 
          "carving", 
          "stonecutters", 
          "stonecutter", 
          "stone", 
          "book"
        ]
      },
      "media_id": "5c613a554585bf60bca734ff582564d4",
      "path": "photos/201802/5c613a554585bf60bca734ff582564d4.jpg",
      "taken": 1518837305,
      "taken_at": "2018-02-17T03:15:05+00:00"
    },
    "sfomuseum:placetype": "instagram",
    "wof:name": "American carved stone books first appeared around 1860...",
    "wof:placetype": "custom"
  },
  "geometry": {"coordinates":[-122.386166,37.616356],"type":"Point"}
}
