{
  "type": "Feature",
  "properties": {
    "date:cessation_lower": "2012-07-30",
    "date:cessation_upper": "2012-07-30",
    "date:inception_lower": "2012-07-30",
    "date:inception_upper": "2012-07-30",
    "instagram:post": {
      "caption": {
        "body": "1960s Southwestern U.S. brooch packs a punch of enameled color!",
        "excerpt": "1960s Southwestern U.S. brooch packs a punch of enameled color!"
      },
      "media_id": "0fc99040b4701e31df01097379e1d805",
      "path": "photos/201207/0fc99040b4701e31df01097379e1d805.jpg",
      "perceptual_hash": "p:82b836c21b9d6de5",
      "taken": 1343653980,
      "taken_at": "Jul 30, 2012, 1:13 PM"
    },
    "sfomuseum:placetype": "instagram",
    "wof:name": "1960s Southwestern U.S. brooch packs a punch of enameled color!..",
    "wof:placetype": "custom"
  },
  "geometry": {"coordinates":[-122.386166,37.616356],"type":"Point"}
}
