{
  "type": "Feature",
  "properties": {
    "date:cessation_lower": "2018-08-28",
    "date:cessation_upper": "2018-08-28",
    "date:inception_lower": "2018-08-28",
    "date:inception_upper": "2018-08-28",
    "instagram:post": {
      "caption": {
        "body": "A sandwich? A ketchup bottle? Gumby? All of the items in this case are radios! See more radios in \"On the Radio\" on display, post-security, in Terminal 3. http://bit.ly/RadioSFO",
        "excerpt": "A sandwich?",
        "hashtags": [
          "radioSFO",
          "ontheradio",
          "radio",
          "radios",
          "wireless",
          "vintage",
          "antique",
          "vintageradios",
          "transistorradio",
          "portableradio",
          "retroradio",
          "retro"
        ]
      },
      "media_id": "57d0374835208ff8e6eb92c4f4579e38",
      "path": "media/other/37143814_645240012543671_806225684274872320_n_17900901247227220.jpg",
      "perceptual_hash": "p:efa08e4dd02ea45b",
      "taken": 1535449740,
      "taken_at": "Aug 28, 2018 9:49 am"
    },
    "sfomuseum:placetype": "instagram",
    "wof:name": "A sandwich?..",
    "wof:placetype": "custom",
    "wof:placetype_alt": [
      "instagram"
    ]
  },
  "geometry": {"coordinates":[-122.386166,37.616356],"type":"Point"}
}
