{
  "type": "Feature",
  "properties": {
    "instagram:post": {
      "caption": {
        "body": "A sandwich? A ketchup bottle? Gumby? All of the items in this case are radios! See more radios in \"On the Radio\" on display, post-security, in Terminal 3. http://bit.ly/RadioSFO",
        "excerpt": "A sandwich?",
        "hashtags": [
          "radioSFO", 
          "ontheradio", 
          "radio", 
          "radios", 
          "wireless", 
          "vintage", 
          "antique", 
          "vintageradios", 
          "transistorradio", 
          "portableradio", 
          "retroradio", 
          "retro"
        ]
      },
      "media_id": "57d0374835208ff8e6eb92c4f4579e38",
      "path": "photos/201808/57d0374835208ff8e6eb92c4f4579e38.jpg",
      "taken": 1535478581,
      "taken_at": "2018-08-28T17:49:41+00:00"
    },
    "sfomuseum:placetype": "instagram",
    "wof:name": "A sandwich?..",
    "wof:placetype": "custom"
  },
  "geometry": {"coordinates":[-122.386166,37.616356],"type":"Point"}
}
