{
  "type": "Feature",
  "properties": {
    "instagram:post": {
      "caption": {
        "body": "Maria Longworth Nichols (1849–1932) founded Rookwood Pottery in Cincinnati, Ohio, in 1880. Before long, it became the largest and most influential pottery in the country. Longworth named the pottery after the country estate of her father, Joseph Longworth, who also provided the funds to establish the pottery. The pottery incorporated a variety of themes, such as Asian and floral motifs. Rookwood produced large numbers of ceramics in the Arts and Crafts, Art Nouveau, and later Art Deco styles. In addition to hand-painted decoration, many of its Arts and Crafts-style pieces were carved and decorated with plants, flowers, and sea creatures and feature bright, thick glazes. The pottery sold wares at its Cincinnati showroom and at department stores throughout the country.  Ceramics courtesy of Kris Steensma. Learn more about #ArtsandCrafts in \"At Home with #ArtsandCrafts\" on display pre-security, in the International Terminal. http://bit.ly/SFOArtsandCrafts",
        "hashtags": [
          "sfoartsandcrafts", 
          "artsandcraftsmovement", 
          "artsandcraftsstyle", 
          "craftsmanstyle", 
          "craftsmanhome", 
          "bungalowstyle", 
          "rookwood", 
          "rookwoodpottery", 
          "ceramics", 
          "floral", 
          "artdeco", 
          "ohio", 
          "cincinnati", 
          "MariaLongworthNichols", 
          "JosephLongworth", 
          "womeninart"
        ]
      },
      "media_id": "e917c7ff63c9aff68447ce91aac98468",
      "path": "photos/201710/e917c7ff63c9aff68447ce91aac98468.jpg",
      "taken": 1507076948,
      "taken_at": "2017-10-04T00:29:08+00:00"
    },
    "sfomuseum:placetype": "instagram",
    "wof:name": "Instagram message #%!d(string=e917c7ff63c9aff68447ce91aac98468)",
    "wof:placetype": "custom"
  },
  "geometry": {"coordinates":[-122.386166,37.616356],"type":"Point"}
}
