{
  "type": "Feature",
  "properties": {
    "date:cessation_lower": "2019-04-11",
    "date:cessation_upper": "2019-04-11",
    "date:inception_lower": "2019-04-11",
    "date:inception_upper": "2019-04-11",
    "instagram:post": {
      "caption": {
        "body": "As commercial aviation advanced in the 1920s and ‘30s, manuals for airliners were separated into flight operations and maintenance categories. Eastern Air Lines was a major operator of the Douglas DC-2 and DC-3 in the 1930s and provided maintenance crews with manuals that included data on the airframe, lubrication, brakes, the electrical system, instruments, engines, the oil system, landing gear, and fuel systems. After World War II,  larger, multi-engine airliners enabled the rapid growth of the airline industry. These aircraft were more demanding to fly and required large crews to operate them and rigorous maintenance schedules. The number of airliner manuals and the complexity of their content grew to voluminous levels. With the arrival of the jet fleets by the late 1950s, more manuals with new types of information were issued. “By the Book: Airliner Flight, Maintenance, and Training Manuals” is on display, pre-security, in the Aviation Museum and Library in the International Terminal. . . .",
        "excerpt": "As commercial aviation advanced in the 1920s and ‘30s, manuals for airliners were separated into flight operations and maintenance categories.",
        "hashtags": [
          "ByTheBook",
          "modelairplane",
          "design",
          "library",
          "avgeek",
          "book"
        ]
      },
      "media_id": "3bd96013e56e66abc94f4969ca4b903d",
      "path": "media/posts/201904/55827168_605929629908045_5078635416952096375_n_18046145047072183.jpg",
      "perceptual_hash": "p:bae0b497962c899d",
      "taken": 1555009080,
      "taken_at": "Apr 11, 2019, 6:58 PM"
    },
    "sfomuseum:placetype": "instagram",
    "wof:name": "As commercial aviation advanced in the 1920s and ‘30s, manuals for airliners were separated into flight operations and maintenance categories...",
    "wof:placetype": "custom"
  },
  "geometry": {"coordinates":[-122.386166,37.616356],"type":"Point"}
}
