{
  "type": "Feature",
  "properties": {
    "instagram:post": {
      "caption": {
        "body": "Did you know that in the 1960s you could fill out mail order forms for flight bags while in the air? The flight bag was featured in airline advertising and promotions, and ordering forms such as this one were included in in-flight information packets. This new type of hand luggage, with its vivid graphics, became a chic and desirable status symbol that identified its user as a member of the new globe-trotting jet set.  Images:  American Airlines flight information packet, 1960. Gift of Thomas G. Dragges, 2015.165.263 e American Airlines airline bag, 1960s. SFO Museum Collection 2010.142.001",
        "hashtags": [
          "avgeek", 
          "aviationhistory", 
          "jetset", 
          "1950s", 
          "1960s", 
          "carryon", 
          "flightbag", 
          "americanairlines", 
          "americanair", 
          "handluggage", 
          "paxex", 
          "jetage"
        ]
      },
      "media_id": "fa19eee6be819b741dd5d008353069a8",
      "path": "photos/201706/fa19eee6be819b741dd5d008353069a8.jpg",
      "taken": 1497322832,
      "taken_at": "2017-06-13T03:00:32+00:00"
    },
    "sfomuseum:placetype": "instagram",
    "wof:name": "Instagram message #%!d(string=fa19eee6be819b741dd5d008353069a8)",
    "wof:placetype": "custom"
  },
  "geometry": {"coordinates":[-122.386166,37.616356],"type":"Point"}
}
