{
  "type": "Feature",
  "properties": {
    "date:cessation_lower": "2019-08-18",
    "date:cessation_upper": "2019-08-18",
    "date:inception_lower": "2019-08-18",
    "date:inception_upper": "2019-08-18",
    "instagram:post": {
      "caption": {
        "body": "The Urban School is an independent high school in San Francisco whose mission is to ignite a passion for learning and to inspire students to become self-motivated, enthusiastic participants in their education, both in high school and beyond.  During the 2018/2019 academic year, student photographers at the Urban School completed a long-term project where they engaged with and reflected upon the contemporary landscape through their perspective as young adults living in the Bay Area. At the beginning of the project, students visited This Land, an exhibition at Pier 24 Photography, an institution in San Francisco that houses the permanent collection of the Pilara Foundation and is dedicated to collecting, preserving, and exhibiting photography. Using This Land as inspiration, students studied the artists exhibited at Pier 24 Photography during the course of the semester while developing their own projects and visual interpretation of “this land.”",
        "excerpt": "The Urban School is an independent high school in San Francisco whose mission is to ignite a passion for learning and to inspire students to become self-motivated, enthusiastic participants in their education, both in high school and beyond.",
        "hashtags": [
          "StudentArt",
          "UrbanSchool",
          "ThisLand",
          "photography",
          "highschool"
        ]
      },
      "media_id": "5d789ddbda0d3415a359608ada5eea07",
      "path": "photos/201908/5d789ddbda0d3415a359608ada5eea07.jpg",
      "perceptual_hash": "p:afb4c04bf462e331",
      "taken": 1566152828,
      "taken_at": "2019-08-18T18:27:08+00:00"
    },
    "sfomuseum:placetype": "instagram",
    "wof:name": "The Urban School is an independent high school in San Francisco whose mission is to ignite a passion for learning and to inspire students to become self-motivated, enthusiastic participants in their education, both in high school and beyond...",
    "wof:placetype": "custom"
  },
  "geometry": {"coordinates":[-122.386166,37.616356],"type":"Point"}
}
