{
  "type": "Feature",
  "properties": {
    "instagram:post": {
      "caption": {
        "body": "Happy Pride to all those flying in for the weekend festivities. If coming in through SFO, stop by the Museum’s Video Arts space in the International Terminal Main Hall to view any of our four fabulous LGBTQ-themed shorts in celebration of Pride. “Red” by Yuchao Feng, “I Have Something To Tell You” by Ben Joyner and Dumaine Babcock, “Fifteen” by AJ Baldwin, “Hope” by Alex Bohs are all now playing. Celebrate all the colors of the rainbow this weekend at SF Pride.  See \"Hope\" by Alex Bohs, now playing in the Video Arts Room located pre-security in the International Terminal. http://bit.ly/2RCCGJ0",
        "hashtags": [
          "VideoArtsSFOM", 
          "film", 
          "video", 
          "pride", 
          "pridemonth", 
          "pride2019", 
          "wlw", 
          "mlm"
        ]
      },
      "location": "San Francisco International Airport (SFO)",
      "media_id": "b0021ea247db180c6cb38aecc6e2023d",
      "path": "photos/201906/b0021ea247db180c6cb38aecc6e2023d.jpg",
      "taken": 1561667478,
      "taken_at": "2019-06-27T20:31:18+00:00"
    },
    "sfomuseum:placetype": "instagram",
    "wof:name": "Instagram message #%!d(string=b0021ea247db180c6cb38aecc6e2023d)",
    "wof:placetype": "custom"
  },
  "geometry": {"coordinates":[-122.386166,37.616356],"type":"Point"}
}
