{
  "type": "Feature",
  "properties": {
    "instagram:post": {
      "caption": {
        "body": "Does a California vacation fit your plans and pocketbook this summer? The 1955 prices would surely fit anyone’s! In 1955, a four-day stay in San Francisco cost $26.78 and a fifteen-day stay including a hotel was $144.55!  United Air Lines advertisement, National Geographic c. 1955 SFO Museum Collection Gift of Thomas G. Dragges, in memory of Robert May 2001.109.296",
        "excerpt": "Does a California vacation fit your plans and pocketbook this summer?"
      },
      "location": "San Francisco International Airport (SFO)",
      "media_id": "590d95156b9da8b811f817a19969765d",
      "path": "photos/201607/590d95156b9da8b811f817a19969765d.jpg",
      "taken": 1467396780,
      "taken_at": "2016-07-01T18:13:00+00:00"
    },
    "sfomuseum:placetype": "instagram",
    "wof:name": "Does a California vacation fit your plans and pocketbook this summer?..",
    "wof:placetype": "custom"
  },
  "geometry": {"coordinates":[-122.386166,37.616356],"type":"Point"}
}
