{
  "type": "Feature",
  "properties": {
    "date:cessation_lower": "2023-04-20",
    "date:cessation_upper": "2023-04-20",
    "date:inception_lower": "2023-04-20",
    "date:inception_upper": "2023-04-20",
    "instagram:post": {
      "caption": {
        "body": "In 2015, SFO Museum presented “I Love You, California: A Natural History.” California has the greatest diversity of natural areas, flora, and fauna species in North America. Around 6,000 species of the plants grow in California and within 160,000 square miles, huge variations in animal life thrive in the country’s third largest state. California also has an abundance of protected and preserved public use lands and national parks such as the Channel Islands, Point Reyes National Seashore, Joshua Tree, Yosemite, and Lassen Volcanic National Parks. Sequoia and Kings Canyon National Park contains many of the oldest trees on Earth and is home to the largest living single organism by volume—the General Sherman, a giant sequoia believed to be about 2,500-years old. The tree is 275 feet tall and 102 feet in circumference.   Relive the exhibition in our online at: http://bit.ly/40Wf5pH",
        "excerpt": "In 2015, SFO Museum presented “I Love You, California: A Natural History.” California has the greatest diversity of natural areas, flora, and fauna species in North America.",
        "hashtags": [
          "EarthMonth",
          "TBT",
          "ThrowbackThursday",
          "ILoveYouCA"
        ]
      },
      "media_id": "ae34f4be76ce20e4a6c297d0e98a236b5d3d5db1",
      "path": "media/posts/202304/342034576_244741748125957_5186639231625600351_n_17962975556414024.jpg",
      "perceptual_hash": "p:ef903ba517c09ca3",
      "taken": 1682007540,
      "taken_at": "Apr 20, 2023, 4:19 PM"
    },
    "sfomuseum:placetype": "instagram",
    "wof:name": "In 2015, SFO Museum presented “I Love You, California: A Natural History.” California has the greatest diversity of natural areas, flora, and fauna species in North America...",
    "wof:placetype": "custom"
  },
  "geometry": {"coordinates":[-122.386166,37.616356],"type":"Point"}
}
