{
  "type": "Feature",
  "properties": {
    "date:cessation_lower": "2018-07-06",
    "date:cessation_upper": "2018-07-06",
    "date:inception_lower": "2018-07-06",
    "date:inception_upper": "2018-07-06",
    "instagram:post": {
      "caption": {
        "body": "As the perspective from the window of Gwyneth Leech’s studio shifts with the construction of a high-rise hotel, so too do the artist’s point of view and her art, which reflect an unexpected appreciation for the beauty in this transformation. See \"The Monolith\" by Angelo J. Guglielmo, Jr., now playing in the Video Arts gallery, located pre-security in the International Terminal. http://bit.ly/2tNokuT",
        "excerpt": "As the perspective from the window of Gwyneth Leech’s studio shifts with the construction of a high-rise hotel, so too do the artist’s point of view and her art, which reflect an unexpected appreciation for the beauty in this transformation.",
        "hashtags": [
          "VideoArtsSFOM",
          "video",
          "film",
          "NewYork",
          "construction",
          "painting",
          "artist",
          "buiding",
          "hotel",
          "transformation",
          "build",
          "newyorkcity",
          "nyc"
        ]
      },
      "file_hash": "ba75b189187e98e3a036d25c8a1dab83ab0865a5f686b0fc11594ff8918d9ad9",
      "media_id": "bec7183bc3d9f32c3b847bb2927ab3e23301fd5d",
      "path": "media/posts/201807/36194755_2284449351573053_6315036252432202271_n_17930613403148811.mp4",
      "taken": 1530872160,
      "taken_at": "Jul 6, 2018, 10:16 AM"
    },
    "sfomuseum:placetype": "instagram",
    "wof:name": "As the perspective from the window of Gwyneth Leech’s studio shifts with the construction of a high-rise hotel, so too do the artist’s point of view and her art, which reflect an unexpected appreciation for the beauty in this transformation...",
    "wof:placetype": "custom"
  },
  "geometry": {"coordinates":[-122.386166,37.616356],"type":"Point"}
}
