{
  "type": "Feature",
  "properties": {
    "date:cessation_lower": "2019-03-15",
    "date:cessation_upper": "2019-03-15",
    "date:inception_lower": "2019-03-15",
    "date:inception_upper": "2019-03-15",
    "instagram:post": {
      "caption": {
        "body": "Filmmaker Olivier Bernier profiles professional trash collector Nick DiMola who, in the process of clearing material from the homes of the deceased, retains those items he finds meaningful, offering insights into the people who once possessed them.  See \"A Garbage Story” by Olivier Bernier, now playing in the Video Arts Room located pre-security in the International Terminal. https://www.flysfo.com/museum/video-arts/garbage-story",
        "excerpt": "Filmmaker Olivier Bernier profiles professional trash collector Nick DiMola who, in the process of clearing material from the homes of the deceased, retains those items he finds meaningful, offering insights into the people who once possessed them.",
        "hashtags": [
          "VideoArtsSFOM",
          "film",
          "video",
          "OlivierBernier",
          "NickDiMola",
          "trash",
          "treasure",
          "garbage"
        ]
      },
      "file_hash": "248ea32c7a4daa2de13bc00ce17afc9eff4d17897dd1a7e70a1ee4c553b6c023",
      "media_id": "73f418294b2ea087ab9a4218b3f6a4479ba186da",
      "path": "media/other/C34200C78D12A67843D7AF4EB77878B1_video_dashinit_18018589786140446.mp4",
      "taken": 1552667460,
      "taken_at": "Mar 15, 2019 4:31 pm"
    },
    "sfomuseum:placetype": "instagram",
    "wof:name": "Filmmaker Olivier Bernier profiles professional trash collector Nick DiMola who, in the process of clearing material from the homes of the deceased, retains those items he finds meaningful, offering insights into the people who once possessed them...",
    "wof:placetype": "custom"
  },
  "geometry": {"coordinates":[-122.386166,37.616356],"type":"Point"}
}
