{
  "type": "Feature",
  "properties": {
    "instagram:post": {
      "caption": {
        "body": "From coast to coast, regions of North America developed distinctive types of hand-carved duck decoys. Master craftsmen created local styles that were passed on through generations of carvers. Artisans also brought their own individual creativity to the birds they crafted, making each one unique. Carvers made some decoys to appear sleeping, preening, or with their heads tucked low into their bodies as if resting.  Duck decoy courtesy of the collection Paul A. Mazzilli. See \"#AmericanFolkArt: An Enduring Legacy\", on display, pre-security, in the International Terminal. http://bit.ly/AmericanFolkArt",
        "hashtags": [
          "AmericanFolkArt", 
          "folkart", 
          "american", 
          "history", 
          "americana", 
          "folkartfun", 
          "antique", 
          "vintage", 
          "antiquefolkart", 
          "vintagefolkart", 
          "design", 
          "folkartdesign", 
          "folkarts", 
          "folkartantiques", 
          "folkartantique", 
          "duckdecoys"
        ]
      },
      "location": "San Francisco International Airport (SFO)",
      "media_id": "c3bc3329573bd81ddc064c18a166cc7e",
      "path": "photos/201803/c3bc3329573bd81ddc064c18a166cc7e.jpg",
      "taken": 1519954070,
      "taken_at": "2018-03-02T01:27:50+00:00"
    },
    "sfomuseum:placetype": "instagram",
    "wof:name": "Instagram message #%!d(string=c3bc3329573bd81ddc064c18a166cc7e)",
    "wof:placetype": "custom"
  },
  "geometry": {"coordinates":[-122.386166,37.616356],"type":"Point"}
}
