{
  "type": "Feature",
  "properties": {
    "date:cessation_lower": "2015-05-29",
    "date:cessation_upper": "2015-05-29",
    "date:inception_lower": "2015-05-29",
    "date:inception_upper": "2015-05-29",
    "instagram:post": {
      "caption": {
        "hashtags": [
          "JoseffOfHollywood",
          "jewelry",
          "design"
        ]
      },
      "media_id": "ecf9cc9b0beeb7084a263dd3e972de3c",
      "path": "photos/201505/ecf9cc9b0beeb7084a263dd3e972de3c.jpg",
      "perceptual_hash": "p:be3e1e1d8f190626",
      "taken": 1432914420,
      "taken_at": "May 29, 2015, 3:47 PM"
    },
    "sfomuseum:placetype": "instagram",
    "wof:name": "..",
    "wof:placetype": "custom"
  },
  "geometry": {"coordinates":[-122.386166,37.616356],"type":"Point"}
}
