{
  "type": "Feature",
  "properties": {
    "instagram:post": {
      "caption": {
        "body": "Famed industrial designer Raymond Loewy (1893–1986) designed and styled everything from Studebaker cars to refrigerators, corporate logos, and the NASA Skylab. Loewy oversaw the first redesign of the iconic Coca-Cola bottle in 1954, in a “slenderized” version with bright, white lettering to stand out in vending machines.  All objects are from the collection of Steve Cabella. See more #midcentury #modern #design in \"#AModernApproach: Mid-Century Design\", on display, pre-security, in the International Terminal. http://bit.ly/AModernApproach ",
        "hashtags": [
          "design", 
          "RaymondLoewy", 
          "industrialdesign", 
          "cocacola", 
          "sodaorpop"
        ]
      },
      "media_id": "2b22f94a784ef1979d27ab9e372ab5ec",
      "path": "photos/201703/2b22f94a784ef1979d27ab9e372ab5ec.jpg",
      "taken": 1490928290,
      "taken_at": "2017-03-31T02:44:50+00:00"
    },
    "sfomuseum:placetype": "instagram",
    "wof:name": "Instagram message #%!d(string=2b22f94a784ef1979d27ab9e372ab5ec)",
    "wof:placetype": "custom"
  },
  "geometry": {"coordinates":[-122.386166,37.616356],"type":"Point"}
}
