{
  "type": "Feature",
  "properties": {
    "date:cessation_lower": "2017-03-30",
    "date:cessation_upper": "2017-03-30",
    "date:inception_lower": "2017-03-30",
    "date:inception_upper": "2017-03-30",
    "instagram:post": {
      "caption": {
        "body": "Famed industrial designer Raymond Loewy (1893–1986) designed and styled everything from Studebaker cars to refrigerators, corporate logos, and the NASA Skylab. Loewy oversaw the first redesign of the iconic Coca-Cola bottle in 1954, in a “slenderized” version with bright, white lettering to stand out in vending machines.  All objects are from the collection of Steve Cabella. See more #midcentury #modern #design in \"#AModernApproach: Mid-Century Design\", on display, pre-security, in the International Terminal. http://bit.ly/AModernApproach ",
        "excerpt": "Famed industrial designer Raymond Loewy (1893–1986) designed and styled everything from Studebaker cars to refrigerators, corporate logos, and the NASA Skylab.",
        "hashtags": [
          "design",
          "RaymondLoewy",
          "industrialdesign",
          "cocacola",
          "sodaorpop"
        ]
      },
      "media_id": "2b22f94a784ef1979d27ab9e372ab5ec",
      "path": "media/posts/201703/17662880_1788241034825487_7484425252848533504_n_17875397701001207.jpg",
      "perceptual_hash": "p:ad24a75b57ec2238",
      "taken": 1490899440,
      "taken_at": "Mar 30, 2017 6:44 pm"
    },
    "sfomuseum:placetype": "instagram",
    "wof:name": "Famed industrial designer Raymond Loewy (1893–1986) designed and styled everything from Studebaker cars to refrigerators, corporate logos, and the NASA Skylab...",
    "wof:placetype": "custom",
    "wof:placetype_alt": [
      "instagram"
    ]
  },
  "geometry": {"coordinates":[-122.386166,37.616356],"type":"Point"}
}
