{
  "type": "Feature",
  "properties": {
    "instagram:post": {
      "caption": {
        "body": "Based in Charlotte, North Carolina, the Carolina #Panthers are going head-to-head with the Denver #Broncos this Sunday at Super Bowl 50! After home game wins, the Panthers fans in the stadium serenade the team with a boisterous version of Neil Diamond’s Sweet Caroline. Have you ever been to North Carolina? #TravelTuesday #SuperBowl50 #SB50  Delta Air Lines, North Carolina playing cards 1969 SFO Museum Collection Gift of Thomas G. Dragges 2010.104.342"
      },
      "location": "San Francisco International Airport (SFO)",
      "media_id": "7efd83386f5a0d2cd66f83e4014aca5c",
      "path": "photos/201602/7efd83386f5a0d2cd66f83e4014aca5c.jpg",
      "taken": 1454465440,
      "taken_at": "2016-02-03T02:10:40+00:00"
    },
    "sfomuseum:placetype": "instagram",
    "wof:name": "Instagram message #%!d(string=7efd83386f5a0d2cd66f83e4014aca5c)",
    "wof:placetype": "custom"
  },
  "geometry": {"coordinates":[-122.386166,37.616356],"type":"Point"}
}
