{
  "type": "Feature",
  "properties": {
    "date:cessation_lower": "2016-02-02",
    "date:cessation_upper": "2016-02-02",
    "date:inception_lower": "2016-02-02",
    "date:inception_upper": "2016-02-02",
    "instagram:post": {
      "caption": {
        "body": "Based in Charlotte, North Carolina, the Carolina #Panthers are going head-to-head with the Denver #Broncos this Sunday at Super Bowl 50! After home game wins, the Panthers fans in the stadium serenade the team with a boisterous version of Neil Diamond’s Sweet Caroline. Have you ever been to North Carolina? #TravelTuesday #SuperBowl50 #SB50  Delta Air Lines, North Carolina playing cards 1969 SFO Museum Collection Gift of Thomas G. Dragges 2010.104.342",
        "excerpt": "Based in Charlotte, North Carolina, the Carolina #Panthers are going head-to-head with the Denver #Broncos this Sunday at Super Bowl 50!"
      },
      "media_id": "7efd83386f5a0d2cd66f83e4014aca5c",
      "path": "media/posts/201602/12407408_1062282343811295_234995454_n_17844190519112390.jpg",
      "perceptual_hash": "p:95ccc33b963c4993",
      "taken": 1454436600,
      "taken_at": "Feb 2, 2016, 6:10 PM"
    },
    "sfomuseum:placetype": "instagram",
    "wof:name": "Based in Charlotte, North Carolina, the Carolina #Panthers are going head-to-head with the Denver #Broncos this Sunday at Super Bowl 50!..",
    "wof:placetype": "custom"
  },
  "geometry": {"coordinates":[-122.386166,37.616356],"type":"Point"}
}
