{
  "type": "Feature",
  "properties": {
    "date:cessation_lower": "2015-06-05",
    "date:cessation_upper": "2015-06-05",
    "date:inception_lower": "2015-06-05",
    "date:inception_upper": "2015-06-05",
    "instagram:post": {
      "caption": {
        "hashtags": [
          "HaroldAllen",
          "EgyptianRevival",
          "architecture",
          "pyramid"
        ]
      },
      "media_id": "c9c52e1d1b7b52a499432a32da8a6521",
      "path": "photos/201506/c9c52e1d1b7b52a499432a32da8a6521.jpg",
      "perceptual_hash": "p:a438d867a790f167",
      "taken": 1433541541,
      "taken_at": "2015-06-05T21:59:01+00:00"
    },
    "sfomuseum:placetype": "instagram",
    "wof:name": "..",
    "wof:placetype": "custom"
  },
  "geometry": {"coordinates":[-122.386166,37.616356],"type":"Point"}
}
