{
  "type": "Feature",
  "properties": {
    "date:cessation_lower": "2024-07-04",
    "date:cessation_upper": "2024-07-04",
    "date:inception_lower": "2024-07-04",
    "date:inception_upper": "2024-07-04",
    "instagram:post": {
      "caption": {
        "body": "The Boeing 747SP (Special Performance) took off on its maiden flight on July 4, 1975. Featuring a shorter fuselage, the 747SP was introduced by Pan American in 1976. Pan American specifically requested the 747SP as it offered longer range, increased speed, and was capable of using shorter runways. Two record-breaking inaugural flights marked the first use of Pan Am's new Boeing B747SP (Special Performance) jetliner on April 25 and 26, 1976. At the time of production, it had the longest range of any commercial aircraft, able to fly non-stop from New York to Tokyo - a distance of 6,916 miles - in 13 hours, 40 minutes.  photograph: Pan American World Airways, Boeing 747SP; c. 1976 Gift of the Estate of Fred Nott 2004.016.120.010",
        "excerpt": "The Boeing 747SP (Special Performance) took off on its maiden flight on July 4, 1975.",
        "hashtags": [
          "AvGeek"
        ]
      },
      "media_id": "003144091aeaf77ee009d2bd0076ce9ff9629928",
      "path": "media/other/449875352_459676840309003_1678055437565641445_n_18041276662740152.jpg",
      "perceptual_hash": "p:aec5c97ab44ec132",
      "taken": 1720099140,
      "taken_at": "Jul 04, 2024 1:19 pm"
    },
    "sfomuseum:placetype": "instagram",
    "wof:name": "The Boeing 747SP (Special Performance) took off on its maiden flight on July 4, 1975...",
    "wof:placetype": "custom"
  },
  "geometry": {"coordinates":[-122.386166,37.616356],"type":"Point"}
}
