{
  "type": "Feature",
  "properties": {
    "instagram:post": {
      "caption": {
        "body": "In addition to showing the interior of a Douglas DC-3, this United Air Lines promotional print from the 1940s states: “This picture shows the inside of the cabin of a Mainliner. Passengers travel in comfortable reclining armchairs. Notice the pillows and blankets which passengers may use for their comfort. This picture shows passengers in peace time. In war time, planes carry few civilians but more soldiers, sailors, flyers and others working to win the war.” Image: United Air Lines, Douglas DC-3 interior, c. 1941. Gift of the Captain John B. Russell Family.2012.172.086",
        "excerpt": "In addition to showing the interior of a Douglas DC-3, this United Air Lines promotional print from the 1940s states: “This picture shows the inside of the cabin of a Mainliner.",
        "hashtags": [
          "avgeek", 
          "mainliner", 
          "united", 
          "DC3"
        ]
      },
      "location": "San Francisco International Airport (SFO)",
      "media_id": "f6c2784d8cad45122173cd673389b81d",
      "path": "photos/201910/f6c2784d8cad45122173cd673389b81d.jpg",
      "taken": 1570847511,
      "taken_at": "2019-10-12T02:31:51+00:00"
    },
    "sfomuseum:placetype": "instagram",
    "wof:name": "In addition to showing the interior of a Douglas DC-3, this United Air Lines promotional print from the 1940s states: “This picture shows the inside of the cabin of a Mainliner...",
    "wof:placetype": "custom"
  },
  "geometry": {"coordinates":[-122.386166,37.616356],"type":"Point"}
}
