{
  "type": "Feature",
  "properties": {
    "date:cessation_lower": "2017-07-22",
    "date:cessation_upper": "2017-07-22",
    "date:inception_lower": "2017-07-22",
    "date:inception_upper": "2017-07-22",
    "instagram:post": {
      "caption": {
        "body": "\"Going Abroad?\" asks this early 1950s Air France advertisement. With a colorful illustration of the Arc de Triomphe located in Paris, the advertisement goes on to say \"Enjoy The Last Word in Luxury Air Travel. Fly Air France!\" Image: Air France advertisement, early 1950s. Gift of the Frank J. Lichtanski Collection. 2011.061.1031",
        "excerpt": "\"Going Abroad?\"",
        "hashtags": [
          "vintageadvertisement",
          "avgeek",
          "aviationhistory",
          "vintage",
          "vintagead",
          "airfrance",
          "france",
          "arcdetriomph"
        ]
      },
      "location": "SFO Museum",
      "media_id": "c369c018b9b6da403c51d4e54bf7cad1",
      "path": "photos/201707/c369c018b9b6da403c51d4e54bf7cad1.jpg",
      "perceptual_hash": "p:e566cc9a9a399c38",
      "taken": 1500724560,
      "taken_at": "Jul 22, 2017, 11:56 AM"
    },
    "sfomuseum:placetype": "instagram",
    "wof:name": "\"Going Abroad?\"..",
    "wof:placetype": "custom"
  },
  "geometry": {"coordinates":[-122.386166,37.616356],"type":"Point"}
}
