{
  "type": "Feature",
  "properties": {
    "date:cessation_lower": "2021-08-11",
    "date:cessation_upper": "2021-08-11",
    "date:inception_lower": "2021-08-11",
    "date:inception_upper": "2021-08-11",
    "instagram:post": {
      "caption": {
        "body": "In 1965, SFO Helicopter Airlines, which operated local helicopter flights between San Francisco and Oakland, introduced a new transbay route operated by a hovercraft. The Westland SRN-5 held 15 passengers and traveled at speeds up to 50 knots between Oakland International Airport, downtown San Francisco, and San Francisco International Airport. SFO Helicopter Airlines was the first American company to operate these vehicles. The company claimed that this was the \"world's first commercial Hovercraft Air Cushion Vehicle test.\" However, this trial run of a commercial hovercraft only lasted about a year. Do you remember seeing these hovercrafts?",
        "excerpt": "In 1965, SFO Helicopter Airlines, which operated local helicopter flights between San Francisco and Oakland, introduced a new transbay route operated by a hovercraft.",
        "hashtags": [
          "ThrowbackThursday",
          "SFOHistory"
        ]
      },
      "media_id": "59301150c75e912f5f5073b558b2f504608bf4a1",
      "path": "media/posts/202108/233852182_386237969807720_2945164167670795698_n_18127023733231564.jpg",
      "perceptual_hash": "p:fec1c138b4c3ea19",
      "taken": 1628698260,
      "taken_at": "Aug 11, 2021, 4:11 PM"
    },
    "sfomuseum:placetype": "instagram",
    "wof:name": "In 1965, SFO Helicopter Airlines, which operated local helicopter flights between San Francisco and Oakland, introduced a new transbay route operated by a hovercraft...",
    "wof:placetype": "custom",
    "wof:placetype_alt": [
      "instagram"
    ]
  },
  "geometry": {"coordinates":[-122.386166,37.616356],"type":"Point"}
}
