{
  "type": "Feature",
  "properties": {
    "date:cessation_lower": "2023-12-29",
    "date:cessation_upper": "2023-12-29",
    "date:inception_lower": "2023-12-29",
    "date:inception_upper": "2023-12-29",
    "instagram:post": {
      "caption": {
        "body": "Harold McMillan Bixby, a midwestern businessman with a strong interest in the emerging technology of aviation, worked for Pan American Airways in the 1930s to the 1950s. The Harold Bixby Collection, acquired by SFO Museum in 2019, contains over five hundred photographic prints and negatives collected by Harold Bixby throughout his career.  Some of the photographs were likely taken by Bixby himself, but most were taken by others documenting events and individuals of interest to Bixby. The photographic collection has particularly good representation in three main areas: the aviation scene at Lambert Field in St. Louis in the 1920s, the operations of the China National Aviation Corporation (CNAC) in the 1930s, and the arrival of Pan American’s inaugural transpacific flight in Manila in 1935.   Our photography essay “Unlocking an Archival Treasure: The Harold Bixby Collection, The Photographs” featuring twenty-one highlights from Harold Bixby’s life with Pan American, is on display in the Aviation Museum and Library. The Aviation Museum and Library is located pre-security in the International Terminal and open daily from 10am to 4:30pm.",
        "excerpt": "Harold McMillan Bixby, a midwestern businessman with a strong interest in the emerging technology of aviation, worked for Pan American Airways in the 1930s to the 1950s.",
        "hashtags": [
          "BixbyCollection",
          "PanAm",
          "PAA",
          "AvGeek",
          "HaroldBixby"
        ]
      },
      "media_id": "c4406139824f552a70e85f03706989f64c4ce6d3",
      "path": "media/posts/202312/414673235_841726067964324_8961800739354976974_n_18212841415272871.jpg",
      "perceptual_hash": "p:eec9816e2dd0622f",
      "taken": 1703861160,
      "taken_at": "Dec 29, 2023 2:46 pm"
    },
    "sfomuseum:placetype": "instagram",
    "wof:name": "Harold McMillan Bixby, a midwestern businessman with a strong interest in the emerging technology of aviation, worked for Pan American Airways in the 1930s to the 1950s...",
    "wof:placetype": "custom"
  },
  "geometry": {"coordinates":[-122.386166,37.616356],"type":"Point"}
}
