{
  "type": "Feature",
  "properties": {
    "instagram:post": {
      "caption": {
        "body": "James Chronister approached making “California (1)” by first hiking in the Bodega Bay area of Northern California and taking hundreds of color photos of the terrain. Back at the studio, he searched the many photos to find an image with the perfect balance of movement, rhythm, space, and “an energy akin to music.” Chronister then digitally changed the source photo into black and white, bumped up the contrast, and projected the image onto the canvas. Using a very small brush, he painted with black oil paint directly from the projection, and over the course of a few months, the completed landscape emerged.  See “California (1)” by #JamesChronister online at: https://bit.ly/34gIb6S",
        "hashtags": [
          "publicart", 
          "painting", 
          "MuseumFromHome"
        ]
      },
      "media_id": "f0e21f42dd11adef91e8cbc6eb622609",
      "path": "photos/202010/f0e21f42dd11adef91e8cbc6eb622609.jpg",
      "taken": 1602030876,
      "taken_at": "2020-10-07T00:34:36+00:00"
    },
    "sfomuseum:placetype": "instagram",
    "wof:name": "Instagram message #%!d(string=f0e21f42dd11adef91e8cbc6eb622609)",
    "wof:placetype": "custom"
  },
  "geometry": {"coordinates":[-122.386166,37.616356],"type":"Point"}
}
