{
  "type": "Feature",
  "properties": {
    "instagram:post": {
      "caption": {
        "hashtags": [
          "diamondsonthesolesofhershoes", 
          "1950s", 
          "fashion", 
          "shoes", 
          "plastics"
        ]
      },
      "media_id": "a7821ac3d7aea9a21d1327d8b897716f",
      "path": "photos/201309/a7821ac3d7aea9a21d1327d8b897716f.jpg",
      "taken": 1379440482,
      "taken_at": "2013-09-17T17:54:42+00:00"
    },
    "sfomuseum:placetype": "instagram",
    "wof:name": "..",
    "wof:placetype": "custom"
  },
  "geometry": {"coordinates":[-122.386166,37.616356],"type":"Point"}
}
