{
  "type": "Feature",
  "properties": {
    "date:cessation_lower": "2019-12-19",
    "date:cessation_upper": "2019-12-19",
    "date:inception_lower": "2019-12-19",
    "date:inception_upper": "2019-12-19",
    "instagram:post": {
      "caption": {
        "body": "In his ongoing series, “Solar Transit”, Bryant Austin makes photographs that reveal the sun’s surface in vivid detail while documenting its apparent transit across the California landscape. His process is complex and often requires the use of three separate telescopes equipped with infrared cameras, and a monochrome video camera with scientific lens filters. Seen through the lens of his telescopes, the sun’s presence is heightened and its connection with the landscape becomes tangible—offering us a poignant reminder of our place in the universe, and of a reality that operates on a much larger timescale.  See ”Solar Transit” by #BryantAustin, on display pre-security on the departures level of Terminal 1. http://bit.ly/2rko9Jf",
        "excerpt": "In his ongoing series, “Solar Transit”, Bryant Austin makes photographs that reveal the sun’s surface in vivid detail while documenting its apparent transit across the California landscape.",
        "hashtags": [
          "photography",
          "photographer",
          "yosemite",
          "california",
          "telescopes",
          "camera",
          "solar",
          "sun"
        ],
        "users": [
          "bryant_austin_"
        ]
      },
      "media_id": "b2746106496545f17bd1ac7031a66538",
      "path": "media/posts/201912/73414967_107205174010770_381013379150201311_n_18080083309150797.jpg",
      "perceptual_hash": "p:cccccec6c6636323",
      "taken": 1576777980,
      "taken_at": "Dec 19, 2019, 5:53 PM"
    },
    "sfomuseum:placetype": "instagram",
    "wof:name": "In his ongoing series, “Solar Transit”, Bryant Austin makes photographs that reveal the sun’s surface in vivid detail while documenting its apparent transit across the California landscape...",
    "wof:placetype": "custom"
  },
  "geometry": {"coordinates":[-122.386166,37.616356],"type":"Point"}
}
