{
  "type": "Feature",
  "properties": {
    "date:cessation_lower": "2022-03-24",
    "date:cessation_upper": "2022-03-24",
    "date:inception_lower": "2022-03-24",
    "date:inception_upper": "2022-03-24",
    "instagram:post": {
      "caption": {
        "body": "Air West was branded with an ultramodern service mark in bright interchangeable color combinations of lime green, royal blue, orange, pink, and bronze. Like the multi-color “jelly bean” airplanes of Braniff, the airline’s aircraft liveries featured various combinations of two of these colors. Their stewardesses were outfitted in futuristic, slim-cut, high-fashion ensembles created by Oleg Cassini and reminiscent of uniforms worn in the original Star Trek television series, which was popular at the time.   In 1968, the newly formed Air West had just launched operations when its multi-million dollar computerized reservation system broke down over the busy Fourth of July weekend, causing a public relations fiasco. The incident resulted in a considerable loss of revenue and left the company on the verge of financial ruin. In stepped Howard Hughes, the famous aviator, Hollywood producer, and billionaire mogul, who saw this as an opportunity to use his financial and political power to acquire the troubled airline. Shortly after the sale was completed in 1970, his renamed Hughes Airwest began operations",
        "excerpt": "Air West was branded with an ultramodern service mark in bright interchangeable color combinations of lime green, royal blue, orange, pink, and bronze.",
        "hashtags": [
          "DefunctThursday",
          "AirWest",
          "PacificAirLines",
          "BonanzaAirLines",
          "WestCoastAirlines",
          "avgeek",
          "aviationhistory"
        ]
      },
      "media_id": "9ea17a0c29d0adcf544fccb5063b4a227526f281",
      "path": "media/posts/202203/277148549_3041207942862058_3127189190868260455_n_18209747914125181.jpg",
      "perceptual_hash": "p:95fee038e88fba20",
      "taken": 1648138200,
      "taken_at": "Mar 24, 2022, 4:10 PM"
    },
    "sfomuseum:placetype": "instagram",
    "wof:name": "Air West was branded with an ultramodern service mark in bright interchangeable color combinations of lime green, royal blue, orange, pink, and bronze...",
    "wof:placetype": "custom"
  },
  "geometry": {"coordinates":[-122.386166,37.616356],"type":"Point"}
}
