{
  "type": "Feature",
  "properties": {
    "date:cessation_lower": "2018-09-28",
    "date:cessation_upper": "2018-09-28",
    "date:inception_lower": "2018-09-28",
    "date:inception_upper": "2018-09-28",
    "instagram:post": {
      "caption": {
        "body": "Introduced in 1952, the de Havilland Comet was the first commercial  passenger jetliner to enter service, years before the introduction of  other jetliners. Initially seen as a major landmark in aeronautical  engineering, after intermittent operation and structural failures,  service and production were canceled until airframe-engineering  deficiencies could be corrected. As a result, after many years of  redesigning, the much-improved, lengthened, Comet 4 was finally  delivered to BOAC in 1958. Shortly after, the airline inaugurated  regular transatlantic jet service from London to New York with one  refueling stop in Newfoundland. BEA inaugurated shorter-range Comet 4B  service on its Tel Aviv to London route in April 1960. The Comet 4  cruised at five hundred miles an hour and comfortably accommodated up to  eighty-one passengers, but ultimately, could not compete with the  Boeing 707 or the Douglas DC-8.  See \"Aviation Evolutions: The Jim Lund 1:72 Scale Model Airplane  Collection\", which features more than 200 models, on display,  pre-security, in the Aviation Museum. http://ow.ly/amRj50jff4P . . .",
        "excerpt": "Introduced in 1952, the de Havilland Comet was the first commercial  passenger jetliner to enter service, years before the introduction of  other jetliners.",
        "hashtags": [
          "AviationEvolutions",
          "jimlund",
          "avgeek",
          "aviationgeek",
          "aviation",
          "aviationhistory",
          "vintageaviation",
          "history",
          "aviationgeeks",
          "modelplane",
          "scalemodel",
          "avgeeks",
          "turboprop"
        ]
      },
      "media_id": "bec05d36b1b64182bba6e64af8506647",
      "path": "photos/201809/bec05d36b1b64182bba6e64af8506647.jpg",
      "perceptual_hash": "p:dc7ea0232bd8c275",
      "taken": 1538122680,
      "taken_at": "Sep 28, 2018, 8:18 AM"
    },
    "sfomuseum:placetype": "instagram",
    "wof:name": "Introduced in 1952, the de Havilland Comet was the first commercial  passenger jetliner to enter service, years before the introduction of  other jetliners...",
    "wof:placetype": "custom",
    "wof:placetype_alt": [
      "instagram"
    ]
  },
  "geometry": {"coordinates":[-122.386166,37.616356],"type":"Point"}
}
