{
  "type": "Feature",
  "properties": {
    "date:cessation_lower": "2019-11-12",
    "date:cessation_upper": "2019-11-12",
    "date:inception_lower": "2019-11-12",
    "date:inception_upper": "2019-11-12",
    "instagram:post": {
      "caption": {
        "body": "“Light has become more important than anything in the object world. There is no life without light. All matter is some form of radiant energy. It is through the magic of photography that light becomes the subject matter with colors, forms, and space/time relationships that express my deepest feelings and beliefs.” Wynn Bullock (1902-1975)  To create the images in “Color Light Abstractions”, photographer Wynn Bullock produced an apparatus that held a number of horizontal sheets of clear glass spaced evenly above one another. Upon these, he would place a series of materials—water, shards of stained glass, brightly colored cellophane. By positioning the camera above and manipulating the materials on each layer of glass below, Bullock could precisely compose each frame to create his light abstractions. The resulting scenes were significant not only in their ability to transport the viewer to evocative worlds consisting solely of light and color. “Color Light Abstractions” by #WynnBullock is on display,  post-security, in Terminal 3. http://bit.ly/2oDnQIr",
        "excerpt": "“Light has become more important than anything in the object world.",
        "hashtags": [
          "photography",
          "WynnBullock",
          "light",
          "color",
          "abstraction",
          "photographer",
          "publicart"
        ]
      },
      "media_id": "b57ea7d62d288cdc2aa9e9b735a3c991",
      "path": "media/posts/201911/69086712_168898384307105_4347722638080961779_n_17904160912391611.jpg",
      "perceptual_hash": "p:850f6077057b3d8e",
      "taken": 1573582920,
      "taken_at": "Nov 12, 2019, 6:22 PM"
    },
    "sfomuseum:placetype": "instagram",
    "wof:name": "“Light has become more important than anything in the object world...",
    "wof:placetype": "custom"
  },
  "geometry": {"coordinates":[-122.386166,37.616356],"type":"Point"}
}
