{
  "type": "Feature",
  "properties": {
    "date:cessation_lower": "2014-08-04",
    "date:cessation_upper": "2014-08-04",
    "date:inception_lower": "2014-08-04",
    "date:inception_upper": "2014-08-04",
    "instagram:post": {
      "caption": {
        "hashtags": [
          "maps",
          "sfmaps",
          "sfhistory"
        ]
      },
      "media_id": "2a64d7ec0475026ed83bca9e53c71e41",
      "path": "media/other/10554075_262343783958918_458838351_n_17841794992062499.jpg",
      "perceptual_hash": "p:df3d7960c25664c8",
      "taken": 1407145860,
      "taken_at": "Aug 04, 2014 9:51 am"
    },
    "sfomuseum:placetype": "instagram",
    "wof:name": "..",
    "wof:placetype": "custom",
    "wof:placetype_alt": [
      "instagram"
    ]
  },
  "geometry": {"coordinates":[-122.386166,37.616356],"type":"Point"}
}
