{
  "type": "Feature",
  "properties": {
    "instagram:post": {
      "caption": {
        "body": "On display in Terminal 2 is the history of the design and use of ouija boards, or talking boards, from the 1800s to the present. This particular talking board, the Magi-Board, from the 1940s, features a planchette consisting of a wooden cross with a large pointer at its center. Users had to balance the device on their fingertips.  All objects are courtesy of Gene Orlando, Museum of Talking Boards, and Robert Murch, The Talking Board Historical Society. Learn more about #Ouija boards in \"The Mysterious Talking Board: #OuijaAndBeyond\", on display, post-security, in Terminal 2. http://bit.ly/OuijaAndBeyond  G O O D B Y E ",
        "excerpt": "On display in Terminal 2 is the history of the design and use of ouija boards, or talking boards, from the 1800s to the present.",
        "hashtags": [
          "Ouija", 
          "ouijaboard", 
          "ouijaboards", 
          "talkingboard", 
          "magiboard"
        ]
      },
      "media_id": "a7680ecd365ffa3640d6e774c0b4113b",
      "path": "photos/201704/a7680ecd365ffa3640d6e774c0b4113b.jpg",
      "taken": 1492738682,
      "taken_at": "2017-04-21T01:38:02+00:00"
    },
    "sfomuseum:placetype": "instagram",
    "wof:name": "On display in Terminal 2 is the history of the design and use of ouija boards, or talking boards, from the 1800s to the present...",
    "wof:placetype": "custom"
  },
  "geometry": {"coordinates":[-122.386166,37.616356],"type":"Point"}
}
