{
  "type": "Feature",
  "properties": {
    "date:cessation_lower": "2021-04-22",
    "date:cessation_upper": "2021-04-22",
    "date:inception_lower": "2021-04-22",
    "date:inception_upper": "2021-04-22",
    "instagram:post": {
      "caption": {
        "body": "It’s Earth Day! Nearly six billion pounds of plastic bottles are discarded each year and it is estimated that half of these once contained only water. With just a third of these containers destined to reach a recycling facility, the 200-billion-dollar bottled water industry stands as a significant contributor to landfills worldwide. In his photography series, All Consumed, artist Gary Emrich draws focus on the growing industry, its advertising imagery, and its embrace of single-use packaging.  To create the photographs on display, Emrich layers a transparent clamshell container with water bottle packaging and places it on a light table in his studio. He then fills the plastic depressions with bottled water and photographs the composition with a large format film camera. Here, Emrich is careful to produce compositions that captivate, challenge, and ultimately beg us to reconsider our own relationship with objects that are so easily consumed and discarded.  \"All Consumed\" by Gary Emrich is on view pre-security in Harvey Milk Terminal 1 until June 29, and online: http://bit.ly/AllConsumed",
        "excerpt": "It’s Earth Day!",
        "hashtags": [
          "EarthDay",
          "AllConsumed",
          "bottledwater",
          "contemporaryphotography",
          "photography"
        ],
        "users": [
          "GaryEmrich",
          "robischongallery"
        ]
      },
      "media_id": "f0e4b01bb538faa4d3c9b66c5c1e533337ae379d",
      "path": "media/posts/202104/176593441_1398822717142972_289597113817802318_n_18107585530229437.jpg",
      "perceptual_hash": "p:ea85943bc54e947a",
      "taken": 1619109060,
      "taken_at": "Apr 22, 2021 4:31 pm"
    },
    "sfomuseum:placetype": "instagram",
    "wof:name": "It’s Earth Day!..",
    "wof:placetype": "custom",
    "wof:placetype_alt": [
      "instagram"
    ]
  },
  "geometry": {"coordinates":[-122.386166,37.616356],"type":"Point"}
}
