{
  "type": "Feature",
  "properties": {
    "date:cessation_lower": "2016-10-28",
    "date:cessation_upper": "2016-10-28",
    "date:inception_lower": "2016-10-28",
    "date:inception_upper": "2016-10-28",
    "instagram:post": {
      "caption": {
        "hashtags": [
          "OnThisDay",
          "AVGeek",
          "AviationHistory",
          "PanAm"
        ]
      },
      "location": "Aeropuerto Internacional de San Francisco",
      "media_id": "b96aec6f7ec1abbbb4a3a97ce4b5ddd7",
      "path": "photos/201610/b96aec6f7ec1abbbb4a3a97ce4b5ddd7.jpg",
      "perceptual_hash": "p:9f2706909e1e1d9b",
      "taken": 1477688019,
      "taken_at": "2016-10-28T20:53:39+00:00"
    },
    "sfomuseum:placetype": "instagram",
    "wof:name": "..",
    "wof:placetype": "custom"
  },
  "geometry": {"coordinates":[-122.386166,37.616356],"type":"Point"}
}
