{
  "type": "Feature",
  "properties": {
    "date:cessation_lower": "2018-06-05",
    "date:cessation_upper": "2018-06-05",
    "date:inception_lower": "2018-06-05",
    "date:inception_upper": "2018-06-05",
    "instagram:post": {
      "caption": {
        "body": "The all-metal, twin-engine Boeing Model 247 was a revolutionary airplane when introduced in 1933. Often referred to as the first modern airliner, it featured numerous advancements including all-aluminum, semi-monocoque construction, a cantilevered wing, wing flaps, variable pitch propellers, trim tabs, autopilot, and semi-retractable landing gear. It entered service with United Air Lines in 1933. Seventy-five of the aircraft were eventually built, with most going to the United Air Lines’ fleet. The aircraft was primarily operated on United’s “Mainline” transcontinental route until the mid 1930s. Although advanced for its time, the Model 247 accommodated only ten passengers, which made it less economical to operate than larger capacity airliners, particularly the more fuel-efficient, fourteen-seat Douglas DC-2, introduced a year later.  See \"Aviation Evolutions: The Jim Lund 1:72 Scale Model Airplane Collection\", which features more than 200 models, on display, pre-security, in the Aviation Museum. http://bit.ly/AviationEvolutions",
        "excerpt": "The all-metal, twin-engine Boeing Model 247 was a revolutionary airplane when introduced in 1933.",
        "hashtags": [
          "jimlund",
          "avgeek",
          "avationgeek",
          "aviation",
          "aviationhistory",
          "vintageaviation",
          "history",
          "avhistory",
          "aviationgeeks",
          "modelplane",
          "avgeeks",
          "modelaircraft",
          "airplane",
          "aircraft"
        ]
      },
      "media_id": "e6fbed415af83b4e6370b26244cc53067589acdc",
      "path": "media/posts/201806/33423241_200132613945291_258931741345972224_n_17941542769079835.jpg",
      "perceptual_hash": "p:95c0c51ae13ff552",
      "taken": 1528188600,
      "taken_at": "Jun 5, 2018, 8:50 AM"
    },
    "sfomuseum:placetype": "instagram",
    "wof:name": "The all-metal, twin-engine Boeing Model 247 was a revolutionary airplane when introduced in 1933...",
    "wof:placetype": "custom"
  },
  "geometry": {"coordinates":[-122.386166,37.616356],"type":"Point"}
}
