{
  "type": "Feature",
  "properties": {
    "date:cessation_lower": "2018-10-05",
    "date:cessation_upper": "2018-10-05",
    "date:inception_lower": "2018-10-05",
    "date:inception_upper": "2018-10-05",
    "instagram:post": {
      "caption": {
        "body": "#Onthisday in 1951, construction began on the new terminal building at San Francisco International Airport. The new terminal (now Terminal 2) was built to serve the international community in the coming jet age. ",
        "excerpt": "#Onthisday in 1951, construction began on the new terminal building at San Francisco International Airport.",
        "hashtags": [
          "SFOHistory",
          "avgeek",
          "aviationgeek",
          "aviation",
          "aviationhistory",
          "aviationlovers",
          "vintageaviation",
          "history",
          "aviationgeeks",
          "avgeeks",
          "airport"
        ]
      },
      "media_id": "40ff3caacc108cc44f1856f85800bec7",
      "path": "photos/201810/40ff3caacc108cc44f1856f85800bec7.jpg",
      "perceptual_hash": "p:e2f7d85820a6d61e",
      "taken": 1538730840,
      "taken_at": "Oct 5, 2018, 9:14 AM"
    },
    "sfomuseum:placetype": "instagram",
    "wof:name": "#Onthisday in 1951, construction began on the new terminal building at San Francisco International Airport...",
    "wof:placetype": "custom"
  },
  "geometry": {"coordinates":[-122.386166,37.616356],"type":"Point"}
}
