{
  "type": "Feature",
  "properties": {
    "date:cessation_lower": "2015-06-09",
    "date:cessation_upper": "2015-06-09",
    "date:inception_lower": "2015-06-09",
    "date:inception_upper": "2015-06-09",
    "instagram:post": {
      "caption": {
        "hashtags": [
          "AgeOfDeco",
          "ArtDeco"
        ]
      },
      "media_id": "95ab3e5006d1cce0e1e41141ed3246ec",
      "path": "photos/201506/95ab3e5006d1cce0e1e41141ed3246ec.jpg",
      "perceptual_hash": "p:8d3253bc344338f7",
      "taken": 1433891169,
      "taken_at": "2015-06-09T23:06:09+00:00"
    },
    "sfomuseum:placetype": "instagram",
    "wof:name": "..",
    "wof:placetype": "custom"
  },
  "geometry": {"coordinates":[-122.386166,37.616356],"type":"Point"}
}
