{
  "type": "Feature",
  "properties": {
    "date:cessation_lower": "2021-11-23",
    "date:cessation_upper": "2021-11-23",
    "date:inception_lower": "2021-11-23",
    "date:inception_upper": "2021-11-23",
    "instagram:post": {
      "caption": {
        "body": "As airline travel became more reliable during the 1930s, San Francisco’s airport initiated major improvements to keep pace. By 1937, SFO had paved and widened runways and taxiways to welcome heavier and faster airliners such as the Douglas DC-3, while boundary and runway lights allowed for safer night operations. A grand Spanish Colonial Revival-style passenger terminal, complete with a modern four-story control tower, also opened that year—crowning the first phase of expansion at the airport.   ”Mills Field and the San Francisco Airport” traces the evolution of SFO from a temporary airfield to a thriving and modern transportation hub. See the exhibition, on display pre-security in the SkyTerrace, located in Terminal 2. SkyTerrace is open Friday - Monday from 10:00 a.m. to 6:00 p.m. https://bit.ly/MillsFieldSFO",
        "excerpt": "As airline travel became more reliable during the 1930s, San Francisco’s airport initiated major improvements to keep pace.",
        "hashtags": [
          "SFOHistory",
          "MillsField",
          "airport",
          "avgeek",
          "aviationhistory"
        ]
      },
      "media_id": "8c9beb3802b28c0469a87cac84552ef3ae692f4e",
      "path": "media/posts/202111/260499616_1933580450156865_967788519147913700_n_17945656504616310.jpg",
      "perceptual_hash": "p:90eb9ef568c81726",
      "taken": 1637686860,
      "taken_at": "Nov 23, 2021, 5:01 PM"
    },
    "sfomuseum:placetype": "instagram",
    "wof:name": "As airline travel became more reliable during the 1930s, San Francisco’s airport initiated major improvements to keep pace...",
    "wof:placetype": "custom"
  },
  "geometry": {"coordinates":[-122.386166,37.616356],"type":"Point"}
}
