{
  "type": "Feature",
  "properties": {
    "date:cessation_lower": "2018-11-16",
    "date:cessation_upper": "2018-11-16",
    "date:inception_lower": "2018-11-16",
    "date:inception_upper": "2018-11-16",
    "instagram:post": {
      "caption": {
        "body": "Introduced to Europe from Japan in the 16th century, fans were an essential fashion accessory in the formal dress of a wealthy woman. They helped to cool a lady’s face and could be used as a subtle tool for flirting with suitors. Painted and lace-embellished fans were common around the turn of the 20th century, when French painter Adolphe Thomasse (1850­–1930) decorated fans with a menagerie of animal images, including cats, often for the famous fan-maker Duvelleroy of Paris.  A very special thank you to Sandy Lerner for making this exhibition possible. See \"Caticons: The Cat in Art\" is on display, pre-security, in the International Terminal. http://ow.ly/wU4t50jIvPN . . .",
        "excerpt": "Introduced to Europe from Japan in the 16th century, fans were an essential fashion accessory in the formal dress of a wealthy woman.",
        "hashtags": [
          "caticons",
          "catsofinstagram",
          "mewseum",
          "caticon",
          "cat",
          "cats",
          "fans",
          "fashion"
        ]
      },
      "media_id": "c3746e986f5298c6205830faa96c03b8",
      "path": "media/posts/201811/44705202_145848369728545_1375673376694331201_n_17986460239129401.jpg",
      "perceptual_hash": "p:e79098cdc21ecf38",
      "taken": 1542400620,
      "taken_at": "Nov 16, 2018, 8:37 PM"
    },
    "sfomuseum:placetype": "instagram",
    "wof:name": "Introduced to Europe from Japan in the 16th century, fans were an essential fashion accessory in the formal dress of a wealthy woman...",
    "wof:placetype": "custom",
    "wof:placetype_alt": [
      "instagram"
    ]
  },
  "geometry": {"coordinates":[-122.386166,37.616356],"type":"Point"}
}
