{
  "type": "Feature",
  "properties": {
    "date:cessation_lower": "2017-09-01",
    "date:cessation_upper": "2017-09-01",
    "date:inception_lower": "2017-09-01",
    "date:inception_upper": "2017-09-01",
    "instagram:post": {
      "caption": {
        "body": "Kanji, or Japanese character writing, is based on Chinese script and shares many meanings and definitions. Officially published in the Jōyō Kanji, around 2,000 Chinese-based characters are listed for use in conjunction with a distinct, Japanese kana alphabet. In 1915, Japanese printer and inventor Kyota Sugimoto (1882–1972) patented a typewriter that printed in both Chinese and Japanese. Manufactured by the Nippon Typewriter Company, the machine featured a large, sliding tray with room for 2,450 individual type-slugs. A moving carriage assembly mounted over the tray contained the typing mechanism. To operate, the typist positioned the tray and carriage along an x–y axis to select a type-slug, and depressed a button to retrieve, ink, and print.  Typewriter courtesy of Thomas S. Mullaney. Learn more about the typewriter in our exhibition, \"The Typewriter: An Innovation in Writing\", post-security, in Terminal 2. http://bit.ly/Thetypewriter",
        "excerpt": "Kanji, or Japanese character writing, is based on Chinese script and shares many meanings and definitions.",
        "hashtags": [
          "thetypewriter",
          "typewriter",
          "typewriters",
          "writing",
          "industrialdesign",
          "keyboard",
          "keyboards",
          "design",
          "innovation",
          "type",
          "typing",
          "typist",
          "oldschool",
          "writer",
          "writing",
          "vintagetypewriter",
          "vintage",
          "analog",
          "antique",
          "typewritten",
          "typewriting",
          "oldtypewriters",
          "typewritersofinstagram",
          "kanji",
          "japanese",
          "japan",
          "japanesetypewriter",
          "nippon",
          "typeslugs"
        ]
      },
      "media_id": "db37492d58f53ee3c49f54da389a619d",
      "path": "photos/201709/db37492d58f53ee3c49f54da389a619d.jpg",
      "perceptual_hash": "p:838375a7c3353c5a",
      "taken": 1504262640,
      "taken_at": "Sep 1, 2017, 10:44 AM"
    },
    "sfomuseum:placetype": "instagram",
    "wof:name": "Kanji, or Japanese character writing, is based on Chinese script and shares many meanings and definitions...",
    "wof:placetype": "custom",
    "wof:placetype_alt": [
      "instagram"
    ]
  },
  "geometry": {"coordinates":[-122.386166,37.616356],"type":"Point"}
}
