{
  "type": "Feature",
  "properties": {
    "date:cessation_lower": "2016-04-21",
    "date:cessation_upper": "2016-04-21",
    "date:inception_lower": "2016-04-21",
    "date:inception_upper": "2016-04-21",
    "instagram:post": {
      "caption": {
        "body": "Creativity Explored @creativityexplored of San Francisco is one of the three pioneering art centers featured in our exhibition \"Celebrating a Vision: #ArtAndDisability”. Yesterday, a few artists from the organization made the trip down to the Airport to see their artwork on display in our exhibition. The artists were really excited to see their artwork on display for the enjoyment of so many people at SFO. For more insight on this organization and its extraordinary work, check out this video featuring artist Christina Marie Fong: https://www.youtube.com/watch?v=Uv1_JUm0sXI",
        "excerpt": "Creativity Explored @creativityexplored of San Francisco is one of the three pioneering art centers featured in our exhibition \"Celebrating a Vision: #ArtAndDisability”."
      },
      "media_id": "7156917121bfe2d082bc52d7cd126c86",
      "path": "media/posts/201604/12445867_623653761120432_998056150_n_17846858917091704.jpg",
      "perceptual_hash": "p:ae86d11d292b527b",
      "taken": 1461269820,
      "taken_at": "Apr 21, 2016, 8:17 PM"
    },
    "sfomuseum:placetype": "instagram",
    "wof:name": "Creativity Explored @creativityexplored of San Francisco is one of the three pioneering art centers featured in our exhibition \"Celebrating a Vision: #ArtAndDisability”...",
    "wof:placetype": "custom",
    "wof:placetype_alt": [
      "instagram"
    ]
  },
  "geometry": {"coordinates":[-122.386166,37.616356],"type":"Point"}
}
