{
  "type": "Feature",
  "properties": {
    "date:cessation_lower": "2018-04-05",
    "date:cessation_upper": "2018-04-05",
    "date:inception_lower": "2018-04-05",
    "date:inception_upper": "2018-04-05",
    "instagram:post": {
      "caption": {
        "body": "#OnThisDay in 1970, the first Boeing 747 widebody jumbojet operated by TWA (Trans World Airlines) departed from San Francisco International Airport for New York City. Just prior to the flight, an inaugural celebration was held to commemorate the momentous event. The Boeing 747-131, registration number N93104, was christened the \"City of San Francisco\" by diplomat and former child star, Shirley Temple Black.  Image:  Shirley Temple Black and Airport Director James K. Carr about to christen the first 747 at SFO \"City of San Francisco\", 1970. SFO Museum Collection. 2011.032.2238",
        "excerpt": "#OnThisDay in 1970, the first Boeing 747 widebody jumbojet operated by TWA (Trans World Airlines) departed from San Francisco International Airport for New York City.",
        "hashtags": [
          "SFOHistory",
          "ThrowbackThursday",
          "SFO",
          "747",
          "TWA",
          "jumbojet",
          "NYC",
          "avgeek",
          "avationgeek",
          "aviation",
          "aviationhistory",
          "vintageaviation",
          "history",
          "avhistory",
          "aviationgeeks",
          "avgeeks",
          "ShirleyTemple"
        ]
      },
      "location": "San Francisco International Airport (SFO)",
      "media_id": "13e79e4bd0f4fb02f40e25d144886de4",
      "path": "photos/201804/13e79e4bd0f4fb02f40e25d144886de4.jpg",
      "perceptual_hash": "p:a9f452e9645235ba",
      "taken": 1522959057,
      "taken_at": "2018-04-05T20:10:57+00:00"
    },
    "sfomuseum:placetype": "instagram",
    "wof:name": "#OnThisDay in 1970, the first Boeing 747 widebody jumbojet operated by TWA (Trans World Airlines) departed from San Francisco International Airport for New York City...",
    "wof:placetype": "custom"
  },
  "geometry": {"coordinates":[-122.386166,37.616356],"type":"Point"}
}
