{
  "type": "Feature",
  "properties": {
    "instagram:post": {
      "caption": {
        "body": "On September 15, 1963, the South Terminal (now Terminal 1) was dedicated at San Francisco International Airport. This was the Airport's first major addition since the Central Terminal was the completed in 1954. Named South Terminal, it further encircled the central parking area and began a pattern of growth that would continue at the airport for decades to come. #OnThisDay #SFOHistory #ThrowbackThursday  San Francisco International Airport, South Terminal construction 1962 SFO Museum Collection  1997.52.051.017"
      },
      "location": "San Francisco International Airport (SFO)",
      "media_id": "b554b5387a2d81f9b87de3afdc9c393a",
      "path": "photos/201609/b554b5387a2d81f9b87de3afdc9c393a.jpg",
      "taken": 1473959152,
      "taken_at": "2016-09-15T17:05:52+00:00"
    },
    "sfomuseum:placetype": "instagram",
    "wof:name": "Instagram message #%!d(string=b554b5387a2d81f9b87de3afdc9c393a)",
    "wof:placetype": "custom"
  },
  "geometry": {"coordinates":[-122.386166,37.616356],"type":"Point"}
}
