{
  "type": "Feature",
  "properties": {
    "instagram:post": {
      "caption": {
        "body": "Ceramic artist Delphine Massier was known for his large jardinières and stands modeled in relief with Art Nouveau maidens, flowers, and scrolling foliage in shades of bold pink or blue.",
        "hashtags": [
          "ArtNouveauSFO"
        ]
      },
      "location": "San Francisco International Airport (SFO)",
      "media_id": "2335a7fdb0a8c8d29f81c1a7afac8802",
      "path": "photos/201608/2335a7fdb0a8c8d29f81c1a7afac8802.jpg",
      "taken": 1470763212,
      "taken_at": "2016-08-09T17:20:12+00:00"
    },
    "sfomuseum:placetype": "instagram",
    "wof:name": "Instagram message #%!d(string=2335a7fdb0a8c8d29f81c1a7afac8802)",
    "wof:placetype": "custom"
  },
  "geometry": {"coordinates":[-122.386166,37.616356],"type":"Point"}
}
