{
  "type": "Feature",
  "properties": {
    "date:cessation_lower": "2023-11-01",
    "date:cessation_upper": "2023-11-01",
    "date:inception_lower": "2023-11-01",
    "date:inception_upper": "2023-11-01",
    "instagram:post": {
      "caption": {
        "body": "Many ballet dancers customize their pointe shoes depending on their needs. Some find the right combination of fit, support, and suppleness in a shoe directly from the manufacturer, while other dancers special order their shoes from a specific maker. A dancer may alter their shoes once they receive them to make them fit perfectly. They often break the shank (the sole of the shoe that runs from toe to heel) or soften the box (the area around the toes that provides the dancer with the stability to be on pointe). Occasionally, a dancer will darn around the platform—the part of the shoe that the dancer balances on while on pointe—to help with stability or to make the shoe last longer. Sometimes, they rough up the bottom of the shoe to provide more traction. A dancer might also prepare their shoes differently depending on the ballet they are performing. If a role is particularly demanding, a dancer may use a brand-new pair of shoes for each performance—or each act!  Special thank you to San Francisco Ballet for making this exhibition possible. See “San Francisco Ballet at 90” on display, pre-security, in the International Terminal and online at: https://bit.ly/SFBalletAt90",
        "excerpt": "Many ballet dancers customize their pointe shoes depending on their needs.",
        "hashtags": [
          "SFBalletAt90",
          "WorldBalletDay"
        ],
        "users": [
          "sfballet"
        ]
      },
      "media_id": "227f01e0cb06f47726c7e9c34afbb5845e5f620c",
      "path": "media/posts/202311/397504119_802498071887124_1117191229990818427_n_17843599389092998.jpg",
      "perceptual_hash": "p:be94f8c070ec0f63",
      "taken": 1698854940,
      "taken_at": "Nov 01, 2023 4:09 pm"
    },
    "sfomuseum:placetype": "instagram",
    "wof:name": "Many ballet dancers customize their pointe shoes depending on their needs...",
    "wof:placetype": "custom"
  },
  "geometry": {"coordinates":[-122.386166,37.616356],"type":"Point"}
}
