{
  "type": "Feature",
  "properties": {
    "date:cessation_lower": "2019-01-12",
    "date:cessation_upper": "2019-01-12",
    "date:inception_lower": "2019-01-12",
    "date:inception_upper": "2019-01-12",
    "instagram:post": {
      "caption": {
        "body": "\"In recent months, I have been moving closer to traditional silversmithing, but I'm still keen to combine this with advanced technology…to bridge the gap between the two different approaches so that they become integrated, with the finished work having a natural feel without any hint of fabrication.\" Hamish Dobbie (b. 1991). Glasgow-based silversmith Hamish Dobbie gains much of his inspiration from the rugged landscape of Western Scotland. With geological features such as the hexagonal formations on the island of Staffa in mind, Dobbie uses advanced techniques that include 3D printing and CAD (Computer Aided Design) software to combine modern aesthetics and traditional silversmithing. Dobbie’s Two Brothers’ bowl comprises a pair of nesting bowls made by the artist in 2014 while in residency at the Glasgow School of Art. The highly polished surface of the spun, inner-bowl reflects an outer mesh basket made from hundreds of joined, silver shapes cast from 3D-printed components. Dobbie was the first recipient of the P \u0026 O Makower Trust Award, granted in 2015 to commission a silver vase for the National Museums of Scotland.  Special thanks to The Pearson Silver Collection. \"A Sterling Renaissance: British Silver Design 1957 to 2018\" is on display, pre-security, in the International Terminal. http://bit.ly/BritishSilver . . .",
        "excerpt": "\"In recent months, I have been moving closer to traditional silversmithing, but I'm still keen to combine this with advanced technology…to bridge the gap between the two different approaches so that they become integrated, with the finished work having a natural feel without any hint of fabrication.\"",
        "hashtags": [
          "BritishSilver",
          "silver",
          "sterling",
          "sterlingsilver",
          "silverdesign",
          "silversmith",
          "silversmithing",
          "handmade",
          "3dprinting",
          "hammishdobbie"
        ]
      },
      "media_id": "9d97e0ac653c9dec9a99eb9fc3c7c808",
      "path": "photos/201901/9d97e0ac653c9dec9a99eb9fc3c7c808.jpg",
      "perceptual_hash": "p:c94b37a46c4d24fc",
      "taken": 1547239860,
      "taken_at": "Jan 11, 2019, 8:51 PM"
    },
    "sfomuseum:placetype": "instagram",
    "wof:name": "\"In recent months, I have been moving closer to traditional silversmithing, but I'm still keen to combine this with advanced technology…to bridge the gap between the two different approaches so that they become integrated, with the finished work having a natural feel without any hint of fabrication.\"..",
    "wof:placetype": "custom",
    "wof:placetype_alt": [
      "instagram"
    ]
  },
  "geometry": {"coordinates":[-122.386166,37.616356],"type":"Point"}
}
