{
  "type": "Feature",
  "properties": {
    "date:cessation_lower": "2016-01-27",
    "date:cessation_upper": "2016-01-27",
    "date:inception_lower": "2016-01-27",
    "date:inception_upper": "2016-01-27",
    "instagram:post": {
      "caption": {
        "hashtags": [
          "WomenInAviation"
        ]
      },
      "media_id": "d1ff49f3d1afc8e2b9c8c9cca205c902",
      "path": "media/posts/201601/12479500_1028180937242522_1882753883_n_17853991042057115.jpg",
      "perceptual_hash": "p:fedce8caa8258929",
      "taken": 1453927320,
      "taken_at": "Jan 27, 2016, 8:42 PM"
    },
    "sfomuseum:placetype": "instagram",
    "wof:name": "..",
    "wof:placetype": "custom"
  },
  "geometry": {"coordinates":[-122.386166,37.616356],"type":"Point"}
}
