{
  "type": "Feature",
  "properties": {
    "date:cessation_lower": "2018-02-27",
    "date:cessation_upper": "2018-02-27",
    "date:inception_lower": "2018-02-27",
    "date:inception_upper": "2018-02-27",
    "instagram:post": {
      "caption": {
        "body": "This is your last week to see \"Flying the Main Line: A History of United Airlines.\" Located post-security in Terminal 3, the exhibition showcases highlights from SFO Museum's collection. Over ninety years of commercial aviation history can be told through the stories of the four companies that merged into a single airline which became a preeminent U.S. carrier. What is your favorite memory of United?  See \"Flying the Main Line: A History of United Airlines\", on display, post-security, in Terminal 3. http://bit.ly/TheMainLine",
        "excerpt": "This is your last week to see \"Flying the Main Line: A History of United Airlines.\"",
        "hashtags": [
          "FlyingTheMainLine",
          "TheMainLine",
          "avgeek",
          "united",
          "aviationhistory",
          "unitedairlines",
          "aviationgeek",
          "aviation"
        ]
      },
      "media_id": "194e0199efc37a6f39b3427797058dba",
      "path": "media/posts/201802/27894358_152926058726924_591943027073744896_n_17929786309061874.jpg",
      "perceptual_hash": "p:85e8621e5bd3e2e2",
      "taken": 1519752660,
      "taken_at": "Feb 27, 2018, 5:31 PM"
    },
    "sfomuseum:placetype": "instagram",
    "wof:name": "This is your last week to see \"Flying the Main Line: A History of United Airlines.\"..",
    "wof:placetype": "custom"
  },
  "geometry": {"coordinates":[-122.386166,37.616356],"type":"Point"}
}
