{
  "type": "Feature",
  "properties": {
    "date:cessation_lower": "2019-04-10",
    "date:cessation_upper": "2019-04-10",
    "date:inception_lower": "2019-04-10",
    "date:inception_upper": "2019-04-10",
    "instagram:post": {
      "caption": {
        "body": "#Onthisday in 1937, Trans-Canada Air Lines (TCA), the flag carrier of Canada, was founded. With a Stearman 4 and two Lockheed Model 10 Electras, TCA took to the skies; the airline's first flight was from Vancouver to Seattle on September 1, 1937. The flight carried mail and two passengers whose round-trip tickets each cost $14.20 CAD, or $176.75 USD in today's currency. TCA was renamed Air Canada in 1965. Did you ever fly on TCA?  Image: Trans-Canada Air Lines postcard, Canadair North Star, 1950s. Gift of Thomas G. Dragges. 2015.166.1496",
        "excerpt": "#Onthisday in 1937, Trans-Canada Air Lines (TCA), the flag carrier of Canada, was founded.",
        "hashtags": [
          "TravelTuesday",
          "AirCanada",
          "TransCanadaAirLines",
          "TCA",
          "Canada"
        ]
      },
      "media_id": "bf046200a5632bdd6095243c55e6f6fc",
      "path": "media/posts/201904/54513610_134910897643293_5953999960551145581_n_17862102469370067.jpg",
      "perceptual_hash": "p:eb0b9f42ea375a08",
      "taken": 1554900180,
      "taken_at": "Apr 10, 2019, 12:43 PM"
    },
    "sfomuseum:placetype": "instagram",
    "wof:name": "#Onthisday in 1937, Trans-Canada Air Lines (TCA), the flag carrier of Canada, was founded...",
    "wof:placetype": "custom"
  },
  "geometry": {"coordinates":[-122.386166,37.616356],"type":"Point"}
}
