{
  "type": "Feature",
  "properties": {
    "instagram:post": {
      "caption": {
        "body": "#DC3 installation underway in the #Aviation Museum! The Pratt \u0026 Whitney R-1830 Twin Wasp cutaway engine heads into its case."
      },
      "media_id": "6a580e651f7a84f44008a3a48082472e",
      "path": "photos/201305/6a580e651f7a84f44008a3a48082472e.jpg",
      "taken": 1367430402,
      "taken_at": "2013-05-01T17:46:42+00:00"
    },
    "sfomuseum:placetype": "instagram",
    "wof:name": "Instagram message #%!d(string=6a580e651f7a84f44008a3a48082472e)",
    "wof:placetype": "custom"
  },
  "geometry": {"coordinates":[-122.386166,37.616356],"type":"Point"}
}
