{
  "type": "Feature",
  "properties": {
    "instagram:post": {
      "caption": {
        "body": "What was it like flying to Paris on TWA in the mid-fifties? Well, passengers would have ordered their food and drinks from a menu like this one with a quaint illustration of Parisian landmarks.  Image:  TWA (Trans World Airlines) menu, c. 1955. Gift of Howard and Midge East. 2002.046.002",
        "excerpt": "What was it like flying to Paris on TWA in the mid-fifties?",
        "hashtags": [
          "TWA", 
          "Paris", 
          "menu", 
          "avgeek", 
          "aviationhistory", 
          "paxex", 
          "airlinemeals", 
          "traveltuesday"
        ]
      },
      "media_id": "f42e1084b2d9bfff173e493ae65fcb06",
      "path": "photos/201705/f42e1084b2d9bfff173e493ae65fcb06.jpg",
      "taken": 1495592336,
      "taken_at": "2017-05-24T02:18:56+00:00"
    },
    "sfomuseum:placetype": "instagram",
    "wof:name": "What was it like flying to Paris on TWA in the mid-fifties?..",
    "wof:placetype": "custom"
  },
  "geometry": {"coordinates":[-122.386166,37.616356],"type":"Point"}
}
