{
  "type": "Feature",
  "properties": {
    "instagram:post": {
      "caption": {
        "hashtags": [
          "Lufthansa", 
          "A380"
        ]
      },
      "media_id": "19a0f7aad4aac5de52f343bec95200fe",
      "path": "photos/201305/19a0f7aad4aac5de52f343bec95200fe.jpg",
      "taken": 1368221155,
      "taken_at": "2013-05-10T21:25:55+00:00"
    },
    "sfomuseum:placetype": "instagram",
    "wof:name": "Instagram message #%!d(string=19a0f7aad4aac5de52f343bec95200fe)",
    "wof:placetype": "custom"
  },
  "geometry": {"coordinates":[-122.386166,37.616356],"type":"Point"}
}
