{
  "type": "Feature",
  "properties": {
    "date:cessation_lower": "2013-05-10",
    "date:cessation_upper": "2013-05-10",
    "date:inception_lower": "2013-05-10",
    "date:inception_upper": "2013-05-10",
    "instagram:post": {
      "caption": {
        "hashtags": [
          "Lufthansa",
          "A380"
        ]
      },
      "media_id": "19a0f7aad4aac5de52f343bec95200fe",
      "path": "media/posts/201305/11263461_871477152918434_79339764_n_17842321291062499.jpg",
      "perceptual_hash": "p:b4134f2c58e33d6c",
      "taken": 1368192300,
      "taken_at": "May 10, 2013, 1:25 PM"
    },
    "sfomuseum:placetype": "instagram",
    "wof:name": "..",
    "wof:placetype": "custom"
  },
  "geometry": {"coordinates":[-122.386166,37.616356],"type":"Point"}
}
