{
  "type": "Feature",
  "properties": {
    "date:cessation_lower": "2016-12-17",
    "date:cessation_upper": "2016-12-17",
    "date:inception_lower": "2016-12-17",
    "date:inception_upper": "2016-12-17",
    "instagram:post": {
      "caption": {
        "body": "Eastern Air Lines brought nostalgic traditionalism to uniform design in the 1990s. Issued with slacks and the midi skirt with matching blazer, this uniform includes the waistcoat style vest of an earlier era. The collection was introduced with the tag line “The hat is back!” for the retro overseas cap by Frank Olive (1929–1995). A classic chain link and medallion pattern scarf adds a touch of burgundy to the outfit. #FashionFriday  See more 1980s fashion in \"#FashionInFlight: A History of Airline Uniform Design\", pre-security, in the Aviation Museum and Library and the Main Hall of the International Terminal. The Aviation Museum and Library is open daily from 10am to 4:30pm, excluding holidays. http://bit.ly/fashioninflight",
        "excerpt": "Eastern Air Lines brought nostalgic traditionalism to uniform design in the 1990s.",
        "hashtags": [
          "EasternAirlines",
          "flightattendant",
          "crewlife",
          "fashion",
          "uniform",
          "vintage",
          "retro"
        ]
      },
      "location": "San Francisco International Airport (SFO)",
      "media_id": "23adac7511cbf0f90a8233f2a9bd62ce",
      "path": "photos/201612/23adac7511cbf0f90a8233f2a9bd62ce.jpg",
      "perceptual_hash": "p:c399b2e03d3b7232",
      "taken": 1481938869,
      "taken_at": "2016-12-17T01:41:09+00:00"
    },
    "sfomuseum:placetype": "instagram",
    "wof:name": "Eastern Air Lines brought nostalgic traditionalism to uniform design in the 1990s...",
    "wof:placetype": "custom"
  },
  "geometry": {"coordinates":[-122.386166,37.616356],"type":"Point"}
}
