{
  "type": "Feature",
  "properties": {
    "date:cessation_lower": "2017-12-29",
    "date:cessation_upper": "2017-12-29",
    "date:inception_lower": "2017-12-29",
    "date:inception_upper": "2017-12-29",
    "instagram:post": {
      "caption": {
        "body": "For more than ninety years, United Airlines personnel have filled the dozens of positions needed to sustain the operations of a global organization. Pilots are outfitted with military style, two-piece suit uniforms and hats. Cuff ranks can designate captains, first officers, and other members of the flight crew. The hat badges and the wings worn on the jacket and shirt complete the outfit. Over the decades, insignia styles have evolved as aircraft and service modernized. The color and finish of United’s hat badges and wings have also changed over the years, but these insignia sets have always retained their classic aeronautical bearings.  See \"Flying the Main Line: A History of United Airlines\", on display, post-security, in Terminal 3. http://bit.ly/TheMainLine  Image: United Air Lines, Douglas DC-8, San Francisco International Airport (SFO), 1962. Gift of Walton F. Kemmerle. 2011.155.007",
        "excerpt": "For more than ninety years, United Airlines personnel have filled the dozens of positions needed to sustain the operations of a global organization.",
        "hashtags": [
          "FlyingTheMainLine",
          "TheMainLine",
          "avgeek",
          "united",
          "aviationhistory",
          "unitedairlines",
          "aviationgeek",
          "aviation",
          "pilot",
          "uniform",
          "crewlife",
          "hatbadges",
          "insignia"
        ]
      },
      "media_id": "a7fec590b8d8ed0cae514d03095798f0",
      "path": "media/other/25023141_183043658950363_5056993879853629440_n_17916445726003041.jpg",
      "perceptual_hash": "p:b4d0999da8726bcc",
      "taken": 1514549340,
      "taken_at": "Dec 29, 2017 12:09 pm"
    },
    "sfomuseum:placetype": "instagram",
    "wof:name": "For more than ninety years, United Airlines personnel have filled the dozens of positions needed to sustain the operations of a global organization...",
    "wof:placetype": "custom",
    "wof:placetype_alt": [
      "instagram"
    ]
  },
  "geometry": {"coordinates":[-122.386166,37.616356],"type":"Point"}
}
