{
  "type": "Feature",
  "properties": {
    "date:cessation_lower": "2017-05-03",
    "date:cessation_upper": "2017-05-03",
    "date:inception_lower": "2017-05-03",
    "date:inception_upper": "2017-05-03",
    "instagram:post": {
      "caption": {
        "body": "Thai Airways International was founded in 1960 as a joint venture between SAS (Scandinavian Airlines System), the flag carrier of Denmark, Norway, and Sweden, and Thai Airways Company (TAC), Thailand's flag carrier, to expand the Thai aviation industry beyond Asia. Thai Airways International took over international flights from TAC while TAC continued to fly domestic routes. In 1988, Thai Airways International and TAC merged into a single flag-carrying airline. Have you ever flown on Thai Airways?  Image: Thai Airways International advertisement, early 1960s.  Gift of Captain Jon Simmonds. 2016.080.028",
        "excerpt": "Thai Airways International was founded in 1960 as a joint venture between SAS (Scandinavian Airlines System), the flag carrier of Denmark, Norway, and Sweden, and Thai Airways Company (TAC), Thailand's flag carrier, to expand the Thai aviation industry beyond Asia.",
        "hashtags": [
          "TravelTuesday",
          "avgeek",
          "aviationhistory",
          "vintagead",
          "fightattendant",
          "thailand",
          "bangkok",
          "thai",
          "thaiairways"
        ]
      },
      "location": "SFO Museum",
      "media_id": "da6d4c12e292822059014dbdfcbd0030",
      "path": "photos/201705/da6d4c12e292822059014dbdfcbd0030.jpg",
      "perceptual_hash": "p:d795b6b744c84952",
      "taken": 1493755920,
      "taken_at": "May 2, 2017, 8:12 PM"
    },
    "sfomuseum:placetype": "instagram",
    "wof:name": "Thai Airways International was founded in 1960 as a joint venture between SAS (Scandinavian Airlines System), the flag carrier of Denmark, Norway, and Sweden, and Thai Airways Company (TAC), Thailand's flag carrier, to expand the Thai aviation industry beyond Asia...",
    "wof:placetype": "custom"
  },
  "geometry": {"coordinates":[-122.386166,37.616356],"type":"Point"}
}
