{
  "type": "Feature",
  "properties": {
    "date:cessation_lower": "2017-05-05",
    "date:cessation_upper": "2017-05-05",
    "date:inception_lower": "2017-05-05",
    "date:inception_upper": "2017-05-05",
    "instagram:post": {
      "caption": {
        "body": "There's a lot to see in this photo from 1967! The shadow of the old Bayshore Highway cutting across the Airport, the Tanforan Racetrack site (destroyed by a fire a few years earlier), Candlestick Park, and sparsely developed Oyster Point, Brisbane, and Marin. What else do you see?  Image:  San Francisco International Airport (SFO), aerial, 1967. SFO Museum Collection. 2011.032.1538",
        "excerpt": "There's a lot to see in this photo from 1967!",
        "hashtags": [
          "SFOHistory",
          "aviationhistory",
          "avgeek",
          "SFOat90",
          "SFHistory\n#notadrone",
          "aerialphotography"
        ]
      },
      "media_id": "0e95618ab0b6cd4a4d8e458f306c22c0",
      "path": "media/posts/201705/18251580_1404245499633870_3723485785182175232_n_17868176530110687.jpg",
      "perceptual_hash": "p:80ab90c7f45b7c5a",
      "taken": 1493984460,
      "taken_at": "May 5, 2017, 11:41 AM"
    },
    "sfomuseum:placetype": "instagram",
    "wof:name": "There's a lot to see in this photo from 1967!..",
    "wof:placetype": "custom"
  },
  "geometry": {"coordinates":[-122.386166,37.616356],"type":"Point"}
}
