{
  "type": "Feature",
  "properties": {
    "date:cessation_lower": "2021-10-07",
    "date:cessation_upper": "2021-10-07",
    "date:inception_lower": "2021-10-07",
    "date:inception_upper": "2021-10-07",
    "instagram:post": {
      "caption": {
        "body": "What’s going on at the museum? For our newly installed exhibition on Victorian wallpaper, Heidi Wright Mead came over to help us install wallpapers. The wallpapers, provided by Bradbury \u0026 Bradbury Art Wallpapers, were hand silk screened in Benicia, CA,  just across the bay from SFO.  Stay tuned for more updates from the Museum!",
        "excerpt": "What’s going on at the museum?",
        "hashtags": [
          "VictorianPaperedWall",
          "behindthescenes",
          "sneakpeek",
          "museumlife"
        ]
      },
      "media_id": "7282a2dd9c3a79a32a5b1f302b88bef1d89f57f8",
      "path": "media/posts/202110/244436781_593707118543263_116995053896527816_n_18030476629312291.jpg",
      "perceptual_hash": "p:db19aceea3503e84",
      "taken": 1633622760,
      "taken_at": "Oct 7, 2021, 4:06 PM"
    },
    "sfomuseum:placetype": "instagram",
    "wof:name": "What’s going on at the museum?..",
    "wof:placetype": "custom"
  },
  "geometry": {"coordinates":[-122.386166,37.616356],"type":"Point"}
}
