{
  "type": "Feature",
  "properties": {
    "date:cessation_lower": "2015-11-24",
    "date:cessation_upper": "2015-11-24",
    "date:inception_lower": "2015-11-24",
    "date:inception_upper": "2015-11-24",
    "instagram:post": {
      "caption": {
        "hashtags": [
          "airportart"
        ],
        "users": [
          "sfacgalleries."
        ]
      },
      "media_id": "b8d40a563acd59186af37c32b42d240c",
      "path": "media/posts/201511/12301159_1493951250906655_942262774_n_17847763429003084.jpg",
      "perceptual_hash": "p:9c0be611d1b4e37c",
      "taken": 1448396640,
      "taken_at": "Nov 24, 2015, 8:24 PM"
    },
    "sfomuseum:placetype": "instagram",
    "wof:name": "..",
    "wof:placetype": "custom",
    "wof:placetype_alt": [
      "instagram"
    ]
  },
  "geometry": {"coordinates":[-122.386166,37.616356],"type":"Point"}
}
