{
  "type": "Feature",
  "properties": {
    "instagram:post": {
      "caption": {
        "body": "In 1973, Bonnie Tiburzi became the first woman pilot hired by a major U.S. commercial airline since Helen Richey was briefly hired by Central Airlines in 1934. She began at American Airlines as part of its Boeing 727 flight crew, and in 1988 was promoted to captain. She retired in 1999, after 26 year at American Airlines.  Image: American Airlines Flight Officer Bonnie Tiburzi in a Boeing 727, c. 1973. SFO Museum Collection. 1994.37.01",
        "hashtags": [
          "WomeninAviation", 
          "avgeek", 
          "avationgeek", 
          "aviation", 
          "aviationhistory", 
          "aviationlovers", 
          "vintageaviation", 
          "history", 
          "avhistory", 
          "aviationgeeks", 
          "instaplane", 
          "flying", 
          "plane", 
          "flight", 
          "airline", 
          "avgeeks", 
          "aviation4u", 
          "aviationdaily", 
          "pilot", 
          "womenpilot"
        ]
      },
      "media_id": "9d335bdff31756d7f9f1aa73ede4cfae",
      "path": "photos/201710/9d335bdff31756d7f9f1aa73ede4cfae.jpg",
      "taken": 1507777329,
      "taken_at": "2017-10-12T03:02:09+00:00"
    },
    "sfomuseum:placetype": "instagram",
    "wof:name": "Instagram message #%!d(string=9d335bdff31756d7f9f1aa73ede4cfae)",
    "wof:placetype": "custom"
  },
  "geometry": {"coordinates":[-122.386166,37.616356],"type":"Point"}
}
