{
  "type": "Feature",
  "properties": {
    "instagram:post": {
      "caption": {
        "body": "#ThrowbackThursday to 1986 and the newly remodeled Terminal 1. T1 is currently undergoing another major renovation, and we're excited for the first section to open next year! Have you ever flown out of Terminal 1?  Image:  San Francisco International Airport (SFO), South Terminal, 1986. SFO Museum Collection. 2005.137.087.001 ",
        "hashtags": [
          "SFOhistory", 
          "SFO", 
          "airport", 
          "tbt"
        ]
      },
      "location": "San Francisco International Airport (SFO)",
      "media_id": "b1e0c0d3895b2939b1f853de8fb90093",
      "path": "photos/201812/b1e0c0d3895b2939b1f853de8fb90093.jpg",
      "taken": 1545956952,
      "taken_at": "2018-12-28T00:29:12+00:00"
    },
    "sfomuseum:placetype": "instagram",
    "wof:name": "Instagram message #%!d(string=b1e0c0d3895b2939b1f853de8fb90093)",
    "wof:placetype": "custom"
  },
  "geometry": {"coordinates":[-122.386166,37.616356],"type":"Point"}
}
