{
  "type": "Feature",
  "properties": {
    "date:cessation_lower": "2022-11-02",
    "date:cessation_upper": "2022-11-02",
    "date:inception_lower": "2022-11-02",
    "date:inception_upper": "2022-11-02",
    "instagram:post": {
      "caption": {
        "body": "What’s happening at the museum? We’re hard at work preparing for our upcoming exhibition, celebrating the centennial\tof San Francisco Opera. Featuring ten costumes from various operas, our preparators have constructed mannequins that specially fit each costume. Stay tuned for more behind the scenes content from the museum!",
        "excerpt": "What’s happening at the museum?",
        "hashtags": [
          "SFOperaCentennial",
          "SFOpera",
          "Opera",
          "BehindTheScenes",
          "sneakpeek"
        ],
        "users": [
          "SFOpera"
        ]
      },
      "media_id": "b7b3d6eb34356b73f2adb5265222cf5e93911e39",
      "path": "media/posts/202211/313944665_441555108125781_794750864200536612_n_17978110849751095.jpg",
      "perceptual_hash": "p:af124a381fb5c34d",
      "taken": 1667405460,
      "taken_at": "Nov 02, 2022 4:11 pm"
    },
    "sfomuseum:placetype": "instagram",
    "wof:name": "What’s happening at the museum?..",
    "wof:placetype": "custom",
    "wof:placetype_alt": [
      "instagram"
    ]
  },
  "geometry": {"coordinates":[-122.386166,37.616356],"type":"Point"}
}
