{
  "type": "Feature",
  "properties": {
    "date:cessation_lower": "2024-07-31",
    "date:cessation_upper": "2024-07-31",
    "date:inception_lower": "2024-07-31",
    "date:inception_upper": "2024-07-31",
    "instagram:post": {
      "caption": {
        "body": "“(As a boy) I had free access to television, which of course goes hand in hand with pop culture. TV has been my biggest influence; it started about the year I was born, and I’m a perfect example of what it can do to you—for better or for worse.” —Mickey McGowan, 1993  The Unknown Museum has prominently featured the television. Mickey McGowan utilized hollowed-out sets as enclosures for many of his dioramas. He assembled stacks of televisions in various outdoor yard installations. At times, McGowan adjusted the signal of a working television placed in an indoor exhibit so all that appeared on the screen was a solitary horizontal line. He mixed jingles from early TV commercials onto audio tapes that played music and excerpts from movies, sitcoms, serials, and newscasts from the era. Audio volume rose and fell in a constant soundtrack; the “Perfect Moment” occurred when a direct connection was made—for example, if the Rice Krispies jingle randomly played while a visitor was looking at the ad characters Snap, Crackle, and Pop in the kitchen area of the museum.   A very special thank you to Mickey McGowan for making this exhibition possible. See “Recollections… from the Unknown Museum” on display, post-security, in Terminal 2. https://bit.ly/Unknown-Museum  📸: Rabbit Ears  1986 Mickey McGowan (b. 1946) television antenna, plush and plastic toy L2023.0301.002a-b  Television antennas  1950s–60s various makers L2023.0301.003.01–.13  Upside-Down TV  1978 Mickey McGowan (b. 1946) Mill Valley, California R2023.0301.001.039",
        "excerpt": "“(As a boy) I had free access to television, which of course goes hand in hand with pop culture.",
        "hashtags": [
          "UnknownMuseum",
          "MickeyMcGowan",
          "BayArea",
          "BayAreaHistory"
        ]
      },
      "media_id": "edb4dcadbec92e8ca86ba0c7b987856af6b2e6f5",
      "path": "media/posts/202407/453414849_995353529268243_8960767221739517580_n_17959880918795351.jpg",
      "perceptual_hash": "p:fc7c434b84d591aa",
      "taken": 1722440100,
      "taken_at": "Jul 31, 2024 3:35 pm"
    },
    "sfomuseum:placetype": "instagram",
    "wof:name": "“(As a boy) I had free access to television, which of course goes hand in hand with pop culture...",
    "wof:placetype": "custom"
  },
  "geometry": {"coordinates":[-122.386166,37.616356],"type":"Point"}
}
