{
  "type": "Feature",
  "properties": {
    "instagram:post": {
      "caption": {
        "body": "This 1950s Pan American World Airways poster features a Boeing 377 Stratocruiser flying above Amsterdam, Netherlands. Just before World War II, in May of 1939, Pan American established the first regular air service across the Atlantic using airplanes. Four years earlier, the airline had established the first regular air service across the Pacific. After the war, Pan American produced beautiful travel posters promoting these transoceanic services. Pan Am’s Stratocruisers would help to define luxury air travel during the era. Have you been to Amsterdam? #TravelTuesday  Pan American World Airways poster, Amsterdam 1950s SFO Museum Collection Gift of Constance Ogilvie 2002.073.019",
        "excerpt": "This 1950s Pan American World Airways poster features a Boeing 377 Stratocruiser flying above Amsterdam, Netherlands."
      },
      "location": "San Francisco International Airport (SFO)",
      "media_id": "2e6b0d12bc66500020814b85d3c7a13e",
      "path": "photos/201603/2e6b0d12bc66500020814b85d3c7a13e.jpg",
      "taken": 1456882139,
      "taken_at": "2016-03-02T01:28:59+00:00"
    },
    "sfomuseum:placetype": "instagram",
    "wof:name": "This 1950s Pan American World Airways poster features a Boeing 377 Stratocruiser flying above Amsterdam, Netherlands...",
    "wof:placetype": "custom"
  },
  "geometry": {"coordinates":[-122.386166,37.616356],"type":"Point"}
}
