{
  "type": "Feature",
  "properties": {
    "date:cessation_lower": "2021-07-22",
    "date:cessation_upper": "2021-07-22",
    "date:inception_lower": "2021-07-22",
    "date:inception_upper": "2021-07-22",
    "instagram:post": {
      "caption": {
        "body": "Artist Alexander Calder was born #onthisday in 1898. In the early 1970s, Calder was commissioned to paint several aircraft operated by Braniff International Airways. This Douglas DC-8-62, named Flying Colors of South America, entered service in 1973, on routes between the U.S. and premier South American destinations. Do you have a favorite airline livery?",
        "excerpt": "Artist Alexander Calder was born #onthisday in 1898.",
        "hashtags": [
          "AlexanderCalder",
          "avgeek",
          "Braniff"
        ]
      },
      "media_id": "c33d9489d1274181e812772d2f6cedb3b9f28573",
      "path": "media/posts/202107/222567438_270713424861166_6769347400681958839_n_17947675741473510.jpg",
      "perceptual_hash": "p:ee6a6bccc393c484",
      "taken": 1626968400,
      "taken_at": "Jul 22, 2021, 3:40 PM"
    },
    "sfomuseum:placetype": "instagram",
    "wof:name": "Artist Alexander Calder was born #onthisday in 1898...",
    "wof:placetype": "custom"
  },
  "geometry": {"coordinates":[-122.386166,37.616356],"type":"Point"}
}
