{
  "type": "Feature",
  "properties": {
    "date:cessation_lower": "2022-10-25",
    "date:cessation_upper": "2022-10-25",
    "date:inception_lower": "2022-10-25",
    "date:inception_upper": "2022-10-25",
    "instagram:post": {
      "caption": {
        "body": "Small utility knives, known as kozuka (小柄), had long been highly valued craft objects in Japan where they were traditionally cast from fine metals, such as bronze. After Japan opened to international trade, craftsmen produced kozuka for Westerners who sometimes repurposed the handles to make dining knives. Eventually Japanese manufacturers began selling the handles alone, crafting them from various metals with die stamped decoration gilded in select areas. The Gorham Manufacturing Company added their own sterling silver blade designs, decorated with butterflies, fans, and geometric patterns applied to Western-style utensils, such as dessert forks and salad servers. The resulting knives resemble Japanese swords with decorated handles.  See “Japonisme: A Passion for Japan” on display, post-security, in Terminal 2 and online at: https://bit.ly/JaponismeSFO",
        "excerpt": "Small utility knives, known as kozuka (小柄), had long been highly valued craft objects in Japan where they were traditionally cast from fine metals, such as bronze.",
        "hashtags": [
          "Japonisme",
          "Japan",
          "Design",
          "knives"
        ]
      },
      "media_id": "3da81cbddf537f5c7c540081dbfa7317e9eb2f7f",
      "path": "media/posts/202210/312344945_504674441522191_8897141040966742594_n_17941111448270700.jpg",
      "perceptual_hash": "p:877b8ae1f80ae13c",
      "taken": 1666697040,
      "taken_at": "Oct 25, 2022 11:24 am"
    },
    "sfomuseum:placetype": "instagram",
    "wof:name": "Small utility knives, known as kozuka (小柄), had long been highly valued craft objects in Japan where they were traditionally cast from fine metals, such as bronze...",
    "wof:placetype": "custom",
    "wof:placetype_alt": [
      "instagram"
    ]
  },
  "geometry": {"coordinates":[-122.386166,37.616356],"type":"Point"}
}
