{
  "type": "Feature",
  "properties": {
    "date:cessation_lower": "2016-08-30",
    "date:cessation_upper": "2016-08-30",
    "date:inception_lower": "2016-08-30",
    "date:inception_upper": "2016-08-30",
    "instagram:post": {
      "caption": {
        "body": "#OnThisDay in 1930, the City and County of San Francisco began purchasing Mills Field and the surrounding property. Three years earlier, San Francisco began leasing land from the Mills Estate to create a temporary, experimental municipal airport. By 1930, climatic studies confirmed that the site was the best possible location for an airport, and San Francisco began a ten-year purchasing program with the Mills Estate to acquire 1,112 acres. Payment was made in annual installments of $105,000 each, the first of which was paid on August 30, 1930. #SFOHistory  Mills Field Municipal Airport of San Francisco, Army Air Corps War Maneuvers air show photograph  1930 SFO Museum Collection 1993.07.17.001 b",
        "excerpt": "#OnThisDay in 1930, the City and County of San Francisco began purchasing Mills Field and the surrounding property."
      },
      "media_id": "fad50e9bffc1e49187d0c82e32a6f10a058e83b4",
      "path": "media/posts/201608/14073032_1171009709624427_2005316066_n_17861549746008206.jpg",
      "perceptual_hash": "p:94cbe4b29b950e35",
      "taken": 1472547360,
      "taken_at": "Aug 30, 2016, 8:56 AM"
    },
    "sfomuseum:placetype": "instagram",
    "wof:name": "#OnThisDay in 1930, the City and County of San Francisco began purchasing Mills Field and the surrounding property...",
    "wof:placetype": "custom",
    "wof:placetype_alt": [
      "instagram"
    ]
  },
  "geometry": {"coordinates":[-122.386166,37.616356],"type":"Point"}
}
