{
  "type": "Feature",
  "properties": {
    "date:cessation_lower": "2020-02-05",
    "date:cessation_upper": "2020-02-05",
    "date:inception_lower": "2020-02-05",
    "date:inception_upper": "2020-02-05",
    "instagram:post": {
      "caption": {
        "body": "What did it take to mount and install the thirty-two lengths of wallpaper that make up the complete set of Zuber’s “Les Vues d’Amérique du Nord (Views of North America)”? A lot! Check out this video that shows the work by wallpaper installation specialists and SFO Museum staff in the paper mounting, review, and exhibition installation.  The first edition of Views of North America was offered in 1834 and designed by Jean-Julien Deltil (1791–1863). The entire panoramic wallpaper requires 1,690 printing blocks, 223 colors, and thirty-two lengths totaling forty-nine feet. “Zuber: The Art of French Scenic Wallpaper” is on display, pre-security in the International Terminal. https://www.youtube.com/watch?v=XKA0zYj8P_s",
        "excerpt": "What did it take to mount and install the thirty-two lengths of wallpaper that make up the complete set of Zuber’s “Les Vues d’Amérique du Nord (Views of North America)”?",
        "hashtags": [
          "ZuberScenicWallpaper",
          "wallpaper",
          "zuber",
          "scenicwallpaper",
          "interiordesign",
          "museum",
          "design",
          "WallpaperWendesday"
        ]
      },
      "file_hash": "d5a81626a51ded6ee661e3f38d4aba6e6a15334b5c92983bcfeba94f529ec899",
      "media_id": "32a0fe1af19cf533eae53c1df2d51594d257b419",
      "path": "media/posts/202002/7E44DD29D98522D61C3531EC8F7B7A89_video_dashinit_17860163287722654.mp4",
      "taken": 1580923020,
      "taken_at": "Feb 05, 2020 5:17 pm"
    },
    "sfomuseum:placetype": "instagram",
    "wof:name": "What did it take to mount and install the thirty-two lengths of wallpaper that make up the complete set of Zuber’s “Les Vues d’Amérique du Nord (Views of North America)”?..",
    "wof:placetype": "custom"
  },
  "geometry": {"coordinates":[-122.386166,37.616356],"type":"Point"}
}
