{
  "type": "Feature",
  "properties": {
    "date:cessation_lower": "2018-05-04",
    "date:cessation_upper": "2018-05-04",
    "date:inception_lower": "2018-05-04",
    "date:inception_upper": "2018-05-04",
    "instagram:post": {
      "caption": {
        "body": "Many amateur craftsmen created unique folk houses and other architectural buildings from the mid-1800s to the early-1900s. The one displayed here evokes something from a fairy tale. This fanciful house has decorative wooden shingles with an elaborate rooftop and entryway finials. The house's wooden front and back façades mimic bricks, while a small side addition appears to be a chapel attached to the house.  Folk house is courtesy of the collection of Ian Berke. See \"#AmericanFolkArt: An Enduring Legacy\", on display, pre-security, in the International Terminal. http://bit.ly/AmericanFolkArt",
        "excerpt": "Many amateur craftsmen created unique folk houses and other architectural buildings from the mid-1800s to the early-1900s.",
        "hashtags": [
          "AmericanFolkArt",
          "folkart",
          "american",
          "history",
          "americana",
          "antique",
          "vintage",
          "design",
          "folkarts",
          "architecture",
          "fairytale",
          "house"
        ]
      },
      "media_id": "936336053a8f595f57ab88cdf33d0f39",
      "path": "media/posts/201805/31163021_803488159860016_6572511981176094720_n_17923605787082035.jpg",
      "perceptual_hash": "p:fb95856a04ee5f80",
      "taken": 1525428780,
      "taken_at": "May 4, 2018, 10:13 AM"
    },
    "sfomuseum:placetype": "instagram",
    "wof:name": "Many amateur craftsmen created unique folk houses and other architectural buildings from the mid-1800s to the early-1900s...",
    "wof:placetype": "custom"
  },
  "geometry": {"coordinates":[-122.386166,37.616356],"type":"Point"}
}
