{
  "type": "Feature",
  "properties": {
    "instagram:post": {
      "caption": {
        "body": "Many amateur craftsmen created unique folk houses and other architectural buildings from the mid-1800s to the early-1900s. The one displayed here evokes something from a fairy tale. This fanciful house has decorative wooden shingles with an elaborate rooftop and entryway finials. The house's wooden front and back façades mimic bricks, while a small side addition appears to be a chapel attached to the house.  Folk house is courtesy of the collection of Ian Berke. See \"#AmericanFolkArt: An Enduring Legacy\", on display, pre-security, in the International Terminal. http://bit.ly/AmericanFolkArt",
        "hashtags": [
          "AmericanFolkArt", 
          "folkart", 
          "american", 
          "history", 
          "americana", 
          "antique", 
          "vintage", 
          "design", 
          "folkarts", 
          "architecture", 
          "fairytale", 
          "house"
        ]
      },
      "media_id": "936336053a8f595f57ab88cdf33d0f39",
      "path": "photos/201805/936336053a8f595f57ab88cdf33d0f39.jpg",
      "taken": 1525457605,
      "taken_at": "2018-05-04T18:13:25+00:00"
    },
    "sfomuseum:placetype": "instagram",
    "wof:name": "Instagram message #%!d(string=936336053a8f595f57ab88cdf33d0f39)",
    "wof:placetype": "custom"
  },
  "geometry": {"coordinates":[-122.386166,37.616356],"type":"Point"}
}
