{
  "type": "Feature",
  "properties": {
    "date:cessation_lower": "2018-03-24",
    "date:cessation_upper": "2018-03-24",
    "date:inception_lower": "2018-03-24",
    "date:inception_upper": "2018-03-24",
    "instagram:post": {
      "caption": {
        "body": "Colonel Charles A. Lindbergh was deeply involved in commercial aviation's development and early airline planning. He chaired the technical board of Transcontinental Air Transport (TAT), popularly known as the \"Lindbergh Line,\" and tested new transport airplanes on its behalf. On March 23, 1929, at SFO, or Mills Field as it was known then, Lindbergh set out to take a distinguished group of local citizens on a TAT promotional air tour in a Keystone K-78 Patrician. With his party aboard, Lindbergh taxied the nearly eight-ton tri-motor to the southern end of the airfield for take-off. However, the right tire broke through the airfield's surface, the landing gear dug in, and the Patrician stopped dead in its tracks-Lindbergh was stuck in the mud! After digging out, the flight eventually got underway, but repercussions from the \"Lindbergh Incident,\" as reported, contributed to administrative changes and improvements in the airport's facilities.  Image: Transcontinental Air Transport (TAT), Charles Lindbergh next to Ford Tri-Motor, c. 1929. Gift of TWA Clipped Wings International, Inc. 2002.113.350",
        "excerpt": "Colonel Charles A. Lindbergh was deeply involved in commercial aviation's development and early airline planning.",
        "hashtags": [
          "OnThisDay",
          "OTDIH",
          "charleslindbergh",
          "SFOHistory",
          "SFHistory",
          "avgeek",
          "avationgeek",
          "aviation",
          "aviationhistory",
          "vintageaviation",
          "history",
          "avhistory",
          "aviationgeeks",
          "avgeeks"
        ]
      },
      "location": "San Francisco International Airport (SFO)",
      "media_id": "323bb03804a89396591e51b155f8fa6d",
      "path": "photos/201803/323bb03804a89396591e51b155f8fa6d.jpg",
      "perceptual_hash": "p:f1e88fc98d96b304",
      "taken": 1521850694,
      "taken_at": "2018-03-24T00:18:14+00:00"
    },
    "sfomuseum:placetype": "instagram",
    "wof:name": "Colonel Charles A. Lindbergh was deeply involved in commercial aviation's development and early airline planning...",
    "wof:placetype": "custom"
  },
  "geometry": {"coordinates":[-122.386166,37.616356],"type":"Point"}
}
