{
  "type": "Feature",
  "properties": {
    "date:cessation_lower": "2013-08-27",
    "date:cessation_upper": "2013-08-27",
    "date:inception_lower": "2013-08-27",
    "date:inception_upper": "2013-08-27",
    "instagram:post": {
      "caption": {
        "body": "How do you store your food? The Bontoc peoples of the Luzon Cordillera have numerous types of #basketry only for rice: for raw \u0026 prepared rice; for ceremonial \u0026 everyday usage; communal meals \u0026 personal containers.",
        "excerpt": "How do you store your food?"
      },
      "media_id": "c64e8c1c2fc62ea66cace1aa7b563c93",
      "path": "media/posts/201308/11274305_1592384637701511_1579511989_n_17842354786062499.jpg",
      "perceptual_hash": "p:abe0d893c72dd2c1",
      "taken": 1377599760,
      "taken_at": "Aug 27, 2013, 10:36 AM"
    },
    "sfomuseum:placetype": "instagram",
    "wof:name": "How do you store your food?..",
    "wof:placetype": "custom"
  },
  "geometry": {"coordinates":[-122.386166,37.616356],"type":"Point"}
}
