{
  "type": "Feature",
  "properties": {
    "instagram:post": {
      "caption": {
        "body": "How do you store your food? The Bontoc peoples of the Luzon Cordillera have numerous types of #basketry only for rice: for raw \u0026 prepared rice; for ceremonial \u0026 everyday usage; communal meals \u0026 personal containers.",
        "excerpt": "How do you store your food?"
      },
      "media_id": "c64e8c1c2fc62ea66cace1aa7b563c93",
      "path": "photos/201308/c64e8c1c2fc62ea66cace1aa7b563c93.jpg",
      "taken": 1377628591,
      "taken_at": "2013-08-27T18:36:31+00:00"
    },
    "sfomuseum:placetype": "instagram",
    "wof:name": "How do you store your food?..",
    "wof:placetype": "custom"
  },
  "geometry": {"coordinates":[-122.386166,37.616356],"type":"Point"}
}
