{
  "type": "Feature",
  "properties": {
    "instagram:post": {
      "caption": {
        "body": "The Boeing 307 Stratoliner was the first commercial airliner put in service to have a pressurized cabin. Named the “Stratoliner” for its ability to cruise near the stratosphere, the airliner had a circular cross-section, tear-drop-shaped fuselage to handle the stresses of pressurization. Only ten were produced: one prototype, five for TWA (Transcontinental \u0026 Western Air), three for Pan American, and one for Howard Hughes. Launched by TWA in 1940, the airline touted its quietness, speed, and advanced capability of flying above bad weather and turbulence.  See \"Aviation Evolutions: The Jim Lund 1:72 Scale Model Airplane Collection\", which features more than 200 models, on display, pre-security, in the Aviation Museum. http://bit.ly/AviationEvolutions",
        "excerpt": "The Boeing 307 Stratoliner was the first commercial airliner put in service to have a pressurized cabin.",
        "hashtags": [
          "AviationEvolutions", 
          "jimlund", 
          "avgeek", 
          "avationgeek", 
          "aviation", 
          "aviationhistory", 
          "vintageaviation", 
          "history", 
          "avhistory", 
          "aviationgeeks", 
          "modelplane", 
          "avgeeks", 
          "modelaircraft", 
          "airplane", 
          "aircraft", 
          "boeing", 
          "boeing307", 
          "TWA"
        ]
      },
      "media_id": "781a495b07df068be2401a2e799392aa",
      "path": "photos/201807/781a495b07df068be2401a2e799392aa.jpg",
      "taken": 1530836049,
      "taken_at": "2018-07-06T00:14:09+00:00"
    },
    "sfomuseum:placetype": "instagram",
    "wof:name": "The Boeing 307 Stratoliner was the first commercial airliner put in service to have a pressurized cabin...",
    "wof:placetype": "custom"
  },
  "geometry": {"coordinates":[-122.386166,37.616356],"type":"Point"}
}
