{
  "type": "Feature",
  "properties": {
    "date:cessation_lower": "2016-11-22",
    "date:cessation_upper": "2016-11-22",
    "date:inception_lower": "2016-11-22",
    "date:inception_upper": "2016-11-22",
    "instagram:post": {
      "caption": {
        "body": "Today marks the eighty-first anniversary of Pan American Airways’ daring transpacific endeavor. A crowd of 125,000 people watched from around the Bay Area as the Martin M-130 “China Clipper” lifted off from the waters of San Francisco Bay and strained into the sky threading its way under and over two partially built bridges. It soared through the Golden Gate and slowly disappeared from land as the ship’s crew of seven set course for the Far East and opened the age of regular transpacific oceanic commercial air service. Here, the crowd gathers around the China Clipper before its historic first take off in Alameda on November 22, 1935.",
        "excerpt": "Today marks the eighty-first anniversary of Pan American Airways’ daring transpacific endeavor.",
        "hashtags": [
          "Onthisday",
          "AvGeek",
          "AviationHistory",
          "ChinaClipper",
          "PanAm",
          "BayAreaHistory"
        ]
      },
      "media_id": "734dfec87967fad09c34d13042b4c79b",
      "path": "media/posts/201611/14718199_791086147698347_6376190142767431680_n_17845210864190484.jpg",
      "perceptual_hash": "p:fbe0980ee3d3e418",
      "taken": 1479809940,
      "taken_at": "Nov 22, 2016, 10:19 AM"
    },
    "sfomuseum:placetype": "instagram",
    "wof:name": "Today marks the eighty-first anniversary of Pan American Airways’ daring transpacific endeavor...",
    "wof:placetype": "custom"
  },
  "geometry": {"coordinates":[-122.386166,37.616356],"type":"Point"}
}
