{
  "type": "Feature",
  "properties": {
    "date:cessation_lower": "2024-05-22",
    "date:cessation_upper": "2024-05-22",
    "date:inception_lower": "2024-05-22",
    "date:inception_upper": "2024-05-22",
    "instagram:post": {
      "caption": {
        "body": "Harvey Milk Day, organized by the Harvey Milk Foundation (@harveymilkfoundation), is celebrated each year on May 22 on Harvey Milk’s birthday. Milk was the first openly gay elected official in the state of California. Elected to the San Francisco Board of Supervisors, Milk represented District 5, which included Castro Street. Milk campaigned for gay rights and along San Francisco Mayor George Moscone helped pass a city ordinance authored by Milk that banned discrimination based on sexual orientation in employment and housing. Milk and Moscone were assassinated in 1978 by former Board of Supervisors member Dan White.  Learn more about Harvey Milk's life and legacy in our exhibition, \"Messenger of Hope,\" which is on view pre-security in Harvey Milk Terminal 1. Not traveling? The exhibition catalog is available to read online! https://bit.ly/HMT1Exhibit  📸:  Supervisor Harvey Milk and Mayor George Moscone at City Hall March 29, 1978 Photograph by Efren Convento Ramirez (1941–2017) Collection of Efren Ramirez; Courtesy of the GLBT Historical Society R2019.0202.007  Harvey Milk watches while Mayor George Moscone signs the citywide anti-discrimination ordinance March 29, 1978 Photograph by Efren Convento Ramirez (1941–2017) Collection of Efren Ramirez; Courtesy of the GLBT Historical Society R2019.0202.012",
        "excerpt": "Harvey Milk Day, organized by the Harvey Milk Foundation (@harveymilkfoundation), is celebrated each year on May 22 on Harvey Milk’s birthday.",
        "hashtags": [
          "HarveyMilkDay"
        ]
      },
      "media_id": "f4a6e2a3b6ce1e6c31c028ccef76b9dcd3bb2eea",
      "path": "media/posts/202405/445838878_467596189067897_7323767013832455000_n_18051126628598484.jpg",
      "perceptual_hash": "p:add04ae79946bf40",
      "taken": 1716393060,
      "taken_at": "May 22, 2024 3:51 pm"
    },
    "sfomuseum:placetype": "instagram",
    "wof:name": "Harvey Milk Day, organized by the Harvey Milk Foundation (@harveymilkfoundation), is celebrated each year on May 22 on Harvey Milk’s birthday...",
    "wof:placetype": "custom"
  },
  "geometry": {"coordinates":[-122.386166,37.616356],"type":"Point"}
}
