{
  "type": "Feature",
  "properties": {
    "date:cessation_lower": "2014-12-16",
    "date:cessation_upper": "2014-12-16",
    "date:inception_lower": "2014-12-16",
    "date:inception_upper": "2014-12-16",
    "instagram:post": {
      "caption": {
        "hashtags": [
          "Tiffany",
          "TiffanyGlass",
          "color"
        ]
      },
      "media_id": "ce18ce5203e1f6e5b6e7e0f1bc4ce87f",
      "path": "photos/201412/ce18ce5203e1f6e5b6e7e0f1bc4ce87f.jpg",
      "perceptual_hash": "p:cbba1c2f38c133c6",
      "taken": 1418774346,
      "taken_at": "2014-12-16T23:59:06+00:00"
    },
    "sfomuseum:placetype": "instagram",
    "wof:name": "..",
    "wof:placetype": "custom"
  },
  "geometry": {"coordinates":[-122.386166,37.616356],"type":"Point"}
}
