{
  "type": "Feature",
  "properties": {
    "date:cessation_lower": "2018-10-24",
    "date:cessation_upper": "2018-10-24",
    "date:inception_lower": "2018-10-24",
    "date:inception_upper": "2018-10-24",
    "instagram:post": {
      "caption": {
        "body": "Coin-operated radios provided an hour of entertainment at the drop of a quarter or dime. Manufactured from the late 1940s into the 1950s, these novel radios are indicative of a bygone era. Following the end of the Second World War, travelers took to their automobiles every weekend in an unprecedented boom in auto tourism. By 1964, more than 61,000 roadside motor hotels, commonly known as motels, dotted America’s highways and byways. Reflecting regional themes, modern architecture, and kitschy design, these simply constructed lodgings were marked by illustrative neon signage and offered modest accommodations for the weary traveler. Many motel proprietors installed coin-operated radios in their rooms to maximize profits. \"On the Radio\" is on display, post-security, in Terminal 3. http://bit.ly/RadioSFO",
        "excerpt": "Coin-operated radios provided an hour of entertainment at the drop of a quarter or dime.",
        "hashtags": [
          "radioSFO",
          "ontheradio",
          "radio",
          "radios",
          "wireless",
          "vintage",
          "antique",
          "vintageradios",
          "coinioperated",
          "portableradio",
          "retroradio",
          "retro"
        ]
      },
      "media_id": "162c7bce50a80b199b330017366a0aec",
      "path": "media/posts/201810/42669437_323528968229651_7739624251673545275_n_17874887752283182.jpg",
      "perceptual_hash": "p:94ce2f901991e76e",
      "taken": 1540401120,
      "taken_at": "Oct 24, 2018 5:12 pm"
    },
    "sfomuseum:placetype": "instagram",
    "wof:name": "Coin-operated radios provided an hour of entertainment at the drop of a quarter or dime...",
    "wof:placetype": "custom",
    "wof:placetype_alt": [
      "instagram"
    ]
  },
  "geometry": {"coordinates":[-122.386166,37.616356],"type":"Point"}
}
