{
  "type": "Feature",
  "properties": {
    "date:cessation_lower": "2023-04-18",
    "date:cessation_upper": "2023-04-18",
    "date:inception_lower": "2023-04-18",
    "date:inception_upper": "2023-04-18",
    "instagram:post": {
      "caption": {
        "body": "Midway Atoll, also called Midway Island, is part of the territory called the United States Minor Outlying Islands. Designated as part of the 583,000-square-mile Papahānaumokuākea Marine National Monument in 2006, the atoll is home to 70% of the world’s Laysan albatross population, whose individuals can live to 55 years or more. An important breeding ground for the Laysan albatross, the birds inhabit the entire island, including human settlements.  From the 1930s to the 1950s, Midway was utilized as an overnight refueling stop for Pan Am’s transpacific flying boat routes on the leg between Hawai’i and Wake Island. Encounters with the Laysan albatross were well documented by Pan Am’s staff and passengers. The awkwardness of the bird on land and their behavioral antics entertained residents and visiting passengers, earning them the nickname “gooney bird.”",
        "excerpt": "Midway Atoll, also called Midway Island, is part of the territory called the United States Minor Outlying Islands.",
        "hashtags": [
          "EarthMonth",
          "AvGeek",
          "PanAm",
          "MidwayIsland"
        ],
        "users": [
          "papahanaumokuakea.hawaii"
        ]
      },
      "media_id": "367ad4a50c57e57055c1f6eedc7ef22b44dc16ac",
      "path": "media/posts/202304/341745749_6137210966397960_3426242253780330216_n_17986284976971893.jpg",
      "perceptual_hash": "p:f698d466dd24360e",
      "taken": 1681811760,
      "taken_at": "Apr 18, 2023, 9:56 AM"
    },
    "sfomuseum:placetype": "instagram",
    "wof:name": "Midway Atoll, also called Midway Island, is part of the territory called the United States Minor Outlying Islands...",
    "wof:placetype": "custom"
  },
  "geometry": {"coordinates":[-122.386166,37.616356],"type":"Point"}
}
