{
  "type": "Feature",
  "properties": {
    "instagram:post": {
      "caption": {
        "body": "Spode Pottery introduced their Caramanian series around 1809. Caramania historically referred to the southern coast of Turkey, known as the Turquoise Coast. Spode copied imagery from the twenty-four aquatints in \"Views in the Ottoman Empire\" (1803) for their series. Imagery from the print “Antique Fragments at Limisso,” displayed on the pieces here, may represent Kolossi Castle in Limassol, on the south coast of Cyprus in the eastern Mediterranean. All objects are from the collection of Michael Sack. See more picturesque landscape painting in \"From #PrintToPlate: Views of the East on Transferware\", on display, pre-security, in the International Terminal. http://bit.ly/PrintToPlate",
        "hashtags": [
          "painting", 
          "blueandwhite", 
          "ceramics", 
          "pottery", 
          "aquatint", 
          "transferware", 
          "spode", 
          "Caramanian"
        ]
      },
      "location": "San Francisco International Airport",
      "media_id": "d4e1dee3f6ce087f6fa6ce9a9aee358c",
      "path": "photos/201611/d4e1dee3f6ce087f6fa6ce9a9aee358c.jpg",
      "taken": 1478024179,
      "taken_at": "2016-11-01T18:16:19+00:00"
    },
    "sfomuseum:placetype": "instagram",
    "wof:name": "Instagram message #%!d(string=d4e1dee3f6ce087f6fa6ce9a9aee358c)",
    "wof:placetype": "custom"
  },
  "geometry": {"coordinates":[-122.386166,37.616356],"type":"Point"}
}
