{
  "type": "Feature",
  "properties": {
    "date:cessation_lower": "2018-05-09",
    "date:cessation_upper": "2018-05-09",
    "date:inception_lower": "2018-05-09",
    "date:inception_upper": "2018-05-09",
    "instagram:post": {
      "caption": {
        "body": "A stock certificate is a legal document printed on paper that represents equity ownership in a company. With ornate borders and usually bearing an illustration that is related to the company's business, such as an airplane, they are printed on bond paper from a finely engraved metal plate. When a stock is redeemed a perforated cancellation mark is made and it then becomes null and void as a financial instrument. Today, stocks are issued electronically and this has increasingly made stock certificates items of interest to collectors. This area of collecting is called scripophily, a combination of the English word \"scrip\" meaning ownership right and the Greek word \"philos\" meaning love. ",
        "excerpt": "A stock certificate is a legal document printed on paper that represents equity ownership in a company.",
        "hashtags": [
          "Scripophily",
          "PanAm",
          "PanAmerican",
          "PAA",
          "stocks",
          "avgeek",
          "avationgeek",
          "aviation",
          "aviationhistory",
          "vintageaviation",
          "history",
          "avhistory",
          "aviationgeeks",
          "avgeeks"
        ]
      },
      "media_id": "3ffe4c139e9dc7bc5f21f34df19c486b",
      "path": "media/posts/201805/31175924_2079643515644621_973835524575854592_n_17919670921136498.jpg",
      "perceptual_hash": "p:e646593966789366",
      "taken": 1525888920,
      "taken_at": "May 9, 2018, 6:02 PM"
    },
    "sfomuseum:placetype": "instagram",
    "wof:name": "A stock certificate is a legal document printed on paper that represents equity ownership in a company...",
    "wof:placetype": "custom",
    "wof:placetype_alt": [
      "instagram"
    ]
  },
  "geometry": {"coordinates":[-122.386166,37.616356],"type":"Point"}
}
