{
  "type": "Feature",
  "properties": {
    "instagram:post": {
      "caption": {
        "body": "Do you recognize this location? San Francisco has changed a lot in the last sixty years but these buildings have stayed the same. Fun fact: this street is now a one-way street!  Image: KLM (Royal Dutch Airlines) sales office, 1952. Gift of Julian Veovich. 2013.126.002",
        "excerpt": "Do you recognize this location?",
        "hashtags": [
          "sanfrancisco", 
          "muni", 
          "bus", 
          "classiccars", 
          "vintage", 
          "goldenage", 
          "1950svintage", 
          "50s", 
          "midcentury", 
          "classic", 
          "retro", 
          "1950s"
        ]
      },
      "location": "SFO Museum",
      "media_id": "c1b91176aab969466276ec3362e3adbb",
      "path": "photos/201812/c1b91176aab969466276ec3362e3adbb.jpg",
      "taken": 1545444679,
      "taken_at": "2018-12-22T02:11:19+00:00"
    },
    "sfomuseum:placetype": "instagram",
    "wof:name": "Do you recognize this location?..",
    "wof:placetype": "custom"
  },
  "geometry": {"coordinates":[-122.386166,37.616356],"type":"Point"}
}
