{
  "type": "Feature",
  "properties": {
    "date:cessation_lower": "2015-12-10",
    "date:cessation_upper": "2015-12-10",
    "date:inception_lower": "2015-12-10",
    "date:inception_upper": "2015-12-10",
    "instagram:post": {
      "caption": {
        "body": "In 2010, we produced an exhibition called “Japanese Ceramics: An Enduring Tradition”. This exhibition presented many of Japan’s ceramic styles from the Medieval period (late 1100s–late 1500s) to the twentieth century—from glazed stoneware, to teabowls and porcelain food-serving vessels, as well as a variety of underglaze blue and overglaze enamel porcelains. Check out our current exhibition “Mingei: Traditional Japanese Arts”, featuring more Japanese ceramics, pre-security, in the International Terminal.",
        "excerpt": "In 2010, we produced an exhibition called “Japanese Ceramics: An Enduring Tradition”."
      },
      "media_id": "fd0b1565f13f74cffe674e52a5ecdeaf",
      "path": "media/posts/201512/12353466_922910264462280_330819927_n_17844155788079287.jpg",
      "perceptual_hash": "p:aaab855a4a873fd0",
      "taken": 1449741000,
      "taken_at": "Dec 10, 2015, 9:50 AM"
    },
    "sfomuseum:placetype": "instagram",
    "wof:name": "In 2010, we produced an exhibition called “Japanese Ceramics: An Enduring Tradition”...",
    "wof:placetype": "custom",
    "wof:placetype_alt": [
      "instagram"
    ]
  },
  "geometry": {"coordinates":[-122.386166,37.616356],"type":"Point"}
}
