{
  "type": "Feature",
  "properties": {
    "instagram:post": {
      "caption": {
        "body": "In 2010, we produced an exhibition called “Japanese Ceramics: An Enduring Tradition”. This exhibition presented many of Japan’s ceramic styles from the Medieval period (late 1100s–late 1500s) to the twentieth century—from glazed stoneware, to teabowls and porcelain food-serving vessels, as well as a variety of underglaze blue and overglaze enamel porcelains. Check out our current exhibition “Mingei: Traditional Japanese Arts”, featuring more Japanese ceramics, pre-security, in the International Terminal.",
        "excerpt": "In 2010, we produced an exhibition called “Japanese Ceramics: An Enduring Tradition”."
      },
      "location": "San Francisco International Airport (SFO)",
      "media_id": "fd0b1565f13f74cffe674e52a5ecdeaf",
      "path": "photos/201512/fd0b1565f13f74cffe674e52a5ecdeaf.jpg",
      "taken": 1449769825,
      "taken_at": "2015-12-10T17:50:25+00:00"
    },
    "sfomuseum:placetype": "instagram",
    "wof:name": "In 2010, we produced an exhibition called “Japanese Ceramics: An Enduring Tradition”...",
    "wof:placetype": "custom"
  },
  "geometry": {"coordinates":[-122.386166,37.616356],"type":"Point"}
}
