{
  "type": "Feature",
  "properties": {
    "date:cessation_lower": "2018-10-02",
    "date:cessation_upper": "2018-10-02",
    "date:inception_lower": "2018-10-02",
    "date:inception_upper": "2018-10-02",
    "instagram:post": {
      "caption": {
        "body": "Did you know our exhibition, \"On The Radio\" is full of local Bay Area history? During the 1920s, some of the best-performing, commercially made crystal radio sets such as the wooden one shown here were manufactured by Uncle Al’s Radio Shop in Oakland, California. Marketed as the Miracle, they used tuning circuits with multiple coils and variable condensers. The sensitivity of Uncle Al’s tuning circuits allowed these radios to select individual stations in metropolitan areas with many frequencies, such as the San Francisco Bay Area. \"On the Radio\" is on display, post-security, in Terminal 3. http://ow.ly/CV1050jiWzy . . .",
        "excerpt": "Did you know our exhibition, \"On The Radio\" is full of local Bay Area history?",
        "hashtags": [
          "radioSFO",
          "ontheradio",
          "radio",
          "radios",
          "wireless",
          "vintage",
          "antique",
          "vintageradio",
          "retroradio",
          "retro",
          "oakland",
          "bayarea",
          "bayareahistory",
          "crystalradio"
        ]
      },
      "media_id": "0109cb42212a6abd49fa9fc524f01ea6",
      "path": "media/posts/201810/41739249_2059863357657567_8329590018418673365_n_17923913404213890.jpg",
      "perceptual_hash": "p:b39ccce93096439e",
      "taken": 1538498100,
      "taken_at": "Oct 2, 2018, 4:35 PM"
    },
    "sfomuseum:placetype": "instagram",
    "wof:name": "Did you know our exhibition, \"On The Radio\" is full of local Bay Area history?..",
    "wof:placetype": "custom"
  },
  "geometry": {"coordinates":[-122.386166,37.616356],"type":"Point"}
}
