{
  "type": "Feature",
  "properties": {
    "date:cessation_lower": "2016-10-24",
    "date:cessation_upper": "2016-10-24",
    "date:inception_lower": "2016-10-24",
    "date:inception_upper": "2016-10-24",
    "instagram:post": {
      "caption": {
        "hashtags": [
          "onthisday",
          "SFOHistory",
          "SpanishColonialRevival",
          "architecture",
          "TDiH"
        ]
      },
      "media_id": "2f2f2fbc78823df9bf54442ee650b4b1",
      "path": "media/posts/201610/14677196_1253310851376694_6992812494305624064_n_17843574376182451.jpg",
      "perceptual_hash": "p:f2c3b1af8f844c58",
      "taken": 1477299840,
      "taken_at": "Oct 24, 2016, 9:04 AM"
    },
    "sfomuseum:placetype": "instagram",
    "wof:name": "..",
    "wof:placetype": "custom"
  },
  "geometry": {"coordinates":[-122.386166,37.616356],"type":"Point"}
}
