{
  "type": "Feature",
  "properties": {
    "instagram:post": {
      "caption": {
        "body": "Prepping for an exhibit on #aviation toys: American Airlines' Little Miss Stewardess Set from the early 1960s included authentic AA dishes, and a wearable hat, wings, and ring."
      },
      "media_id": "5f4aaec1c7a080247803c3e44d060c79",
      "path": "photos/201308/5f4aaec1c7a080247803c3e44d060c79.jpg",
      "taken": 1375830804,
      "taken_at": "2013-08-06T23:13:24+00:00"
    },
    "sfomuseum:placetype": "instagram",
    "wof:name": "Instagram message #%!d(string=5f4aaec1c7a080247803c3e44d060c79)",
    "wof:placetype": "custom"
  },
  "geometry": {"coordinates":[-122.386166,37.616356],"type":"Point"}
}
