{
  "type": "Feature",
  "properties": {
    "date:cessation_lower": "2013-08-06",
    "date:cessation_upper": "2013-08-06",
    "date:inception_lower": "2013-08-06",
    "date:inception_upper": "2013-08-06",
    "instagram:post": {
      "caption": {
        "body": "Prepping for an exhibit on #aviation toys: American Airlines' Little Miss Stewardess Set from the early 1960s included authentic AA dishes, and a wearable hat, wings, and ring.",
        "excerpt": "Prepping for an exhibit on #aviation toys: American Airlines' Little Miss Stewardess Set from the early 1960s included authentic AA dishes, and a wearable hat, wings, and ring."
      },
      "media_id": "5f4aaec1c7a080247803c3e44d060c79",
      "path": "media/posts/201308/11328305_1614147828823514_2033444884_n_17842348162062499.jpg",
      "perceptual_hash": "p:84f87a87d90f7078",
      "taken": 1375801980,
      "taken_at": "Aug 6, 2013, 3:13 PM"
    },
    "sfomuseum:placetype": "instagram",
    "wof:name": "Prepping for an exhibit on #aviation toys: American Airlines' Little Miss Stewardess Set from the early 1960s included authentic AA dishes, and a wearable hat, wings, and ring...",
    "wof:placetype": "custom",
    "wof:placetype_alt": [
      "instagram"
    ]
  },
  "geometry": {"coordinates":[-122.386166,37.616356],"type":"Point"}
}
