{
  "type": "Feature",
  "properties": {
    "instagram:post": {
      "caption": {
        "hashtags": [
          "OnThisDay", 
          "AVGeek"
        ]
      },
      "location": "San Francisco International Airport (SFO)",
      "media_id": "894e8c298d47f8a20b2a7beecfe30100",
      "path": "photos/201510/894e8c298d47f8a20b2a7beecfe30100.jpg",
      "taken": 1446057760,
      "taken_at": "2015-10-28T18:42:40+00:00"
    },
    "sfomuseum:placetype": "instagram",
    "wof:name": "Instagram message #%!d(string=894e8c298d47f8a20b2a7beecfe30100)",
    "wof:placetype": "custom"
  },
  "geometry": {"coordinates":[-122.386166,37.616356],"type":"Point"}
}
